Workbook

Sheet Setup

Sheet Customer Enquiry Form
A1: Timestamp | B1: Name | C1: Mobile Number | D1: Purchase Type | E1: Category | F1: Product | G1: Estimate Budget | H1: Specific Requirement | I1: Design Reference if any upload pic | J1: Attended by | K1: Follow up Needed by | L1: Where Did You Find US | M1: Requirement Needed by Date | N1: Priority Urgency | O1: Referred By (optional) | P1: Email Id | Q1: url
A2: 44625.486 | B2: Kusha ji | D2: General | E2: Diamond Jewellery, Gold Jewellery | F2: Earring / Tops | G2: 20k | H2: Round vaali with plain heart shaped gold hanging | J2: Saarika | K2: Saarika | L2: Old | M2: 44625 | N2: This Week | Q2: https://docs.google.com/forms/d/e/1FAIpQLSeQ0wUAy9WJrwwZ_8x6kCxvJSihLYtbLF2nbMncVH08fybLWQ/viewform?edit2=2_ABaOnucOBtuzIBq648ZrMfcYHOkW9UiP3oPSq_Lj9KHly_tPcKrmgp2EdiB5cOtOKJ0hAaw
A3: 44625.563 | B3: Vinod | D3: General | E3: Diamond Jewellery, Solitaire | F3: Chain, Nosepin | G3: 50000 | J3: Shivani | K3: Seema Mam | L3: Old | M3: 44628 | N3: This Week | Q3: https://docs.google.com/forms/d/e/1FAIpQLSeQ0wUAy9WJrwwZ_8x6kCxvJSihLYtbLF2nbMncVH08fybLWQ/viewform?edit2=2_ABaOnucjSholQ0zznOsx1FWO_yTZ6SDKtCeJJ5kjGajuBRYP2y8S8fehKqvKRlknV7fXnrY
A4: 44626.502 | B4: Jojo | D4: General | E4: Diamond Jewellery | F4: Ladies Bracelet / Kada | G4: 150000 | H4: Cartier | J4: Saurav Sir | K4: Saurav Sir | L4: Old | M4: 44635 | N4: This Month | Q4: https://docs.google.com/forms/d/e/1FAIpQLSeQ0wUAy9WJrwwZ_8x6kCxvJSihLYtbLF2nbMncVH08fybLWQ/viewform?edit2=2_ABaOnudzstLQLbsbfevudiqxmMbvo4c8F070bC6Ec9-XWfWjuyfadq2gpm97VcnByzM_lWg
A5: 44626.505 | B5: Jaspreet ji | D5: General | E5: Gemstone | F5: Misc | G5: 5000 | H5: Strings | J5: Shivani | K5: Shivani | L5: Old | M5: 44635 | N5: Later | Q5: https://docs.google.com/forms/d/e/1FAIpQLSeQ0wUAy9WJrwwZ_8x6kCxvJSihLYtbLF2nbMncVH08fybLWQ/viewform?edit2=2_ABaOnuef_QZ5PJqCr0A29KrVkoIpdtcp6RFnaomNPQxqa9dhkZAJyO8lFtRmuMfh2Yru4fY
A6: 44626.513 | B6: Nayaa | D6: General | E6: Solitaire | F6: Earring / Tops | G6: 800000 | J6: Saurav Sir | K6: Shivani | L6: Old | M6: 44635 | N6: This Month | Q6: https://docs.google.com/forms/d/e/1FAIpQLSeQ0wUAy9WJrwwZ_8x6kCxvJSihLYtbLF2nbMncVH08fybLWQ/viewform?edit2=2_ABaOnudv1eVSFQipyUBIKXWvcu6u4piRqVxPSAeLKoubF7n7aMVzCRm0IPuzhKWCHkLXvKA
A7: 44626.522 | B7: Kamal ji | D7: General | E7: Solitaire | F7: Gents Ring | G7: 100000 | J7: Sanjeev Sir | K7: Shivani | L7: Old | M7: 3/15/0022 | N7: This Month | Q7: https://docs.google.com/forms/d/e/1FAIpQLSeQ0wUAy9WJrwwZ_8x6kCxvJSihLYtbLF2nbMncVH08fybLWQ/viewform?edit2=2_ABaOnudmPtp-Yo7RJhF-TX7kjoSvgyWU41wdPmDThSvksNUM6S-QQGMiBZOiP6FluTV5ZtM
A8: 44626.523 | B8: Aditi ji | D8: General | E8: Gold Jewellery | F8: Chain | G8: 20000 | J8: Shivani | K8: Shivani | L8: Old | M8: 3/10/0022 | N8: This Month | Q8: https://docs.google.com/forms/d/e/1FAIpQLSeQ0wUAy9WJrwwZ_8x6kCxvJSihLYtbLF2nbMncVH08fybLWQ/viewform?edit2=2_ABaOnudCq-EU8GSLgt4-aW5ke8lVNZrfPZ2MVjHS6gbu6xW3APTVvBbmTKhyuTVo2QBWzf4
A9: 44626.526 | B9: Vineeta ji AV | D9: General | E9: Gold Jewellery | F9: Necklace Set | G9: Necklace Set | J9: Sanjeev Sir | K9: Shivani | L9: Old | M9: 3/30/0022 | N9: This Month | Q9: https://docs.google.com/forms/d/e/1FAIpQLSeQ0wUAy9WJrwwZ_8x6kCxvJSihLYtbLF2nbMncVH08fybLWQ/viewform?edit2=2_ABaOnud8T0R4en4Ba9JioWznv4aRt7hUzMQd9p6Lw2O9OW9GThL9t6GXSQiRVroTw_32_XI
A10: 44626.528 | B10: Nidhi ji weblink | D10: General | E10: Gold 24kt | F10: Misc | G10: 1000000 | J10: Shivani | K10: Shivani | L10: Old | M10: 3/30/0022 | N10: This Month | Q10: https://docs.google.com/forms/d/e/1FAIpQLSeQ0wUAy9WJrwwZ_8x6kCxvJSihLYtbLF2nbMncVH08fybLWQ/viewform?edit2=2_ABaOnufqNoSp79APZEidMKtRkuQ_OswUqDzptB_SiQZp02M3nUvbCPK3gCouTdmfqqy4S2g
A11: 44626.666 | B11: Pradeep Sachdeva ji | D11: General | E11: Gold Jewellery | F11: Gents Bracelet / Kada | G11: 250000 | J11: Saurav Sir | K11: Shivani | L11: Old | M11: 3/15/0022 | N11: This Month | Q11: https://docs.google.com/forms/d/e/1FAIpQLSeQ0wUAy9WJrwwZ_8x6kCxvJSihLYtbLF2nbMncVH08fybLWQ/viewform?edit2=2_ABaOnudO6Z8VUv-EFN6OXH8DD9GWjlu0VN93Iw7DGizr7gZGrUnvFNT3Lo8BFOY1y1sCJC8
A12: 44626.668 | B12: Shobha jo c o sheera | D12: General | E12: Diamond Jewellery, Gemstone | F12: Misc | G12: 50000 | J12: Pallavi | K12: Saarika | L12: Reference | M12: 3/15/0022 | N12: This Month | Q12: https://docs.google.com/forms/d/e/1FAIpQLSeQ0wUAy9WJrwwZ_8x6kCxvJSihLYtbLF2nbMncVH08fybLWQ/viewform?edit2=2_ABaOnufka6HO4xJFRWoKBT5oupkTDgJ0_tAP3liJJxf-1Q3aBJxx6CPMar2sL_sOu7sKMZ4
A13: 44626.669 | B13: Sareena ji | D13: Gifting | E13: Silver | F13: Misc | G13: 5000 | J13: Shivani | K13: Shivani | L13: Old | M13: 3/10/0022 | N13: This Week | Q13: https://docs.google.com/forms/d/e/1FAIpQLSeQ0wUAy9WJrwwZ_8x6kCxvJSihLYtbLF2nbMncVH08fybLWQ/viewform?edit2=2_ABaOnuc9erjsOwfkNDVTn8bOLGNIgcEAXBqlUi8-OIOD2_WGMpX_rWK3Bl6iKh_Hp6OSpNQ
A14: 44626.671 | B14: Mridu ji | D14: General | E14: Solitaire | F14: Bangle | G14: 5500000 | H14: .50 pointer bangles GHVS | J14: Shivani | K14: Shivani | L14: Reference | M14: 3/10/0022 | N14: This Week | Q14: https://docs.google.com/forms/d/e/1FAIpQLSeQ0wUAy9WJrwwZ_8x6kCxvJSihLYtbLF2nbMncVH08fybLWQ/viewform?edit2=2_ABaOnue8XevbleIOLV6Zvd2G37FlNxMZJOVw5Q8ZveOXrl-aDLrqeulbaZs0ZmX_O5OIZGA
A15: 44626.673 | B15: Sonali ji | D15: General | E15: Diamond Jewellery, Solitaire | F15: Solitaire | G15: 500000 | J15: Sanjeev Sir | K15: Shivani | L15: Old | M15: 3/10/0022 | N15: This Week | Q15: https://docs.google.com/forms/d/e/1FAIpQLSeQ0wUAy9WJrwwZ_8x6kCxvJSihLYtbLF2nbMncVH08fybLWQ/viewform?edit2=2_ABaOnufU10HXks4gtKyjw2PBrrIZ7bPmtUydfCqliHEmErlsazHoHwp9wwSAXEjdDzzgKt0
A16: 44628.493 | B16: Anuj ji | D16: General | E16: Diamond Jewellery | F16: Nosepin | G16: 100000 | J16: Shivani | K16: Shivani | L16: Old | M16: 3/10/0022 | N16: This Week | Q16: https://docs.google.com/forms/d/e/1FAIpQLSeQ0wUAy9WJrwwZ_8x6kCxvJSihLYtbLF2nbMncVH08fybLWQ/viewform?edit2=2_ABaOnufFH8SnKCuhonbjl2dCGvrCncAaPrAMZz7Cwjz2fpfcF0S4PLFCFSMPjINr9CpOZEA
A17: 44629.479 | B17: Sangeeta ji | D17: Gifting | E17: Silver | F17: Misc | J17: Saurav Sir | K17: Shivani | L17: Old | M17: 3/15/0022 | N17: This Month | Q17: https://docs.google.com/forms/d/e/1FAIpQLSeQ0wUAy9WJrwwZ_8x6kCxvJSihLYtbLF2nbMncVH08fybLWQ/viewform?edit2=2_ABaOnudtBKuQlAKSKmcGaH3jWqaYVTx86soVcJ-EDjo7hh0oWjmZe8C_usSNef6DiKAxzU4
A18: 44635.722 | B18: Sunny Anchal | C18: 9810265393 | D18: General | E18: Solitaire | F18: Solitaire | G18: 1500+ | H18: 4-5ct round range 25-30 | J18: Saurav Sir | K18: Saurav Sir | L18: Old | M18: 44637 | N18: This Month | Q18: https://docs.google.com/forms/d/e/1FAIpQLSeQ0wUAy9WJrwwZ_8x6kCxvJSihLYtbLF2nbMncVH08fybLWQ/viewform?edit2=2_ABaOnuc8H0F6VxAESAEYvHMp1DIAZ4L3BkNgLHEemRz_GT__2UHav6-PTcU8LU7zETkhmDE
A19: 44636.493 | B19: Arun gupta ji | D19: General | E19: Gold Jewellery, Solitaire | F19: Earring / Tops, Necklace Set | J19: Sanjeev Sir | K19: Shivani | L19: Old | M19: 3/15/0022 | N19: This Week | Q19: https://docs.google.com/forms/d/e/1FAIpQLSeQ0wUAy9WJrwwZ_8x6kCxvJSihLYtbLF2nbMncVH08fybLWQ/viewform?edit2=2_ABaOnuc82M0MnGYwWslEVOfcdsN9fr5i2iHOy1Vg5BSzzzZNOBVM6mo5NWyovhjnf581ZaM
A20: 44636.495 | B20: Vijay ji Amritsar | D20: General | E20: Gold Jewellery, Solitaire | F20: Necklace Set, Solitaire | J20: Sanjeev Sir | K20: Shivani | L20: Old | M20: 3/15/0022 | N20: This Week | Q20: https://docs.google.com/forms/d/e/1FAIpQLSeQ0wUAy9WJrwwZ_8x6kCxvJSihLYtbLF2nbMncVH08fybLWQ/viewform?edit2=2_ABaOnudShLJWg3dSuNxIAUAfVQg5mpuRyvp9QszOlmROUYtVrt0Z7XeejNh423tF1nY3m00
A21: 44636.498 | B21: Abhinav gupta | C21: 9711789059 | D21: General | E21: Diamond Jewellery | F21: Ladies Ring | H21: Fancy Big Ring | J21: Pallavi | K21: Shivani | L21: Old | M21: 3/13/0022 | N21: This Month | Q21: https://docs.google.com/forms/d/e/1FAIpQLSeQ0wUAy9WJrwwZ_8x6kCxvJSihLYtbLF2nbMncVH08fybLWQ/viewform?edit2=2_ABaOnueCDtj4VPxWl6VFbbL8jupX5CTCAq3hp2blVV3i0lZqeXRld_dACJd0YwZ0O_XHgf4
A22: 44636.502 | B22: Satish ji | D22: General | E22: Solitaire | F22: Solitaire Ring | H22: 3-4 ct solitaire | J22: Sanjeev Sir | K22: Shivani | L22: Old | M22: 3/15/0022 | N22: This Month | Q22: https://docs.google.com/forms/d/e/1FAIpQLSeQ0wUAy9WJrwwZ_8x6kCxvJSihLYtbLF2nbMncVH08fybLWQ/viewform?edit2=2_ABaOnudMErVkFq2TMTblXUutgWwRnbW51W7MmcFAuNsGDJggHzUzeZ9Q5ozmoHSxWQPghU0
A23: 44636.509 | B23: Rammo didi | D23: Gifting | E23: Silver | F23: Misc | G23: 5 | J23: Shivani | K23: Shivani | L23: Old | M23: 3/15/0022 | N23: This Week | Q23: https://docs.google.com/forms/d/e/1FAIpQLSeQ0wUAy9WJrwwZ_8x6kCxvJSihLYtbLF2nbMncVH08fybLWQ/viewform?edit2=2_ABaOnuc7VksDuY6bH1GiOtJuafk91fHnTLZbNeDer1y5iZE0qMwvKGgQ4FszCpiNUnpVoHU
A24: 44636.526 | B24: Ankur ji CL | D24: Kitty | E24: Kitty | F24: Misc | H24: 3 gram coin | J24: Saurav Sir | K24: Saurav Sir | L24: Old | M24: 3/15/0022 | N24: This Month | Q24: https://docs.google.com/forms/d/e/1FAIpQLSeQ0wUAy9WJrwwZ_8x6kCxvJSihLYtbLF2nbMncVH08fybLWQ/viewform?edit2=2_ABaOnueWqpAzFDX08CmCtPz3UajMCKOmKXkhTjvwT3fcj2mSr9Y7m4qgbEbKX8BAbngJjP0
A25: 44643.688 | B25: Khurana ji | D25: General | E25: Silver | F25: Necklace Set | J25: Saurav Sir | K25: Shivani | L25: Old | M25: 44651 | N25: This Month | Q25: https://docs.google.com/forms/d/e/1FAIpQLSeQ0wUAy9WJrwwZ_8x6kCxvJSihLYtbLF2nbMncVH08fybLWQ/viewform?edit2=2_ABaOnudqXjPiMidtiEFJ2dxQmsyOqCe9dLKDPDG-8gAPGNrtdRDmHbhY2kuwMmAfQma295Y
A26: 44643.69 | B26: Ritin ji | C26: 9829452525 | D26: General | E26: Solitaire | F26: Earring / Tops | H26: 1.00 ct | J26: Saurav Sir | K26: Shivani | L26: Old | M26: 44651 | N26: This Month | Q26: https://docs.google.com/forms/d/e/1FAIpQLSeQ0wUAy9WJrwwZ_8x6kCxvJSihLYtbLF2nbMncVH08fybLWQ/viewform?edit2=2_ABaOnudEjLWPj55sqw4qj9MSo0oSnsDAfSbr1FcOeLcek3NuRs97QRYY6fbUBT7Jx-e-MGk
A27: 44643.691 | B27: Gaurav ji | C27: 9111000111 | D27: General | E27: Gold Jewellery | F27: Bangle | J27: Saurav Sir | K27: Shivani | L27: Old | M27: 44651 | N27: This Month | Q27: https://docs.google.com/forms/d/e/1FAIpQLSeQ0wUAy9WJrwwZ_8x6kCxvJSihLYtbLF2nbMncVH08fybLWQ/viewform?edit2=2_ABaOnucoHthyvcR-P3HYtzl92jA-jLbUZQqHK-ItmgYLgblqCxKraEibhLfhj-a-YylMIyA
A28: 44643.692 | B28: Sonal ji | D28: General | E28: Polki | F28: Earring / Tops | J28: Saurav Sir | K28: Saarika | L28: Old | M28: 44651 | N28: This Month | Q28: https://docs.google.com/forms/d/e/1FAIpQLSeQ0wUAy9WJrwwZ_8x6kCxvJSihLYtbLF2nbMncVH08fybLWQ/viewform?edit2=2_ABaOnudr1wd2Oy_UwcNNtmZR39C_gvOynHV247G7KDhHidbM4KpshSiXAvZ5YV4AH7tRKD0
A29: 44643.693 | B29: Pradeep sachdeva ji | D29: General | E29: Gold Jewellery | F29: Bangle | G29: 1500+ | J29: Saurav Sir | K29: Shivani | L29: Old | M29: 44651 | N29: This Month | Q29: https://docs.google.com/forms/d/e/1FAIpQLSeQ0wUAy9WJrwwZ_8x6kCxvJSihLYtbLF2nbMncVH08fybLWQ/viewform?edit2=2_ABaOnucxMsYOIH4YXb0eCm2m7AsZ9eKd41wIuk-Q2xGOzjR5TxCBvtsErQgr1cRJGe1k2yQ
A30: 44645.583 | B30: Lalit Mehra | D30: General | E30: Gemstone | F30: Gemstone | H30: 3 ratti | J30: Sanjeev Sir | K30: Shivani | L30: Old | M30: 44651 | N30: This Month | Q30: https://docs.google.com/forms/d/e/1FAIpQLSeQ0wUAy9WJrwwZ_8x6kCxvJSihLYtbLF2nbMncVH08fybLWQ/viewform?edit2=2_ABaOnucnIl29Yt-KjOVJx1Zm8F4FQelnGgAaQmiA7aFQwOQXJoXyQKYSi614TFclx-3DQNU
A31: 44645.802 | B31: Shashi ji jaipur | C31: 9828158871 | D31: General | E31: Diamond Jewellery | F31: Chain, Necklace Set, Ladies Ring, Solitaire | G31: 750-1000 | J31: Saurav Sir | K31: Saarika | L31: Old | M31: 44645 | N31: This Week | Q31: https://docs.google.com/forms/d/e/1FAIpQLSeQ0wUAy9WJrwwZ_8x6kCxvJSihLYtbLF2nbMncVH08fybLWQ/viewform?edit2=2_ABaOnueNYsSlY2wMog1-GG65HFhU5AMIwkg5Hp4TC-v9PmSt1zQlOVPqOSNXp2Mf_sMQQvs
A32: 44678.492 | B32: Puneet jain | D32: Gifting | E32: Solitaire | F32: Solitaire | G32: 750-1000 | J32: Sanjeev Sir | K32: Shivani | L32: Reference | M32: 4/30/0022 | N32: This Month | Q32: https://docs.google.com/forms/d/e/1FAIpQLSeQ0wUAy9WJrwwZ_8x6kCxvJSihLYtbLF2nbMncVH08fybLWQ/viewform?edit2=2_ABaOnucI-EYKA4fkV_WpDA26gRHrI7jMBrinenkiDutZRc7MMU86r6-PynxqsR-IgKmKJrM
A33: 44678.493 | B33: Chattarpati ji | D33: General | E33: Gold Jewellery | F33: Bangle | J33: Sanjeev Sir | K33: Shivani | L33: Old | M33: 5/5/0022 | N33: This Month | Q33: https://docs.google.com/forms/d/e/1FAIpQLSeQ0wUAy9WJrwwZ_8x6kCxvJSihLYtbLF2nbMncVH08fybLWQ/viewform?edit2=2_ABaOnufdiLKHlsa4JX-pIMDN1cUruT4CFzoXu6IcRkTEAwgErnCkdJVWHCpQVglgdwnWdqk
A34: 44680.736 | B34: Shashikant ji | D34: General | E34: Diamond Jewellery, Solitaire | F34: Bangle, Solitaire | H34: FG VVS 17 pointer bangles And 1.60 + 1.60 each pc | J34: Saurav Sir | K34: Shivani | L34: Old | M34: 5/10/0022 | N34: This Month | Q34: https://docs.google.com/forms/d/e/1FAIpQLSeQ0wUAy9WJrwwZ_8x6kCxvJSihLYtbLF2nbMncVH08fybLWQ/viewform?edit2=2_ABaOnueEqk26LvFXb6hmACEYOGriy4YIWhJ3FO5zKzaWHv_izLdISNo-vWo9vi198828nbY
A35: 44680.738 | B35: Suchita ji | D35: General | E35: Diamond Jewellery, Gold Jewellery | F35: Earring / Tops | G35: 30-50 | J35: Shivani | K35: Shivani | L35: Old | M35: 5/5/0022 | N35: This Month | Q35: https://docs.google.com/forms/d/e/1FAIpQLSeQ0wUAy9WJrwwZ_8x6kCxvJSihLYtbLF2nbMncVH08fybLWQ/viewform?edit2=2_ABaOnuesfEGKeT2XLhNiIoCYgDbDHzygpNLvIKW1W8OEO-vpRD7L5gNUw7GuhDUiLSLYWUU
A36: 44680.739 | B36: Faridabad | D36: General | E36: Solitaire | F36: Bangle, Solitaire | H36: 10 ct pair and 7. 00 ct pc and 1.50 ct bangle | J36: Saurav Sir | K36: Saurav Sir | L36: Old | M36: 5/10/0022 | N36: This Month | Q36: https://docs.google.com/forms/d/e/1FAIpQLSeQ0wUAy9WJrwwZ_8x6kCxvJSihLYtbLF2nbMncVH08fybLWQ/viewform?edit2=2_ABaOnudDN-904Ec89OvdxY3kSI87iEcQB98sK4nGQ7MNv6WyVpxl2QNhilDeWHRG8hbwcHw
A37: 44681.558 | B37: Charu Ji | D37: Gifting | E37: Gold Jewellery | F37: Chain | G37: 30-50 | J37: Shivani | K37: Shivani | L37: Old | M37: 5/15/0022 | N37: This Month | Q37: https://docs.google.com/forms/d/e/1FAIpQLSeQ0wUAy9WJrwwZ_8x6kCxvJSihLYtbLF2nbMncVH08fybLWQ/viewform?edit2=2_ABaOnucrVgOYsiSTSx3QKmTsfSlXb-fIGGM7gWltOnyoYZ332XD_ozejrBIyFnYpU5AsQx8
A38: 44684.611 | B38: Sabina ji | D38: General | E38: Gold Jewellery | F38: Bangle | H38: Kundan bangle | J38: Saurav Sir | K38: Shivani | L38: Old | M38: 5/15/0022 | N38: This Month | Q38: https://docs.google.com/forms/d/e/1FAIpQLSeQ0wUAy9WJrwwZ_8x6kCxvJSihLYtbLF2nbMncVH08fybLWQ/viewform?edit2=2_ABaOnudkRctbvTuUNJzXs0QGFXMQiWq1TLuloQig-dzlKWx73qcvb_R37rW4HH4jHHdeOYk
A39: 44685.489 | B39: Sabina ji | D39: General | E39: Gold Jewellery, Solitaire | F39: Bangle, Solitaire | J39: Saurav Sir | K39: Saurav Sir | L39: Old | M39: 5/15/0022 | N39: This Month | Q39: https://docs.google.com/forms/d/e/1FAIpQLSeQ0wUAy9WJrwwZ_8x6kCxvJSihLYtbLF2nbMncVH08fybLWQ/viewform?edit2=2_ABaOnufp7FhY8NkWnbkd_YNcp4jE4izzEWlRMgkST4rUtdsYEQTJU1-rL2KQ9DOLct82E9k
A40: 44689.484 | B40: Anju Malik | D40: General | E40: Gold Jewellery | F40: Pendant Set | H40: 30-35 gms | J40: Radhu Mam | K40: Radhu Mam | L40: Old | M40: 5/15/0022 | N40: This Month | Q40: https://docs.google.com/forms/d/e/1FAIpQLSeQ0wUAy9WJrwwZ_8x6kCxvJSihLYtbLF2nbMncVH08fybLWQ/viewform?edit2=2_ABaOnucdwO_2WInpvPXQNqDyDTU2UV2av_Pz3BJlb-vXog78ecyx-dV1zmvOTmNSCcNyyDE
A41: 44694.487 | B41: Paras ji | D41: General | E41: Diamond Jewellery | F41: Bangle | J41: Saurav Sir | K41: Saurav Sir | L41: Old | M41: 5/30/0022 | N41: This Month | Q41: https://docs.google.com/forms/d/e/1FAIpQLSeQ0wUAy9WJrwwZ_8x6kCxvJSihLYtbLF2nbMncVH08fybLWQ/viewform?edit2=2_ABaOnucztBTwIn6dDTo6tfotFf36JavZmXcnamrLqzHsOjyHsvf831Gq2vVpi4obZTt_a7s
A42: 44694.489 | B42: Shashikant ji | D42: General | E42: Diamond Jewellery | F42: Necklace Set | G42: 2500+ | J42: Saurav Sir | K42: Shivani | L42: Old | M42: 5/30/0022 | N42: This Month | Q42: https://docs.google.com/forms/d/e/1FAIpQLSeQ0wUAy9WJrwwZ_8x6kCxvJSihLYtbLF2nbMncVH08fybLWQ/viewform?edit2=2_ABaOnuenTjVpOC82zh7Z-_pZHMug-dYdJCDqUmw1bZcepUuHmw_tYVrsL7NlfpuEdwO06jc
A43: 44694.49 | B43: Mukesh ji | D43: General | E43: Diamond Jewellery | F43: Bangle | J43: Saurav Sir | K43: Saurav Sir | L43: Old | M43: 5/30/0022 | N43: This Month | Q43: https://docs.google.com/forms/d/e/1FAIpQLSeQ0wUAy9WJrwwZ_8x6kCxvJSihLYtbLF2nbMncVH08fybLWQ/viewform?edit2=2_ABaOnufwQxJKLONjUaOfkcNp4xda32ZjyPDTqruNLebfZ9sQcCl3oddVCDdt75pjSWIUKrE
A44: 44709.649 | B44: Sandeep ji | D44: General | E44: Solitaire | F44: Solitaire | H44: 12-15 range | J44: Saurav Sir | K44: Saurav Sir | L44: Old | M44: 6/15/0022 | N44: This Month | Q44: https://docs.google.com/forms/d/e/1FAIpQLSeQ0wUAy9WJrwwZ_8x6kCxvJSihLYtbLF2nbMncVH08fybLWQ/viewform?edit2=2_ABaOnuekBr3x2DnkMbPkUH7oPv94IaWPbe0p1pNjayybS3fnRRL7dA3TrwWKoqOjnFZQozM
A45: 44710.513 | B45: Sumit ji | D45: General | E45: Gold Jewellery, Polki | F45: Necklace Set, Solitaire | J45: Saurav Sir | K45: Saurav Sir | L45: Old | M45: 5/15/0022 | N45: This Month | Q45: https://docs.google.com/forms/d/e/1FAIpQLSeQ0wUAy9WJrwwZ_8x6kCxvJSihLYtbLF2nbMncVH08fybLWQ/viewform?edit2=2_ABaOnuc5xirfqPFWvrU29ljPzyUmZua7FO715SULGwAZ2Wou5fgKnpP0NEZeUkujezlvAqM
A46: 44710.515 | B46: Priyanka Bansal | D46: General | E46: Solitaire | F46: Earring / Tops | J46: Saurav Sir | K46: Saurav Sir | L46: Old | M46: 5/15/0022 | N46: This Month | Q46: https://docs.google.com/forms/d/e/1FAIpQLSeQ0wUAy9WJrwwZ_8x6kCxvJSihLYtbLF2nbMncVH08fybLWQ/viewform?edit2=2_ABaOnud4N1vDaAU_nejdiYG5HQrTPUcvBki3J_Kqi2UNCTbAKzZFWaFpHFupcOYlzSZcBAI
A47: 44720.52 | B47: Manisha hi Amritsar | D47: General | E47: Diamond Jewellery, Solitaire | F47: Necklace Set, Solitaire | J47: Sanjeev Sir | K47: Shivani | L47: Old | M47: 6/20/0022 | N47: This Month | Q47: https://docs.google.com/forms/d/e/1FAIpQLSeQ0wUAy9WJrwwZ_8x6kCxvJSihLYtbLF2nbMncVH08fybLWQ/viewform?edit2=2_ABaOnue2HXNXeRg2tvKeKs8UkfaJWR7TmEOCf3qFsLDUc6aJudYSfVSI_Rfu3OAvujIBuRY
A48: 44720.524 | B48: Shiv ji | D48: General | E48: Solitaire, Gemstone | F48: Solitaire Ring | J48: Sanjeev Sir | K48: Shivani | L48: New Walkin | M48: 6/8/0022 | N48: This Month | Q48: https://docs.google.com/forms/d/e/1FAIpQLSeQ0wUAy9WJrwwZ_8x6kCxvJSihLYtbLF2nbMncVH08fybLWQ/viewform?edit2=2_ABaOnueHAq57_Vr8j_nsxWqPxXZgsqW0E_nHdcxrExw5EFDR5w8R-hR2wmuvOEuLE_LeN40
A49: 44720.525 | B49: Arvind ji DIL | D49: General | E49: Diamond Jewellery | F49: Pendant | G49: 50-100 | J49: Shivani | K49: Shivani | L49: Old | M49: 8/6/0022 | N49: This Month | Q49: https://docs.google.com/forms/d/e/1FAIpQLSeQ0wUAy9WJrwwZ_8x6kCxvJSihLYtbLF2nbMncVH08fybLWQ/viewform?edit2=2_ABaOnuewRcH5_Sq0vFDU1LrP-F24hqTqjiE_9PSKfy9Oug_mGlDaU-RIcwUV0VU-ohCeKg8
A50: 44720.526 | B50: Vimmi ji | D50: General | E50: Diamond Jewellery | F50: Ladies Ring | G50: 30-50 | J50: Seema Mam | K50: Saarika | L50: Old | M50: 6/8/0022 | N50: This Month | Q50: https://docs.google.com/forms/d/e/1FAIpQLSeQ0wUAy9WJrwwZ_8x6kCxvJSihLYtbLF2nbMncVH08fybLWQ/viewform?edit2=2_ABaOnueGGLFx9V4Gx0DpENMt8Th21toqJ1YovxKQ18-OOGYYrKKxVVw82EiP5nmkg37fVUU
A51: 44722.536 | B51: Vimmi ji | D51: General | E51: Diamond Jewellery | F51: Ladies Ring, Misc | H51: Watch | J51: Seema Mam | K51: Shivani | L51: Old | M51: 6/20/0022 | N51: This Month | Q51: https://docs.google.com/forms/d/e/1FAIpQLSeQ0wUAy9WJrwwZ_8x6kCxvJSihLYtbLF2nbMncVH08fybLWQ/viewform?edit2=2_ABaOnucJcmfqLAilAzXPphxXfO1hCtJb9WrmOscpOUMV7MQ4Ir9sOUrrDu8uKBKdRZDtF28
A52: 44726.542 | B52: Kavita Nagpal | D52: General | E52: Silver | F52: Misc | G52: 15-30 | H52: Kids | J52: Saurav Sir | K52: Shivani | L52: Old | M52: 6/20/0022 | N52: This Month | Q52: https://docs.google.com/forms/d/e/1FAIpQLSeQ0wUAy9WJrwwZ_8x6kCxvJSihLYtbLF2nbMncVH08fybLWQ/viewform?edit2=2_ABaOnudwj9F9eTBuvoCaans65qHrOuXW7_b09YoMtm9WnUQjPRrYXKwply_aNo7ZsNbaPdc
A53: 44727.528 | B53: sangeeta ji | C53: 9971091907 | D53: Gifting | E53: Silver | F53: Misc | G53: 5 | H53: ganesha in silver | J53: Saurav Sir | K53: Shivani | L53: Old | M53: 44728 | N53: This Week | Q53: https://docs.google.com/forms/d/e/1FAIpQLSeQ0wUAy9WJrwwZ_8x6kCxvJSihLYtbLF2nbMncVH08fybLWQ/viewform?edit2=2_ABaOnueXXQC-EIep8m2CTGpiJsibQDMYoVhHd73Ftwe3CYBC6o_sjone9xdZm9-3IPF_GX8
A54: 44727.568 | B54: vir jewellers | C54: 8800000000 | D54: General | E54: Gold Jewellery | F54: Bangle | H54: 6 pc sets 55-75 gms | J54: Saurav Sir | K54: Shivani | L54: Old | M54: 44727 | N54: This Week | Q54: https://docs.google.com/forms/d/e/1FAIpQLSeQ0wUAy9WJrwwZ_8x6kCxvJSihLYtbLF2nbMncVH08fybLWQ/viewform?edit2=2_ABaOnueCDvbuQSZuWXxwL05GyyJmu0gB-5G9IAhAXJnmcH3YNDT6IusNm6tpVvRq5B-DO-0
A55: 44728.739 | B55: Test | C55: 25363329 | D55: General | E55: Silver | F55: Chain | G55: 10-15 | H55: Test | J55: Shivani | K55: Saarika | L55: Reference | M55: 44728 | N55: 3 Months | O55: Test | Q55: https://docs.google.com/forms/d/e/1FAIpQLSeQ0wUAy9WJrwwZ_8x6kCxvJSihLYtbLF2nbMncVH08fybLWQ/viewform?edit2=2_ABaOnueJH3gp5NrYkKl4qEpBn3jiw4qrafEORyapbXP1pUIDz7z33Z8Cg524A7TVVcEwwEA
A56: 44730.703 | B56: Rubina ji | D56: General | E56: Diamond Jewellery | F56: Ladies Ring | G56: 50-100 | J56: Saurav Sir | K56: Shivani | L56: Old | M56: 6/16/0022 | N56: This Month | Q56: https://docs.google.com/forms/d/e/1FAIpQLSeQ0wUAy9WJrwwZ_8x6kCxvJSihLYtbLF2nbMncVH08fybLWQ/viewform?edit2=2_ABaOnudixqiDMKbIIxSMNOx02of6mQQqJc3LzLxBayhE8sVWGrxllOgtgzW9oAwnzMhg6DA
A57: 44730.706 | B57: Shashikant ji | D57: General | E57: Diamond Jewellery | F57: Ladies Ring | G57: 15-30 | J57: Saurav Sir | K57: Shivani | L57: Old | M57: 6/16/0022 | N57: This Month | Q57: https://docs.google.com/forms/d/e/1FAIpQLSeQ0wUAy9WJrwwZ_8x6kCxvJSihLYtbLF2nbMncVH08fybLWQ/viewform?edit2=2_ABaOnufppoDW79Y2Ztnjio6gk7O-unhOkYhBTp9IJYBTVF3S1u0oa2W3XvS1ZOm32KQtngs
A58: 44730.707 | B58: Deepak ji BNI | D58: General | E58: Diamond Jewellery | F58: Necklace Set | H58: South Sea pearl Mala | J58: Sanjeev Sir | K58: Shivani | L58: Old | M58: 6/16/0022 | N58: This Month | Q58: https://docs.google.com/forms/d/e/1FAIpQLSeQ0wUAy9WJrwwZ_8x6kCxvJSihLYtbLF2nbMncVH08fybLWQ/viewform?edit2=2_ABaOnucwdv8sDFeCZfo1jIfLsUMO3m32Thufgo7c66CnCuLhoEL1eYbUGCLo7Pqethlr5VQ
A59: 44730.709 | B59: Tanvi ji | D59: General | E59: Gemstone | F59: Misc | H59: Pink quarts | J59: Saurav Sir | K59: Shivani | L59: Old | M59: 6/16/0022 | N59: This Month | Q59: https://docs.google.com/forms/d/e/1FAIpQLSeQ0wUAy9WJrwwZ_8x6kCxvJSihLYtbLF2nbMncVH08fybLWQ/viewform?edit2=2_ABaOnuev3crQ1E6ptoqBEFO-Xfy1myMz00oXtL0pjdFokVqaBde93XpfPNeWNly6A1nR1Eg
A60: 44730.711 | B60: Jatin Nagpal | D60: General | E60: Silver | F60: Misc | G60: 15-30 | J60: Saurav Sir | K60: Shivani | L60: Old | M60: 6/14/0022 | N60: This Month | Q60: https://docs.google.com/forms/d/e/1FAIpQLSeQ0wUAy9WJrwwZ_8x6kCxvJSihLYtbLF2nbMncVH08fybLWQ/viewform?edit2=2_ABaOnudYFoPJiInv5VM3YTEbychqrusVSLpYAPh7zjXmjxvpTLAxkwoB7Tv9_nF7cmCG8zU
A61: 44730.715 | B61: Ashish ji | D61: General | E61: Solitaire | F61: Solitaire | H61: 2.00 ct /200-250 ct P ct /2.50-3.00 ct HVS | J61: Saurav Sir | K61: Shivani | L61: Old | M61: 6/16/0022 | N61: This Month | Q61: https://docs.google.com/forms/d/e/1FAIpQLSeQ0wUAy9WJrwwZ_8x6kCxvJSihLYtbLF2nbMncVH08fybLWQ/viewform?edit2=2_ABaOnufBy56bBzP1lEsgrQo3Lrwqriy11TntP8c8l3fqJTcC-ZKfvEVCtTlBEbjGEivnN28
A62: 44733.552 | B62: Sunaina ji | D62: Gifting | E62: Diamond Jewellery | F62: Earring / Tops | G62: 30-50 | H62: Kids | J62: Sanjeev Sir | K62: Shivani | L62: Old | M62: 6/21/0022 | N62: This Month | Q62: https://docs.google.com/forms/d/e/1FAIpQLSeQ0wUAy9WJrwwZ_8x6kCxvJSihLYtbLF2nbMncVH08fybLWQ/viewform?edit2=2_ABaOnuehPa8wZR4ifFfsalobqi5pRl7-iMFixGGrAtePUIhK7EDtDM_hwXIXlc8VG5MLVAw
A63: 44741.75 | B63: deepak ji | D63: General | E63: Gemstone | F63: Gemstone | J63: Saurav Sir | K63: Saurav Sir | L63: Old | M63: 44688 | N63: This Month | Q63: https://docs.google.com/forms/d/e/1FAIpQLSeQ0wUAy9WJrwwZ_8x6kCxvJSihLYtbLF2nbMncVH08fybLWQ/viewform?edit2=2_ABaOnudr31xJtSPGrx3pcTCN2ESz50fp6y7IUcd3OmTgRCcJkVfDK16Hmatr4xYCjdIm9tM
A64: 44741.752 | B64: yogesh ji | D64: General | E64: Gold Jewellery | F64: Earring / Tops | J64: Saurav Sir | K64: Saurav Sir | L64: Old | M64: 44749 | N64: This Week | Q64: https://docs.google.com/forms/d/e/1FAIpQLSeQ0wUAy9WJrwwZ_8x6kCxvJSihLYtbLF2nbMncVH08fybLWQ/viewform?edit2=2_ABaOnucNVr43RZWnWkfLpp8oFMW7q8R6iqPpBxhNVFY6LC3_QiPRGekyDlEEEK_QJM3AT5Q
A65: 44743.573 | B65: Arvind ji | D65: General | E65: Gold Jewellery | F65: Chain | J65: Sanjeev Sir | K65: Shivani | L65: Old | M65: 7/1/0022 | N65: This Month | Q65: https://docs.google.com/forms/d/e/1FAIpQLSeQ0wUAy9WJrwwZ_8x6kCxvJSihLYtbLF2nbMncVH08fybLWQ/viewform?edit2=2_ABaOnucIVteNQbjd6_SeiGXtAjV5Hiq_o9Q2VqAitcOnwktg0isvOkOp_giUvi0N5zorZlw
A66: 44743.672 | B66: Bina rawal ji | D66: General | E66: Gold Jewellery | F66: Bangle | J66: Shivani | K66: Shivani | L66: Old | M66: 7/1/0022 | N66: This Month | Q66: https://docs.google.com/forms/d/e/1FAIpQLSeQ0wUAy9WJrwwZ_8x6kCxvJSihLYtbLF2nbMncVH08fybLWQ/viewform?edit2=2_ABaOnuf4UNJvSsKaoekH2uosC8ek08WinWlYScQ21gsow7z6ettrdH0V8J29R6XQkp-YF68
A67: 44744.651 | B67: Chawla hi DMN | D67: General | E67: Gold Jewellery | F67: Bangle | H67: Single pc 30 gm | J67: Shivani | K67: Shivani | L67: Old | M67: 7/30/0022 | N67: This Month | Q67: https://docs.google.com/forms/d/e/1FAIpQLSeQ0wUAy9WJrwwZ_8x6kCxvJSihLYtbLF2nbMncVH08fybLWQ/viewform?edit2=2_ABaOnuf67xZ1vi03t9dC9odu4-3jrUM8mdzNHrBiEIUtYwRWc0EhIu1m1szBMsYslAUev8o
A68: 44745.766 | B68: Ritu Ji K-17 | D68: General | E68: Diamond Jewellery | F68: Necklace Set | G68: 2500+ | H68: 400-500 range | J68: Shivani | K68: Shivani | L68: Old | M68: 7/30/0022 | N68: 3 Months | Q68: https://docs.google.com/forms/d/e/1FAIpQLSeQ0wUAy9WJrwwZ_8x6kCxvJSihLYtbLF2nbMncVH08fybLWQ/viewform?edit2=2_ABaOnudRlGtqLl4Y0n0Ak_-kpOvgL76wQdUbz8xqT_-iuT46Q-QfmTkB3C9EIYO2knL-qqo
A69: 44747.525 | B69: Sara | D69: General | E69: Gold Jewellery | F69: Chain | H69: Waaris Sara Siddharth | J69: Saurav Sir | K69: Shivani | L69: Old | M69: 5/15/0022 | N69: This Month | Q69: https://docs.google.com/forms/d/e/1FAIpQLSeQ0wUAy9WJrwwZ_8x6kCxvJSihLYtbLF2nbMncVH08fybLWQ/viewform?edit2=2_ABaOnuem1uJIuYCggWgMtfSbXWS7PMp0wZDtubPdzeXdVQAF_crqzZaTdrm1Jv00b3hHFBo
A70: 44752.564 | B70: Chattarpati ji | D70: General | E70: Solitaire | F70: Solitaire | H70: 5.00 ct HIVS | J70: Sanjeev Sir | K70: Shivani | L70: Old | M70: 7/25/0022 | N70: This Month | Q70: https://docs.google.com/forms/d/e/1FAIpQLSeQ0wUAy9WJrwwZ_8x6kCxvJSihLYtbLF2nbMncVH08fybLWQ/viewform?edit2=2_ABaOnufqCmmg8tsnGLCcYKDdB8ugolwhWd3wacK0lW0NMVEZKqmgqmDhrg3H2nhiVn-8PkM
A71: 44754.547 | B71: Anita Ji Toronto | D71: General | E71: Gold Jewellery | F71: Misc | H71: Kids | J71: Sanjeev Sir | K71: Shivani | L71: Old | M71: 7/20/0022 | N71: This Month | Q71: https://docs.google.com/forms/d/e/1FAIpQLSeQ0wUAy9WJrwwZ_8x6kCxvJSihLYtbLF2nbMncVH08fybLWQ/viewform?edit2=2_ABaOnud_TvJb5VKGIL8XOr26dxI9M63ZCTna0EN0V4GyRIs6sCQ-ae9dmzTBZqwQZ2Y2mHk
A72: 44754.583 | B72: Sardar ji | D72: General | E72: Diamond Jewellery | F72: Bangle | H72: Single line .15 pointer | J72: Sanjeev Sir | K72: Shivani | L72: Old | M72: 7/20/0022 | N72: This Month | Q72: https://docs.google.com/forms/d/e/1FAIpQLSeQ0wUAy9WJrwwZ_8x6kCxvJSihLYtbLF2nbMncVH08fybLWQ/viewform?edit2=2_ABaOnucRf4JPuU4mjP3zE9gpZPRNmC0wVUU2frxrwgHdt68xcOOzBJMs8npQeWE9A7vX_pU
A73: 44754.584 | B73: Arvind hi DIL | D73: General | E73: Diamond Jewellery | F73: Pendant | G73: 50-100 | J73: Shivani | K73: Shivani | L73: Old | M73: 7/30/0022 | N73: This Month | Q73: https://docs.google.com/forms/d/e/1FAIpQLSeQ0wUAy9WJrwwZ_8x6kCxvJSihLYtbLF2nbMncVH08fybLWQ/viewform?edit2=2_ABaOnuc6Njlfl-h5tpmgSa-o6UeWLdDPkqu8U-sJfb3dJIP7GuGRALnHfdUg5MNHhr9_sXo
A74: 44754.612 | B74: RTY Gaurav ji | D74: General | E74: Diamond Jewellery | F74: Ladies Ring | G74: 30-50 | J74: Saurav Sir | K74: Shivani | L74: Old | M74: 7/12/0022 | N74: This Week | Q74: https://docs.google.com/forms/d/e/1FAIpQLSeQ0wUAy9WJrwwZ_8x6kCxvJSihLYtbLF2nbMncVH08fybLWQ/viewform?edit2=2_ABaOnueY-ZPHdq_39gaSxWTabv39DbvcT5Q2bNMTGGnpKmX0yZj-lgpWdC6Yy3eQy0SnYhE
A75: 44755.683 | B75: Snowee | D75: General | E75: Solitaire | F75: Solitaire | H75: 2-2.25 ct | J75: Sanjeev Sir | K75: Shivani | L75: Old | M75: 7/20/0022 | N75: This Month | Q75: https://docs.google.com/forms/d/e/1FAIpQLSeQ0wUAy9WJrwwZ_8x6kCxvJSihLYtbLF2nbMncVH08fybLWQ/viewform?edit2=2_ABaOnuex7uxCm4emqiSmjAHbOqnNgzztr7qh8H9V2wrSTC84wHokPQnzIXh4X-pLyIwuZFA
A76: 44757.521 | B76: Mridul ji | D76: General | E76: Gold Jewellery | F76: Chain | G76: 100-250 | H76: Gents chain 28 gm length 28 inch | J76: Saurav Sir | K76: Saurav Sir | L76: Old | M76: 7/15/0022 | N76: This Month | Q76: https://docs.google.com/forms/d/e/1FAIpQLSeQ0wUAy9WJrwwZ_8x6kCxvJSihLYtbLF2nbMncVH08fybLWQ/viewform?edit2=2_ABaOnudl4xnFgQfEn-Y3HKIH7D99D8u2anZsuXnUn0JrEFWTml6Mkt6Nh7H0gvOqPTmQvAQ
A77: 44758.594 | B77: Saloni ji | D77: General | E77: Diamond Jewellery | F77: Ladies Bracelet / Kada | H77: Cartier mail design | J77: Saurav Sir | K77: Saurav Sir | L77: Old | M77: 7/16/0022 | N77: This Month | Q77: https://docs.google.com/forms/d/e/1FAIpQLSeQ0wUAy9WJrwwZ_8x6kCxvJSihLYtbLF2nbMncVH08fybLWQ/viewform?edit2=2_ABaOnucsNSS1Ktv01vO5qm7x9iLN_jz8ycl52x2yU-vjT9F26lU5Jb-OLs7YSp0_wenI-xs
A78: 44761.516 | B78: USA | D78: General | E78: Solitaire | F78: Solitaire | H78: 1.5 to 2 ct HVSSI | J78: Sanjeev Sir | K78: Shivani | L78: Old | M78: 7/25/0022 | N78: This Month | Q78: https://docs.google.com/forms/d/e/1FAIpQLSeQ0wUAy9WJrwwZ_8x6kCxvJSihLYtbLF2nbMncVH08fybLWQ/viewform?edit2=2_ABaOnucuDDlzFM7duzQUw5JO-u0jWCg5ku2n8gftuX8b_7mXpq6S7kEcd9Mc1v3pst68XSE
A79: 44763.506 | B79: Jyoti bajaj ji | D79: General | E79: Gold 24kt | F79: Ginni 4/8 gm | G79: 30-50 | J79: Saurav Sir | K79: Shivani | L79: Old | M79: 7/21/0022 | N79: This Week | Q79: https://docs.google.com/forms/d/e/1FAIpQLSeQ0wUAy9WJrwwZ_8x6kCxvJSihLYtbLF2nbMncVH08fybLWQ/viewform?edit2=2_ABaOnufY_ZiBqGsfqx9TU-TSRT9WhMyBOVxWsfFmpTJbFzA6JJuhAgo4P_QNtmfpavutR8M
A80: 44764.508 | B80: Vishnu ji | D80: General | E80: Gold Jewellery | F80: Chain | G80: 100-250 | J80: Shivani | K80: Shivani | L80: Old | M80: 7/22/0022 | N80: This Month | Q80: https://docs.google.com/forms/d/e/1FAIpQLSeQ0wUAy9WJrwwZ_8x6kCxvJSihLYtbLF2nbMncVH08fybLWQ/viewform?edit2=2_ABaOnucdZ3896fdERO0PufpVs-P-H2sPa9CMac0AxSBgmQj3CdNyWwqFOW613Kf0SHS-VLM
A81: 44766.629 | B81: Rajni bhabhi ji | D81: General | E81: Diamond Jewellery, Solitaire | F81: Necklace Set, Bangle, Solitaire, 5 ct pc IVS2-SI2/2+2 ct pair single line Bng 1 ct size fancy sets | J81: Saurav Sir | K81: Saurav Sir | L81: Old | M81: 7/30/0022 | N81: This Month | Q81: https://docs.google.com/forms/d/e/1FAIpQLSeQ0wUAy9WJrwwZ_8x6kCxvJSihLYtbLF2nbMncVH08fybLWQ/viewform?edit2=2_ABaOnucJM5cURV3e6sBpZ0_-XJq3pepSYucFCX9YR7KAmVvJAcwfae8HbVOv2xruJ_GbcI8
A82: 44768.49 | B82: Pooja hi noida | D82: General | E82: Diamond Jewellery | F82: Band | G82: 50-100 | H82: .10/.15 pointer | J82: Shivani | K82: Shivani | L82: Old | M82: 7/30/0022 | N82: This Month | Q82: https://docs.google.com/forms/d/e/1FAIpQLSeQ0wUAy9WJrwwZ_8x6kCxvJSihLYtbLF2nbMncVH08fybLWQ/viewform?edit2=2_ABaOnufvO6pp_Ca2DJZ9en1OEYYUVe_sdXotbIL9drtBj-78xGLHTIPWtOSmfi9SQhvY8EY
A83: 44768.491 | B83: Shama Ji k-17 | D83: General | E83: Gold Jewellery | F83: Chain, Necklace Set | G83: 2500+ | J83: Sanjeev Sir | K83: Sanjeev Sir | L83: Old | M83: 7/26/0022 | N83: 3 Months | Q83: https://docs.google.com/forms/d/e/1FAIpQLSeQ0wUAy9WJrwwZ_8x6kCxvJSihLYtbLF2nbMncVH08fybLWQ/viewform?edit2=2_ABaOnudPb2x2deTKMc-uzTBwrcvrRMSpFXwAYMYOdXUSOsyBXMyTb9WorhDYnaDR4uherwU
A84: 44769.722 | B84: Kunal ji | D84: General | E84: Solitaire | F84: Solitaire | G84: 2500+ | H84: 1.50 ct EFF VVS | J84: Saurav Sir | K84: Saurav Sir | L84: Old | M84: 7/27/0022 | N84: This Month | Q84: https://docs.google.com/forms/d/e/1FAIpQLSeQ0wUAy9WJrwwZ_8x6kCxvJSihLYtbLF2nbMncVH08fybLWQ/viewform?edit2=2_ABaOnudh7grK8QBFjlgk32PAxaUOkNBwRtrssLGVOGPz40tcandwBZ5ZP59Z5MgsDoUmOug
A85: 44770.698 | B85: Shilpa Singhania | D85: General | E85: Gold Jewellery | F85: Chain, Ladies Bracelet / Kada, Italian | G85: 30-50 | J85: Sanjeev Sir | K85: Shivani | L85: Old | M85: 7/28/0022 | N85: This Month | Q85: https://docs.google.com/forms/d/e/1FAIpQLSeQ0wUAy9WJrwwZ_8x6kCxvJSihLYtbLF2nbMncVH08fybLWQ/viewform?edit2=2_ABaOnue1XStlNbJaUEeBFMyBMSBfLgSyMBOgOuin7GwkNV461oJ93q_DmJC02Pdn_xbvWEc
A86: 44776.699 | B86: PARDEEP | C86: 98103 35225 | D86: General | E86: Polki | F86: Necklace Set | G86: 2500+ | H86: TYAANI SET IS RANGE OF 2.5 LAC | J86: Saurav Sir | K86: Kajal | L86: Old | M86: 44790 | N86: This Month | Q86: https://docs.google.com/forms/d/e/1FAIpQLSeQ0wUAy9WJrwwZ_8x6kCxvJSihLYtbLF2nbMncVH08fybLWQ/viewform?edit2=2_ABaOnufxPy1fjLeYOUQS918bPPO57WgXghTLvfYwywDztJpM_hkWdDzkEOMwQ0RNEpGBrpg
A87: 44776.703 | B87: RAJNIJI civil lines | D87: Wedding | E87: Diamond Jewellery, Polki, Solitaire | F87: Chain, Necklace Set, Pendant Set, Solitaire Ring, Solitaire | H87: earring pair 2+2 or 3+3 cts, gents ring round or prncess 2.5-3 cts, tayani polki giftng pendant sets 1.5 lac * 5, Italian 3 layr chain, DIa choker with emerald 35-40 range | J87: Saurav Sir | K87: Saurav Sir | L87: Old | M87: 44790 | N87: This Month | Q87: https://docs.google.com/forms/d/e/1FAIpQLSeQ0wUAy9WJrwwZ_8x6kCxvJSihLYtbLF2nbMncVH08fybLWQ/viewform?edit2=2_ABaOnuc5grXEy1aMljF-kTXOIlMDGPKarktEo0T3SIRIISBTorRbfIK4hC3BZZo9sdtV-Ss
A88: 44779.554 | B88: Mrs Kapilla ji | D88: General | E88: Polki | F88: Necklace Set | H88: Sat lara | J88: Sanjeev Sir | K88: Sanjeev Sir | L88: Old | M88: 8/25/0022 | N88: This Month | Q88: https://docs.google.com/forms/d/e/1FAIpQLSeQ0wUAy9WJrwwZ_8x6kCxvJSihLYtbLF2nbMncVH08fybLWQ/viewform?edit2=2_ABaOnue-o1TymOrHfDlDajZVIs7Bt3xNuCXP_bz-11665QWvyTmDSpypmZ9ai3g3n9crzwA
A89: 44783.662 | B89: Kaish Ali Siddique | C89: 9953023858 | D89: Wedding | E89: Diamond Jewellery | F89: Ladies Ring, Gents Ring | H89: DIAMOND RING | J89: Kajal | K89: Kajal | L89: New Walkin | M89: 44783 | N89: This Month | Q89: https://docs.google.com/forms/d/e/1FAIpQLSeQ0wUAy9WJrwwZ_8x6kCxvJSihLYtbLF2nbMncVH08fybLWQ/viewform?edit2=2_ABaOnudJ_0a0L6flN6aGFR0bB3VACoKBjgHkT2lTt3Tq3touboAZfbDKIF6MJJVb2Oz5qcY
A90: 44785.588 | B90: Nidhi ji Dwarka | D90: General | E90: Diamond Jewellery, Gemstone | F90: Earring / Tops | G90: 30-50 | H90: Opal 7 Ratti | J90: Shivani | K90: Shivani | L90: Old | M90: 8/20/0022 | N90: This Month | Q90: https://docs.google.com/forms/d/e/1FAIpQLSeQ0wUAy9WJrwwZ_8x6kCxvJSihLYtbLF2nbMncVH08fybLWQ/viewform?edit2=2_ABaOnueMv81dXmOuX-Es00OYtqMPMbTP7c52G9UNsK2cfHn97_f75GglKqr5_oCIr1bR4Lw
A91: 44786.788 | B91: MONTY | C91: 9999776364 | D91: General | E91: Gold Jewellery | F91: Bangle | G91: 5 | J91: Kajal | K91: Kajal | L91: New Walkin | M91: 44787 | N91: This Week | Q91: https://docs.google.com/forms/d/e/1FAIpQLSeQ0wUAy9WJrwwZ_8x6kCxvJSihLYtbLF2nbMncVH08fybLWQ/viewform?edit2=2_ABaOnufQeLyHbYj13V1rpFIM45kt1He0gbCXbzXPKo275SZvc4liZwhjZiDSCciQt331sCs
A92: 44790.471 | B92: Mrs Aggarwal | D92: General | E92: Solitaire | F92: Earring / Tops | H92: 6 ct pair | J92: Sanjeev Sir | K92: Sanjeev Sir | L92: Old | M92: 8/17/0022 | N92: This Month | Q92: https://docs.google.com/forms/d/e/1FAIpQLSeQ0wUAy9WJrwwZ_8x6kCxvJSihLYtbLF2nbMncVH08fybLWQ/viewform?edit2=2_ABaOnucYNn_yukr-FmLlcxxJIP90ay4iVliZHREHzLCMImHdOGr_9zTw3JE8MscSkfJnZQM
A93: 44793.512 | B93: somna | D93: Gifting | E93: Solitaire | F93: Ladies Bracelet / Kada | G93: 10-15 | J93: Saurav Sir | K93: Saurav Sir | L93: Old | M93: 44796 | N93: This Week | Q93: https://docs.google.com/forms/d/e/1FAIpQLSeQ0wUAy9WJrwwZ_8x6kCxvJSihLYtbLF2nbMncVH08fybLWQ/viewform?edit2=2_ABaOnufZ4fxOpmuGehXs6ASpqdEDXbDIvpZ6EA5bJ7_Y7KWGrhKoQBZ2NrXxbhoBf5TPCxQ
A94: 44793.582 | B94: manish ji | C94: 9811016739 | D94: General | E94: Gold Jewellery | F94: Bangle, Ladies Ring | G94: 5 | J94: Saurav Sir | K94: Saurav Sir | L94: Old | M94: 44796 | N94: This Month | Q94: https://docs.google.com/forms/d/e/1FAIpQLSeQ0wUAy9WJrwwZ_8x6kCxvJSihLYtbLF2nbMncVH08fybLWQ/viewform?edit2=2_ABaOnud3ShlyaXKC2KgLJEWb73m22yu5uBr3vBpNiYkuoxcSmGE4NVg7NbI2d5rZiGcrhS0
A95: 44793.585 | B95: Bal krishna | C95: 9911088852 | D95: General | E95: Diamond Jewellery | F95: diamond pair | G95: 5 | J95: Saurav Sir | K95: Saurav Sir | L95: Old | M95: 44796 | N95: This Month | Q95: https://docs.google.com/forms/d/e/1FAIpQLSeQ0wUAy9WJrwwZ_8x6kCxvJSihLYtbLF2nbMncVH08fybLWQ/viewform?edit2=2_ABaOnudG61Qy54MgPehkrALosAoknqmiKULzLfliMZlepUv5kRP7npXjldIdpVF6lZvIvLc
A96: 44793.597 | B96: shikha | C96: 9782015737 | D96: General | E96: Diamond Jewellery, Gemstone | F96: Ladies Bracelet / Kada | G96: 5 | J96: Saurav Sir | K96: Saurav Sir | L96: Old | M96: 44798 | N96: This Month | Q96: https://docs.google.com/forms/d/e/1FAIpQLSeQ0wUAy9WJrwwZ_8x6kCxvJSihLYtbLF2nbMncVH08fybLWQ/viewform?edit2=2_ABaOnuff68Knt67AfHEMl3ahzzt4RQGoO6DBzx0AwdKMonFLc9HjD8eAPOgQmqdwwlRLsTo
A97: 44794.452 | B97: mukesh | C97: 9910225010 | D97: General | E97: Gold Jewellery, Kitty | F97: kitty | G97: 5 | J97: Saurav Sir | K97: Saurav Sir | L97: Old | M97: 44794 | N97: This Month | Q97: https://docs.google.com/forms/d/e/1FAIpQLSeQ0wUAy9WJrwwZ_8x6kCxvJSihLYtbLF2nbMncVH08fybLWQ/viewform?edit2=2_ABaOnudWrFMJHp2J2_gi_gce8kaY9tgaTjD363wssIlFg3BCRKZlkL_weU6TAeflNKmnJWQ
A98: 44799.517 | B98: RISHIKA | C98: 9797872525 | D98: Gifting | E98: Silver | F98: Ladies Bracelet / Kada, LORD DURGA AND LORD GANESHA | G98: 5 | J98: Saurav Sir | K98: Saurav Sir | L98: Old | M98: 44804 | N98: This Month | Q98: https://docs.google.com/forms/d/e/1FAIpQLSeQ0wUAy9WJrwwZ_8x6kCxvJSihLYtbLF2nbMncVH08fybLWQ/viewform?edit2=2_ABaOnucGbF1yExF0E9yxwyMK9iAs8JNP572TZeKZjmfLHSJSkznGs6ajJFx_33Ooo-nRuBo
A99: 44799.69 | B99: Deepak joshi | D99: General | E99: Diamond Jewellery | F99: Gents Ring | G99: 50-100 | H99: Platinum band | J99: Sanjeev Sir | K99: Sanjeev Sir | L99: Old | M99: 8/26/0022 | N99: This Month | Q99: https://docs.google.com/forms/d/e/1FAIpQLSeQ0wUAy9WJrwwZ_8x6kCxvJSihLYtbLF2nbMncVH08fybLWQ/viewform?edit2=2_ABaOnud4BkodrUSNtcIZtqdDBt0itdMAj1ZLAPzaTIgGYVnuNzed9VZ627foZcHBE4Ila2A
A100: 44800.58 | B100: Rajeev kapoor | C100: 9810086566 | D100: Gifting | E100: Gold Jewellery | F100: Ladies Bracelet / Kada | G100: 100-250 | J100: Shivani | K100: Shivani | L100: Old | M100: 44804 | N100: This Week | Q100: https://docs.google.com/forms/d/e/1FAIpQLSeQ0wUAy9WJrwwZ_8x6kCxvJSihLYtbLF2nbMncVH08fybLWQ/viewform?edit2=2_ABaOnuc3QAsHPzk3NBCdC3sUemacdJ7XK3PEsKrqn41QsKFc5ZSRFJ6YmuXGJmP4smTq2DQ
...

Sheet Sheet13
A2: 45262 | B2: Shama Kapoor | C2: 919555586195 | J2: Bhumika | P2: shamakapoor1975@gmail.com
A3: 45262 | B3: Ritesh Saini | C3: 919896859990 | J3: Bhumika | P3: sainiritesh099@gmail.com
A4: 45262 | B4: Bharat kochhar | C4: 918146302837 | J4: Bhumika | P4: bharatkochhar777@gmail.com
A5: 45262 | B5: Cuboid Jeans Co | C5: 919999995592 | J5: Bhumika | P5: cuboidjeansco@gmail.com
A6: 45262 | B6: Kiru Bisht | C6: 919711192649 | J6: Bhumika | P6: kiranbisht109@yahoo.com
A7: 45262 | B7: Vijay Bansal | C7: 919718028256 | J7: Bhumika | P7: vijaykumarbansal30@gmail.com
A8: 45262 | B8: Sushma Dhar | C8: 919717462277 | J8: Bhumika | P8: drsushmadhar@yahoo.com
A9: 45262 | B9: Indu Chaudhary | C9: 919599427401 | J9: Bhumika | P9: indukumari3@gmail.com
A10: 45262 | B10: Lovely Santosh Sk | C10: 918448745003 | J10: Bhumika | P10: santoshbosak18@gmail.com
A11: 45262 | B11: Bina Pathak | C11: 919548916659 | J11: Bhumika | P11: bina.pathak2019@gmail.com
A12: 45262 | B12: Jeeti Bhinder | C12: 919996145792 | J12: Bhumika | P12: 676712@gmail.com
A13: 45262 | B13: Vung Biaklun | C13: 919650585014 | J13: Bhumika | P13: luwang334@gmail.com
... A45: 45262 | B45: Gauraev Mittal | C45: 919911198444 | J45: Bhumika | P45: dpconstco786@gmail.com
A46: 45314 | B46: Asha Solanki | C46: =+918800141965 -> 918800141965 | F46: Wedding jewellery | P46: ashasolanki098@gmail.com
A47: 45314 | B47: Noor Afroz | C47: =+919971016813 -> 919971016813 | F47: Wedding jewellery | P47: noorafroz85@gmail.com
A48: 45314 | B48: Kalp Jyoti Jain | C48: =+919871276271 -> 919871276271 | F48: Wedding jewellery | P48: Kalpjyotijain@gmail.com
A49: 45314 | B49: Simmi Mishra | C49: =+919870255623 -> 919870255623 | F49: Wedding jewellery | P49: simmimishra1967@gmail.com
A50: 45314 | B50: Archana Prajapati | C50: =+919559725020 -> 919559725020 | F50: Wedding jewellery | P50: efmyuvi@gmail.com
A51: 45314 | B51: Meena Gupta | C51: =+919582908403 -> 919582908403 | F51: Wedding jewellery | P51: meenagupta.1111972@gmail.com
A52: 45314 | B52: Manisha Goel | C52: =+918800374621 -> 918800374621 | F52: Wedding jewellery | P52: manishagoelmg123@gmail.com
A53: 45314 | B53: Seema Narula | C53: =+919910056771 -> 919910056771 | F53: Wedding jewellery | P53: shailendernarula56@gmail.com

Sheet FMS
A1: =now() -> 46133.984
A2: what | O2: Enquire & Coordinate with client | U2: Estimate | AB2: Follow up | AI2: Contact for any order update | AN2: Price Negotiation | AS2: Closure Finale | AX2: Reason for Pending
A3: Who | G3: pallavi | K3: pallavi | O3: sales person - first shivani | U3: shivani | AB3: Kajal | AI3: Kajal | AN3: Kajal
A4: How
A5: When | G5: 0.70833333 | K5: 0.79166667 | O5: 1 | U5: 1 | AI5: 0.75 | AN5: 1 | AS5: 2
A6: Timestamp | G6: Planned | H6: Actual | I6: Status | J6: Time Delay | K6: Planned | L6: Actual | M6: Status | N6: Time Delay | O6: Planned | P6: Actual | Q6: Status | R6: Time Delay | S6: Remarks | T6: Share Design with Client | U6: Planned | V6: Actual | W6: Status | X6: Time Delay | Y6: Vendor 1 | Z6: Vendor 2 | AA6: Remarks | AB6: 1 | AC6: 2 | AD6: 3 | AE6: 4 | AF6: 5 | AG6: Remarks | AH6: Planned | AI6: Planned | AJ6: Actual | AK6: Status | AL6: Time Delay | AM6: Remarks | AN6: Planned | AO6: Actual | AP6: Status | AQ6: Time Delay | AR6: Remarks | AS6: Planned | AT6: Actual | AU6: Status | AV6: Time Delay | AW6: Remarks | AX6: Status
A7: {=INDEX('Customer Enquiry Form'!$A$2:$A1000,0)} -> 44625.486 | G7: =if(A7,_xlfn.workday.intl(int(A7),1,"1000000",Holidays!A:A)+17/24,"") -> 44626.708 | H7: =if(H7,H7,if(I7<>"",$A$1,"")) | J7: =if(G7,if(H7<>"",if(H7>G7,H7-G7,""),$A$1-G7),"") -> 1507.2756 | K7: =if(G7,_xlfn.workday.intl(int(G7),0,"1000000",Holidays!A:A)+19/24,"") -> 44626.792 | L7: =if(L7,L7,if(M7<>"",$A$1,"")) | N7: =if(K7,if(L7<>"",if(L7>K7,L7-K7,""),$A$1-K7),"") -> 1507.1922 | O7: =if(A7,_xlfn.WORKDAY.INTL(A7,O$5,"1000000",Holidays!A:A)+hour(A7)/24+MINUTE(A7)/1440,"") -> 44626.485 | P7: 44827.718 | Q7: done | R7: =if(O7,if(P7<>"",if(P7>O7,P7-O7,""),$A$1-O7),"") -> 201.2323 | T7: done | U7: =if(O7,_xlfn.WORKDAY.INTL(O7,U$5,"1000000",Holidays!A:A)+hour(O7)/24+MINUTE(O7)/1440,"") -> 44628.485 | V7: =if(V7,V7,if(W7<>"",$A$1,"")) -> 44916.733 | W7: done | X7: =if(U7,if(V7<>"",if(V7>U7,V7-U7,""),$A$1-U7),"") -> 288.24728 | Y7: done | AB7: 1 | AH7: =(IF(P7="","",P7+AB7+AC7+AD7+AE7+AF7)) -> 44828.718 | AI7: =if(AH7,_xlfn.workday.intl(int(AH7),0,"1000000",Holidays!A:A)+18/24,"") -> 44828.75 | AJ7: =if(AJ7,AJ7,if(AK7<>"",$A$1,"")) -> 44728.715 | AK7: Done | AL7: =if(AI7,if(AJ7<>"",if(AJ7>AI7,AJ7-AI7,""),$A$1-AI7),"") | AN7: =if(AJ7,if(and(hour(AJ7+AN$5)>11,(hour(AJ7+AN$5)<20)),AJ7+AN$5,_xlfn.workday.intl(int(AJ7),1,"1000000",Holidays!A:A)+hour(AJ7+AN$5-$B$1)/24+minute(AJ7)/1440),"") -> 44729.715 | AO7: =if(AO7,AO7,if(AP7<>"",$A$1,"")) -> 44916.733 | AP7: done | AQ7: =if(AN7,if(AO7<>"",if(AO7>AN7,AO7-AN7,""),$A$1-AN7),"") -> 187.01797 | AS7: =if(AJ7,if(and(hour(AJ7+AS$5)>11,(hour(AJ7+AS$5)<20)),AJ7+AS$5,_xlfn.workday.intl(int(AJ7),1,"1000000",Holidays!A:A)+hour(AJ7+AS$5-$B$1)/24+minute(AJ7)/1440),"") -> 44730.715 | AT7: =if(AT7,AT7,if(AU7<>"",$A$1,"")) -> 44730.599 | AU7: yes | AV7: =if(AS7,if(AT7<>"",if(AT7>AS7,AT7-AS7,""),$A$1-AS7),"") | AX7: done
A8: 44625.563 | G8: =if(A8,_xlfn.workday.intl(int(A8),1,"1000000",Holidays!A:A)+17/24,"") -> 44626.708 | H8: =if(H8,H8,if(I8<>"",$A$1,"")) | J8: =if(G8,if(H8<>"",if(H8>G8,H8-G8,""),$A$1-G8),"") -> 1507.2756 | K8: =if(G8,_xlfn.workday.intl(int(G8),0,"1000000",Holidays!A:A)+19/24,"") -> 44626.792 | L8: =if(L8,L8,if(M8<>"",$A$1,"")) | N8: =if(K8,if(L8<>"",if(L8>K8,L8-K8,""),$A$1-K8),"") -> 1507.1922 | O8: =if(A8,_xlfn.WORKDAY.INTL(A8,O$5,"1000000",Holidays!A:A)+hour(A8)/24+MINUTE(A8)/1440,"") -> 44626.562 | P8: 44728.721 | Q8: Done | R8: =if(O8,if(P8<>"",if(P8>O8,P8-O8,""),$A$1-O8),"") -> 102.15859 | U8: =if(O8,_xlfn.WORKDAY.INTL(O8,U$5,"1000000",Holidays!A:A)+hour(O8)/24+MINUTE(O8)/1440,"") -> 44628.562 | V8: =if(V8,V8,if(W8<>"",$A$1,"")) | X8: =if(U8,if(V8<>"",if(V8>U8,V8-U8,""),$A$1-U8),"") -> 1505.4214 | AH8: =IF(P8="","",P8+AB8+AC8+AD8+AE8+AF8) -> 44728.721 | AI8: =if(AH8,_xlfn.workday.intl(int(AH8),0,"1000000",Holidays!A:A)+18/24,"") -> 44728.75 | AJ8: =if(AJ8,AJ8,if(AK8<>"",$A$1,"")) -> 44728.717 | AK8: Done | AL8: =if(AI8,if(AJ8<>"",if(AJ8>AI8,AJ8-AI8,""),$A$1-AI8),"") | AN8: =if(AJ8,if(and(hour(AJ8+AN$5)>11,(hour(AJ8+AN$5)<20)),AJ8+AN$5,_xlfn.workday.intl(int(AJ8),1,"1000000",Holidays!A:A)+hour(AJ8+AN$5-$B$1)/24+minute(AJ8)/1440),"") -> 44729.717 | AO8: =if(AO8,AO8,if(AP8<>"",$A$1,"")) | AQ8: =if(AN8,if(AO8<>"",if(AO8>AN8,AO8-AN8,""),$A$1-AN8),"") -> 1404.2674 | AS8: =if(AJ8,if(and(hour(AJ8+AS$5)>11,(hour(AJ8+AS$5)<20)),AJ8+AS$5,_xlfn.workday.intl(int(AJ8),1,"1000000",Holidays!A:A)+hour(AJ8+AS$5-$B$1)/24+minute(AJ8)/1440),"") -> 44730.717 | AT8: =if(AT8,AT8,if(AU8<>"",$A$1,"")) -> 44734.719 | AU8: no | AV8: =if(AS8,if(AT8<>"",if(AT8>AS8,AT8-AS8,""),$A$1-AS8),"") -> 4.0028988 | AX8: Hold
A9: 44626.502 | G9: =if(A9,_xlfn.workday.intl(int(A9),1,"1000000",Holidays!A:A)+17/24,"") -> 44628.708 | H9: =if(H9,H9,if(I9<>"",$A$1,"")) | J9: =if(G9,if(H9<>"",if(H9>G9,H9-G9,""),$A$1-G9),"") -> 1505.2756 | K9: =if(G9,_xlfn.workday.intl(int(G9),0,"1000000",Holidays!A:A)+19/24,"") -> 44628.792 | L9: =if(L9,L9,if(M9<>"",$A$1,"")) | N9: =if(K9,if(L9<>"",if(L9>K9,L9-K9,""),$A$1-K9),"") -> 1505.1922 | O9: =if(A9,_xlfn.WORKDAY.INTL(A9,O$5,"1000000",Holidays!A:A)+hour(A9)/24+MINUTE(A9)/1440,"") -> 44628.502 | R9: =if(O9,if(P9<>"",if(P9>O9,P9-O9,""),$A$1-O9),"") -> 1505.4818 | U9: =if(O9,_xlfn.WORKDAY.INTL(O9,U$5,"1000000",Holidays!A:A)+hour(O9)/24+MINUTE(O9)/1440,"") -> 44629.502 | V9: =if(V9,V9,if(W9<>"",$A$1,"")) | X9: =if(U9,if(V9<>"",if(V9>U9,V9-U9,""),$A$1-U9),"") -> 1504.4818 | AH9: =IF(P9="","",P9+AB9+AC9+AD9+AE9+AF9) | AI9: =if(AH9,_xlfn.workday.intl(int(AH9),0,"1000000",Holidays!A:A)+18/24,"") | AJ9: =if(AJ9,AJ9,if(AK9<>"",$A$1,"")) | AL9: =if(AI9,if(AJ9<>"",if(AJ9>AI9,AJ9-AI9,""),$A$1-AI9),"") | AN9: =if(AJ9,if(and(hour(AJ9+AN$5)>11,(hour(AJ9+AN$5)<20)),AJ9+AN$5,_xlfn.workday.intl(int(AJ9),1,"1000000",Holidays!A:A)+hour(AJ9+AN$5-$B$1)/24+minute(AJ9)/1440),"") | AO9: =if(AO9,AO9,if(AP9<>"",$A$1,"")) | AQ9: =if(AN9,if(AO9<>"",if(AO9>AN9,AO9-AN9,""),$A$1-AN9),"") | AS9: =if(AJ9,if(and(hour(AJ9+AS$5)>11,(hour(AJ9+AS$5)<20)),AJ9+AS$5,_xlfn.workday.intl(int(AJ9),1,"1000000",Holidays!A:A)+hour(AJ9+AS$5-$B$1)/24+minute(AJ9)/1440),"") | AT9: =if(AT9,AT9,if(AU9<>"",$A$1,"")) -> 44734.728 | AU9: no | AV9: =if(AS9,if(AT9<>"",if(AT9>AS9,AT9-AS9,""),$A$1-AS9),"") | AX9: Hold
A10: 44626.505 | G10: =if(A10,_xlfn.workday.intl(int(A10),1,"1000000",Holidays!A:A)+17/24,"") -> 44628.708 | H10: =if(H10,H10,if(I10<>"",$A$1,"")) -> 44744.459 | I10: done | J10: =if(G10,if(H10<>"",if(H10>G10,H10-G10,""),$A$1-G10),"") -> 115.75098 | K10: =if(G10,_xlfn.workday.intl(int(G10),0,"1000000",Holidays!A:A)+19/24,"") -> 44628.792 | L10: =if(L10,L10,if(M10<>"",$A$1,"")) -> 44744.459 | M10: done | N10: =if(K10,if(L10<>"",if(L10>K10,L10-K10,""),$A$1-K10),"") -> 115.66768 | O10: =if(A10,_xlfn.WORKDAY.INTL(A10,O$5,"1000000",Holidays!A:A)+hour(A10)/24+MINUTE(A10)/1440,"") -> 44628.504 | P10: 44744.459 | Q10: done | R10: =if(O10,if(P10<>"",if(P10>O10,P10-O10,""),$A$1-O10),"") -> 115.95521 | T10: done | U10: =if(O10,_xlfn.WORKDAY.INTL(O10,U$5,"1000000",Holidays!A:A)+hour(O10)/24+MINUTE(O10)/1440,"") -> 44629.504 | V10: =if(V10,V10,if(W10<>"",$A$1,"")) -> 44916.733 | W10: done | X10: =if(U10,if(V10<>"",if(V10>U10,V10-U10,""),$A$1-U10),"") -> 287.22899 | Y10: done | AB10: 1 | AC10: 2 | AD10: 3 | AE10: 4 | AF10: 5 | AH10: =IF(P10="","",P10+AB10+AC10+AD10+AE10+AF10) -> 44759.459 | AI10: =if(AH10,_xlfn.workday.intl(int(AH10),0,"1000000",Holidays!A:A)+18/24,"") -> 44759.75 | AJ10: =if(AJ10,AJ10,if(AK10<>"",$A$1,"")) -> 44733.663 | AK10: done | AL10: =if(AI10,if(AJ10<>"",if(AJ10>AI10,AJ10-AI10,""),$A$1-AI10),"") | AN10: =if(AJ10,if(and(hour(AJ10+AN$5)>11,(hour(AJ10+AN$5)<20)),AJ10+AN$5,_xlfn.workday.intl(int(AJ10),1,"1000000",Holidays!A:A)+hour(AJ10+AN$5-$B$1)/24+minute(AJ10)/1440),"") -> 44734.663 | AO10: =if(AO10,AO10,if(AP10<>"",$A$1,"")) -> 44744.459 | AP10: done | AQ10: =if(AN10,if(AO10<>"",if(AO10>AN10,AO10-AN10,""),$A$1-AN10),"") -> 9.7965623 | AS10: =if(AJ10,if(and(hour(AJ10+AS$5)>11,(hour(AJ10+AS$5)<20)),AJ10+AS$5,_xlfn.workday.intl(int(AJ10),1,"1000000",Holidays!A:A)+hour(AJ10+AS$5-$B$1)/24+minute(AJ10)/1440),"") -> 44735.663 | AT10: =if(AT10,AT10,if(AU10<>"",$A$1,"")) -> 44734.728 | AU10: yes | AV10: =if(AS10,if(AT10<>"",if(AT10>AS10,AT10-AS10,""),$A$1-AS10),"") | AX10: done
A11: 44626.513 | G11: =if(A11,_xlfn.workday.intl(int(A11),1,"1000000",Holidays!A:A)+17/24,"") -> 44628.708 | H11: =if(H11,H11,if(I11<>"",$A$1,"")) | J11: =if(G11,if(H11<>"",if(H11>G11,H11-G11,""),$A$1-G11),"") -> 1505.2756 | K11: =if(G11,_xlfn.workday.intl(int(G11),0,"1000000",Holidays!A:A)+19/24,"") -> 44628.792 | L11: =if(L11,L11,if(M11<>"",$A$1,"")) | N11: =if(K11,if(L11<>"",if(L11>K11,L11-K11,""),$A$1-K11),"") -> 1505.1922 | O11: =if(A11,_xlfn.WORKDAY.INTL(A11,O$5,"1000000",Holidays!A:A)+hour(A11)/24+MINUTE(A11)/1440,"") -> 44628.513 | P11: 44912.681 | Q11: done | R11: =if(O11,if(P11<>"",if(P11>O11,P11-O11,""),$A$1-O11),"") -> 284.16773 | T11: done | U11: =if(O11,_xlfn.WORKDAY.INTL(O11,U$5,"1000000",Holidays!A:A)+hour(O11)/24+MINUTE(O11)/1440,"") -> 44629.513 | V11: =if(V11,V11,if(W11<>"",$A$1,"")) -> 44924.794 | W11: done | X11: =if(U11,if(V11<>"",if(V11>U11,V11-U11,""),$A$1-U11),"") -> 295.28061 | Y11: done | AB11: 1 | AC11: 2 | AD11: 3 | AH11: =IF(P11="","",P11+AB11+AC11+AD11+AE11+AF11) -> 44918.681 | AI11: =if(AH11,_xlfn.workday.intl(int(AH11),0,"1000000",Holidays!A:A)+18/24,"") -> 44918.75 | AJ11: =if(AJ11,AJ11,if(AK11<>"",$A$1,"")) | AL11: =if(AI11,if(AJ11<>"",if(AJ11>AI11,AJ11-AI11,""),$A$1-AI11),"") -> 1215.2339 | AN11: =if(AJ11,if(and(hour(AJ11+AN$5)>11,(hour(AJ11+AN$5)<20)),AJ11+AN$5,_xlfn.workday.intl(int(AJ11),1,"1000000",Holidays!A:A)+hour(AJ11+AN$5-$B$1)/24+minute(AJ11)/1440),"") | AO11: =if(AO11,AO11,if(AP11<>"",$A$1,"")) | AQ11: =if(AN11,if(AO11<>"",if(AO11>AN11,AO11-AN11,""),$A$1-AN11),"") | AS11: =if(AJ11,if(and(hour(AJ11+AS$5)>11,(hour(AJ11+AS$5)<20)),AJ11+AS$5,_xlfn.workday.intl(int(AJ11),1,"1000000",Holidays!A:A)+hour(AJ11+AS$5-$B$1)/24+minute(AJ11)/1440),"") | AT11: =if(AT11,AT11,if(AU11<>"",$A$1,"")) -> 44736.55 | AU11: yes | AV11: =if(AS11,if(AT11<>"",if(AT11>AS11,AT11-AS11,""),$A$1-AS11),"") | AX11: done
A12: 44626.522 | G12: =if(A12,_xlfn.workday.intl(int(A12),1,"1000000",Holidays!A:A)+17/24,"") -> 44628.708 | H12: =if(H12,H12,if(I12<>"",$A$1,"")) -> 44744.459 | I12: done | J12: =if(G12,if(H12<>"",if(H12>G12,H12-G12,""),$A$1-G12),"") -> 115.75039 | K12: =if(G12,_xlfn.workday.intl(int(G12),0,"1000000",Holidays!A:A)+19/24,"") -> 44628.792 | L12: =if(L12,L12,if(M12<>"",$A$1,"")) -> 44744.459 | M12: done | N12: =if(K12,if(L12<>"",if(L12>K12,L12-K12,""),$A$1-K12),"") -> 115.66708 | O12: =if(A12,_xlfn.WORKDAY.INTL(A12,O$5,"1000000",Holidays!A:A)+hour(A12)/24+MINUTE(A12)/1440,"") -> 44628.522 | P12: 44744.459 | Q12: done | R12: =if(O12,if(P12<>"",if(P12>O12,P12-O12,""),$A$1-O12),"") -> 115.93657 | T12: done | U12: =if(O12,_xlfn.WORKDAY.INTL(O12,U$5,"1000000",Holidays!A:A)+hour(O12)/24+MINUTE(O12)/1440,"") -> 44629.522 | V12: =if(V12,V12,if(W12<>"",$A$1,"")) -> 44924.794 | W12: done | X12: =if(U12,if(V12<>"",if(V12>U12,V12-U12,""),$A$1-U12),"") -> 295.2716 | Y12: done | AB12: 1 | AC12: 2 | AD12: 3 | AH12: =IF(P12="","",P12+AB12+AC12+AD12+AE12+AF12) -> 44750.459 | AI12: =if(AH12,_xlfn.workday.intl(int(AH12),0,"1000000",Holidays!A:A)+18/24,"") -> 44750.75 | AJ12: =if(AJ12,AJ12,if(AK12<>"",$A$1,"")) -> 44733.663 | AK12: done | AL12: =if(AI12,if(AJ12<>"",if(AJ12>AI12,AJ12-AI12,""),$A$1-AI12),"") | AN12: =if(AJ12,if(and(hour(AJ12+AN$5)>11,(hour(AJ12+AN$5)<20)),AJ12+AN$5,_xlfn.workday.intl(int(AJ12),1,"1000000",Holidays!A:A)+hour(AJ12+AN$5-$B$1)/24+minute(AJ12)/1440),"") -> 44734.663 | AO12: =if(AO12,AO12,if(AP12<>"",$A$1,"")) -> 44744.459 | AP12: done | AQ12: =if(AN12,if(AO12<>"",if(AO12>AN12,AO12-AN12,""),$A$1-AN12),"") -> 9.795894 | AS12: =if(AJ12,if(and(hour(AJ12+AS$5)>11,(hour(AJ12+AS$5)<20)),AJ12+AS$5,_xlfn.workday.intl(int(AJ12),1,"1000000",Holidays!A:A)+hour(AJ12+AS$5-$B$1)/24+minute(AJ12)/1440),"") -> 44735.663 | AT12: =if(AT12,AT12,if(AU12<>"",$A$1,"")) -> 44744.459 | AU12: yes | AV12: =if(AS12,if(AT12<>"",if(AT12>AS12,AT12-AS12,""),$A$1-AS12),"") -> 8.7959279 | AX12: done
A13: 44626.523 | G13: =if(A13,_xlfn.workday.intl(int(A13),1,"1000000",Holidays!A:A)+17/24,"") -> 44628.708 | H13: =if(H13,H13,if(I13<>"",$A$1,"")) -> 44744.458 | I13: done | J13: =if(G13,if(H13<>"",if(H13>G13,H13-G13,""),$A$1-G13),"") -> 115.75012 | K13: =if(G13,_xlfn.workday.intl(int(G13),0,"1000000",Holidays!A:A)+19/24,"") -> 44628.792 | L13: =if(L13,L13,if(M13<>"",$A$1,"")) -> 44744.458 | M13: done | N13: =if(K13,if(L13<>"",if(L13>K13,L13-K13,""),$A$1-K13),"") -> 115.66681 | O13: =if(A13,_xlfn.WORKDAY.INTL(A13,O$5,"1000000",Holidays!A:A)+hour(A13)/24+MINUTE(A13)/1440,"") -> 44628.523 | P13: 44744.459 | Q13: done | R13: =if(O13,if(P13<>"",if(P13>O13,P13-O13,""),$A$1-O13),"") -> 115.93562 | T13: done | U13: =if(O13,_xlfn.WORKDAY.INTL(O13,U$5,"1000000",Holidays!A:A)+hour(O13)/24+MINUTE(O13)/1440,"") -> 44629.523 | V13: =if(V13,V13,if(W13<>"",$A$1,"")) -> 44924.794 | W13: done | X13: =if(U13,if(V13<>"",if(V13>U13,V13-U13,""),$A$1-U13),"") -> 295.27092 | Y13: done | AB13: 1 | AC13: 2 | AD13: 3 | AH13: =IF(P13="","",P13+AB13+AC13+AD13+AE13+AF13) -> 44750.459 | AI13: =if(AH13,_xlfn.workday.intl(int(AH13),0,"1000000",Holidays!A:A)+18/24,"") -> 44750.75 | AJ13: =if(AJ13,AJ13,if(AK13<>"",$A$1,"")) -> 44733.663 | AK13: done | AL13: =if(AI13,if(AJ13<>"",if(AJ13>AI13,AJ13-AI13,""),$A$1-AI13),"") | AN13: =if(AJ13,if(and(hour(AJ13+AN$5)>11,(hour(AJ13+AN$5)<20)),AJ13+AN$5,_xlfn.workday.intl(int(AJ13),1,"1000000",Holidays!A:A)+hour(AJ13+AN$5-$B$1)/24+minute(AJ13)/1440),"") -> 44734.663 | AO13: =if(AO13,AO13,if(AP13<>"",$A$1,"")) -> 44744.459 | AP13: done | AQ13: =if(AN13,if(AO13<>"",if(AO13>AN13,AO13-AN13,""),$A$1-AN13),"") -> 9.7955569 | AS13: =if(AJ13,if(and(hour(AJ13+AS$5)>11,(hour(AJ13+AS$5)<20)),AJ13+AS$5,_xlfn.workday.intl(int(AJ13),1,"1000000",Holidays!A:A)+hour(AJ13+AS$5-$B$1)/24+minute(AJ13)/1440),"") -> 44735.663 | AT13: =if(AT13,AT13,if(AU13<>"",$A$1,"")) -> 44744.459 | AU13: yes | AV13: =if(AS13,if(AT13<>"",if(AT13>AS13,AT13-AS13,""),$A$1-AS13),"") -> 8.795586 | AX13: done
A14: 44626.526 | G14: =if(A14,_xlfn.workday.intl(int(A14),1,"1000000",Holidays!A:A)+17/24,"") -> 44628.708 | H14: =if(H14,H14,if(I14<>"",$A$1,"")) -> 44744.458 | I14: done | J14: =if(G14,if(H14<>"",if(H14>G14,H14-G14,""),$A$1-G14),"") -> 115.7497 | K14: =if(G14,_xlfn.workday.intl(int(G14),0,"1000000",Holidays!A:A)+19/24,"") -> 44628.792 | L14: =if(L14,L14,if(M14<>"",$A$1,"")) -> 44744.458 | M14: done | N14: =if(K14,if(L14<>"",if(L14>K14,L14-K14,""),$A$1-K14),"") -> 115.6664 | O14: =if(A14,_xlfn.WORKDAY.INTL(A14,O$5,"1000000",Holidays!A:A)+hour(A14)/24+MINUTE(A14)/1440,"") -> 44628.525 | P14: 44744.458 | Q14: done | R14: =if(O14,if(P14<>"",if(P14>O14,P14-O14,""),$A$1-O14),"") -> 115.93313 | T14: done | U14: =if(O14,_xlfn.WORKDAY.INTL(O14,U$5,"1000000",Holidays!A:A)+hour(O14)/24+MINUTE(O14)/1440,"") -> 44629.525 | V14: =if(V14,V14,if(W14<>"",$A$1,"")) -> 44924.794 | W14: done | X14: =if(U14,if(V14<>"",if(V14>U14,V14-U14,""),$A$1-U14),"") -> 295.26889 | Y14: done | AB14: 1 | AC14: 2 | AD14: 3 | AH14: =IF(P14="","",P14+AB14+AC14+AD14+AE14+AF14) -> 44750.458 | AI14: =if(AH14,_xlfn.workday.intl(int(AH14),0,"1000000",Holidays!A:A)+18/24,"") -> 44750.75 | AJ14: =if(AJ14,AJ14,if(AK14<>"",$A$1,"")) -> 44733.663 | AK14: done | AL14: =if(AI14,if(AJ14<>"",if(AJ14>AI14,AJ14-AI14,""),$A$1-AI14),"") | AN14: =if(AJ14,if(and(hour(AJ14+AN$5)>11,(hour(AJ14+AN$5)<20)),AJ14+AN$5,_xlfn.workday.intl(int(AJ14),1,"1000000",Holidays!A:A)+hour(AJ14+AN$5-$B$1)/24+minute(AJ14)/1440),"") -> 44734.663 | AO14: =if(AO14,AO14,if(AP14<>"",$A$1,"")) -> 44744.458 | AP14: done | AQ14: =if(AN14,if(AO14<>"",if(AO14>AN14,AO14-AN14,""),$A$1-AN14),"") -> 9.7951225 | AS14: =if(AJ14,if(and(hour(AJ14+AS$5)>11,(hour(AJ14+AS$5)<20)),AJ14+AS$5,_xlfn.workday.intl(int(AJ14),1,"1000000",Holidays!A:A)+hour(AJ14+AS$5-$B$1)/24+minute(AJ14)/1440),"") -> 44735.663 | AT14: =if(AT14,AT14,if(AU14<>"",$A$1,"")) -> 44744.458 | AU14: yes | AV14: =if(AS14,if(AT14<>"",if(AT14>AS14,AT14-AS14,""),$A$1-AS14),"") -> 8.795186 | AX14: done
A15: 44626.528 | G15: =if(A15,_xlfn.workday.intl(int(A15),1,"1000000",Holidays!A:A)+17/24,"") -> 44628.708 | H15: =if(H15,H15,if(I15<>"",$A$1,"")) -> 44744.458 | I15: done | J15: =if(G15,if(H15<>"",if(H15>G15,H15-G15,""),$A$1-G15),"") -> 115.74939 | K15: =if(G15,_xlfn.workday.intl(int(G15),0,"1000000",Holidays!A:A)+19/24,"") -> 44628.792 | L15: =if(L15,L15,if(M15<>"",$A$1,"")) -> 44744.458 | M15: done | N15: =if(K15,if(L15<>"",if(L15>K15,L15-K15,""),$A$1-K15),"") -> 115.66609 | O15: =if(A15,_xlfn.WORKDAY.INTL(A15,O$5,"1000000",Holidays!A:A)+hour(A15)/24+MINUTE(A15)/1440,"") -> 44628.528 | P15: 44744.458 | Q15: done | R15: =if(O15,if(P15<>"",if(P15>O15,P15-O15,""),$A$1-O15),"") -> 115.93001 | T15: done | U15: =if(O15,_xlfn.WORKDAY.INTL(O15,U$5,"1000000",Holidays!A:A)+hour(O15)/24+MINUTE(O15)/1440,"") -> 44629.528 | V15: =if(V15,V15,if(W15<>"",$A$1,"")) -> 44924.794 | W15: done | X15: =if(U15,if(V15<>"",if(V15>U15,V15-U15,""),$A$1-U15),"") -> 295.26608 | Y15: done | AB15: 1 | AC15: 2 | AD15: 3 | AH15: =IF(P15="","",P15+AB15+AC15+AD15+AE15+AF15) -> 44750.458 | AI15: =if(AH15,_xlfn.workday.intl(int(AH15),0,"1000000",Holidays!A:A)+18/24,"") -> 44750.75 | AJ15: =if(AJ15,AJ15,if(AK15<>"",$A$1,"")) -> 44733.663 | AK15: done | AL15: =if(AI15,if(AJ15<>"",if(AJ15>AI15,AJ15-AI15,""),$A$1-AI15),"") | AN15: =if(AJ15,if(and(hour(AJ15+AN$5)>11,(hour(AJ15+AN$5)<20)),AJ15+AN$5,_xlfn.workday.intl(int(AJ15),1,"1000000",Holidays!A:A)+hour(AJ15+AN$5-$B$1)/24+minute(AJ15)/1440),"") -> 44734.663 | AO15: =if(AO15,AO15,if(AP15<>"",$A$1,"")) -> 44744.458 | AP15: done | AQ15: =if(AN15,if(AO15<>"",if(AO15>AN15,AO15-AN15,""),$A$1-AN15),"") -> 9.7946667 | AS15: =if(AJ15,if(and(hour(AJ15+AS$5)>11,(hour(AJ15+AS$5)<20)),AJ15+AS$5,_xlfn.workday.intl(int(AJ15),1,"1000000",Holidays!A:A)+hour(AJ15+AS$5-$B$1)/24+minute(AJ15)/1440),"") -> 44735.663 | AT15: =if(AT15,AT15,if(AU15<>"",$A$1,"")) -> 44744.458 | AU15: yes | AV15: =if(AS15,if(AT15<>"",if(AT15>AS15,AT15-AS15,""),$A$1-AS15),"") -> 8.7946953 | AX15: done
A16: 44626.666 | G16: =if(A16,_xlfn.workday.intl(int(A16),1,"1000000",Holidays!A:A)+17/24,"") -> 44628.708 | H16: =if(H16,H16,if(I16<>"",$A$1,"")) -> 44744.457 | I16: done | J16: =if(G16,if(H16<>"",if(H16>G16,H16-G16,""),$A$1-G16),"") -> 115.74905 | K16: =if(G16,_xlfn.workday.intl(int(G16),0,"1000000",Holidays!A:A)+19/24,"") -> 44628.792 | L16: =if(L16,L16,if(M16<>"",$A$1,"")) -> 44744.457 | M16: done | N16: =if(K16,if(L16<>"",if(L16>K16,L16-K16,""),$A$1-K16),"") -> 115.66577 | O16: =if(A16,_xlfn.WORKDAY.INTL(A16,O$5,"1000000",Holidays!A:A)+hour(A16)/24+MINUTE(A16)/1440,"") -> 44628.666 | P16: 44744.458 | Q16: done | R16: =if(O16,if(P16<>"",if(P16>O16,P16-O16,""),$A$1-O16),"") -> 115.79155 | T16: done | U16: =if(O16,_xlfn.WORKDAY.INTL(O16,U$5,"1000000",Holidays!A:A)+hour(O16)/24+MINUTE(O16)/1440,"") -> 44629.666 | V16: =if(V16,V16,if(W16<>"",$A$1,"")) -> 44924.794 | W16: done | X16: =if(U16,if(V16<>"",if(V16>U16,V16-U16,""),$A$1-U16),"") -> 295.12842 | Y16: done | AB16: 1 | AC16: 2 | AD16: 3 | AH16: =IF(P16="","",P16+AB16+AC16+AD16+AE16+AF16) -> 44750.458 | AI16: =if(AH16,_xlfn.workday.intl(int(AH16),0,"1000000",Holidays!A:A)+18/24,"") -> 44750.75 | AJ16: =if(AJ16,AJ16,if(AK16<>"",$A$1,"")) -> 44744.458 | AK16: done | AL16: =if(AI16,if(AJ16<>"",if(AJ16>AI16,AJ16-AI16,""),$A$1-AI16),"") | AN16: =if(AJ16,if(and(hour(AJ16+AN$5)>11,(hour(AJ16+AN$5)<20)),AJ16+AN$5,_xlfn.workday.intl(int(AJ16),1,"1000000",Holidays!A:A)+hour(AJ16+AN$5-$B$1)/24+minute(AJ16)/1440),"") -> 44745.457 | AO16: =if(AO16,AO16,if(AP16<>"",$A$1,"")) -> 44744.458 | AP16: done | AQ16: =if(AN16,if(AO16<>"",if(AO16>AN16,AO16-AN16,""),$A$1-AN16),"") | AS16: =if(AJ16,if(and(hour(AJ16+AS$5)>11,(hour(AJ16+AS$5)<20)),AJ16+AS$5,_xlfn.workday.intl(int(AJ16),1,"1000000",Holidays!A:A)+hour(AJ16+AS$5-$B$1)/24+minute(AJ16)/1440),"") -> 44745.457 | AT16: =if(AT16,AT16,if(AU16<>"",$A$1,"")) -> 44744.458 | AU16: yes | AV16: =if(AS16,if(AT16<>"",if(AT16>AS16,AT16-AS16,""),$A$1-AS16),"") | AX16: done
A17: 44626.668 | G17: =if(A17,_xlfn.workday.intl(int(A17),1,"1000000",Holidays!A:A)+17/24,"") -> 44628.708 | H17: =if(H17,H17,if(I17<>"",$A$1,"")) | J17: =if(G17,if(H17<>"",if(H17>G17,H17-G17,""),$A$1-G17),"") -> 1505.2756 | K17: =if(G17,_xlfn.workday.intl(int(G17),0,"1000000",Holidays!A:A)+19/24,"") -> 44628.792 | L17: =if(L17,L17,if(M17<>"",$A$1,"")) | N17: =if(K17,if(L17<>"",if(L17>K17,L17-K17,""),$A$1-K17),"") -> 1505.1922 | O17: =if(A17,_xlfn.WORKDAY.INTL(A17,O$5,"1000000",Holidays!A:A)+hour(A17)/24+MINUTE(A17)/1440,"") -> 44628.668 | R17: =if(O17,if(P17<>"",if(P17>O17,P17-O17,""),$A$1-O17),"") -> 1505.3159 | U17: =if(O17,_xlfn.WORKDAY.INTL(O17,U$5,"1000000",Holidays!A:A)+hour(O17)/24+MINUTE(O17)/1440,"") -> 44629.668 | V17: =if(V17,V17,if(W17<>"",$A$1,"")) | X17: =if(U17,if(V17<>"",if(V17>U17,V17-U17,""),$A$1-U17),"") -> 1504.3159 | AH17: =IF(P17="","",P17+AB17+AC17+AD17+AE17+AF17) | AI17: =if(AH17,_xlfn.workday.intl(int(AH17),0,"1000000",Holidays!A:A)+18/24,"") | AJ17: =if(AJ17,AJ17,if(AK17<>"",$A$1,"")) | AL17: =if(AI17,if(AJ17<>"",if(AJ17>AI17,AJ17-AI17,""),$A$1-AI17),"") | AN17: =if(AJ17,if(and(hour(AJ17+AN$5)>11,(hour(AJ17+AN$5)<20)),AJ17+AN$5,_xlfn.workday.intl(int(AJ17),1,"1000000",Holidays!A:A)+hour(AJ17+AN$5-$B$1)/24+minute(AJ17)/1440),"") | AS17: =if(AJ17,if(and(hour(AJ17+AS$5)>11,(hour(AJ17+AS$5)<20)),AJ17+AS$5,_xlfn.workday.intl(int(AJ17),1,"1000000",Holidays!A:A)+hour(AJ17+AS$5-$B$1)/24+minute(AJ17)/1440),"") | AT17: =if(AT17,AT17,if(AU17<>"",$A$1,"")) | AV17: =if(AS17,if(AT17<>"",if(AT17>AS17,AT17-AS17,""),$A$1-AS17),"") | AX17: No Response
A18: 44626.669 | G18: =if(A18,_xlfn.workday.intl(int(A18),1,"1000000",Holidays!A:A)+17/24,"") -> 44628.708 | H18: =if(H18,H18,if(I18<>"",$A$1,"")) | J18: =if(G18,if(H18<>"",if(H18>G18,H18-G18,""),$A$1-G18),"") -> 1505.2756 | K18: =if(G18,_xlfn.workday.intl(int(G18),0,"1000000",Holidays!A:A)+19/24,"") -> 44628.792 | L18: =if(L18,L18,if(M18<>"",$A$1,"")) | N18: =if(K18,if(L18<>"",if(L18>K18,L18-K18,""),$A$1-K18),"") -> 1505.1922 | O18: =if(A18,_xlfn.WORKDAY.INTL(A18,O$5,"1000000",Holidays!A:A)+hour(A18)/24+MINUTE(A18)/1440,"") -> 44628.669 | R18: =if(O18,if(P18<>"",if(P18>O18,P18-O18,""),$A$1-O18),"") -> 1505.3152 | U18: =if(O18,_xlfn.WORKDAY.INTL(O18,U$5,"1000000",Holidays!A:A)+hour(O18)/24+MINUTE(O18)/1440,"") -> 44629.669 | V18: =if(V18,V18,if(W18<>"",$A$1,"")) | X18: =if(U18,if(V18<>"",if(V18>U18,V18-U18,""),$A$1-U18),"") -> 1504.3152 | AH18: =IF(P18="","",P18+AB18+AC18+AD18+AE18+AF18) | AI18: =if(AH18,_xlfn.workday.intl(int(AH18),0,"1000000",Holidays!A:A)+18/24,"") | AJ18: =if(AJ18,AJ18,if(AK18<>"",$A$1,"")) | AL18: =if(AI18,if(AJ18<>"",if(AJ18>AI18,AJ18-AI18,""),$A$1-AI18),"") | AN18: =if(AJ18,if(and(hour(AJ18+AN$5)>11,(hour(AJ18+AN$5)<20)),AJ18+AN$5,_xlfn.workday.intl(int(AJ18),1,"1000000",Holidays!A:A)+hour(AJ18+AN$5-$B$1)/24+minute(AJ18)/1440),"") | AO18: =if(AO18,AO18,if(AP18<>"",$A$1,"")) | AQ18: =if(AN18,if(AO18<>"",if(AO18>AN18,AO18-AN18,""),$A$1-AN18),"") | AS18: =if(AJ18,if(and(hour(AJ18+AS$5)>11,(hour(AJ18+AS$5)<20)),AJ18+AS$5,_xlfn.workday.intl(int(AJ18),1,"1000000",Holidays!A:A)+hour(AJ18+AS$5-$B$1)/24+minute(AJ18)/1440),"") | AT18: =if(AT18,AT18,if(AU18<>"",$A$1,"")) | AV18: =if(AS18,if(AT18<>"",if(AT18>AS18,AT18-AS18,""),$A$1-AS18),"") | AX18: No Response
A19: 44626.671 | G19: =if(A19,_xlfn.workday.intl(int(A19),1,"1000000",Holidays!A:A)+17/24,"") -> 44628.708 | H19: =if(H19,H19,if(I19<>"",$A$1,"")) | J19: =if(G19,if(H19<>"",if(H19>G19,H19-G19,""),$A$1-G19),"") -> 1505.2756 | K19: =if(G19,_xlfn.workday.intl(int(G19),0,"1000000",Holidays!A:A)+19/24,"") -> 44628.792 | L19: =if(L19,L19,if(M19<>"",$A$1,"")) | N19: =if(K19,if(L19<>"",if(L19>K19,L19-K19,""),$A$1-K19),"") -> 1505.1922 | O19: =if(A19,_xlfn.WORKDAY.INTL(A19,O$5,"1000000",Holidays!A:A)+hour(A19)/24+MINUTE(A19)/1440,"") -> 44628.671 | R19: =if(O19,if(P19<>"",if(P19>O19,P19-O19,""),$A$1-O19),"") -> 1505.3131 | U19: =if(O19,_xlfn.WORKDAY.INTL(O19,U$5,"1000000",Holidays!A:A)+hour(O19)/24+MINUTE(O19)/1440,"") -> 44629.671 | V19: =if(V19,V19,if(W19<>"",$A$1,"")) | X19: =if(U19,if(V19<>"",if(V19>U19,V19-U19,""),$A$1-U19),"") -> 1504.3131 | AH19: =IF(P19="","",P19+AB19+AC19+AD19+AE19+AF19) | AI19: =if(AH19,_xlfn.workday.intl(int(AH19),0,"1000000",Holidays!A:A)+18/24,"") | AJ19: =if(AJ19,AJ19,if(AK19<>"",$A$1,"")) | AL19: =if(AI19,if(AJ19<>"",if(AJ19>AI19,AJ19-AI19,""),$A$1-AI19),"") | AN19: =if(AJ19,if(and(hour(AJ19+AN$5)>11,(hour(AJ19+AN$5)<20)),AJ19+AN$5,_xlfn.workday.intl(int(AJ19),1,"1000000",Holidays!A:A)+hour(AJ19+AN$5-$B$1)/24+minute(AJ19)/1440),"") | AO19: =if(AO19,AO19,if(AP19<>"",$A$1,"")) | AQ19: =if(AN19,if(AO19<>"",if(AO19>AN19,AO19-AN19,""),$A$1-AN19),"") | AS19: =if(AJ19,if(and(hour(AJ19+AS$5)>11,(hour(AJ19+AS$5)<20)),AJ19+AS$5,_xlfn.workday.intl(int(AJ19),1,"1000000",Holidays!A:A)+hour(AJ19+AS$5-$B$1)/24+minute(AJ19)/1440),"") | AT19: =if(AT19,AT19,if(AU19<>"",$A$1,"")) | AV19: =if(AS19,if(AT19<>"",if(AT19>AS19,AT19-AS19,""),$A$1-AS19),"") | AX19: No Response
A20: 44626.673 | G20: =if(A20,_xlfn.workday.intl(int(A20),1,"1000000",Holidays!A:A)+17/24,"") -> 44628.708 | H20: =if(H20,H20,if(I20<>"",$A$1,"")) -> 44744.457 | I20: done | J20: =if(G20,if(H20<>"",if(H20>G20,H20-G20,""),$A$1-G20),"") -> 115.74833 | K20: =if(G20,_xlfn.workday.intl(int(G20),0,"1000000",Holidays!A:A)+19/24,"") -> 44628.792 | L20: =if(L20,L20,if(M20<>"",$A$1,"")) -> 44744.457 | M20: done | N20: =if(K20,if(L20<>"",if(L20>K20,L20-K20,""),$A$1-K20),"") -> 115.66503 | O20: =if(A20,_xlfn.WORKDAY.INTL(A20,O$5,"1000000",Holidays!A:A)+hour(A20)/24+MINUTE(A20)/1440,"") -> 44628.673 | P20: 44744.457 | Q20: done | R20: =if(O20,if(P20<>"",if(P20>O20,P20-O20,""),$A$1-O20),"") -> 115.78381 | T20: done | U20: =if(O20,_xlfn.WORKDAY.INTL(O20,U$5,"1000000",Holidays!A:A)+hour(O20)/24+MINUTE(O20)/1440,"") -> 44629.673 | V20: =if(V20,V20,if(W20<>"",$A$1,"")) -> 44924.796 | W20: done | X20: =if(U20,if(V20<>"",if(V20>U20,V20-U20,""),$A$1-U20),"") -> 295.12264 | Y20: done | AB20: 1 | AC20: 2 | AD20: 3 | AH20: =IF(P20="","",P20+AB20+AC20+AD20+AE20+AF20) -> 44750.457 | AI20: =if(AH20,_xlfn.workday.intl(int(AH20),0,"1000000",Holidays!A:A)+18/24,"") -> 44750.75 | AJ20: =if(AJ20,AJ20,if(AK20<>"",$A$1,"")) -> 44733.664 | AK20: done | AL20: =if(AI20,if(AJ20<>"",if(AJ20>AI20,AJ20-AI20,""),$A$1-AI20),"") | AN20: =if(AJ20,if(and(hour(AJ20+AN$5)>11,(hour(AJ20+AN$5)<20)),AJ20+AN$5,_xlfn.workday.intl(int(AJ20),1,"1000000",Holidays!A:A)+hour(AJ20+AN$5-$B$1)/24+minute(AJ20)/1440),"") -> 44734.664 | AO20: =if(AO20,AO20,if(AP20<>"",$A$1,"")) -> 44744.457 | AP20: done | AQ20: =if(AN20,if(AO20<>"",if(AO20>AN20,AO20-AN20,""),$A$1-AN20),"") -> 9.7932748 | AS20: =if(AJ20,if(and(hour(AJ20+AS$5)>11,(hour(AJ20+AS$5)<20)),AJ20+AS$5,_xlfn.workday.intl(int(AJ20),1,"1000000",Holidays!A:A)+hour(AJ20+AS$5-$B$1)/24+minute(AJ20)/1440),"") -> 44735.664 | AT20: =if(AT20,AT20,if(AU20<>"",$A$1,"")) -> 44744.457 | AU20: yes | AV20: =if(AS20,if(AT20<>"",if(AT20>AS20,AT20-AS20,""),$A$1-AS20),"") -> 8.7933066 | AX20: done
A21: 44628.493 | G21: =if(A21,_xlfn.workday.intl(int(A21),1,"1000000",Holidays!A:A)+17/24,"") -> 44629.708 | H21: =if(H21,H21,if(I21<>"",$A$1,"")) -> 44744.456 | I21: done | J21: =if(G21,if(H21<>"",if(H21>G21,H21-G21,""),$A$1-G21),"") -> 114.74804 | K21: =if(G21,_xlfn.workday.intl(int(G21),0,"1000000",Holidays!A:A)+19/24,"") -> 44629.792 | L21: =if(L21,L21,if(M21<>"",$A$1,"")) -> 44744.456 | M21: done | N21: =if(K21,if(L21<>"",if(L21>K21,L21-K21,""),$A$1-K21),"") -> 114.66477 | O21: =if(A21,_xlfn.WORKDAY.INTL(A21,O$5,"1000000",Holidays!A:A)+hour(A21)/24+MINUTE(A21)/1440,"") -> 44629.492 | P21: 44744.456 | Q21: done | R21: =if(O21,if(P21<>"",if(P21>O21,P21-O21,""),$A$1-O21),"") -> 114.96412 | T21: done | U21: =if(O21,_xlfn.WORKDAY.INTL(O21,U$5,"1000000",Holidays!A:A)+hour(O21)/24+MINUTE(O21)/1440,"") -> 44630.492 | V21: =if(V21,V21,if(W21<>"",$A$1,"")) -> 44924.796 | W21: done | X21: =if(U21,if(V21<>"",if(V21>U21,V21-U21,""),$A$1-U21),"") -> 294.30317 | Y21: done | AB21: 1 | AC21: 2 | AD21: 3 | AH21: =IF(P21="","",P21+AB21+AC21+AD21+AE21+AF21) -> 44750.456 | AI21: =if(AH21,_xlfn.workday.intl(int(AH21),0,"1000000",Holidays!A:A)+18/24,"") -> 44750.75 | AJ21: =if(AJ21,AJ21,if(AK21<>"",$A$1,"")) -> 44733.664 | AK21: done | AL21: =if(AI21,if(AJ21<>"",if(AJ21>AI21,AJ21-AI21,""),$A$1-AI21),"") | AN21: =if(AJ21,if(and(hour(AJ21+AN$5)>11,(hour(AJ21+AN$5)<20)),AJ21+AN$5,_xlfn.workday.intl(int(AJ21),1,"1000000",Holidays!A:A)+hour(AJ21+AN$5-$B$1)/24+minute(AJ21)/1440),"") -> 44734.664 | AO21: =if(AO21,AO21,if(AP21<>"",$A$1,"")) -> 44744.457 | AP21: done | AQ21: =if(AN21,if(AO21<>"",if(AO21>AN21,AO21-AN21,""),$A$1-AN21),"") -> 9.7929588 | AS21: =if(AJ21,if(and(hour(AJ21+AS$5)>11,(hour(AJ21+AS$5)<20)),AJ21+AS$5,_xlfn.workday.intl(int(AJ21),1,"1000000",Holidays!A:A)+hour(AJ21+AS$5-$B$1)/24+minute(AJ21)/1440),"") -> 44735.664 | AT21: =if(AT21,AT21,if(AU21<>"",$A$1,"")) -> 44744.457 | AU21: yes | AV21: =if(AS21,if(AT21<>"",if(AT21>AS21,AT21-AS21,""),$A$1-AS21),"") -> 8.7929912 | AX21: done
A22: 44629.479 | G22: =if(A22,_xlfn.workday.intl(int(A22),1,"1000000",Holidays!A:A)+17/24,"") -> 44630.708 | H22: =if(H22,H22,if(I22<>"",$A$1,"")) -> 44744.456 | I22: done | J22: =if(G22,if(H22<>"",if(H22>G22,H22-G22,""),$A$1-G22),"") -> 113.74771 | K22: =if(G22,_xlfn.workday.intl(int(G22),0,"1000000",Holidays!A:A)+19/24,"") -> 44630.792 | L22: =if(L22,L22,if(M22<>"",$A$1,"")) -> 44744.456 | M22: done | N22: =if(K22,if(L22<>"",if(L22>K22,L22-K22,""),$A$1-K22),"") -> 113.6644 | O22: =if(A22,_xlfn.WORKDAY.INTL(A22,O$5,"1000000",Holidays!A:A)+hour(A22)/24+MINUTE(A22)/1440,"") -> 44630.478 | P22: 44744.456 | Q22: done | R22: =if(O22,if(P22<>"",if(P22>O22,P22-O22,""),$A$1-O22),"") -> 113.97762 | T22: done | U22: =if(O22,_xlfn.WORKDAY.INTL(O22,U$5,"1000000",Holidays!A:A)+hour(O22)/24+MINUTE(O22)/1440,"") -> 44631.478 | V22: =if(V22,V22,if(W22<>"",$A$1,"")) -> 44924.796 | W22: done | X22: =if(U22,if(V22<>"",if(V22>U22,V22-U22,""),$A$1-U22),"") -> 293.31704 | Y22: done | AB22: 1 | AC22: 2 | AD22: 3 | AH22: =IF(P22="","",P22+AB22+AC22+AD22+AE22+AF22) -> 44750.456 | AI22: =if(AH22,_xlfn.workday.intl(int(AH22),0,"1000000",Holidays!A:A)+18/24,"") -> 44750.75 | AJ22: =if(AJ22,AJ22,if(AK22<>"",$A$1,"")) -> 44733.664 | AK22: done | AL22: =if(AI22,if(AJ22<>"",if(AJ22>AI22,AJ22-AI22,""),$A$1-AI22),"") | AN22: =if(AJ22,if(and(hour(AJ22+AN$5)>11,(hour(AJ22+AN$5)<20)),AJ22+AN$5,_xlfn.workday.intl(int(AJ22),1,"1000000",Holidays!A:A)+hour(AJ22+AN$5-$B$1)/24+minute(AJ22)/1440),"") -> 44734.664 | AO22: =if(AO22,AO22,if(AP22<>"",$A$1,"")) -> 44744.456 | AP22: done | AQ22: =if(AN22,if(AO22<>"",if(AO22>AN22,AO22-AN22,""),$A$1-AN22),"") -> 9.7925208 | AS22: =if(AJ22,if(and(hour(AJ22+AS$5)>11,(hour(AJ22+AS$5)<20)),AJ22+AS$5,_xlfn.workday.intl(int(AJ22),1,"1000000",Holidays!A:A)+hour(AJ22+AS$5-$B$1)/24+minute(AJ22)/1440),"") -> 44735.664 | AT22: =if(AT22,AT22,if(AU22<>"",$A$1,"")) -> 44744.456 | AU22: yes | AV22: =if(AS22,if(AT22<>"",if(AT22>AS22,AT22-AS22,""),$A$1-AS22),"") -> 8.7925522 | AX22: done
A23: 44635.722 | G23: =if(A23,_xlfn.workday.intl(int(A23),1,"1000000",Holidays!A:A)+17/24,"") -> 44636.708 | H23: =if(H23,H23,if(I23<>"",$A$1,"")) | J23: =if(G23,if(H23<>"",if(H23>G23,H23-G23,""),$A$1-G23),"") -> 1497.2756 | K23: =if(G23,_xlfn.workday.intl(int(G23),0,"1000000",Holidays!A:A)+19/24,"") -> 44636.792 | L23: =if(L23,L23,if(M23<>"",$A$1,"")) | N23: =if(K23,if(L23<>"",if(L23>K23,L23-K23,""),$A$1-K23),"") -> 1497.1922 | O23: =if(A23,_xlfn.WORKDAY.INTL(A23,O$5,"1000000",Holidays!A:A)+hour(A23)/24+MINUTE(A23)/1440,"") -> 44636.722 | R23: =if(O23,if(P23<>"",if(P23>O23,P23-O23,""),$A$1-O23),"") -> 1497.2624 | U23: =if(O23,_xlfn.WORKDAY.INTL(O23,U$5,"1000000",Holidays!A:A)+hour(O23)/24+MINUTE(O23)/1440,"") -> 44637.722 | V23: =if(V23,V23,if(W23<>"",$A$1,"")) | X23: =if(U23,if(V23<>"",if(V23>U23,V23-U23,""),$A$1-U23),"") -> 1496.2624 | AH23: =IF(P23="","",P23+AB23+AC23+AD23+AE23+AF23) | AI23: =if(AH23,_xlfn.workday.intl(int(AH23),0,"1000000",Holidays!A:A)+18/24,"") | AJ23: =if(AJ23,AJ23,if(AK23<>"",$A$1,"")) | AL23: =if(AI23,if(AJ23<>"",if(AJ23>AI23,AJ23-AI23,""),$A$1-AI23),"") | AN23: =if(AJ23,if(and(hour(AJ23+AN$5)>11,(hour(AJ23+AN$5)<20)),AJ23+AN$5,_xlfn.workday.intl(int(AJ23),1,"1000000",Holidays!A:A)+hour(AJ23+AN$5-$B$1)/24+minute(AJ23)/1440),"") | AO23: =if(AO23,AO23,if(AP23<>"",$A$1,"")) | AQ23: =if(AN23,if(AO23<>"",if(AO23>AN23,AO23-AN23,""),$A$1-AN23),"") | AS23: =if(AJ23,if(and(hour(AJ23+AS$5)>11,(hour(AJ23+AS$5)<20)),AJ23+AS$5,_xlfn.workday.intl(int(AJ23),1,"1000000",Holidays!A:A)+hour(AJ23+AS$5-$B$1)/24+minute(AJ23)/1440),"") | AT23: =if(AT23,AT23,if(AU23<>"",$A$1,"")) | AV23: =if(AS23,if(AT23<>"",if(AT23>AS23,AT23-AS23,""),$A$1-AS23),"") | AX23: Hold
A24: 44636.493 | G24: =if(A24,_xlfn.workday.intl(int(A24),1,"1000000",Holidays!A:A)+17/24,"") -> 44637.708 | H24: =if(H24,H24,if(I24<>"",$A$1,"")) -> 44744.455 | I24: done | J24: =if(G24,if(H24<>"",if(H24>G24,H24-G24,""),$A$1-G24),"") -> 106.74716 | K24: =if(G24,_xlfn.workday.intl(int(G24),0,"1000000",Holidays!A:A)+19/24,"") -> 44637.792 | L24: =if(L24,L24,if(M24<>"",$A$1,"")) -> 44744.456 | M24: done | N24: =if(K24,if(L24<>"",if(L24>K24,L24-K24,""),$A$1-K24),"") -> 106.66386 | O24: =if(A24,_xlfn.WORKDAY.INTL(A24,O$5,"1000000",Holidays!A:A)+hour(A24)/24+MINUTE(A24)/1440,"") -> 44637.492 | P24: 44744.456 | Q24: done | R24: =if(O24,if(P24<>"",if(P24>O24,P24-O24,""),$A$1-O24),"") -> 106.9632 | T24: done | U24: =if(O24,_xlfn.WORKDAY.INTL(O24,U$5,"1000000",Holidays!A:A)+hour(O24)/24+MINUTE(O24)/1440,"") -> 44638.492 | V24: =if(V24,V24,if(W24<>"",$A$1,"")) -> 44924.796 | W24: done | X24: =if(U24,if(V24<>"",if(V24>U24,V24-U24,""),$A$1-U24),"") -> 286.30366 | Y24: done | AB24: 1 | AC24: 2 | AH24: =IF(P24="","",P24+AB24+AC24+AD24+AE24+AF24) -> 44747.456 | AI24: =if(AH24,_xlfn.workday.intl(int(AH24),0,"1000000",Holidays!A:A)+18/24,"") -> 44747.75 | AJ24: =if(AJ24,AJ24,if(AK24<>"",$A$1,"")) -> 44733.664 | AK24: done | AL24: =if(AI24,if(AJ24<>"",if(AJ24>AI24,AJ24-AI24,""),$A$1-AI24),"") | AN24: =if(AJ24,if(and(hour(AJ24+AN$5)>11,(hour(AJ24+AN$5)<20)),AJ24+AN$5,_xlfn.workday.intl(int(AJ24),1,"1000000",Holidays!A:A)+hour(AJ24+AN$5-$B$1)/24+minute(AJ24)/1440),"") -> 44734.664 | AO24: =if(AO24,AO24,if(AP24<>"",$A$1,"")) -> 44744.456 | AP24: done | AQ24: =if(AN24,if(AO24<>"",if(AO24>AN24,AO24-AN24,""),$A$1-AN24),"") -> 9.7916254 | AS24: =if(AJ24,if(and(hour(AJ24+AS$5)>11,(hour(AJ24+AS$5)<20)),AJ24+AS$5,_xlfn.workday.intl(int(AJ24),1,"1000000",Holidays!A:A)+hour(AJ24+AS$5-$B$1)/24+minute(AJ24)/1440),"") -> 44735.664 | AT24: =if(AT24,AT24,if(AU24<>"",$A$1,"")) -> 44744.456 | AU24: yes | AV24: =if(AS24,if(AT24<>"",if(AT24>AS24,AT24-AS24,""),$A$1-AS24),"") -> 8.7916652 | AX24: done
A25: 44636.495 | G25: =if(A25,_xlfn.workday.intl(int(A25),1,"1000000",Holidays!A:A)+17/24,"") -> 44637.708 | H25: =if(H25,H25,if(I25<>"",$A$1,"")) | J25: =if(G25,if(H25<>"",if(H25>G25,H25-G25,""),$A$1-G25),"") -> 1496.2756 | K25: =if(G25,_xlfn.workday.intl(int(G25),0,"1000000",Holidays!A:A)+19/24,"") -> 44637.792 | L25: =if(L25,L25,if(M25<>"",$A$1,"")) -> 44744.776 | M25: done | N25: =if(K25,if(L25<>"",if(L25>K25,L25-K25,""),$A$1-K25),"") -> 106.98472 | O25: =if(A25,_xlfn.WORKDAY.INTL(A25,O$5,"1000000",Holidays!A:A)+hour(A25)/24+MINUTE(A25)/1440,"") -> 44637.494 | P25: 44744.455 | Q25: done | R25: =if(O25,if(P25<>"",if(P25>O25,P25-O25,""),$A$1-O25),"") -> 106.96079 | T25: done | U25: =if(O25,_xlfn.WORKDAY.INTL(O25,U$5,"1000000",Holidays!A:A)+hour(O25)/24+MINUTE(O25)/1440,"") -> 44638.494 | V25: =if(V25,V25,if(W25<>"",$A$1,"")) -> 44924.796 | W25: done | X25: =if(U25,if(V25<>"",if(V25>U25,V25-U25,""),$A$1-U25),"") -> 286.3016 | Y25: done | AB25: 6 | AC25: 1 | AH25: =IF(P25="","",P25+AB25+AC25+AD25+AE25+AF25) -> 44751.455 | AI25: =if(AH25,_xlfn.workday.intl(int(AH25),0,"1000000",Holidays!A:A)+18/24,"") -> 44751.75 | AJ25: =if(AJ25,AJ25,if(AK25<>"",$A$1,"")) -> 44733.665 | AK25: done | AL25: =if(AI25,if(AJ25<>"",if(AJ25>AI25,AJ25-AI25,""),$A$1-AI25),"") | AN25: =if(AJ25,if(and(hour(AJ25+AN$5)>11,(hour(AJ25+AN$5)<20)),AJ25+AN$5,_xlfn.workday.intl(int(AJ25),1,"1000000",Holidays!A:A)+hour(AJ25+AN$5-$B$1)/24+minute(AJ25)/1440),"") -> 44734.665 | AO25: =if(AO25,AO25,if(AP25<>"",$A$1,"")) -> 44744.455 | AP25: done | AQ25: =if(AN25,if(AO25<>"",if(AO25>AN25,AO25-AN25,""),$A$1-AN25),"") -> 9.7907108 | AS25: =if(AJ25,if(and(hour(AJ25+AS$5)>11,(hour(AJ25+AS$5)<20)),AJ25+AS$5,_xlfn.workday.intl(int(AJ25),1,"1000000",Holidays!A:A)+hour(AJ25+AS$5-$B$1)/24+minute(AJ25)/1440),"") -> 44735.665 | AT25: =if(AT25,AT25,if(AU25<>"",$A$1,"")) -> 44744.455 | AU25: yes | AV25: =if(AS25,if(AT25<>"",if(AT25>AS25,AT25-AS25,""),$A$1-AS25),"") -> 8.7907506 | AX25: done
A26: 44636.498 | G26: =if(A26,_xlfn.workday.intl(int(A26),1,"1000000",Holidays!A:A)+17/24,"") -> 44637.708 | H26: =if(H26,H26,if(I26<>"",$A$1,"")) | J26: =if(G26,if(H26<>"",if(H26>G26,H26-G26,""),$A$1-G26),"") -> 1496.2756 | K26: =if(G26,_xlfn.workday.intl(int(G26),0,"1000000",Holidays!A:A)+19/24,"") -> 44637.792 | L26: =if(L26,L26,if(M26<>"",$A$1,"")) | N26: =if(K26,if(L26<>"",if(L26>K26,L26-K26,""),$A$1-K26),"") -> 1496.1922 | O26: =if(A26,_xlfn.WORKDAY.INTL(A26,O$5,"1000000",Holidays!A:A)+hour(A26)/24+MINUTE(A26)/1440,"") -> 44637.497 | R26: =if(O26,if(P26<>"",if(P26>O26,P26-O26,""),$A$1-O26),"") -> 1496.4867 | U26: =if(O26,_xlfn.WORKDAY.INTL(O26,U$5,"1000000",Holidays!A:A)+hour(O26)/24+MINUTE(O26)/1440,"") -> 44638.497 | V26: =if(V26,V26,if(W26<>"",$A$1,"")) | X26: =if(U26,if(V26<>"",if(V26>U26,V26-U26,""),$A$1-U26),"") -> 1495.4867 | AH26: =IF(P26="","",P26+AB26+AC26+AD26+AE26+AF26) | AI26: =if(AH26,_xlfn.workday.intl(int(AH26),0,"1000000",Holidays!A:A)+18/24,"") | AJ26: =if(AJ26,AJ26,if(AK26<>"",$A$1,"")) | AL26: =if(AI26,if(AJ26<>"",if(AJ26>AI26,AJ26-AI26,""),$A$1-AI26),"") | AN26: =if(AJ26,if(and(hour(AJ26+AN$5)>11,(hour(AJ26+AN$5)<20)),AJ26+AN$5,_xlfn.workday.intl(int(AJ26),1,"1000000",Holidays!A:A)+hour(AJ26+AN$5-$B$1)/24+minute(AJ26)/1440),"") | AO26: =if(AO26,AO26,if(AP26<>"",$A$1,"")) | AQ26: =if(AN26,if(AO26<>"",if(AO26>AN26,AO26-AN26,""),$A$1-AN26),"") | AS26: =if(AJ26,if(and(hour(AJ26+AS$5)>11,(hour(AJ26+AS$5)<20)),AJ26+AS$5,_xlfn.workday.intl(int(AJ26),1,"1000000",Holidays!A:A)+hour(AJ26+AS$5-$B$1)/24+minute(AJ26)/1440),"") | AT26: =if(AT26,AT26,if(AU26<>"",$A$1,"")) | AV26: =if(AS26,if(AT26<>"",if(AT26>AS26,AT26-AS26,""),$A$1-AS26),"") | AX26: No Response
A27: 44636.502 | G27: =if(A27,_xlfn.workday.intl(int(A27),1,"1000000",Holidays!A:A)+17/24,"") -> 44637.708 | H27: =if(H27,H27,if(I27<>"",$A$1,"")) | J27: =if(G27,if(H27<>"",if(H27>G27,H27-G27,""),$A$1-G27),"") -> 1496.2756 | K27: =if(G27,_xlfn.workday.intl(int(G27),0,"1000000",Holidays!A:A)+19/24,"") -> 44637.792 | L27: =if(L27,L27,if(M27<>"",$A$1,"")) | N27: =if(K27,if(L27<>"",if(L27>K27,L27-K27,""),$A$1-K27),"") -> 1496.1922 | O27: =if(A27,_xlfn.WORKDAY.INTL(A27,O$5,"1000000",Holidays!A:A)+hour(A27)/24+MINUTE(A27)/1440,"") -> 44637.501 | R27: =if(O27,if(P27<>"",if(P27>O27,P27-O27,""),$A$1-O27),"") -> 1496.4825 | U27: =if(O27,_xlfn.WORKDAY.INTL(O27,U$5,"1000000",Holidays!A:A)+hour(O27)/24+MINUTE(O27)/1440,"") -> 44638.501 | V27: =if(V27,V27,if(W27<>"",$A$1,"")) | X27: =if(U27,if(V27<>"",if(V27>U27,V27-U27,""),$A$1-U27),"") -> 1495.4825 | AB27: 2 | AH27: =IF(P27="","",P27+AB27+AC27+AD27+AE27+AF27) | AI27: =if(AH27,_xlfn.workday.intl(int(AH27),0,"1000000",Holidays!A:A)+18/24,"") | AJ27: =if(AJ27,AJ27,if(AK27<>"",$A$1,"")) | AL27: =if(AI27,if(AJ27<>"",if(AJ27>AI27,AJ27-AI27,""),$A$1-AI27),"") | AN27: =if(AJ27,if(and(hour(AJ27+AN$5)>11,(hour(AJ27+AN$5)<20)),AJ27+AN$5,_xlfn.workday.intl(int(AJ27),1,"1000000",Holidays!A:A)+hour(AJ27+AN$5-$B$1)/24+minute(AJ27)/1440),"") | AO27: =if(AO27,AO27,if(AP27<>"",$A$1,"")) | AQ27: =if(AN27,if(AO27<>"",if(AO27>AN27,AO27-AN27,""),$A$1-AN27),"") | AS27: =if(AJ27,if(and(hour(AJ27+AS$5)>11,(hour(AJ27+AS$5)<20)),AJ27+AS$5,_xlfn.workday.intl(int(AJ27),1,"1000000",Holidays!A:A)+hour(AJ27+AS$5-$B$1)/24+minute(AJ27)/1440),"") | AT27: =if(AT27,AT27,if(AU27<>"",$A$1,"")) | AV27: =if(AS27,if(AT27<>"",if(AT27>AS27,AT27-AS27,""),$A$1-AS27),"") | AX27: Hold
A28: 44636.509 | G28: =if(A28,_xlfn.workday.intl(int(A28),1,"1000000",Holidays!A:A)+17/24,"") -> 44637.708 | H28: =if(H28,H28,if(I28<>"",$A$1,"")) | J28: =if(G28,if(H28<>"",if(H28>G28,H28-G28,""),$A$1-G28),"") -> 1496.2756 | K28: =if(G28,_xlfn.workday.intl(int(G28),0,"1000000",Holidays!A:A)+19/24,"") -> 44637.792 | L28: =if(L28,L28,if(M28<>"",$A$1,"")) | N28: =if(K28,if(L28<>"",if(L28>K28,L28-K28,""),$A$1-K28),"") -> 1496.1922 | O28: =if(A28,_xlfn.WORKDAY.INTL(A28,O$5,"1000000",Holidays!A:A)+hour(A28)/24+MINUTE(A28)/1440,"") -> 44637.509 | R28: =if(O28,if(P28<>"",if(P28>O28,P28-O28,""),$A$1-O28),"") -> 1496.4749 | U28: =if(O28,_xlfn.WORKDAY.INTL(O28,U$5,"1000000",Holidays!A:A)+hour(O28)/24+MINUTE(O28)/1440,"") -> 44638.509 | V28: =if(V28,V28,if(W28<>"",$A$1,"")) | X28: =if(U28,if(V28<>"",if(V28>U28,V28-U28,""),$A$1-U28),"") -> 1495.4749 | AH28: =IF(P28="","",P28+AB28+AC28+AD28+AE28+AF28) | AI28: =if(AH28,_xlfn.workday.intl(int(AH28),0,"1000000",Holidays!A:A)+18/24,"") | AL28: =if(AI28,if(AJ28<>"",if(AJ28>AI28,AJ28-AI28,""),$A$1-AI28),"") | AN28: =if(AJ28,if(and(hour(AJ28+AN$5)>11,(hour(AJ28+AN$5)<20)),AJ28+AN$5,_xlfn.workday.intl(int(AJ28),1,"1000000",Holidays!A:A)+hour(AJ28+AN$5-$B$1)/24+minute(AJ28)/1440),"") | AO28: =if(AO28,AO28,if(AP28<>"",$A$1,"")) | AQ28: =if(AN28,if(AO28<>"",if(AO28>AN28,AO28-AN28,""),$A$1-AN28),"") | AS28: =if(AJ28,if(and(hour(AJ28+AS$5)>11,(hour(AJ28+AS$5)<20)),AJ28+AS$5,_xlfn.workday.intl(int(AJ28),1,"1000000",Holidays!A:A)+hour(AJ28+AS$5-$B$1)/24+minute(AJ28)/1440),"") | AT28: =if(AT28,AT28,if(AU28<>"",$A$1,"")) | AV28: =if(AS28,if(AT28<>"",if(AT28>AS28,AT28-AS28,""),$A$1-AS28),"") | AX28: Hold
A29: 44636.526 | G29: =if(A29,_xlfn.workday.intl(int(A29),1,"1000000",Holidays!A:A)+17/24,"") -> 44637.708 | H29: =if(H29,H29,if(I29<>"",$A$1,"")) -> 44744.479 | I29: done | J29: =if(G29,if(H29<>"",if(H29>G29,H29-G29,""),$A$1-G29),"") -> 106.77089 | K29: =if(G29,_xlfn.workday.intl(int(G29),0,"1000000",Holidays!A:A)+19/24,"") -> 44637.792 | L29: =if(L29,L29,if(M29<>"",$A$1,"")) -> 44744.454 | M29: done | N29: =if(K29,if(L29<>"",if(L29>K29,L29-K29,""),$A$1-K29),"") -> 106.66248 | O29: =if(A29,_xlfn.WORKDAY.INTL(A29,O$5,"1000000",Holidays!A:A)+hour(A29)/24+MINUTE(A29)/1440,"") -> 44637.525 | P29: 44744.454 | Q29: done | R29: =if(O29,if(P29<>"",if(P29>O29,P29-O29,""),$A$1-O29),"") -> 106.92919 | T29: done | U29: =if(O29,_xlfn.WORKDAY.INTL(O29,U$5,"1000000",Holidays!A:A)+hour(O29)/24+MINUTE(O29)/1440,"") -> 44638.525 | V29: =if(V29,V29,if(W29<>"",$A$1,"")) -> 44924.802 | W29: done | X29: =if(U29,if(V29<>"",if(V29>U29,V29-U29,""),$A$1-U29),"") -> 286.27744 | Y29: done | AB29: 1 | AC29: 2 | AH29: =IF(P29="","",P29+AB29+AC29+AD29+AE29+AF29) -> 44747.454 | AI29: =if(AH29,_xlfn.workday.intl(int(AH29),0,"1000000",Holidays!A:A)+18/24,"") -> 44747.75 | AJ29: =if(AJ29,AJ29,if(AK29<>"",$A$1,"")) -> 44744.454 | AK29: done | AL29: =if(AI29,if(AJ29<>"",if(AJ29>AI29,AJ29-AI29,""),$A$1-AI29),"") | AN29: =if(AJ29,if(and(hour(AJ29+AN$5)>11,(hour(AJ29+AN$5)<20)),AJ29+AN$5,_xlfn.workday.intl(int(AJ29),1,"1000000",Holidays!A:A)+hour(AJ29+AN$5-$B$1)/24+minute(AJ29)/1440),"") -> 44745.454 | AO29: =if(AO29,AO29,if(AP29<>"",$A$1,"")) -> 44744.454 | AP29: done | AQ29: =if(AN29,if(AO29<>"",if(AO29>AN29,AO29-AN29,""),$A$1-AN29),"") | AS29: =if(AJ29,if(and(hour(AJ29+AS$5)>11,(hour(AJ29+AS$5)<20)),AJ29+AS$5,_xlfn.workday.intl(int(AJ29),1,"1000000",Holidays!A:A)+hour(AJ29+AS$5-$B$1)/24+minute(AJ29)/1440),"") -> 44745.454 | AT29: =if(AT29,AT29,if(AU29<>"",$A$1,"")) -> 44744.454 | AU29: yes | AV29: =if(AS29,if(AT29<>"",if(AT29>AS29,AT29-AS29,""),$A$1-AS29),"") | AX29: done
A30: 44643.688 | G30: =if(A30,_xlfn.workday.intl(int(A30),1,"1000000",Holidays!A:A)+17/24,"") -> 44644.708 | H30: =if(H30,H30,if(I30<>"",$A$1,"")) | J30: =if(G30,if(H30<>"",if(H30>G30,H30-G30,""),$A$1-G30),"") -> 1489.2756 | K30: =if(G30,_xlfn.workday.intl(int(G30),0,"1000000",Holidays!A:A)+19/24,"") -> 44644.792 | L30: =if(L30,L30,if(M30<>"",$A$1,"")) | N30: =if(K30,if(L30<>"",if(L30>K30,L30-K30,""),$A$1-K30),"") -> 1489.1922 | O30: =if(A30,_xlfn.WORKDAY.INTL(A30,O$5,"1000000",Holidays!A:A)+hour(A30)/24+MINUTE(A30)/1440,"") -> 44644.688 | R30: =if(O30,if(P30<>"",if(P30>O30,P30-O30,""),$A$1-O30),"") -> 1489.2957 | U30: =if(O30,_xlfn.WORKDAY.INTL(O30,U$5,"1000000",Holidays!A:A)+hour(O30)/24+MINUTE(O30)/1440,"") -> 44645.688 | V30: =if(V30,V30,if(W30<>"",$A$1,"")) | X30: =if(U30,if(V30<>"",if(V30>U30,V30-U30,""),$A$1-U30),"") -> 1488.2957 | AH30: =IF(P30="","",P30+AB30+AC30+AD30+AE30+AF30) | AI30: =if(AH30,_xlfn.workday.intl(int(AH30),0,"1000000",Holidays!A:A)+18/24,"") | AJ30: =if(AJ30,AJ30,if(AK30<>"",$A$1,"")) | AL30: =if(AI30,if(AJ30<>"",if(AJ30>AI30,AJ30-AI30,""),$A$1-AI30),"") | AN30: =if(AJ30,if(and(hour(AJ30+AN$5)>11,(hour(AJ30+AN$5)<20)),AJ30+AN$5,_xlfn.workday.intl(int(AJ30),1,"1000000",Holidays!A:A)+hour(AJ30+AN$5-$B$1)/24+minute(AJ30)/1440),"") | AO30: =if(AO30,AO30,if(AP30<>"",$A$1,"")) | AQ30: =if(AN30,if(AO30<>"",if(AO30>AN30,AO30-AN30,""),$A$1-AN30),"") | AS30: =if(AJ30,if(and(hour(AJ30+AS$5)>11,(hour(AJ30+AS$5)<20)),AJ30+AS$5,_xlfn.workday.intl(int(AJ30),1,"1000000",Holidays!A:A)+hour(AJ30+AS$5-$B$1)/24+minute(AJ30)/1440),"") | AT30: =if(AT30,AT30,if(AU30<>"",$A$1,"")) | AV30: =if(AS30,if(AT30<>"",if(AT30>AS30,AT30-AS30,""),$A$1-AS30),"") | AX30: No Response
A31: 44643.69 | G31: =if(A31,_xlfn.workday.intl(int(A31),1,"1000000",Holidays!A:A)+17/24,"") -> 44644.708 | H31: =if(H31,H31,if(I31<>"",$A$1,"")) | J31: =if(G31,if(H31<>"",if(H31>G31,H31-G31,""),$A$1-G31),"") -> 1489.2756 | K31: =if(G31,_xlfn.workday.intl(int(G31),0,"1000000",Holidays!A:A)+19/24,"") -> 44644.792 | L31: =if(L31,L31,if(M31<>"",$A$1,"")) | N31: =if(K31,if(L31<>"",if(L31>K31,L31-K31,""),$A$1-K31),"") -> 1489.1922 | O31: =if(A31,_xlfn.WORKDAY.INTL(A31,O$5,"1000000",Holidays!A:A)+hour(A31)/24+MINUTE(A31)/1440,"") -> 44644.69 | R31: =if(O31,if(P31<>"",if(P31>O31,P31-O31,""),$A$1-O31),"") -> 1489.2943 | U31: =if(O31,_xlfn.WORKDAY.INTL(O31,U$5,"1000000",Holidays!A:A)+hour(O31)/24+MINUTE(O31)/1440,"") -> 44645.69 | V31: =if(V31,V31,if(W31<>"",$A$1,"")) | X31: =if(U31,if(V31<>"",if(V31>U31,V31-U31,""),$A$1-U31),"") -> 1488.2943 | AH31: =IF(P31="","",P31+AB31+AC31+AD31+AE31+AF31) | AI31: =if(AH31,_xlfn.workday.intl(int(AH31),0,"1000000",Holidays!A:A)+18/24,"") | AJ31: =if(AJ31,AJ31,if(AK31<>"",$A$1,"")) | AL31: =if(AI31,if(AJ31<>"",if(AJ31>AI31,AJ31-AI31,""),$A$1-AI31),"") | AN31: =if(AJ31,if(and(hour(AJ31+AN$5)>11,(hour(AJ31+AN$5)<20)),AJ31+AN$5,_xlfn.workday.intl(int(AJ31),1,"1000000",Holidays!A:A)+hour(AJ31+AN$5-$B$1)/24+minute(AJ31)/1440),"") | AO31: =if(AO31,AO31,if(AP31<>"",$A$1,"")) | AQ31: =if(AN31,if(AO31<>"",if(AO31>AN31,AO31-AN31,""),$A$1-AN31),"") | AS31: =if(AJ31,if(and(hour(AJ31+AS$5)>11,(hour(AJ31+AS$5)<20)),AJ31+AS$5,_xlfn.workday.intl(int(AJ31),1,"1000000",Holidays!A:A)+hour(AJ31+AS$5-$B$1)/24+minute(AJ31)/1440),"") | AT31: =if(AT31,AT31,if(AU31<>"",$A$1,"")) | AV31: =if(AS31,if(AT31<>"",if(AT31>AS31,AT31-AS31,""),$A$1-AS31),"") | AX31: Hold
A32: 44643.691 | G32: =if(A32,_xlfn.workday.intl(int(A32),1,"1000000",Holidays!A:A)+17/24,"") -> 44644.708 | H32: =if(H32,H32,if(I32<>"",$A$1,"")) | J32: =if(G32,if(H32<>"",if(H32>G32,H32-G32,""),$A$1-G32),"") -> 1489.2756 | K32: =if(G32,_xlfn.workday.intl(int(G32),0,"1000000",Holidays!A:A)+19/24,"") -> 44644.792 | L32: =if(L32,L32,if(M32<>"",$A$1,"")) | N32: =if(K32,if(L32<>"",if(L32>K32,L32-K32,""),$A$1-K32),"") -> 1489.1922 | O32: =if(A32,_xlfn.WORKDAY.INTL(A32,O$5,"1000000",Holidays!A:A)+hour(A32)/24+MINUTE(A32)/1440,"") -> 44644.691 | R32: =if(O32,if(P32<>"",if(P32>O32,P32-O32,""),$A$1-O32),"") -> 1489.2929 | U32: =if(O32,_xlfn.WORKDAY.INTL(O32,U$5,"1000000",Holidays!A:A)+hour(O32)/24+MINUTE(O32)/1440,"") -> 44645.691 | V32: =if(V32,V32,if(W32<>"",$A$1,"")) | X32: =if(U32,if(V32<>"",if(V32>U32,V32-U32,""),$A$1-U32),"") -> 1488.2929 | AH32: =IF(P32="","",P32+AB32+AC32+AD32+AE32+AF32) | AI32: =if(AH32,_xlfn.workday.intl(int(AH32),0,"1000000",Holidays!A:A)+18/24,"") | AJ32: =if(AJ32,AJ32,if(AK32<>"",$A$1,"")) | AL32: =if(AI32,if(AJ32<>"",if(AJ32>AI32,AJ32-AI32,""),$A$1-AI32),"") | AN32: =if(AJ32,if(and(hour(AJ32+AN$5)>11,(hour(AJ32+AN$5)<20)),AJ32+AN$5,_xlfn.workday.intl(int(AJ32),1,"1000000",Holidays!A:A)+hour(AJ32+AN$5-$B$1)/24+minute(AJ32)/1440),"") | AO32: =if(AO32,AO32,if(AP32<>"",$A$1,"")) | AQ32: =if(AN32,if(AO32<>"",if(AO32>AN32,AO32-AN32,""),$A$1-AN32),"") | AS32: =if(AJ32,if(and(hour(AJ32+AS$5)>11,(hour(AJ32+AS$5)<20)),AJ32+AS$5,_xlfn.workday.intl(int(AJ32),1,"1000000",Holidays!A:A)+hour(AJ32+AS$5-$B$1)/24+minute(AJ32)/1440),"") | AT32: =if(AT32,AT32,if(AU32<>"",$A$1,"")) | AV32: =if(AS32,if(AT32<>"",if(AT32>AS32,AT32-AS32,""),$A$1-AS32),"") | AX32: No Response
A33: 44643.692 | G33: =if(A33,_xlfn.workday.intl(int(A33),1,"1000000",Holidays!A:A)+17/24,"") -> 44644.708 | H33: =if(H33,H33,if(I33<>"",$A$1,"")) | J33: =if(G33,if(H33<>"",if(H33>G33,H33-G33,""),$A$1-G33),"") -> 1489.2756 | K33: =if(G33,_xlfn.workday.intl(int(G33),0,"1000000",Holidays!A:A)+19/24,"") -> 44644.792 | L33: =if(L33,L33,if(M33<>"",$A$1,"")) | N33: =if(K33,if(L33<>"",if(L33>K33,L33-K33,""),$A$1-K33),"") -> 1489.1922 | O33: =if(A33,_xlfn.WORKDAY.INTL(A33,O$5,"1000000",Holidays!A:A)+hour(A33)/24+MINUTE(A33)/1440,"") -> 44644.692 | R33: =if(O33,if(P33<>"",if(P33>O33,P33-O33,""),$A$1-O33),"") -> 1489.2922 | U33: =if(O33,_xlfn.WORKDAY.INTL(O33,U$5,"1000000",Holidays!A:A)+hour(O33)/24+MINUTE(O33)/1440,"") -> 44645.692 | V33: =if(V33,V33,if(W33<>"",$A$1,"")) | X33: =if(U33,if(V33<>"",if(V33>U33,V33-U33,""),$A$1-U33),"") -> 1488.2922 | AH33: =IF(P33="","",P33+AB33+AC33+AD33+AE33+AF33) | AI33: =if(AH33,_xlfn.workday.intl(int(AH33),0,"1000000",Holidays!A:A)+18/24,"") | AJ33: =if(AJ33,AJ33,if(AK33<>"",$A$1,"")) | AL33: =if(AI33,if(AJ33<>"",if(AJ33>AI33,AJ33-AI33,""),$A$1-AI33),"") | AN33: =if(AJ33,if(and(hour(AJ33+AN$5)>11,(hour(AJ33+AN$5)<20)),AJ33+AN$5,_xlfn.workday.intl(int(AJ33),1,"1000000",Holidays!A:A)+hour(AJ33+AN$5-$B$1)/24+minute(AJ33)/1440),"") | AO33: =if(AO33,AO33,if(AP33<>"",$A$1,"")) | AQ33: =if(AN33,if(AO33<>"",if(AO33>AN33,AO33-AN33,""),$A$1-AN33),"") | AS33: =if(AJ33,if(and(hour(AJ33+AS$5)>11,(hour(AJ33+AS$5)<20)),AJ33+AS$5,_xlfn.workday.intl(int(AJ33),1,"1000000",Holidays!A:A)+hour(AJ33+AS$5-$B$1)/24+minute(AJ33)/1440),"") | AT33: =if(AT33,AT33,if(AU33<>"",$A$1,"")) | AV33: =if(AS33,if(AT33<>"",if(AT33>AS33,AT33-AS33,""),$A$1-AS33),"") | AX33: No Response
A34: 44643.693 | G34: =if(A34,_xlfn.workday.intl(int(A34),1,"1000000",Holidays!A:A)+17/24,"") -> 44644.708 | H34: =if(H34,H34,if(I34<>"",$A$1,"")) | J34: =if(G34,if(H34<>"",if(H34>G34,H34-G34,""),$A$1-G34),"") -> 1489.2756 | K34: =if(G34,_xlfn.workday.intl(int(G34),0,"1000000",Holidays!A:A)+19/24,"") -> 44644.792 | L34: =if(L34,L34,if(M34<>"",$A$1,"")) | N34: =if(K34,if(L34<>"",if(L34>K34,L34-K34,""),$A$1-K34),"") -> 1489.1922 | O34: =if(A34,_xlfn.WORKDAY.INTL(A34,O$5,"1000000",Holidays!A:A)+hour(A34)/24+MINUTE(A34)/1440,"") -> 44644.693 | R34: =if(O34,if(P34<>"",if(P34>O34,P34-O34,""),$A$1-O34),"") -> 1489.2909 | U34: =if(O34,_xlfn.WORKDAY.INTL(O34,U$5,"1000000",Holidays!A:A)+hour(O34)/24+MINUTE(O34)/1440,"") -> 44645.693 | V34: =if(V34,V34,if(W34<>"",$A$1,"")) | X34: =if(U34,if(V34<>"",if(V34>U34,V34-U34,""),$A$1-U34),"") -> 1488.2909 | AH34: =IF(P34="","",P34+AB34+AC34+AD34+AE34+AF34) | AI34: =if(AH34,_xlfn.workday.intl(int(AH34),0,"1000000",Holidays!A:A)+18/24,"") | AJ34: =if(AJ34,AJ34,if(AK34<>"",$A$1,"")) | AL34: =if(AI34,if(AJ34<>"",if(AJ34>AI34,AJ34-AI34,""),$A$1-AI34),"") | AN34: =if(AJ34,if(and(hour(AJ34+AN$5)>11,(hour(AJ34+AN$5)<20)),AJ34+AN$5,_xlfn.workday.intl(int(AJ34),1,"1000000",Holidays!A:A)+hour(AJ34+AN$5-$B$1)/24+minute(AJ34)/1440),"") | AO34: =if(AO34,AO34,if(AP34<>"",$A$1,"")) | AQ34: =if(AN34,if(AO34<>"",if(AO34>AN34,AO34-AN34,""),$A$1-AN34),"") | AS34: =if(AJ34,if(and(hour(AJ34+AS$5)>11,(hour(AJ34+AS$5)<20)),AJ34+AS$5,_xlfn.workday.intl(int(AJ34),1,"1000000",Holidays!A:A)+hour(AJ34+AS$5-$B$1)/24+minute(AJ34)/1440),"") | AT34: =if(AT34,AT34,if(AU34<>"",$A$1,"")) | AV34: =if(AS34,if(AT34<>"",if(AT34>AS34,AT34-AS34,""),$A$1-AS34),"") | AX34: Hold
A35: 44645.583 | G35: =if(A35,_xlfn.workday.intl(int(A35),1,"1000000",Holidays!A:A)+17/24,"") -> 44646.708 | H35: =if(H35,H35,if(I35<>"",$A$1,"")) | J35: =if(G35,if(H35<>"",if(H35>G35,H35-G35,""),$A$1-G35),"") -> 1487.2756 | K35: =if(G35,_xlfn.workday.intl(int(G35),0,"1000000",Holidays!A:A)+19/24,"") -> 44646.792 | L35: =if(L35,L35,if(M35<>"",$A$1,"")) | N35: =if(K35,if(L35<>"",if(L35>K35,L35-K35,""),$A$1-K35),"") -> 1487.1922 | O35: =if(A35,_xlfn.WORKDAY.INTL(A35,O$5,"1000000",Holidays!A:A)+hour(A35)/24+MINUTE(A35)/1440,"") -> 44646.583 | R35: =if(O35,if(P35<>"",if(P35>O35,P35-O35,""),$A$1-O35),"") -> 1487.4013 | U35: =if(O35,_xlfn.WORKDAY.INTL(O35,U$5,"1000000",Holidays!A:A)+hour(O35)/24+MINUTE(O35)/1440,"") -> 44647.583 | V35: =if(V35,V35,if(W35<>"",$A$1,"")) | X35: =if(U35,if(V35<>"",if(V35>U35,V35-U35,""),$A$1-U35),"") -> 1486.4013 | AH35: =IF(P35="","",P35+AB35+AC35+AD35+AE35+AF35) | AI35: =if(AH35,_xlfn.workday.intl(int(AH35),0,"1000000",Holidays!A:A)+18/24,"") | AJ35: =if(AJ35,AJ35,if(AK35<>"",$A$1,"")) | AL35: =if(AI35,if(AJ35<>"",if(AJ35>AI35,AJ35-AI35,""),$A$1-AI35),"") | AN35: =if(AJ35,if(and(hour(AJ35+AN$5)>11,(hour(AJ35+AN$5)<20)),AJ35+AN$5,_xlfn.workday.intl(int(AJ35),1,"1000000",Holidays!A:A)+hour(AJ35+AN$5-$B$1)/24+minute(AJ35)/1440),"") | AO35: =if(AO35,AO35,if(AP35<>"",$A$1,"")) | AQ35: =if(AN35,if(AO35<>"",if(AO35>AN35,AO35-AN35,""),$A$1-AN35),"") | AS35: =if(AJ35,if(and(hour(AJ35+AS$5)>11,(hour(AJ35+AS$5)<20)),AJ35+AS$5,_xlfn.workday.intl(int(AJ35),1,"1000000",Holidays!A:A)+hour(AJ35+AS$5-$B$1)/24+minute(AJ35)/1440),"") | AT35: =if(AT35,AT35,if(AU35<>"",$A$1,"")) | AV35: =if(AS35,if(AT35<>"",if(AT35>AS35,AT35-AS35,""),$A$1-AS35),"") | AX35: No Response
A36: 44645.802 | G36: =if(A36,_xlfn.workday.intl(int(A36),1,"1000000",Holidays!A:A)+17/24,"") -> 44646.708 | H36: =if(H36,H36,if(I36<>"",$A$1,"")) -> 44744.475 | I36: done | J36: =if(G36,if(H36<>"",if(H36>G36,H36-G36,""),$A$1-G36),"") -> 97.766285 | K36: =if(G36,_xlfn.workday.intl(int(G36),0,"1000000",Holidays!A:A)+19/24,"") -> 44646.792 | L36: =if(L36,L36,if(M36<>"",$A$1,"")) -> 44744.453 | M36: done | N36: =if(K36,if(L36<>"",if(L36>K36,L36-K36,""),$A$1-K36),"") -> 97.661092 | O36: =if(A36,_xlfn.WORKDAY.INTL(A36,O$5,"1000000",Holidays!A:A)+hour(A36)/24+MINUTE(A36)/1440,"") -> 44646.801 | P36: 44744.453 | Q36: done | R36: =if(O36,if(P36<>"",if(P36>O36,P36-O36,""),$A$1-O36),"") -> 97.6514 | T36: done | U36: =if(O36,_xlfn.WORKDAY.INTL(O36,U$5,"1000000",Holidays!A:A)+hour(O36)/24+MINUTE(O36)/1440,"") -> 44647.801 | V36: =if(V36,V36,if(W36<>"",$A$1,"")) -> 44924.804 | W36: done | X36: =if(U36,if(V36<>"",if(V36>U36,V36-U36,""),$A$1-U36),"") -> 277.00301 | Y36: done | AB36: 1 | AC36: 2 | AD36: 3 | AE36: 4 | AH36: =IF(P36="","",P36+AB36+AC36+AD36+AE36+AF36) -> 44754.453 | AI36: =if(AH36,_xlfn.workday.intl(int(AH36),0,"1000000",Holidays!A:A)+18/24,"") -> 44754.75 | AJ36: =if(AJ36,AJ36,if(AK36<>"",$A$1,"")) -> 44733.665 | AK36: done | AL36: =if(AI36,if(AJ36<>"",if(AJ36>AI36,AJ36-AI36,""),$A$1-AI36),"") | AN36: =if(AJ36,if(and(hour(AJ36+AN$5)>11,(hour(AJ36+AN$5)<20)),AJ36+AN$5,_xlfn.workday.intl(int(AJ36),1,"1000000",Holidays!A:A)+hour(AJ36+AN$5-$B$1)/24+minute(AJ36)/1440),"") -> 44734.665 | AO36: =if(AO36,AO36,if(AP36<>"",$A$1,"")) -> 44744.453 | AP36: done | AQ36: =if(AN36,if(AO36<>"",if(AO36>AN36,AO36-AN36,""),$A$1-AN36),"") -> 9.7878979 | AS36: =if(AJ36,if(and(hour(AJ36+AS$5)>11,(hour(AJ36+AS$5)<20)),AJ36+AS$5,_xlfn.workday.intl(int(AJ36),1,"1000000",Holidays!A:A)+hour(AJ36+AS$5-$B$1)/24+minute(AJ36)/1440),"") -> 44735.665 | AT36: =if(AT36,AT36,if(AU36<>"",$A$1,"")) -> 44744.453 | AU36: yes | AV36: =if(AS36,if(AT36<>"",if(AT36>AS36,AT36-AS36,""),$A$1-AS36),"") -> 8.7879318 | AX36: done
A37: 44678.492 | G37: =if(A37,_xlfn.workday.intl(int(A37),1,"1000000",Holidays!A:A)+17/24,"") -> 44679.708 | H37: =if(H37,H37,if(I37<>"",$A$1,"")) | J37: =if(G37,if(H37<>"",if(H37>G37,H37-G37,""),$A$1-G37),"") -> 1454.2756 | K37: =if(G37,_xlfn.workday.intl(int(G37),0,"1000000",Holidays!A:A)+19/24,"") -> 44679.792 | L37: =if(L37,L37,if(M37<>"",$A$1,"")) | N37: =if(K37,if(L37<>"",if(L37>K37,L37-K37,""),$A$1-K37),"") -> 1454.1922 | O37: =if(A37,_xlfn.WORKDAY.INTL(A37,O$5,"1000000",Holidays!A:A)+hour(A37)/24+MINUTE(A37)/1440,"") -> 44679.491 | R37: =if(O37,if(P37<>"",if(P37>O37,P37-O37,""),$A$1-O37),"") -> 1454.4929 | U37: =if(O37,_xlfn.WORKDAY.INTL(O37,U$5,"1000000",Holidays!A:A)+hour(O37)/24+MINUTE(O37)/1440,"") -> 44680.491 | V37: =if(V37,V37,if(W37<>"",$A$1,"")) | X37: =if(U37,if(V37<>"",if(V37>U37,V37-U37,""),$A$1-U37),"") -> 1453.4929 | AH37: =IF(P37="","",P37+AB37+AC37+AD37+AE37+AF37) | AI37: =if(AH37,_xlfn.workday.intl(int(AH37),0,"1000000",Holidays!A:A)+18/24,"") | AJ37: =if(AJ37,AJ37,if(AK37<>"",$A$1,"")) | AL37: =if(AI37,if(AJ37<>"",if(AJ37>AI37,AJ37-AI37,""),$A$1-AI37),"") | AN37: =if(AJ37,if(and(hour(AJ37+AN$5)>11,(hour(AJ37+AN$5)<20)),AJ37+AN$5,_xlfn.workday.intl(int(AJ37),1,"1000000",Holidays!A:A)+hour(AJ37+AN$5-$B$1)/24+minute(AJ37)/1440),"") | AO37: =if(AO37,AO37,if(AP37<>"",$A$1,"")) | AQ37: =if(AN37,if(AO37<>"",if(AO37>AN37,AO37-AN37,""),$A$1-AN37),"") | AS37: =if(AJ37,if(and(hour(AJ37+AS$5)>11,(hour(AJ37+AS$5)<20)),AJ37+AS$5,_xlfn.workday.intl(int(AJ37),1,"1000000",Holidays!A:A)+hour(AJ37+AS$5-$B$1)/24+minute(AJ37)/1440),"") | AT37: =if(AT37,AT37,if(AU37<>"",$A$1,"")) | AV37: =if(AS37,if(AT37<>"",if(AT37>AS37,AT37-AS37,""),$A$1-AS37),"") | AX37: No Response
A38: 44678.493 | G38: =if(A38,_xlfn.workday.intl(int(A38),1,"1000000",Holidays!A:A)+17/24,"") -> 44679.708 | H38: =if(H38,H38,if(I38<>"",$A$1,"")) -> 44744.451 | I38: done | J38: =if(G38,if(H38<>"",if(H38>G38,H38-G38,""),$A$1-G38),"") -> 64.743161 | K38: =if(G38,_xlfn.workday.intl(int(G38),0,"1000000",Holidays!A:A)+19/24,"") -> 44679.792 | L38: =if(L38,L38,if(M38<>"",$A$1,"")) -> 44744.452 | M38: done | N38: =if(K38,if(L38<>"",if(L38>K38,L38-K38,""),$A$1-K38),"") -> 64.659858 | O38: =if(A38,_xlfn.WORKDAY.INTL(A38,O$5,"1000000",Holidays!A:A)+hour(A38)/24+MINUTE(A38)/1440,"") -> 44679.492 | P38: 44744.452 | Q38: done | R38: =if(O38,if(P38<>"",if(P38>O38,P38-O38,""),$A$1-O38),"") -> 64.959272 | T38: done | U38: =if(O38,_xlfn.WORKDAY.INTL(O38,U$5,"1000000",Holidays!A:A)+hour(O38)/24+MINUTE(O38)/1440,"") -> 44680.492 | V38: =if(V38,V38,if(W38<>"",$A$1,"")) -> 44924.805 | W38: done | X38: =if(U38,if(V38<>"",if(V38>U38,V38-U38,""),$A$1-U38),"") -> 244.31281 | Y38: done | AB38: 1 | AC38: 2 | AD38: 3 | AH38: =IF(P38="","",P38+AB38+AC38+AD38+AE38+AF38) -> 44750.452 | AI38: =if(AH38,_xlfn.workday.intl(int(AH38),0,"1000000",Holidays!A:A)+18/24,"") -> 44750.75 | AJ38: =if(AJ38,AJ38,if(AK38<>"",$A$1,"")) -> 44733.665 | AK38: done | AL38: =if(AI38,if(AJ38<>"",if(AJ38>AI38,AJ38-AI38,""),$A$1-AI38),"") | AN38: =if(AJ38,if(and(hour(AJ38+AN$5)>11,(hour(AJ38+AN$5)<20)),AJ38+AN$5,_xlfn.workday.intl(int(AJ38),1,"1000000",Holidays!A:A)+hour(AJ38+AN$5-$B$1)/24+minute(AJ38)/1440),"") -> 44734.665 | AO38: =if(AO38,AO38,if(AP38<>"",$A$1,"")) -> 44744.452 | AP38: done | AQ38: =if(AN38,if(AO38<>"",if(AO38>AN38,AO38-AN38,""),$A$1-AN38),"") -> 9.7862736 | AS38: =if(AJ38,if(and(hour(AJ38+AS$5)>11,(hour(AJ38+AS$5)<20)),AJ38+AS$5,_xlfn.workday.intl(int(AJ38),1,"1000000",Holidays!A:A)+hour(AJ38+AS$5-$B$1)/24+minute(AJ38)/1440),"") -> 44735.665 | AT38: =if(AT38,AT38,if(AU38<>"",$A$1,"")) -> 44744.452 | AU38: yes | AV38: =if(AS38,if(AT38<>"",if(AT38>AS38,AT38-AS38,""),$A$1-AS38),"") -> 8.7863046 | AX38: done
A39: 44680.736 | G39: =if(A39,_xlfn.workday.intl(int(A39),1,"1000000",Holidays!A:A)+17/24,"") -> 44681.708 | H39: =if(H39,H39,if(I39<>"",$A$1,"")) -> 44744.452 | I39: done | J39: =if(G39,if(H39<>"",if(H39>G39,H39-G39,""),$A$1-G39),"") -> 62.74347 | K39: =if(G39,_xlfn.workday.intl(int(G39),0,"1000000",Holidays!A:A)+19/24,"") -> 44681.792 | L39: =if(L39,L39,if(M39<>"",$A$1,"")) -> 44744.452 | M39: done | N39: =if(K39,if(L39<>"",if(L39>K39,L39-K39,""),$A$1-K39),"") -> 62.660155 | O39: =if(A39,_xlfn.WORKDAY.INTL(A39,O$5,"1000000",Holidays!A:A)+hour(A39)/24+MINUTE(A39)/1440,"") -> 44681.736 | P39: 44744.452 | Q39: done | R39: =if(O39,if(P39<>"",if(P39>O39,P39-O39,""),$A$1-O39),"") -> 62.715725 | T39: done | U39: =if(O39,_xlfn.WORKDAY.INTL(O39,U$5,"1000000",Holidays!A:A)+hour(O39)/24+MINUTE(O39)/1440,"") -> 44682.736 | V39: =if(V39,V39,if(W39<>"",$A$1,"")) -> 44924.805 | W39: done | X39: =if(U39,if(V39<>"",if(V39>U39,V39-U39,""),$A$1-U39),"") -> 242.06908 | Y39: done | AB39: 1 | AC39: 1 | AD39: 2 | AE39: 3 | AF39: 4 | AH39: =IF(P39="","",P39+AB39+AC39+AD39+AE39+AF39) -> 44755.452 | AI39: =if(AH39,_xlfn.workday.intl(int(AH39),0,"1000000",Holidays!A:A)+18/24,"") -> 44755.75 | AJ39: =if(AJ39,AJ39,if(AK39<>"",$A$1,"")) -> 44744.452 | AK39: done | AL39: =if(AI39,if(AJ39<>"",if(AJ39>AI39,AJ39-AI39,""),$A$1-AI39),"") | AN39: =if(AJ39,if(and(hour(AJ39+AN$5)>11,(hour(AJ39+AN$5)<20)),AJ39+AN$5,_xlfn.workday.intl(int(AJ39),1,"1000000",Holidays!A:A)+hour(AJ39+AN$5-$B$1)/24+minute(AJ39)/1440),"") -> 44745.451 | AO39: =if(AO39,AO39,if(AP39<>"",$A$1,"")) -> 44744.452 | AP39: done | AQ39: =if(AN39,if(AO39<>"",if(AO39>AN39,AO39-AN39,""),$A$1-AN39),"") | AS39: =if(AJ39,if(and(hour(AJ39+AS$5)>11,(hour(AJ39+AS$5)<20)),AJ39+AS$5,_xlfn.workday.intl(int(AJ39),1,"1000000",Holidays!A:A)+hour(AJ39+AS$5-$B$1)/24+minute(AJ39)/1440),"") -> 44745.451 | AT39: =if(AT39,AT39,if(AU39<>"",$A$1,"")) -> 44744.452 | AU39: yes | AV39: =if(AS39,if(AT39<>"",if(AT39>AS39,AT39-AS39,""),$A$1-AS39),"") | AX39: done
A40: 44680.738 | G40: =if(A40,_xlfn.workday.intl(int(A40),1,"1000000",Holidays!A:A)+17/24,"") -> 44681.708 | H40: =if(H40,H40,if(I40<>"",$A$1,"")) -> 44744.452 | I40: done | J40: =if(G40,if(H40<>"",if(H40>G40,H40-G40,""),$A$1-G40),"") -> 62.743744 | K40: =if(G40,_xlfn.workday.intl(int(G40),0,"1000000",Holidays!A:A)+19/24,"") -> 44681.792 | L40: =if(L40,L40,if(M40<>"",$A$1,"")) -> 44744.452 | M40: done | N40: =if(K40,if(L40<>"",if(L40>K40,L40-K40,""),$A$1-K40),"") -> 62.660425 | O40: =if(A40,_xlfn.WORKDAY.INTL(A40,O$5,"1000000",Holidays!A:A)+hour(A40)/24+MINUTE(A40)/1440,"") -> 44681.738 | P40: 44744.452 | Q40: done | R40: =if(O40,if(P40<>"",if(P40>O40,P40-O40,""),$A$1-O40),"") -> 62.71461 | T40: done | U40: =if(O40,_xlfn.WORKDAY.INTL(O40,U$5,"1000000",Holidays!A:A)+hour(O40)/24+MINUTE(O40)/1440,"") -> 44682.738 | V40: =if(V40,V40,if(W40<>"",$A$1,"")) -> 44924.805 | W40: done | X40: =if(U40,if(V40<>"",if(V40>U40,V40-U40,""),$A$1-U40),"") -> 242.0677 | Y40: done | AB40: 1 | AC40: 3 | AD40: 4 | AH40: =IF(P40="","",P40+AB40+AC40+AD40+AE40+AF40) -> 44752.452 | AI40: =if(AH40,_xlfn.workday.intl(int(AH40),0,"1000000",Holidays!A:A)+18/24,"") -> 44752.75 | AJ40: =if(AJ40,AJ40,if(AK40<>"",$A$1,"")) -> 44733.666 | AK40: done | AL40: =if(AI40,if(AJ40<>"",if(AJ40>AI40,AJ40-AI40,""),$A$1-AI40),"") | AN40: =if(AJ40,if(and(hour(AJ40+AN$5)>11,(hour(AJ40+AN$5)<20)),AJ40+AN$5,_xlfn.workday.intl(int(AJ40),1,"1000000",Holidays!A:A)+hour(AJ40+AN$5-$B$1)/24+minute(AJ40)/1440),"") -> 44734.666 | AO40: =if(AO40,AO40,if(AP40<>"",$A$1,"")) -> 44744.452 | AP40: done | AQ40: =if(AN40,if(AO40<>"",if(AO40>AN40,AO40-AN40,""),$A$1-AN40),"") -> 9.7866417 | AS40: =if(AJ40,if(and(hour(AJ40+AS$5)>11,(hour(AJ40+AS$5)<20)),AJ40+AS$5,_xlfn.workday.intl(int(AJ40),1,"1000000",Holidays!A:A)+hour(AJ40+AS$5-$B$1)/24+minute(AJ40)/1440),"") -> 44735.666 | AT40: =if(AT40,AT40,if(AU40<>"",$A$1,"")) -> 44744.452 | AU40: yes | AV40: =if(AS40,if(AT40<>"",if(AT40>AS40,AT40-AS40,""),$A$1-AS40),"") -> 8.786657 | AX40: done
A41: 44680.739 | G41: =if(A41,_xlfn.workday.intl(int(A41),1,"1000000",Holidays!A:A)+17/24,"") -> 44681.708 | H41: =if(H41,H41,if(I41<>"",$A$1,"")) | J41: =if(G41,if(H41<>"",if(H41>G41,H41-G41,""),$A$1-G41),"") -> 1452.2756 | K41: =if(G41,_xlfn.workday.intl(int(G41),0,"1000000",Holidays!A:A)+19/24,"") -> 44681.792 | L41: =if(L41,L41,if(M41<>"",$A$1,"")) | N41: =if(K41,if(L41<>"",if(L41>K41,L41-K41,""),$A$1-K41),"") -> 1452.1922 | O41: =if(A41,_xlfn.WORKDAY.INTL(A41,O$5,"1000000",Holidays!A:A)+hour(A41)/24+MINUTE(A41)/1440,"") -> 44681.739 | R41: =if(O41,if(P41<>"",if(P41>O41,P41-O41,""),$A$1-O41),"") -> 1452.245 | U41: =if(O41,_xlfn.WORKDAY.INTL(O41,U$5,"1000000",Holidays!A:A)+hour(O41)/24+MINUTE(O41)/1440,"") -> 44682.739 | V41: =if(V41,V41,if(W41<>"",$A$1,"")) | X41: =if(U41,if(V41<>"",if(V41>U41,V41-U41,""),$A$1-U41),"") -> 1451.245 | AH41: =IF(P41="","",P41+AB41+AC41+AD41+AE41+AF41) | AI41: =if(AH41,_xlfn.workday.intl(int(AH41),0,"1000000",Holidays!A:A)+18/24,"") | AJ41: =if(AJ41,AJ41,if(AK41<>"",$A$1,"")) -> 44733.666 | AK41: done | AL41: =if(AI41,if(AJ41<>"",if(AJ41>AI41,AJ41-AI41,""),$A$1-AI41),"") | AN41: =if(AJ41,if(and(hour(AJ41+AN$5)>11,(hour(AJ41+AN$5)<20)),AJ41+AN$5,_xlfn.workday.intl(int(AJ41),1,"1000000",Holidays!A:A)+hour(AJ41+AN$5-$B$1)/24+minute(AJ41)/1440),"") -> 44734.666 | AO41: =if(AO41,AO41,if(AP41<>"",$A$1,"")) | AQ41: =if(AN41,if(AO41<>"",if(AO41>AN41,AO41-AN41,""),$A$1-AN41),"") -> 1399.3183 | AS41: =if(AJ41,if(and(hour(AJ41+AS$5)>11,(hour(AJ41+AS$5)<20)),AJ41+AS$5,_xlfn.workday.intl(int(AJ41),1,"1000000",Holidays!A:A)+hour(AJ41+AS$5-$B$1)/24+minute(AJ41)/1440),"") -> 44735.666 | AT41: =if(AT41,AT41,if(AU41<>"",$A$1,"")) | AV41: =if(AS41,if(AT41<>"",if(AT41>AS41,AT41-AS41,""),$A$1-AS41),"") -> 1398.3183 | AX41: no response
A42: 44681.558 | G42: =if(A42,_xlfn.workday.intl(int(A42),1,"1000000",Holidays!A:A)+17/24,"") -> 44682.708 | H42: =if(H42,H42,if(I42<>"",$A$1,"")) | J42: =if(G42,if(H42<>"",if(H42>G42,H42-G42,""),$A$1-G42),"") -> 1451.2756 | K42: =if(G42,_xlfn.workday.intl(int(G42),0,"1000000",Holidays!A:A)+19/24,"") -> 44682.792 | L42: =if(L42,L42,if(M42<>"",$A$1,"")) | N42: =if(K42,if(L42<>"",if(L42>K42,L42-K42,""),$A$1-K42),"") -> 1451.1922 | O42: =if(A42,_xlfn.WORKDAY.INTL(A42,O$5,"1000000",Holidays!A:A)+hour(A42)/24+MINUTE(A42)/1440,"") -> 44682.558 | P42: 44924.806 | Q42: done | R42: =if(O42,if(P42<>"",if(P42>O42,P42-O42,""),$A$1-O42),"") -> 242.24845 | T42: done | U42: =if(O42,_xlfn.WORKDAY.INTL(O42,U$5,"1000000",Holidays!A:A)+hour(O42)/24+MINUTE(O42)/1440,"") -> 44684.558 | V42: =if(V42,V42,if(W42<>"",$A$1,"")) -> 44924.806 | W42: done | X42: =if(U42,if(V42<>"",if(V42>U42,V42-U42,""),$A$1-U42),"") -> 240.24828 | Y42: done | AB42: 1 | AC42: 3 | AH42: =IF(P42="","",P42+AB42+AC42+AD42+AE42+AF42) -> 44928.806 | AI42: =if(AH42,_xlfn.workday.intl(int(AH42),0,"1000000",Holidays!A:A)+18/24,"") -> 44928.75 | AJ42: =if(AJ42,AJ42,if(AK42<>"",$A$1,"")) -> 44728.733 | AK42: DONE | AL42: =if(AI42,if(AJ42<>"",if(AJ42>AI42,AJ42-AI42,""),$A$1-AI42),"") | AN42: =if(AJ42,if(and(hour(AJ42+AN$5)>11,(hour(AJ42+AN$5)<20)),AJ42+AN$5,_xlfn.workday.intl(int(AJ42),1,"1000000",Holidays!A:A)+hour(AJ42+AN$5-$B$1)/24+minute(AJ42)/1440),"") -> 44729.733 | AO42: =if(AO42,AO42,if(AP42<>"",$A$1,"")) -> 44924.806 | AP42: done | AQ42: =if(AN42,if(AO42<>"",if(AO42>AN42,AO42-AN42,""),$A$1-AN42),"") -> 195.07246 | AS42: =if(AJ42,if(and(hour(AJ42+AS$5)>11,(hour(AJ42+AS$5)<20)),AJ42+AS$5,_xlfn.workday.intl(int(AJ42),1,"1000000",Holidays!A:A)+hour(AJ42+AS$5-$B$1)/24+minute(AJ42)/1440),"") -> 44730.733 | AT42: =if(AT42,AT42,if(AU42<>"",$A$1,"")) -> 44835.489 | AU42: yes | AV42: =if(AS42,if(AT42<>"",if(AT42>AS42,AT42-AS42,""),$A$1-AS42),"") -> 104.75561 | AX42: DONE
A43: 44684.611 | G43: =if(A43,_xlfn.workday.intl(int(A43),1,"1000000",Holidays!A:A)+17/24,"") -> 44685.708 | H43: =if(H43,H43,if(I43<>"",$A$1,"")) | J43: =if(G43,if(H43<>"",if(H43>G43,H43-G43,""),$A$1-G43),"") -> 1448.2756 | K43: =if(G43,_xlfn.workday.intl(int(G43),0,"1000000",Holidays!A:A)+19/24,"") -> 44685.792 | L43: =if(L43,L43,if(M43<>"",$A$1,"")) | N43: =if(K43,if(L43<>"",if(L43>K43,L43-K43,""),$A$1-K43),"") -> 1448.1922 | O43: =if(A43,_xlfn.WORKDAY.INTL(A43,O$5,"1000000",Holidays!A:A)+hour(A43)/24+MINUTE(A43)/1440,"") -> 44685.61 | R43: =if(O43,if(P43<>"",if(P43>O43,P43-O43,""),$A$1-O43),"") -> 1448.3735 | U43: =if(O43,_xlfn.WORKDAY.INTL(O43,U$5,"1000000",Holidays!A:A)+hour(O43)/24+MINUTE(O43)/1440,"") -> 44686.61 | V43: =if(V43,V43,if(W43<>"",$A$1,"")) | X43: =if(U43,if(V43<>"",if(V43>U43,V43-U43,""),$A$1-U43),"") -> 1447.3735 | AH43: =IF(P43="","",P43+AB43+AC43+AD43+AE43+AF43) | AI43: =if(AH43,_xlfn.workday.intl(int(AH43),0,"1000000",Holidays!A:A)+18/24,"") | AJ43: =if(AJ43,AJ43,if(AK43<>"",$A$1,"")) | AL43: =if(AI43,if(AJ43<>"",if(AJ43>AI43,AJ43-AI43,""),$A$1-AI43),"") | AN43: =if(AJ43,if(and(hour(AJ43+AN$5)>11,(hour(AJ43+AN$5)<20)),AJ43+AN$5,_xlfn.workday.intl(int(AJ43),1,"1000000",Holidays!A:A)+hour(AJ43+AN$5-$B$1)/24+minute(AJ43)/1440),"") | AO43: =if(AO43,AO43,if(AP43<>"",$A$1,"")) | AQ43: =if(AN43,if(AO43<>"",if(AO43>AN43,AO43-AN43,""),$A$1-AN43),"") | AS43: =if(AJ43,if(and(hour(AJ43+AS$5)>11,(hour(AJ43+AS$5)<20)),AJ43+AS$5,_xlfn.workday.intl(int(AJ43),1,"1000000",Holidays!A:A)+hour(AJ43+AS$5-$B$1)/24+minute(AJ43)/1440),"") | AT43: =if(AT43,AT43,if(AU43<>"",$A$1,"")) | AV43: =if(AS43,if(AT43<>"",if(AT43>AS43,AT43-AS43,""),$A$1-AS43),"") | AX43: no response
A44: 44685.489 | G44: =if(A44,_xlfn.workday.intl(int(A44),1,"1000000",Holidays!A:A)+17/24,"") -> 44686.708 | H44: =if(H44,H44,if(I44<>"",$A$1,"")) | J44: =if(G44,if(H44<>"",if(H44>G44,H44-G44,""),$A$1-G44),"") -> 1447.2756 | K44: =if(G44,_xlfn.workday.intl(int(G44),0,"1000000",Holidays!A:A)+19/24,"") -> 44686.792 | L44: =if(L44,L44,if(M44<>"",$A$1,"")) | N44: =if(K44,if(L44<>"",if(L44>K44,L44-K44,""),$A$1-K44),"") -> 1447.1922 | O44: =if(A44,_xlfn.WORKDAY.INTL(A44,O$5,"1000000",Holidays!A:A)+hour(A44)/24+MINUTE(A44)/1440,"") -> 44686.489 | R44: =if(O44,if(P44<>"",if(P44>O44,P44-O44,""),$A$1-O44),"") -> 1447.495 | U44: =if(O44,_xlfn.WORKDAY.INTL(O44,U$5,"1000000",Holidays!A:A)+hour(O44)/24+MINUTE(O44)/1440,"") -> 44687.489 | V44: =if(V44,V44,if(W44<>"",$A$1,"")) | X44: =if(U44,if(V44<>"",if(V44>U44,V44-U44,""),$A$1-U44),"") -> 1446.495 | AH44: =IF(P44="","",P44+AB44+AC44+AD44+AE44+AF44) | AI44: =IF(AH44,_xlfn.workday.intl(int(AH44),0,"1000000",Holidays!A:A)+18/24,"") | AJ44: =if(AJ44,AJ44,if(AK44<>"",$A$1,"")) | AL44: =if(AI44,if(AJ44<>"",if(AJ44>AI44,AJ44-AI44,""),$A$1-AI44),"") | AN44: =if(AJ44,if(and(hour(AJ44+AN$5)>11,(hour(AJ44+AN$5)<20)),AJ44+AN$5,_xlfn.workday.intl(int(AJ44),1,"1000000",Holidays!A:A)+hour(AJ44+AN$5-$B$1)/24+minute(AJ44)/1440),"") | AO44: =if(AO44,AO44,if(AP44<>"",$A$1,"")) | AQ44: =if(AN44,if(AO44<>"",if(AO44>AN44,AO44-AN44,""),$A$1-AN44),"") | AS44: =if(AJ44,if(and(hour(AJ44+AS$5)>11,(hour(AJ44+AS$5)<20)),AJ44+AS$5,_xlfn.workday.intl(int(AJ44),1,"1000000",Holidays!A:A)+hour(AJ44+AS$5-$B$1)/24+minute(AJ44)/1440),"") | AT44: =if(AT44,AT44,if(AU44<>"",$A$1,"")) | AV44: =if(AS44,if(AT44<>"",if(AT44>AS44,AT44-AS44,""),$A$1-AS44),"") | AX44: no response
A45: 44689.484 | G45: =if(A45,_xlfn.workday.intl(int(A45),1,"1000000",Holidays!A:A)+17/24,"") -> 44691.708 | H45: =if(H45,H45,if(I45<>"",$A$1,"")) -> 44744.461 | I45: done | J45: =if(G45,if(H45<>"",if(H45>G45,H45-G45,""),$A$1-G45),"") -> 52.752615 | K45: =if(G45,_xlfn.workday.intl(int(G45),0,"1000000",Holidays!A:A)+19/24,"") -> 44691.792 | L45: =if(L45,L45,if(M45<>"",$A$1,"")) -> 44744.461 | M45: done | N45: =if(K45,if(L45<>"",if(L45>K45,L45-K45,""),$A$1-K45),"") -> 52.669338 | O45: =if(A45,_xlfn.WORKDAY.INTL(A45,O$5,"1000000",Holidays!A:A)+hour(A45)/24+MINUTE(A45)/1440,"") -> 44691.484 | P45: 44744.461 | Q45: done | R45: =if(O45,if(P45<>"",if(P45>O45,P45-O45,""),$A$1-O45),"") -> 52.977058 | U45: =if(O45,_xlfn.WORKDAY.INTL(O45,U$5,"1000000",Holidays!A:A)+hour(O45)/24+MINUTE(O45)/1440,"") -> 44692.484 | V45: =if(V45,V45,if(W45<>"",$A$1,"")) | X45: =if(U45,if(V45<>"",if(V45>U45,V45-U45,""),$A$1-U45),"") -> 1441.4999 | AH45: =IF(P45="","",P45+AB45+AC45+AD45+AE45+AF45) -> 44744.461 | AI45: =if(AH45,_xlfn.workday.intl(int(AH45),0,"1000000",Holidays!A:A)+18/24,"") -> 44744.75 | AJ45: =if(AJ45,AJ45,if(AK45<>"",$A$1,"")) -> 44733.666 | AK45: done | AL45: =if(AI45,if(AJ45<>"",if(AJ45>AI45,AJ45-AI45,""),$A$1-AI45),"") | AN45: =if(AJ45,if(and(hour(AJ45+AN$5)>11,(hour(AJ45+AN$5)<20)),AJ45+AN$5,_xlfn.workday.intl(int(AJ45),1,"1000000",Holidays!A:A)+hour(AJ45+AN$5-$B$1)/24+minute(AJ45)/1440),"") -> 44734.666 | AO45: =if(AO45,AO45,if(AP45<>"",$A$1,"")) -> 44744.461 | AP45: done | AQ45: =if(AN45,if(AO45<>"",if(AO45>AN45,AO45-AN45,""),$A$1-AN45),"") -> 9.7951385 | AS45: =if(AJ45,if(and(hour(AJ45+AS$5)>11,(hour(AJ45+AS$5)<20)),AJ45+AS$5,_xlfn.workday.intl(int(AJ45),1,"1000000",Holidays!A:A)+hour(AJ45+AS$5-$B$1)/24+minute(AJ45)/1440),"") -> 44735.666 | AT45: =if(AT45,AT45,if(AU45<>"",$A$1,"")) -> 44744.461 | AU45: yes | AV45: =if(AS45,if(AT45<>"",if(AT45>AS45,AT45-AS45,""),$A$1-AS45),"") -> 8.7951707 | AX45: done
A46: 44694.487 | G46: =if(A46,_xlfn.workday.intl(int(A46),1,"1000000",Holidays!A:A)+17/24,"") -> 44695.708 | H46: =if(H46,H46,if(I46<>"",$A$1,"")) -> 44744.461 | I46: done | J46: =if(G46,if(H46<>"",if(H46>G46,H46-G46,""),$A$1-G46),"") -> 48.752973 | K46: =if(G46,_xlfn.workday.intl(int(G46),0,"1000000",Holidays!A:A)+19/24,"") -> 44695.792 | L46: =if(L46,L46,if(M46<>"",$A$1,"")) -> 44744.461 | M46: done | N46: =if(K46,if(L46<>"",if(L46>K46,L46-K46,""),$A$1-K46),"") -> 48.669663 | O46: =if(A46,_xlfn.WORKDAY.INTL(A46,O$5,"1000000",Holidays!A:A)+hour(A46)/24+MINUTE(A46)/1440,"") -> 44695.487 | P46: 44744.461 | Q46: done | R46: =if(O46,if(P46<>"",if(P46>O46,P46-O46,""),$A$1-O46),"") -> 48.974542 | U46: =if(O46,_xlfn.WORKDAY.INTL(O46,U$5,"1000000",Holidays!A:A)+hour(O46)/24+MINUTE(O46)/1440,"") -> 44696.487 | V46: =if(V46,V46,if(W46<>"",$A$1,"")) | X46: =if(U46,if(V46<>"",if(V46>U46,V46-U46,""),$A$1-U46),"") -> 1437.4971 | AH46: =IF(P46="","",P46+AB46+AC46+AD46+AE46+AF46) -> 44744.461 | AI46: =if(AH46,_xlfn.workday.intl(int(AH46),0,"1000000",Holidays!A:A)+18/24,"") -> 44744.75 | AJ46: =if(AJ46,AJ46,if(AK46<>"",$A$1,"")) -> 44733.666 | AK46: done | AL46: =if(AI46,if(AJ46<>"",if(AJ46>AI46,AJ46-AI46,""),$A$1-AI46),"") | AN46: =if(AJ46,if(and(hour(AJ46+AN$5)>11,(hour(AJ46+AN$5)<20)),AJ46+AN$5,_xlfn.workday.intl(int(AJ46),1,"1000000",Holidays!A:A)+hour(AJ46+AN$5-$B$1)/24+minute(AJ46)/1440),"") -> 44734.666 | AO46: =if(AO46,AO46,if(AP46<>"",$A$1,"")) -> 44744.461 | AP46: done | AQ46: =if(AN46,if(AO46<>"",if(AO46>AN46,AO46-AN46,""),$A$1-AN46),"") -> 9.7952983 | AS46: =if(AJ46,if(and(hour(AJ46+AS$5)>11,(hour(AJ46+AS$5)<20)),AJ46+AS$5,_xlfn.workday.intl(int(AJ46),1,"1000000",Holidays!A:A)+hour(AJ46+AS$5-$B$1)/24+minute(AJ46)/1440),"") -> 44735.666 | AT46: =if(AT46,AT46,if(AU46<>"",$A$1,"")) -> 44744.462 | AU46: yes | AV46: =if(AS46,if(AT46<>"",if(AT46>AS46,AT46-AS46,""),$A$1-AS46),"") -> 8.7956231 | AX46: done
A47: 44694.489 | G47: =if(A47,_xlfn.workday.intl(int(A47),1,"1000000",Holidays!A:A)+17/24,"") -> 44695.708 | H47: =if(H47,H47,if(I47<>"",$A$1,"")) -> 44744.462 | I47: done | J47: =if(G47,if(H47<>"",if(H47>G47,H47-G47,""),$A$1-G47),"") -> 48.753219 | K47: =if(G47,_xlfn.workday.intl(int(G47),0,"1000000",Holidays!A:A)+19/24,"") -> 44695.792 | L47: =if(L47,L47,if(M47<>"",$A$1,"")) -> 44744.462 | M47: done | N47: =if(K47,if(L47<>"",if(L47>K47,L47-K47,""),$A$1-K47),"") -> 48.669907 | O47: =if(A47,_xlfn.WORKDAY.INTL(A47,O$5,"1000000",Holidays!A:A)+hour(A47)/24+MINUTE(A47)/1440,"") -> 44695.488 | P47: 44744.462 | Q47: done | R47: =if(O47,if(P47<>"",if(P47>O47,P47-O47,""),$A$1-O47),"") -> 48.973394 | U47: =if(O47,_xlfn.WORKDAY.INTL(O47,U$5,"1000000",Holidays!A:A)+hour(O47)/24+MINUTE(O47)/1440,"") -> 44696.488 | V47: =if(V47,V47,if(W47<>"",$A$1,"")) | X47: =if(U47,if(V47<>"",if(V47>U47,V47-U47,""),$A$1-U47),"") -> 1437.4957 | AH47: =IF(P47="","",P47+AB47+AC47+AD47+AE47+AF47) -> 44744.462 | AI47: =if(AH47,_xlfn.workday.intl(int(AH47),0,"1000000",Holidays!A:A)+18/24,"") -> 44744.75 | AJ47: =if(AJ47,AJ47,if(AK47<>"",$A$1,"")) -> 44733.666 | AK47: done | AL47: =if(AI47,if(AJ47<>"",if(AJ47>AI47,AJ47-AI47,""),$A$1-AI47),"") | AN47: =if(AJ47,if(and(hour(AJ47+AN$5)>11,(hour(AJ47+AN$5)<20)),AJ47+AN$5,_xlfn.workday.intl(int(AJ47),1,"1000000",Holidays!A:A)+hour(AJ47+AN$5-$B$1)/24+minute(AJ47)/1440),"") -> 44734.666 | AO47: =if(AO47,AO47,if(AP47<>"",$A$1,"")) -> 44744.462 | AP47: done | AQ47: =if(AN47,if(AO47<>"",if(AO47>AN47,AO47-AN47,""),$A$1-AN47),"") -> 9.7953629 | AS47: =if(AJ47,if(and(hour(AJ47+AS$5)>11,(hour(AJ47+AS$5)<20)),AJ47+AS$5,_xlfn.workday.intl(int(AJ47),1,"1000000",Holidays!A:A)+hour(AJ47+AS$5-$B$1)/24+minute(AJ47)/1440),"") -> 44735.666 | AT47: =if(AT47,AT47,if(AU47<>"",$A$1,"")) -> 44744.462 | AU47: yes | AV47: =if(AS47,if(AT47<>"",if(AT47>AS47,AT47-AS47,""),$A$1-AS47),"") -> 8.7954285 | AX47: done
A48: 44694.49 | G48: =if(A48,_xlfn.workday.intl(int(A48),1,"1000000",Holidays!A:A)+17/24,"") -> 44695.708 | H48: =if(H48,H48,if(I48<>"",$A$1,"")) | J48: =if(G48,if(H48<>"",if(H48>G48,H48-G48,""),$A$1-G48),"") -> 1438.2756 | K48: =if(G48,_xlfn.workday.intl(int(G48),0,"1000000",Holidays!A:A)+19/24,"") -> 44695.792 | L48: =if(L48,L48,if(M48<>"",$A$1,"")) | N48: =if(K48,if(L48<>"",if(L48>K48,L48-K48,""),$A$1-K48),"") -> 1438.1922 | O48: =if(A48,_xlfn.WORKDAY.INTL(A48,O$5,"1000000",Holidays!A:A)+hour(A48)/24+MINUTE(A48)/1440,"") -> 44695.49 | R48: =if(O48,if(P48<>"",if(P48>O48,P48-O48,""),$A$1-O48),"") -> 1438.4943 | U48: =if(O48,_xlfn.WORKDAY.INTL(O48,U$5,"1000000",Holidays!A:A)+hour(O48)/24+MINUTE(O48)/1440,"") -> 44696.49 | V48: =if(V48,V48,if(W48<>"",$A$1,"")) | X48: =if(U48,if(V48<>"",if(V48>U48,V48-U48,""),$A$1-U48),"") -> 1437.4943 | AH48: =IF(P48="","",P48+AB48+AC48+AD48+AE48+AF48) | AI48: =if(AH48,_xlfn.workday.intl(int(AH48),0,"1000000",Holidays!A:A)+18/24,"") | AJ48: =if(AJ48,AJ48,if(AK48<>"",$A$1,"")) | AL48: =if(AI48,if(AJ48<>"",if(AJ48>AI48,AJ48-AI48,""),$A$1-AI48),"") | AN48: =if(AJ48,if(and(hour(AJ48+AN$5)>11,(hour(AJ48+AN$5)<20)),AJ48+AN$5,_xlfn.workday.intl(int(AJ48),1,"1000000",Holidays!A:A)+hour(AJ48+AN$5-$B$1)/24+minute(AJ48)/1440),"") | AO48: =if(AO48,AO48,if(AP48<>"",$A$1,"")) | AQ48: =if(AN48,if(AO48<>"",if(AO48>AN48,AO48-AN48,""),$A$1-AN48),"") | AS48: =if(AJ48,if(and(hour(AJ48+AS$5)>11,(hour(AJ48+AS$5)<20)),AJ48+AS$5,_xlfn.workday.intl(int(AJ48),1,"1000000",Holidays!A:A)+hour(AJ48+AS$5-$B$1)/24+minute(AJ48)/1440),"") | AT48: =if(AT48,AT48,if(AU48<>"",$A$1,"")) | AV48: =if(AS48,if(AT48<>"",if(AT48>AS48,AT48-AS48,""),$A$1-AS48),"") | AX48: Hold
A49: 44709.649 | G49: =if(A49,_xlfn.workday.intl(int(A49),1,"1000000",Holidays!A:A)+17/24,"") -> 44710.708 | H49: =if(H49,H49,if(I49<>"",$A$1,"")) | J49: =if(G49,if(H49<>"",if(H49>G49,H49-G49,""),$A$1-G49),"") -> 1423.2756 | K49: =if(G49,_xlfn.workday.intl(int(G49),0,"1000000",Holidays!A:A)+19/24,"") -> 44710.792 | L49: =if(L49,L49,if(M49<>"",$A$1,"")) | N49: =if(K49,if(L49<>"",if(L49>K49,L49-K49,""),$A$1-K49),"") -> 1423.1922 | O49: =if(A49,_xlfn.WORKDAY.INTL(A49,O$5,"1000000",Holidays!A:A)+hour(A49)/24+MINUTE(A49)/1440,"") -> 44710.649 | R49: =if(O49,if(P49<>"",if(P49>O49,P49-O49,""),$A$1-O49),"") -> 1423.3353 | U49: =if(O49,_xlfn.WORKDAY.INTL(O49,U$5,"1000000",Holidays!A:A)+hour(O49)/24+MINUTE(O49)/1440,"") -> 44712.649 | V49: =if(V49,V49,if(W49<>"",$A$1,"")) | X49: =if(U49,if(V49<>"",if(V49>U49,V49-U49,""),$A$1-U49),"") -> 1421.3353 | AH49: =IF(P49="","",P49+AB49+AC49+AD49+AE49+AF49) | AI49: =if(AH49,_xlfn.workday.intl(int(AH49),0,"1000000",Holidays!A:A)+18/24,"") | AJ49: =if(AJ49,AJ49,if(AK49<>"",$A$1,"")) | AL49: =if(AI49,if(AJ49<>"",if(AJ49>AI49,AJ49-AI49,""),$A$1-AI49),"") | AN49: =if(AJ49,if(and(hour(AJ49+AN$5)>11,(hour(AJ49+AN$5)<20)),AJ49+AN$5,_xlfn.workday.intl(int(AJ49),1,"1000000",Holidays!A:A)+hour(AJ49+AN$5-$B$1)/24+minute(AJ49)/1440),"") | AO49: =if(AO49,AO49,if(AP49<>"",$A$1,"")) | AQ49: =if(AN49,if(AO49<>"",if(AO49>AN49,AO49-AN49,""),$A$1-AN49),"") | AS49: =if(AJ49,if(and(hour(AJ49+AS$5)>11,(hour(AJ49+AS$5)<20)),AJ49+AS$5,_xlfn.workday.intl(int(AJ49),1,"1000000",Holidays!A:A)+hour(AJ49+AS$5-$B$1)/24+minute(AJ49)/1440),"") | AT49: =if(AT49,AT49,if(AU49<>"",$A$1,"")) | AV49: =if(AS49,if(AT49<>"",if(AT49>AS49,AT49-AS49,""),$A$1-AS49),"") | AX49: done
A50: 44710.513 | G50: =if(A50,_xlfn.workday.intl(int(A50),1,"1000000",Holidays!A:A)+17/24,"") -> 44712.708 | H50: =if(H50,H50,if(I50<>"",$A$1,"")) | J50: =if(G50,if(H50<>"",if(H50>G50,H50-G50,""),$A$1-G50),"") -> 1421.2756 | K50: =if(G50,_xlfn.workday.intl(int(G50),0,"1000000",Holidays!A:A)+19/24,"") -> 44712.792 | L50: =if(L50,L50,if(M50<>"",$A$1,"")) | N50: =if(K50,if(L50<>"",if(L50>K50,L50-K50,""),$A$1-K50),"") -> 1421.1922 | O50: =if(A50,_xlfn.WORKDAY.INTL(A50,O$5,"1000000",Holidays!A:A)+hour(A50)/24+MINUTE(A50)/1440,"") -> 44712.512 | R50: =if(O50,if(P50<>"",if(P50>O50,P50-O50,""),$A$1-O50),"") -> 1421.4714 | U50: =if(O50,_xlfn.WORKDAY.INTL(O50,U$5,"1000000",Holidays!A:A)+hour(O50)/24+MINUTE(O50)/1440,"") -> 44713.512 | V50: =if(V50,V50,if(W50<>"",$A$1,"")) | X50: =if(U50,if(V50<>"",if(V50>U50,V50-U50,""),$A$1-U50),"") -> 1420.4714 | AH50: =IF(P50="","",P50+AB50+AC50+AD50+AE50+AF50) | AI50: =if(AH50,_xlfn.workday.intl(int(AH50),0,"1000000",Holidays!A:A)+18/24,"") | AJ50: =if(AJ50,AJ50,if(AK50<>"",$A$1,"")) | AL50: =if(AI50,if(AJ50<>"",if(AJ50>AI50,AJ50-AI50,""),$A$1-AI50),"") | AN50: =if(AJ50,if(and(hour(AJ50+AN$5)>11,(hour(AJ50+AN$5)<20)),AJ50+AN$5,_xlfn.workday.intl(int(AJ50),1,"1000000",Holidays!A:A)+hour(AJ50+AN$5-$B$1)/24+minute(AJ50)/1440),"") | AO50: =if(AO50,AO50,if(AP50<>"",$A$1,"")) | AQ50: =if(AN50,if(AO50<>"",if(AO50>AN50,AO50-AN50,""),$A$1-AN50),"") | AS50: =if(AJ50,if(and(hour(AJ50+AS$5)>11,(hour(AJ50+AS$5)<20)),AJ50+AS$5,_xlfn.workday.intl(int(AJ50),1,"1000000",Holidays!A:A)+hour(AJ50+AS$5-$B$1)/24+minute(AJ50)/1440),"") | AT50: =if(AT50,AT50,if(AU50<>"",$A$1,"")) | AV50: =if(AS50,if(AT50<>"",if(AT50>AS50,AT50-AS50,""),$A$1-AS50),"") | AX50: hold
A51: 44710.515 | G51: =if(A51,_xlfn.workday.intl(int(A51),1,"1000000",Holidays!A:A)+17/24,"") -> 44712.708 | H51: =if(H51,H51,if(I51<>"",$A$1,"")) | J51: =if(G51,if(H51<>"",if(H51>G51,H51-G51,""),$A$1-G51),"") -> 1421.2756 | K51: =if(G51,_xlfn.workday.intl(int(G51),0,"1000000",Holidays!A:A)+19/24,"") -> 44712.792 | L51: =if(L51,L51,if(M51<>"",$A$1,"")) | N51: =if(K51,if(L51<>"",if(L51>K51,L51-K51,""),$A$1-K51),"") -> 1421.1922 | O51: =if(A51,_xlfn.WORKDAY.INTL(A51,O$5,"1000000",Holidays!A:A)+hour(A51)/24+MINUTE(A51)/1440,"") -> 44712.515 | R51: =if(O51,if(P51<>"",if(P51>O51,P51-O51,""),$A$1-O51),"") -> 1421.4693 | U51: =if(O51,_xlfn.WORKDAY.INTL(O51,U$5,"1000000",Holidays!A:A)+hour(O51)/24+MINUTE(O51)/1440,"") -> 44713.515 | V51: =if(V51,V51,if(W51<>"",$A$1,"")) | X51: =if(U51,if(V51<>"",if(V51>U51,V51-U51,""),$A$1-U51),"") -> 1420.4693 | AH51: =IF(P51="","",P51+AB51+AC51+AD51+AE51+AF51) | AI51: =if(AH51,_xlfn.workday.intl(int(AH51),0,"1000000",Holidays!A:A)+18/24,"") | AJ51: =if(AJ51,AJ51,if(AK51<>"",$A$1,"")) | AL51: =if(AI51,if(AJ51<>"",if(AJ51>AI51,AJ51-AI51,""),$A$1-AI51),"") | AN51: =if(AJ51,if(and(hour(AJ51+AN$5)>11,(hour(AJ51+AN$5)<20)),AJ51+AN$5,_xlfn.workday.intl(int(AJ51),1,"1000000",Holidays!A:A)+hour(AJ51+AN$5-$B$1)/24+minute(AJ51)/1440),"") | AO51: =if(AO51,AO51,if(AP51<>"",$A$1,"")) | AQ51: =if(AN51,if(AO51<>"",if(AO51>AN51,AO51-AN51,""),$A$1-AN51),"") | AS51: =if(AJ51,if(and(hour(AJ51+AS$5)>11,(hour(AJ51+AS$5)<20)),AJ51+AS$5,_xlfn.workday.intl(int(AJ51),1,"1000000",Holidays!A:A)+hour(AJ51+AS$5-$B$1)/24+minute(AJ51)/1440),"") | AT51: =if(AT51,AT51,if(AU51<>"",$A$1,"")) | AV51: =if(AS51,if(AT51<>"",if(AT51>AS51,AT51-AS51,""),$A$1-AS51),"") | AX51: hold
A52: 44720.52 | G52: =if(A52,_xlfn.workday.intl(int(A52),1,"1000000",Holidays!A:A)+17/24,"") -> 44721.708 | H52: =if(H52,H52,if(I52<>"",$A$1,"")) | J52: =if(G52,if(H52<>"",if(H52>G52,H52-G52,""),$A$1-G52),"") -> 1412.2756 | K52: =if(G52,_xlfn.workday.intl(int(G52),0,"1000000",Holidays!A:A)+19/24,"") -> 44721.792 | L52: =if(L52,L52,if(M52<>"",$A$1,"")) | N52: =if(K52,if(L52<>"",if(L52>K52,L52-K52,""),$A$1-K52),"") -> 1412.1922 | O52: =if(A52,_xlfn.WORKDAY.INTL(A52,O$5,"1000000",Holidays!A:A)+hour(A52)/24+MINUTE(A52)/1440,"") -> 44721.52 | R52: =if(O52,if(P52<>"",if(P52>O52,P52-O52,""),$A$1-O52),"") -> 1412.4638 | U52: =if(O52,_xlfn.WORKDAY.INTL(O52,U$5,"1000000",Holidays!A:A)+hour(O52)/24+MINUTE(O52)/1440,"") -> 44722.52 | V52: =if(V52,V52,if(W52<>"",$A$1,"")) | X52: =if(U52,if(V52<>"",if(V52>U52,V52-U52,""),$A$1-U52),"") -> 1411.4638 | AH52: =IF(P52="","",P52+AB52+AC52+AD52+AE52+AF52) | AI52: =if(AH52,_xlfn.workday.intl(int(AH52),0,"1000000",Holidays!A:A)+18/24,"") | AJ52: =if(AJ52,AJ52,if(AK52<>"",$A$1,"")) | AL52: =if(AI52,if(AJ52<>"",if(AJ52>AI52,AJ52-AI52,""),$A$1-AI52),"") | AN52: =if(AJ52,if(and(hour(AJ52+AN$5)>11,(hour(AJ52+AN$5)<20)),AJ52+AN$5,_xlfn.workday.intl(int(AJ52),1,"1000000",Holidays!A:A)+hour(AJ52+AN$5-$B$1)/24+minute(AJ52)/1440),"") | AO52: =if(AO52,AO52,if(AP52<>"",$A$1,"")) | AQ52: =if(AN52,if(AO52<>"",if(AO52>AN52,AO52-AN52,""),$A$1-AN52),"") | AS52: =if(AJ52,if(and(hour(AJ52+AS$5)>11,(hour(AJ52+AS$5)<20)),AJ52+AS$5,_xlfn.workday.intl(int(AJ52),1,"1000000",Holidays!A:A)+hour(AJ52+AS$5-$B$1)/24+minute(AJ52)/1440),"") | AT52: =if(AT52,AT52,if(AU52<>"",$A$1,"")) | AV52: =if(AS52,if(AT52<>"",if(AT52>AS52,AT52-AS52,""),$A$1-AS52),"") | AX52: no response
A53: 44720.524 | G53: =if(A53,_xlfn.workday.intl(int(A53),1,"1000000",Holidays!A:A)+17/24,"") -> 44721.708 | H53: =if(H53,H53,if(I53<>"",$A$1,"")) -> 44744.444 | I53: done | J53: =if(G53,if(H53<>"",if(H53>G53,H53-G53,""),$A$1-G53),"") -> 22.735554 | K53: =if(G53,_xlfn.workday.intl(int(G53),0,"1000000",Holidays!A:A)+19/24,"") -> 44721.792 | L53: =if(L53,L53,if(M53<>"",$A$1,"")) -> 44744.444 | M53: done | N53: =if(K53,if(L53<>"",if(L53>K53,L53-K53,""),$A$1-K53),"") -> 22.652262 | O53: =if(A53,_xlfn.WORKDAY.INTL(A53,O$5,"1000000",Holidays!A:A)+hour(A53)/24+MINUTE(A53)/1440,"") -> 44721.524 | P53: 44744.444 | Q53: done | R53: =if(O53,if(P53<>"",if(P53>O53,P53-O53,""),$A$1-O53),"") -> 22.920355 | U53: =if(O53,_xlfn.WORKDAY.INTL(O53,U$5,"1000000",Holidays!A:A)+hour(O53)/24+MINUTE(O53)/1440,"") -> 44722.524 | V53: =if(V53,V53,if(W53<>"",$A$1,"")) | X53: =if(U53,if(V53<>"",if(V53>U53,V53-U53,""),$A$1-U53),"") -> 1411.4603 | AH53: =IF(P53="","",P53+AB53+AC53+AD53+AE53+AF53) -> 44744.444 | AI53: =if(AH53,_xlfn.workday.intl(int(AH53),0,"1000000",Holidays!A:A)+18/24,"") -> 44744.75 | AJ53: =if(AJ53,AJ53,if(AK53<>"",$A$1,"")) -> 44733.666 | AK53: done | AL53: =if(AI53,if(AJ53<>"",if(AJ53>AI53,AJ53-AI53,""),$A$1-AI53),"") | AN53: =if(AJ53,if(and(hour(AJ53+AN$5)>11,(hour(AJ53+AN$5)<20)),AJ53+AN$5,_xlfn.workday.intl(int(AJ53),1,"1000000",Holidays!A:A)+hour(AJ53+AN$5-$B$1)/24+minute(AJ53)/1440),"") -> 44734.666 | AO53: =if(AO53,AO53,if(AP53<>"",$A$1,"")) -> 44744.444 | AP53: done | AQ53: =if(AN53,if(AO53<>"",if(AO53>AN53,AO53-AN53,""),$A$1-AN53),"") -> 9.7775988 | AS53: =if(AJ53,if(and(hour(AJ53+AS$5)>11,(hour(AJ53+AS$5)<20)),AJ53+AS$5,_xlfn.workday.intl(int(AJ53),1,"1000000",Holidays!A:A)+hour(AJ53+AS$5-$B$1)/24+minute(AJ53)/1440),"") -> 44735.666 | AT53: =if(AT53,AT53,if(AU53<>"",$A$1,"")) -> 44744.444 | AU53: yes | AV53: =if(AS53,if(AT53<>"",if(AT53>AS53,AT53-AS53,""),$A$1-AS53),"") -> 8.7777937 | AX53: done
A54: 44720.525 | G54: =if(A54,_xlfn.workday.intl(int(A54),1,"1000000",Holidays!A:A)+17/24,"") -> 44721.708 | H54: =if(H54,H54,if(I54<>"",$A$1,"")) -> 44750.728 | I54: done | J54: =if(G54,if(H54<>"",if(H54>G54,H54-G54,""),$A$1-G54),"") -> 29.019451 | K54: =if(G54,_xlfn.workday.intl(int(G54),0,"1000000",Holidays!A:A)+19/24,"") -> 44721.792 | L54: =if(L54,L54,if(M54<>"",$A$1,"")) -> 44750.728 | M54: done | N54: =if(K54,if(L54<>"",if(L54>K54,L54-K54,""),$A$1-K54),"") -> 28.936153 | O54: =if(A54,_xlfn.WORKDAY.INTL(A54,O$5,"1000000",Holidays!A:A)+hour(A54)/24+MINUTE(A54)/1440,"") -> 44721.525 | P54: 44750.721 | Q54: done | R54: =if(O54,if(P54<>"",if(P54>O54,P54-O54,""),$A$1-O54),"") -> 29.195702 | U54: =if(O54,_xlfn.WORKDAY.INTL(O54,U$5,"1000000",Holidays!A:A)+hour(O54)/24+MINUTE(O54)/1440,"") -> 44722.525 | V54: =if(V54,V54,if(W54<>"",$A$1,"")) | X54: =if(U54,if(V54<>"",if(V54>U54,V54-U54,""),$A$1-U54),"") -> 1411.4589 | AH54: =IF(P54="","",P54+AB54+AC54+AD54+AE54+AF54) -> 44750.721 | AI54: =if(AH54,_xlfn.workday.intl(int(AH54),0,"1000000",Holidays!A:A)+18/24,"") -> 44750.75 | AJ54: =if(AJ54,AJ54,if(AK54<>"",$A$1,"")) -> 44750.728 | AK54: done | AL54: =if(AI54,if(AJ54<>"",if(AJ54>AI54,AJ54-AI54,""),$A$1-AI54),"") | AN54: =if(AJ54,if(and(hour(AJ54+AN$5)>11,(hour(AJ54+AN$5)<20)),AJ54+AN$5,_xlfn.workday.intl(int(AJ54),1,"1000000",Holidays!A:A)+hour(AJ54+AN$5-$B$1)/24+minute(AJ54)/1440),"") -> 44751.728 | AO54: =if(AO54,AO54,if(AP54<>"",$A$1,"")) -> 44750.728 | AP54: done | AQ54: =if(AN54,if(AO54<>"",if(AO54>AN54,AO54-AN54,""),$A$1-AN54),"") | AS54: =if(AJ54,if(and(hour(AJ54+AS$5)>11,(hour(AJ54+AS$5)<20)),AJ54+AS$5,_xlfn.workday.intl(int(AJ54),1,"1000000",Holidays!A:A)+hour(AJ54+AS$5-$B$1)/24+minute(AJ54)/1440),"") -> 44752.728 | AT54: =if(AT54,AT54,if(AU54<>"",$A$1,"")) -> 44750.728 | AU54: yes | AV54: =if(AS54,if(AT54<>"",if(AT54>AS54,AT54-AS54,""),$A$1-AS54),"") | AX54: done
A55: 44720.526 | G55: =if(A55,_xlfn.workday.intl(int(A55),1,"1000000",Holidays!A:A)+17/24,"") -> 44721.708 | H55: =if(H55,H55,if(I55<>"",$A$1,"")) -> 44744.445 | I55: done | J55: =if(G55,if(H55<>"",if(H55>G55,H55-G55,""),$A$1-G55),"") -> 22.73659 | K55: =if(G55,_xlfn.workday.intl(int(G55),0,"1000000",Holidays!A:A)+19/24,"") -> 44721.792 | L55: =if(L55,L55,if(M55<>"",$A$1,"")) -> 44744.445 | M55: done | N55: =if(K55,if(L55<>"",if(L55>K55,L55-K55,""),$A$1-K55),"") -> 22.653288 | O55: =if(A55,_xlfn.WORKDAY.INTL(A55,O$5,"1000000",Holidays!A:A)+hour(A55)/24+MINUTE(A55)/1440,"") -> 44721.526 | P55: 44744.445 | Q55: done | R55: =if(O55,if(P55<>"",if(P55>O55,P55-O55,""),$A$1-O55),"") -> 22.918605 | U55: =if(O55,_xlfn.WORKDAY.INTL(O55,U$5,"1000000",Holidays!A:A)+hour(O55)/24+MINUTE(O55)/1440,"") -> 44722.526 | V55: =if(V55,V55,if(W55<>"",$A$1,"")) | X55: =if(U55,if(V55<>"",if(V55>U55,V55-U55,""),$A$1-U55),"") -> 1411.4575 | AH55: =IF(P55="","",P55+AB55+AC55+AD55+AE55+AF55) -> 44744.445 | AI55: =if(AH55,_xlfn.workday.intl(int(AH55),0,"1000000",Holidays!A:A)+18/24,"") -> 44744.75 | AJ55: =if(AJ55,AJ55,if(AK55<>"",$A$1,"")) -> 44744.445 | AK55: done | AL55: =if(AI55,if(AJ55<>"",if(AJ55>AI55,AJ55-AI55,""),$A$1-AI55),"") | AN55: =if(AJ55,if(and(hour(AJ55+AN$5)>11,(hour(AJ55+AN$5)<20)),AJ55+AN$5,_xlfn.workday.intl(int(AJ55),1,"1000000",Holidays!A:A)+hour(AJ55+AN$5-$B$1)/24+minute(AJ55)/1440),"") -> 44745.444 | AO55: =if(AO55,AO55,if(AP55<>"",$A$1,"")) -> 44744.445 | AP55: done | AQ55: =if(AN55,if(AO55<>"",if(AO55>AN55,AO55-AN55,""),$A$1-AN55),"") | AS55: =if(AJ55,if(and(hour(AJ55+AS$5)>11,(hour(AJ55+AS$5)<20)),AJ55+AS$5,_xlfn.workday.intl(int(AJ55),1,"1000000",Holidays!A:A)+hour(AJ55+AS$5-$B$1)/24+minute(AJ55)/1440),"") -> 44745.444 | AT55: =if(AT55,AT55,if(AU55<>"",$A$1,"")) -> 44744.445 | AU55: yes | AV55: =if(AS55,if(AT55<>"",if(AT55>AS55,AT55-AS55,""),$A$1-AS55),"") | AX55: done
A56: 44722.536 | G56: =if(A56,_xlfn.workday.intl(int(A56),1,"1000000",Holidays!A:A)+17/24,"") -> 44723.708 | H56: =if(H56,H56,if(I56<>"",$A$1,"")) -> 44744.445 | I56: done | J56: =if(G56,if(H56<>"",if(H56>G56,H56-G56,""),$A$1-G56),"") -> 20.73698 | K56: =if(G56,_xlfn.workday.intl(int(G56),0,"1000000",Holidays!A:A)+19/24,"") -> 44723.792 | L56: =if(L56,L56,if(M56<>"",$A$1,"")) -> 44744.445 | M56: done | N56: =if(K56,if(L56<>"",if(L56>K56,L56-K56,""),$A$1-K56),"") -> 20.653671 | O56: =if(A56,_xlfn.WORKDAY.INTL(A56,O$5,"1000000",Holidays!A:A)+hour(A56)/24+MINUTE(A56)/1440,"") -> 44723.536 | P56: 44744.445 | Q56: done | R56: =if(O56,if(P56<>"",if(P56>O56,P56-O56,""),$A$1-O56),"") -> 20.909252 | U56: =if(O56,_xlfn.WORKDAY.INTL(O56,U$5,"1000000",Holidays!A:A)+hour(O56)/24+MINUTE(O56)/1440,"") -> 44724.536 | V56: =if(V56,V56,if(W56<>"",$A$1,"")) | X56: =if(U56,if(V56<>"",if(V56>U56,V56-U56,""),$A$1-U56),"") -> 1409.4478 | AH56: =IF(P56="","",P56+AB56+AC56+AD56+AE56+AF56) -> 44744.445 | AI56: =if(AH56,_xlfn.workday.intl(int(AH56),0,"1000000",Holidays!A:A)+18/24,"") -> 44744.75 | AJ56: =if(AJ56,AJ56,if(AK56<>"",$A$1,"")) -> 44744.445 | AK56: done | AL56: =if(AI56,if(AJ56<>"",if(AJ56>AI56,AJ56-AI56,""),$A$1-AI56),"") | AN56: =if(AJ56,if(and(hour(AJ56+AN$5)>11,(hour(AJ56+AN$5)<20)),AJ56+AN$5,_xlfn.workday.intl(int(AJ56),1,"1000000",Holidays!A:A)+hour(AJ56+AN$5-$B$1)/24+minute(AJ56)/1440),"") -> 44745.445 | AO56: =if(AO56,AO56,if(AP56<>"",$A$1,"")) -> 44744.445 | AP56: done | AQ56: =if(AN56,if(AO56<>"",if(AO56>AN56,AO56-AN56,""),$A$1-AN56),"") | AS56: =if(AJ56,if(and(hour(AJ56+AS$5)>11,(hour(AJ56+AS$5)<20)),AJ56+AS$5,_xlfn.workday.intl(int(AJ56),1,"1000000",Holidays!A:A)+hour(AJ56+AS$5-$B$1)/24+minute(AJ56)/1440),"") -> 44745.445 | AT56: =if(AT56,AT56,if(AU56<>"",$A$1,"")) -> 44744.445 | AU56: yes | AV56: =if(AS56,if(AT56<>"",if(AT56>AS56,AT56-AS56,""),$A$1-AS56),"") | AX56: done
A57: 44726.542 | G57: =if(A57,_xlfn.workday.intl(int(A57),1,"1000000",Holidays!A:A)+17/24,"") -> 44727.708 | H57: =if(H57,H57,if(I57<>"",$A$1,"")) | J57: =if(G57,if(H57<>"",if(H57>G57,H57-G57,""),$A$1-G57),"") -> 1406.2756 | K57: =if(G57,_xlfn.workday.intl(int(G57),0,"1000000",Holidays!A:A)+19/24,"") -> 44727.792 | L57: =if(L57,L57,if(M57<>"",$A$1,"")) | N57: =if(K57,if(L57<>"",if(L57>K57,L57-K57,""),$A$1-K57),"") -> 1406.1922 | O57: =if(A57,_xlfn.WORKDAY.INTL(A57,O$5,"1000000",Holidays!A:A)+hour(A57)/24+MINUTE(A57)/1440,"") -> 44727.542 | R57: =if(O57,if(P57<>"",if(P57>O57,P57-O57,""),$A$1-O57),"") -> 1406.4422 | U57: =if(O57,_xlfn.WORKDAY.INTL(O57,U$5,"1000000",Holidays!A:A)+hour(O57)/24+MINUTE(O57)/1440,"") -> 44728.542 | V57: =if(V57,V57,if(W57<>"",$A$1,"")) | X57: =if(U57,if(V57<>"",if(V57>U57,V57-U57,""),$A$1-U57),"") -> 1405.4422 | AH57: =IF(P57="","",P57+AB57+AC57+AD57+AE57+AF57) | AI57: =if(AH57,_xlfn.workday.intl(int(AH57),0,"1000000",Holidays!A:A)+18/24,"") | AJ57: =if(AJ57,AJ57,if(AK57<>"",$A$1,"")) | AL57: =if(AI57,if(AJ57<>"",if(AJ57>AI57,AJ57-AI57,""),$A$1-AI57),"") | AN57: =if(AJ57,if(and(hour(AJ57+AN$5)>11,(hour(AJ57+AN$5)<20)),AJ57+AN$5,_xlfn.workday.intl(int(AJ57),1,"1000000",Holidays!A:A)+hour(AJ57+AN$5-$B$1)/24+minute(AJ57)/1440),"") | AO57: =if(AO57,AO57,if(AP57<>"",$A$1,"")) | AQ57: =if(AN57,if(AO57<>"",if(AO57>AN57,AO57-AN57,""),$A$1-AN57),"") | AS57: =if(AJ57,if(and(hour(AJ57+AS$5)>11,(hour(AJ57+AS$5)<20)),AJ57+AS$5,_xlfn.workday.intl(int(AJ57),1,"1000000",Holidays!A:A)+hour(AJ57+AS$5-$B$1)/24+minute(AJ57)/1440),"") | AT57: =if(AT57,AT57,if(AU57<>"",$A$1,"")) | AV57: =if(AS57,if(AT57<>"",if(AT57>AS57,AT57-AS57,""),$A$1-AS57),"") | AX57: No Response
A58: 44727.528 | G58: =if(A58,_xlfn.workday.intl(int(A58),1,"1000000",Holidays!A:A)+17/24,"") -> 44728.708 | H58: =if(H58,H58,if(I58<>"",$A$1,"")) -> 44744.446 | I58: done | J58: =if(G58,if(H58<>"",if(H58>G58,H58-G58,""),$A$1-G58),"") -> 15.737625 | K58: =if(G58,_xlfn.workday.intl(int(G58),0,"1000000",Holidays!A:A)+19/24,"") -> 44728.792 | L58: =if(L58,L58,if(M58<>"",$A$1,"")) -> 44744.446 | M58: done | N58: =if(K58,if(L58<>"",if(L58>K58,L58-K58,""),$A$1-K58),"") -> 15.654321 | O58: =if(A58,_xlfn.WORKDAY.INTL(A58,O$5,"1000000",Holidays!A:A)+hour(A58)/24+MINUTE(A58)/1440,"") -> 44728.528 | P58: 44744.446 | Q58: done | R58: =if(O58,if(P58<>"",if(P58>O58,P58-O58,""),$A$1-O58),"") -> 15.918239 | U58: =if(O58,_xlfn.WORKDAY.INTL(O58,U$5,"1000000",Holidays!A:A)+hour(O58)/24+MINUTE(O58)/1440,"") -> 44729.528 | V58: =if(V58,V58,if(W58<>"",$A$1,"")) | X58: =if(U58,if(V58<>"",if(V58>U58,V58-U58,""),$A$1-U58),"") -> 1404.4561 | AH58: =IF(P58="","",P58+AB58+AC58+AD58+AE58+AF58) -> 44744.446 | AI58: =if(AH58,_xlfn.workday.intl(int(AH58),0,"1000000",Holidays!A:A)+18/24,"") -> 44744.75 | AJ58: =if(AJ58,AJ58,if(AK58<>"",$A$1,"")) -> 44744.446 | AK58: done | AL58: =if(AI58,if(AJ58<>"",if(AJ58>AI58,AJ58-AI58,""),$A$1-AI58),"") | AN58: =if(AJ58,if(and(hour(AJ58+AN$5)>11,(hour(AJ58+AN$5)<20)),AJ58+AN$5,_xlfn.workday.intl(int(AJ58),1,"1000000",Holidays!A:A)+hour(AJ58+AN$5-$B$1)/24+minute(AJ58)/1440),"") -> 44745.446 | AO58: =if(AO58,AO58,if(AP58<>"",$A$1,"")) -> 44744.446 | AP58: done | AQ58: =if(AN58,if(AO58<>"",if(AO58>AN58,AO58-AN58,""),$A$1-AN58),"") | AS58: =if(AJ58,if(and(hour(AJ58+AS$5)>11,(hour(AJ58+AS$5)<20)),AJ58+AS$5,_xlfn.workday.intl(int(AJ58),1,"1000000",Holidays!A:A)+hour(AJ58+AS$5-$B$1)/24+minute(AJ58)/1440),"") -> 44745.446 | AT58: =if(AT58,AT58,if(AU58<>"",$A$1,"")) -> 44744.446 | AU58: yes | AV58: =if(AS58,if(AT58<>"",if(AT58>AS58,AT58-AS58,""),$A$1-AS58),"") | AX58: done
A59: 44727.568 | G59: =if(A59,_xlfn.workday.intl(int(A59),1,"1000000",Holidays!A:A)+17/24,"") -> 44728.708 | H59: =if(H59,H59,if(I59<>"",$A$1,"")) | J59: =if(G59,if(H59<>"",if(H59>G59,H59-G59,""),$A$1-G59),"") -> 1405.2756 | K59: =if(G59,_xlfn.workday.intl(int(G59),0,"1000000",Holidays!A:A)+19/24,"") -> 44728.792 | L59: =if(L59,L59,if(M59<>"",$A$1,"")) | N59: =if(K59,if(L59<>"",if(L59>K59,L59-K59,""),$A$1-K59),"") -> 1405.1922 | O59: =if(A59,_xlfn.WORKDAY.INTL(A59,O$5,"1000000",Holidays!A:A)+hour(A59)/24+MINUTE(A59)/1440,"") -> 44728.567 | R59: =if(O59,if(P59<>"",if(P59>O59,P59-O59,""),$A$1-O59),"") -> 1405.4165 | U59: =if(O59,_xlfn.WORKDAY.INTL(O59,U$5,"1000000",Holidays!A:A)+hour(O59)/24+MINUTE(O59)/1440,"") -> 44729.567 | V59: =if(V59,V59,if(W59<>"",$A$1,"")) | X59: =if(U59,if(V59<>"",if(V59>U59,V59-U59,""),$A$1-U59),"") -> 1404.4165 | AH59: =IF(P59="","",P59+AB59+AC59+AD59+AE59+AF59) | AI59: =if(AH59,_xlfn.workday.intl(int(AH59),0,"1000000",Holidays!A:A)+18/24,"") | AJ59: =if(AJ59,AJ59,if(AK59<>"",$A$1,"")) | AL59: =if(AI59,if(AJ59<>"",if(AJ59>AI59,AJ59-AI59,""),$A$1-AI59),"") | AN59: =if(AJ59,if(and(hour(AJ59+AN$5)>11,(hour(AJ59+AN$5)<20)),AJ59+AN$5,_xlfn.workday.intl(int(AJ59),1,"1000000",Holidays!A:A)+hour(AJ59+AN$5-$B$1)/24+minute(AJ59)/1440),"") | AO59: =if(AO59,AO59,if(AP59<>"",$A$1,"")) | AQ59: =if(AN59,if(AO59<>"",if(AO59>AN59,AO59-AN59,""),$A$1-AN59),"") | AS59: =if(AJ59,if(and(hour(AJ59+AS$5)>11,(hour(AJ59+AS$5)<20)),AJ59+AS$5,_xlfn.workday.intl(int(AJ59),1,"1000000",Holidays!A:A)+hour(AJ59+AS$5-$B$1)/24+minute(AJ59)/1440),"") | AT59: =if(AT59,AT59,if(AU59<>"",$A$1,"")) | AV59: =if(AS59,if(AT59<>"",if(AT59>AS59,AT59-AS59,""),$A$1-AS59),"") | AX59: No Response
A60: 44728.739 | G60: =if(A60,_xlfn.workday.intl(int(A60),1,"1000000",Holidays!A:A)+17/24,"") -> 44729.708 | H60: =if(H60,H60,if(I60<>"",$A$1,"")) -> 44745.697 | I60: done | J60: =if(G60,if(H60<>"",if(H60>G60,H60-G60,""),$A$1-G60),"") -> 15.988419 | K60: =if(G60,_xlfn.workday.intl(int(G60),0,"1000000",Holidays!A:A)+19/24,"") -> 44729.792 | L60: =if(L60,L60,if(M60<>"",$A$1,"")) -> 44745.697 | M60: done | N60: =if(K60,if(L60<>"",if(L60>K60,L60-K60,""),$A$1-K60),"") -> 15.905777 | O60: =if(A60,_xlfn.WORKDAY.INTL(A60,O$5,"1000000",Holidays!A:A)+hour(A60)/24+MINUTE(A60)/1440,"") -> 44729.738 | P60: 44745.698 | Q60: done | R60: =if(O60,if(P60<>"",if(P60>O60,P60-O60,""),$A$1-O60),"") -> 15.959336 | U60: =if(O60,_xlfn.WORKDAY.INTL(O60,U$5,"1000000",Holidays!A:A)+hour(O60)/24+MINUTE(O60)/1440,"") -> 44730.738 | V60: =if(V60,V60,if(W60<>"",$A$1,"")) | X60: =if(U60,if(V60<>"",if(V60>U60,V60-U60,""),$A$1-U60),"") -> 1403.2457 | AH60: =IF(P60="","",P60+AB60+AC60+AD60+AE60+AF60) -> 44745.698 | AI60: =if(AH60,_xlfn.workday.intl(int(AH60),0,"1000000",Holidays!A:A)+18/24,"") -> 44745.75 | AJ60: =if(AJ60,AJ60,if(AK60<>"",$A$1,"")) | AL60: =if(AI60,if(AJ60<>"",if(AJ60>AI60,AJ60-AI60,""),$A$1-AI60),"") -> 1388.2339 | AN60: =if(AJ60,if(and(hour(AJ60+AN$5)>11,(hour(AJ60+AN$5)<20)),AJ60+AN$5,_xlfn.workday.intl(int(AJ60),1,"1000000",Holidays!A:A)+hour(AJ60+AN$5-$B$1)/24+minute(AJ60)/1440),"") | AO60: =if(AO60,AO60,if(AP60<>"",$A$1,"")) | AQ60: =if(AN60,if(AO60<>"",if(AO60>AN60,AO60-AN60,""),$A$1-AN60),"") | AS60: =if(AJ60,if(and(hour(AJ60+AS$5)>11,(hour(AJ60+AS$5)<20)),AJ60+AS$5,_xlfn.workday.intl(int(AJ60),1,"1000000",Holidays!A:A)+hour(AJ60+AS$5-$B$1)/24+minute(AJ60)/1440),"") | AT60: =if(AT60,AT60,if(AU60<>"",$A$1,"")) | AV60: =if(AS60,if(AT60<>"",if(AT60>AS60,AT60-AS60,""),$A$1-AS60),"")
A61: 44730.703 | G61: =if(A61,_xlfn.workday.intl(int(A61),1,"1000000",Holidays!A:A)+17/24,"") -> 44731.708 | H61: =if(H61,H61,if(I61<>"",$A$1,"")) | J61: =if(G61,if(H61<>"",if(H61>G61,H61-G61,""),$A$1-G61),"") -> 1402.2756 | K61: =if(G61,_xlfn.workday.intl(int(G61),0,"1000000",Holidays!A:A)+19/24,"") -> 44731.792 | L61: =if(L61,L61,if(M61<>"",$A$1,"")) | N61: =if(K61,if(L61<>"",if(L61>K61,L61-K61,""),$A$1-K61),"") -> 1402.1922 | O61: =if(A61,_xlfn.WORKDAY.INTL(A61,O$5,"1000000",Holidays!A:A)+hour(A61)/24+MINUTE(A61)/1440,"") -> 44731.703 | R61: =if(O61,if(P61<>"",if(P61>O61,P61-O61,""),$A$1-O61),"") -> 1402.2811 | U61: =if(O61,_xlfn.WORKDAY.INTL(O61,U$5,"1000000",Holidays!A:A)+hour(O61)/24+MINUTE(O61)/1440,"") -> 44733.703 | V61: =if(V61,V61,if(W61<>"",$A$1,"")) | X61: =if(U61,if(V61<>"",if(V61>U61,V61-U61,""),$A$1-U61),"") -> 1400.2811 | AH61: =IF(P61="","",P61+AB61+AC61+AD61+AE61+AF61) | AI61: =if(AH61,_xlfn.workday.intl(int(AH61),0,"1000000",Holidays!A:A)+18/24,"") | AJ61: =if(AJ61,AJ61,if(AK61<>"",$A$1,"")) | AL61: =if(AI61,if(AJ61<>"",if(AJ61>AI61,AJ61-AI61,""),$A$1-AI61),"") | AN61: =if(AJ61,if(and(hour(AJ61+AN$5)>11,(hour(AJ61+AN$5)<20)),AJ61+AN$5,_xlfn.workday.intl(int(AJ61),1,"1000000",Holidays!A:A)+hour(AJ61+AN$5-$B$1)/24+minute(AJ61)/1440),"") | AO61: =if(AO61,AO61,if(AP61<>"",$A$1,"")) | AQ61: =if(AN61,if(AO61<>"",if(AO61>AN61,AO61-AN61,""),$A$1-AN61),"") | AS61: =if(AJ61,if(and(hour(AJ61+AS$5)>11,(hour(AJ61+AS$5)<20)),AJ61+AS$5,_xlfn.workday.intl(int(AJ61),1,"1000000",Holidays!A:A)+hour(AJ61+AS$5-$B$1)/24+minute(AJ61)/1440),"") | AT61: =if(AT61,AT61,if(AU61<>"",$A$1,"")) | AV61: =if(AS61,if(AT61<>"",if(AT61>AS61,AT61-AS61,""),$A$1-AS61),"") | AX61: No Response
A62: 44730.706 | G62: =if(A62,_xlfn.workday.intl(int(A62),1,"1000000",Holidays!A:A)+17/24,"") -> 44731.708 | H62: =if(H62,H62,if(I62<>"",$A$1,"")) | J62: =if(G62,if(H62<>"",if(H62>G62,H62-G62,""),$A$1-G62),"") -> 1402.2756 | K62: =if(G62,_xlfn.workday.intl(int(G62),0,"1000000",Holidays!A:A)+19/24,"") -> 44731.792 | L62: =if(L62,L62,if(M62<>"",$A$1,"")) | N62: =if(K62,if(L62<>"",if(L62>K62,L62-K62,""),$A$1-K62),"") -> 1402.1922 | O62: =if(A62,_xlfn.WORKDAY.INTL(A62,O$5,"1000000",Holidays!A:A)+hour(A62)/24+MINUTE(A62)/1440,"") -> 44731.706 | R62: =if(O62,if(P62<>"",if(P62>O62,P62-O62,""),$A$1-O62),"") -> 1402.2784 | U62: =if(O62,_xlfn.WORKDAY.INTL(O62,U$5,"1000000",Holidays!A:A)+hour(O62)/24+MINUTE(O62)/1440,"") -> 44733.706 | V62: =if(V62,V62,if(W62<>"",$A$1,"")) | X62: =if(U62,if(V62<>"",if(V62>U62,V62-U62,""),$A$1-U62),"") -> 1400.2784 | AH62: =IF(P62="","",P62+AB62+AC62+AD62+AE62+AF62) | AI62: =if(AH62,_xlfn.workday.intl(int(AH62),0,"1000000",Holidays!A:A)+18/24,"") | AJ62: =if(AJ62,AJ62,if(AK62<>"",$A$1,"")) | AL62: =if(AI62,if(AJ62<>"",if(AJ62>AI62,AJ62-AI62,""),$A$1-AI62),"") | AN62: =if(AJ62,if(and(hour(AJ62+AN$5)>11,(hour(AJ62+AN$5)<20)),AJ62+AN$5,_xlfn.workday.intl(int(AJ62),1,"1000000",Holidays!A:A)+hour(AJ62+AN$5-$B$1)/24+minute(AJ62)/1440),"") | AO62: =if(AO62,AO62,if(AP62<>"",$A$1,"")) | AQ62: =if(AN62,if(AO62<>"",if(AO62>AN62,AO62-AN62,""),$A$1-AN62),"") | AS62: =if(AJ62,if(and(hour(AJ62+AS$5)>11,(hour(AJ62+AS$5)<20)),AJ62+AS$5,_xlfn.workday.intl(int(AJ62),1,"1000000",Holidays!A:A)+hour(AJ62+AS$5-$B$1)/24+minute(AJ62)/1440),"") | AT62: =if(AT62,AT62,if(AU62<>"",$A$1,"")) -> 44842.658 | AU62: yes | AV62: =if(AS62,if(AT62<>"",if(AT62>AS62,AT62-AS62,""),$A$1-AS62),"") | AX62: done
A63: 44730.707 | G63: =if(A63,_xlfn.workday.intl(int(A63),1,"1000000",Holidays!A:A)+17/24,"") -> 44731.708 | H63: =if(H63,H63,if(I63<>"",$A$1,"")) -> 44772.516 | I63: done | J63: =if(G63,if(H63<>"",if(H63>G63,H63-G63,""),$A$1-G63),"") -> 40.808006 | K63: =if(G63,_xlfn.workday.intl(int(G63),0,"1000000",Holidays!A:A)+19/24,"") -> 44731.792 | L63: =if(L63,L63,if(M63<>"",$A$1,"")) -> 44772.516 | M63: done | N63: =if(K63,if(L63<>"",if(L63>K63,L63-K63,""),$A$1-K63),"") -> 40.724548 | O63: =if(A63,_xlfn.WORKDAY.INTL(A63,O$5,"1000000",Holidays!A:A)+hour(A63)/24+MINUTE(A63)/1440,"") -> 44731.707 | P63: 44766.712 | Q63: done | R63: =if(O63,if(P63<>"",if(P63>O63,P63-O63,""),$A$1-O63),"") -> 35.004676 | U63: =if(O63,_xlfn.WORKDAY.INTL(O63,U$5,"1000000",Holidays!A:A)+hour(O63)/24+MINUTE(O63)/1440,"") -> 44733.707 | V63: =if(V63,V63,if(W63<>"",$A$1,"")) | X63: =if(U63,if(V63<>"",if(V63>U63,V63-U63,""),$A$1-U63),"") -> 1400.277 | AH63: =IF(P63="","",P63+AB63+AC63+AD63+AE63+AF63) -> 44766.712 | AI63: =if(AH63,_xlfn.workday.intl(int(AH63),0,"1000000",Holidays!A:A)+18/24,"") -> 44766.75 | AJ63: =if(AJ63,AJ63,if(AK63<>"",$A$1,"")) -> 44772.516 | AK63: done | AL63: =if(AI63,if(AJ63<>"",if(AJ63>AI63,AJ63-AI63,""),$A$1-AI63),"") -> 5.7664275 | AN63: =if(AJ63,if(and(hour(AJ63+AN$5)>11,(hour(AJ63+AN$5)<20)),AJ63+AN$5,_xlfn.workday.intl(int(AJ63),1,"1000000",Holidays!A:A)+hour(AJ63+AN$5-$B$1)/24+minute(AJ63)/1440),"") -> 44773.516 | AO63: =if(AO63,AO63,if(AP63<>"",$A$1,"")) -> 44772.516 | AP63: done | AQ63: =if(AN63,if(AO63<>"",if(AO63>AN63,AO63-AN63,""),$A$1-AN63),"") | AS63: =if(AJ63,if(and(hour(AJ63+AS$5)>11,(hour(AJ63+AS$5)<20)),AJ63+AS$5,_xlfn.workday.intl(int(AJ63),1,"1000000",Holidays!A:A)+hour(AJ63+AS$5-$B$1)/24+minute(AJ63)/1440),"") -> 44774.516 | AT63: =if(AT63,AT63,if(AU63<>"",$A$1,"")) -> 44772.517 | AU63: yes | AV63: =if(AS63,if(AT63<>"",if(AT63>AS63,AT63-AS63,""),$A$1-AS63),"") | AX63: done
A64: 44730.709 | G64: =if(A64,_xlfn.workday.intl(int(A64),1,"1000000",Holidays!A:A)+17/24,"") -> 44731.708 | H64: =if(H64,H64,if(I64<>"",$A$1,"")) | J64: =if(G64,if(H64<>"",if(H64>G64,H64-G64,""),$A$1-G64),"") -> 1402.2756 | K64: =if(G64,_xlfn.workday.intl(int(G64),0,"1000000",Holidays!A:A)+19/24,"") -> 44731.792 | L64: =if(L64,L64,if(M64<>"",$A$1,"")) -> 44777.498 | M64: done | N64: =if(K64,if(L64<>"",if(L64>K64,L64-K64,""),$A$1-K64),"") -> 45.706576 | O64: =if(A64,_xlfn.WORKDAY.INTL(A64,O$5,"1000000",Holidays!A:A)+hour(A64)/24+MINUTE(A64)/1440,"") -> 44731.708 | P64: 44777.498 | Q64: done | R64: =if(O64,if(P64<>"",if(P64>O64,P64-O64,""),$A$1-O64),"") -> 45.789965 | U64: =if(O64,_xlfn.WORKDAY.INTL(O64,U$5,"1000000",Holidays!A:A)+hour(O64)/24+MINUTE(O64)/1440,"") -> 44733.708 | V64: =if(V64,V64,if(W64<>"",$A$1,"")) | X64: =if(U64,if(V64<>"",if(V64>U64,V64-U64,""),$A$1-U64),"") -> 1400.2756 | AB64: 1 | AH64: =IF(P64="","",P64+AB64+AC64+AD64+AE64+AF64) -> 44778.498 | AI64: =if(AH64,_xlfn.workday.intl(int(AH64),0,"1000000",Holidays!A:A)+18/24,"") -> 44778.75 | AJ64: =if(AJ64,AJ64,if(AK64<>"",$A$1,"")) | AL64: =if(AI64,if(AJ64<>"",if(AJ64>AI64,AJ64-AI64,""),$A$1-AI64),"") -> 1355.2339 | AN64: =if(AJ64,if(and(hour(AJ64+AN$5)>11,(hour(AJ64+AN$5)<20)),AJ64+AN$5,_xlfn.workday.intl(int(AJ64),1,"1000000",Holidays!A:A)+hour(AJ64+AN$5-$B$1)/24+minute(AJ64)/1440),"") | AO64: =if(AO64,AO64,if(AP64<>"",$A$1,"")) -> 44777.498 | AP64: done | AQ64: =if(AN64,if(AO64<>"",if(AO64>AN64,AO64-AN64,""),$A$1-AN64),"") | AS64: =if(AJ64,if(and(hour(AJ64+AS$5)>11,(hour(AJ64+AS$5)<20)),AJ64+AS$5,_xlfn.workday.intl(int(AJ64),1,"1000000",Holidays!A:A)+hour(AJ64+AS$5-$B$1)/24+minute(AJ64)/1440),"") | AT64: =if(AT64,AT64,if(AU64<>"",$A$1,"")) -> 44905.622 | AU64: yes | AV64: =if(AS64,if(AT64<>"",if(AT64>AS64,AT64-AS64,""),$A$1-AS64),"") | AX64: done
A65: 44730.711 | G65: =if(A65,_xlfn.workday.intl(int(A65),1,"1000000",Holidays!A:A)+17/24,"") -> 44731.708 | H65: =if(H65,H65,if(I65<>"",$A$1,"")) -> 44777.498 | I65: done | J65: =if(G65,if(H65<>"",if(H65>G65,H65-G65,""),$A$1-G65),"") -> 45.789473 | K65: =if(G65,_xlfn.workday.intl(int(G65),0,"1000000",Holidays!A:A)+19/24,"") -> 44731.792 | L65: =if(L65,L65,if(M65<>"",$A$1,"")) -> 44777.498 | M65: done | N65: =if(K65,if(L65<>"",if(L65>K65,L65-K65,""),$A$1-K65),"") -> 45.70618 | O65: =if(A65,_xlfn.WORKDAY.INTL(A65,O$5,"1000000",Holidays!A:A)+hour(A65)/24+MINUTE(A65)/1440,"") -> 44731.71 | P65: 44777.498 | Q65: done | R65: =if(O65,if(P65<>"",if(P65>O65,P65-O65,""),$A$1-O65),"") -> 45.787464 | U65: =if(O65,_xlfn.WORKDAY.INTL(O65,U$5,"1000000",Holidays!A:A)+hour(O65)/24+MINUTE(O65)/1440,"") -> 44733.71 | V65: =if(V65,V65,if(W65<>"",$A$1,"")) | X65: =if(U65,if(V65<>"",if(V65>U65,V65-U65,""),$A$1-U65),"") -> 1400.2735 | AB65: 1 | AH65: =IF(P65="","",P65+AB65+AC65+AD65+AE65+AF65) -> 44778.498 | AI65: =if(AH65,_xlfn.workday.intl(int(AH65),0,"1000000",Holidays!A:A)+18/24,"") -> 44778.75 | AJ65: =if(AJ65,AJ65,if(AK65<>"",$A$1,"")) | AL65: =if(AI65,if(AJ65<>"",if(AJ65>AI65,AJ65-AI65,""),$A$1-AI65),"") -> 1355.2339 | AN65: =if(AJ65,if(and(hour(AJ65+AN$5)>11,(hour(AJ65+AN$5)<20)),AJ65+AN$5,_xlfn.workday.intl(int(AJ65),1,"1000000",Holidays!A:A)+hour(AJ65+AN$5-$B$1)/24+minute(AJ65)/1440),"") | AO65: =if(AO65,AO65,if(AP65<>"",$A$1,"")) -> 44777.498 | AP65: done | AQ65: =if(AN65,if(AO65<>"",if(AO65>AN65,AO65-AN65,""),$A$1-AN65),"") | AS65: =if(AJ65,if(and(hour(AJ65+AS$5)>11,(hour(AJ65+AS$5)<20)),AJ65+AS$5,_xlfn.workday.intl(int(AJ65),1,"1000000",Holidays!A:A)+hour(AJ65+AS$5-$B$1)/24+minute(AJ65)/1440),"") | AT65: =if(AT65,AT65,if(AU65<>"",$A$1,"")) | AV65: =if(AS65,if(AT65<>"",if(AT65>AS65,AT65-AS65,""),$A$1-AS65),"") | AX65: No Response
A66: 44730.715 | G66: =if(A66,_xlfn.workday.intl(int(A66),1,"1000000",Holidays!A:A)+17/24,"") -> 44731.708 | H66: =if(H66,H66,if(I66<>"",$A$1,"")) | J66: =if(G66,if(H66<>"",if(H66>G66,H66-G66,""),$A$1-G66),"") -> 1402.2756 | K66: =if(G66,_xlfn.workday.intl(int(G66),0,"1000000",Holidays!A:A)+19/24,"") -> 44731.792 | L66: =if(L66,L66,if(M66<>"",$A$1,"")) | N66: =if(K66,if(L66<>"",if(L66>K66,L66-K66,""),$A$1-K66),"") -> 1402.1922 | O66: =if(A66,_xlfn.WORKDAY.INTL(A66,O$5,"1000000",Holidays!A:A)+hour(A66)/24+MINUTE(A66)/1440,"") -> 44731.715 | R66: =if(O66,if(P66<>"",if(P66>O66,P66-O66,""),$A$1-O66),"") -> 1402.2693 | U66: =if(O66,_xlfn.WORKDAY.INTL(O66,U$5,"1000000",Holidays!A:A)+hour(O66)/24+MINUTE(O66)/1440,"") -> 44733.715 | V66: =if(V66,V66,if(W66<>"",$A$1,"")) | X66: =if(U66,if(V66<>"",if(V66>U66,V66-U66,""),$A$1-U66),"") -> 1400.2693 | AH66: =IF(P66="","",P66+AB66+AC66+AD66+AE66+AF66) | AI66: =if(AH66,_xlfn.workday.intl(int(AH66),0,"1000000",Holidays!A:A)+18/24,"") | AJ66: =if(AJ66,AJ66,if(AK66<>"",$A$1,"")) | AL66: =if(AI66,if(AJ66<>"",if(AJ66>AI66,AJ66-AI66,""),$A$1-AI66),"") | AN66: =if(AJ66,if(and(hour(AJ66+AN$5)>11,(hour(AJ66+AN$5)<20)),AJ66+AN$5,_xlfn.workday.intl(int(AJ66),1,"1000000",Holidays!A:A)+hour(AJ66+AN$5-$B$1)/24+minute(AJ66)/1440),"") | AO66: =if(AO66,AO66,if(AP66<>"",$A$1,"")) | AQ66: =if(AN66,if(AO66<>"",if(AO66>AN66,AO66-AN66,""),$A$1-AN66),"") | AS66: =if(AJ66,if(and(hour(AJ66+AS$5)>11,(hour(AJ66+AS$5)<20)),AJ66+AS$5,_xlfn.workday.intl(int(AJ66),1,"1000000",Holidays!A:A)+hour(AJ66+AS$5-$B$1)/24+minute(AJ66)/1440),"") | AT66: =if(AT66,AT66,if(AU66<>"",$A$1,"")) | AV66: =if(AS66,if(AT66<>"",if(AT66>AS66,AT66-AS66,""),$A$1-AS66),"") | AX66: Hold
A67: 44733.552 | G67: =if(A67,_xlfn.workday.intl(int(A67),1,"1000000",Holidays!A:A)+17/24,"") -> 44734.708 | H67: =if(H67,H67,if(I67<>"",$A$1,"")) -> 44744.464 | I67: done | J67: =if(G67,if(H67<>"",if(H67>G67,H67-G67,""),$A$1-G67),"") -> 9.7555212 | K67: =if(G67,_xlfn.workday.intl(int(G67),0,"1000000",Holidays!A:A)+19/24,"") -> 44734.792 | L67: =if(L67,L67,if(M67<>"",$A$1,"")) -> 44744.464 | M67: done | N67: =if(K67,if(L67<>"",if(L67>K67,L67-K67,""),$A$1-K67),"") -> 9.6722506 | O67: =if(A67,_xlfn.WORKDAY.INTL(A67,O$5,"1000000",Holidays!A:A)+hour(A67)/24+MINUTE(A67)/1440,"") -> 44734.551 | P67: 44744.464 | Q67: done | R67: =if(O67,if(P67<>"",if(P67>O67,P67-O67,""),$A$1-O67),"") -> 9.9125639 | U67: =if(O67,_xlfn.WORKDAY.INTL(O67,U$5,"1000000",Holidays!A:A)+hour(O67)/24+MINUTE(O67)/1440,"") -> 44735.551 | V67: =if(V67,V67,if(W67<>"",$A$1,"")) | X67: =if(U67,if(V67<>"",if(V67>U67,V67-U67,""),$A$1-U67),"") -> 1398.4325 | AH67: =IF(P67="","",P67+AB67+AC67+AD67+AE67+AF67) -> 44744.464 | AI67: =if(AH67,_xlfn.workday.intl(int(AH67),0,"1000000",Holidays!A:A)+18/24,"") -> 44744.75 | AJ67: =if(AJ67,AJ67,if(AK67<>"",$A$1,"")) -> 44744.464 | AK67: done | AL67: =if(AI67,if(AJ67<>"",if(AJ67>AI67,AJ67-AI67,""),$A$1-AI67),"") | AN67: =if(AJ67,if(and(hour(AJ67+AN$5)>11,(hour(AJ67+AN$5)<20)),AJ67+AN$5,_xlfn.workday.intl(int(AJ67),1,"1000000",Holidays!A:A)+hour(AJ67+AN$5-$B$1)/24+minute(AJ67)/1440),"") -> 44745.464 | AO67: =if(AO67,AO67,if(AP67<>"",$A$1,"")) -> 44744.464 | AP67: done | AQ67: =if(AN67,if(AO67<>"",if(AO67>AN67,AO67-AN67,""),$A$1-AN67),"") | AS67: =if(AJ67,if(and(hour(AJ67+AS$5)>11,(hour(AJ67+AS$5)<20)),AJ67+AS$5,_xlfn.workday.intl(int(AJ67),1,"1000000",Holidays!A:A)+hour(AJ67+AS$5-$B$1)/24+minute(AJ67)/1440),"") -> 44745.464 | AT67: =if(AT67,AT67,if(AU67<>"",$A$1,"")) -> 44744.464 | AU67: yes | AV67: =if(AS67,if(AT67<>"",if(AT67>AS67,AT67-AS67,""),$A$1-AS67),"") | AX67: done
A68: 44741.75 | G68: =if(A68,_xlfn.workday.intl(int(A68),1,"1000000",Holidays!A:A)+17/24,"") -> 44742.708 | H68: =if(H68,H68,if(I68<>"",$A$1,"")) -> 44761.514 | I68: done | J68: =if(G68,if(H68<>"",if(H68>G68,H68-G68,""),$A$1-G68),"") -> 18.80539 | K68: =if(G68,_xlfn.workday.intl(int(G68),0,"1000000",Holidays!A:A)+19/24,"") -> 44742.792 | L68: =if(L68,L68,if(M68<>"",$A$1,"")) -> 44773.573 | M68: done | N68: =if(K68,if(L68<>"",if(L68>K68,L68-K68,""),$A$1-K68),"") -> 30.78178 | O68: =if(A68,_xlfn.WORKDAY.INTL(A68,O$5,"1000000",Holidays!A:A)+hour(A68)/24+MINUTE(A68)/1440,"") -> 44742.75 | P68: 44761.739 | Q68: done | R68: =if(O68,if(P68<>"",if(P68>O68,P68-O68,""),$A$1-O68),"") -> 18.989432 | U68: =if(O68,_xlfn.WORKDAY.INTL(O68,U$5,"1000000",Holidays!A:A)+hour(O68)/24+MINUTE(O68)/1440,"") -> 44743.75 | V68: =if(V68,V68,if(W68<>"",$A$1,"")) | X68: =if(U68,if(V68<>"",if(V68>U68,V68-U68,""),$A$1-U68),"") -> 1390.2339 | AH68: =IF(P68="","",P68+AB68+AC68+AD68+AE68+AF68) -> 44761.739 | AI68: =if(AH68,_xlfn.workday.intl(int(AH68),0,"1000000",Holidays!A:A)+18/24,"") -> 44761.75 | AJ68: =if(AJ68,AJ68,if(AK68<>"",$A$1,"")) | AL68: =if(AI68,if(AJ68<>"",if(AJ68>AI68,AJ68-AI68,""),$A$1-AI68),"") -> 1372.2339 | AN68: =if(AJ68,if(and(hour(AJ68+AN$5)>11,(hour(AJ68+AN$5)<20)),AJ68+AN$5,_xlfn.workday.intl(int(AJ68),1,"1000000",Holidays!A:A)+hour(AJ68+AN$5-$B$1)/24+minute(AJ68)/1440),"") | AO68: =if(AO68,AO68,if(AP68<>"",$A$1,"")) | AQ68: =if(AN68,if(AO68<>"",if(AO68>AN68,AO68-AN68,""),$A$1-AN68),"") | AS68: =if(AJ68,if(and(hour(AJ68+AS$5)>11,(hour(AJ68+AS$5)<20)),AJ68+AS$5,_xlfn.workday.intl(int(AJ68),1,"1000000",Holidays!A:A)+hour(AJ68+AS$5-$B$1)/24+minute(AJ68)/1440),"") | AT68: =if(AT68,AT68,if(AU68<>"",$A$1,"")) | AV68: =if(AS68,if(AT68<>"",if(AT68>AS68,AT68-AS68,""),$A$1-AS68),"") | AX68: Hold
A69: 44741.752 | G69: =if(A69,_xlfn.workday.intl(int(A69),1,"1000000",Holidays!A:A)+17/24,"") -> 44742.708 | H69: =if(H69,H69,if(I69<>"",$A$1,"")) -> 44761.514 | I69: done | J69: =if(G69,if(H69<>"",if(H69>G69,H69-G69,""),$A$1-G69),"") -> 18.805432 | K69: =if(G69,_xlfn.workday.intl(int(G69),0,"1000000",Holidays!A:A)+19/24,"") -> 44742.792 | L69: =if(L69,L69,if(M69<>"",$A$1,"")) -> 44773.573 | M69: done | N69: =if(K69,if(L69<>"",if(L69>K69,L69-K69,""),$A$1-K69),"") -> 30.78178 | O69: =if(A69,_xlfn.WORKDAY.INTL(A69,O$5,"1000000",Holidays!A:A)+hour(A69)/24+MINUTE(A69)/1440,"") -> 44742.751 | P69: 44747.62 | Q69: done | R69: =if(O69,if(P69<>"",if(P69>O69,P69-O69,""),$A$1-O69),"") -> 4.8682092 | U69: =if(O69,_xlfn.WORKDAY.INTL(O69,U$5,"1000000",Holidays!A:A)+hour(O69)/24+MINUTE(O69)/1440,"") -> 44743.751 | V69: =if(V69,V69,if(W69<>"",$A$1,"")) | X69: =if(U69,if(V69<>"",if(V69>U69,V69-U69,""),$A$1-U69),"") -> 1390.2325 | AH69: =IF(P69="","",P69+AB69+AC69+AD69+AE69+AF69) -> 44747.62 | AI69: =if(AH69,_xlfn.workday.intl(int(AH69),0,"1000000",Holidays!A:A)+18/24,"") -> 44747.75 | AJ69: =if(AJ69,AJ69,if(AK69<>"",$A$1,"")) | AL69: =if(AI69,if(AJ69<>"",if(AJ69>AI69,AJ69-AI69,""),$A$1-AI69),"") -> 1386.2339 | AN69: =if(AJ69,if(and(hour(AJ69+AN$5)>11,(hour(AJ69+AN$5)<20)),AJ69+AN$5,_xlfn.workday.intl(int(AJ69),1,"1000000",Holidays!A:A)+hour(AJ69+AN$5-$B$1)/24+minute(AJ69)/1440),"") | AO69: =if(AO69,AO69,if(AP69<>"",$A$1,"")) | AQ69: =if(AN69,if(AO69<>"",if(AO69>AN69,AO69-AN69,""),$A$1-AN69),"") | AS69: =if(AJ69,if(and(hour(AJ69+AS$5)>11,(hour(AJ69+AS$5)<20)),AJ69+AS$5,_xlfn.workday.intl(int(AJ69),1,"1000000",Holidays!A:A)+hour(AJ69+AS$5-$B$1)/24+minute(AJ69)/1440),"") | AT69: =if(AT69,AT69,if(AU69<>"",$A$1,"")) | AV69: =if(AS69,if(AT69<>"",if(AT69>AS69,AT69-AS69,""),$A$1-AS69),"") | AX69: Hold
A70: 44743.573 | G70: =if(A70,_xlfn.workday.intl(int(A70),1,"1000000",Holidays!A:A)+17/24,"") -> 44744.708 | J70: =if(G70,if(H70<>"",if(H70>G70,H70-G70,""),$A$1-G70),"") -> 1389.2756 | K70: =if(G70,_xlfn.workday.intl(int(G70),0,"1000000",Holidays!A:A)+19/24,"") -> 44744.792 | L70: =if(L70,L70,if(M70<>"",$A$1,"")) -> 44773.573 | M70: done | N70: =if(K70,if(L70<>"",if(L70>K70,L70-K70,""),$A$1-K70),"") -> 28.78178 | O70: =if(A70,_xlfn.WORKDAY.INTL(A70,O$5,"1000000",Holidays!A:A)+hour(A70)/24+MINUTE(A70)/1440,"") -> 44744.572 | P70: 44773.573 | Q70: done | R70: =if(O70,if(P70<>"",if(P70>O70,P70-O70,""),$A$1-O70),"") -> 29.001224 | U70: =if(O70,_xlfn.WORKDAY.INTL(O70,U$5,"1000000",Holidays!A:A)+hour(O70)/24+MINUTE(O70)/1440,"") -> 44745.572 | V70: =if(V70,V70,if(W70<>"",$A$1,"")) | X70: =if(U70,if(V70<>"",if(V70>U70,V70-U70,""),$A$1-U70),"") -> 1388.4117 | AH70: =IF(P70="","",P70+AB70+AC70+AD70+AE70+AF70) -> 44773.573 | AI70: =if(AH70,_xlfn.workday.intl(int(AH70),0,"1000000",Holidays!A:A)+18/24,"") -> 44773.75 | AJ70: =if(AJ70,AJ70,if(AK70<>"",$A$1,"")) | AL70: =if(AI70,if(AJ70<>"",if(AJ70>AI70,AJ70-AI70,""),$A$1-AI70),"") -> 1360.2339 | AN70: =if(AJ70,if(and(hour(AJ70+AN$5)>11,(hour(AJ70+AN$5)<20)),AJ70+AN$5,_xlfn.workday.intl(int(AJ70),1,"1000000",Holidays!A:A)+hour(AJ70+AN$5-$B$1)/24+minute(AJ70)/1440),"") | AO70: =if(AO70,AO70,if(AP70<>"",$A$1,"")) | AQ70: =if(AN70,if(AO70<>"",if(AO70>AN70,AO70-AN70,""),$A$1-AN70),"") | AS70: =if(AJ70,if(and(hour(AJ70+AS$5)>11,(hour(AJ70+AS$5)<20)),AJ70+AS$5,_xlfn.workday.intl(int(AJ70),1,"1000000",Holidays!A:A)+hour(AJ70+AS$5-$B$1)/24+minute(AJ70)/1440),"") | AT70: =if(AT70,AT70,if(AU70<>"",$A$1,"")) | AV70: =if(AS70,if(AT70<>"",if(AT70>AS70,AT70-AS70,""),$A$1-AS70),"") | AX70: No Response
A71: 44743.672 | G71: =if(A71,_xlfn.workday.intl(int(A71),1,"1000000",Holidays!A:A)+17/24,"") -> 44744.708 | H71: =if(H71,H71,if(I71<>"",$A$1,"")) -> 44761.514 | I71: done | J71: =if(G71,if(H71<>"",if(H71>G71,H71-G71,""),$A$1-G71),"") -> 16.80561 | K71: =if(G71,_xlfn.workday.intl(int(G71),0,"1000000",Holidays!A:A)+19/24,"") -> 44744.792 | L71: =if(L71,L71,if(M71<>"",$A$1,"")) -> 44773.573 | M71: done | N71: =if(K71,if(L71<>"",if(L71>K71,L71-K71,""),$A$1-K71),"") -> 28.781415 | O71: =if(A71,_xlfn.WORKDAY.INTL(A71,O$5,"1000000",Holidays!A:A)+hour(A71)/24+MINUTE(A71)/1440,"") -> 44744.672 | P71: 44745.632 | Q71: done | R71: =if(O71,if(P71<>"",if(P71>O71,P71-O71,""),$A$1-O71),"") -> 0.95958795 | U71: =if(O71,_xlfn.WORKDAY.INTL(O71,U$5,"1000000",Holidays!A:A)+hour(O71)/24+MINUTE(O71)/1440,"") -> 44745.672 | V71: =if(V71,V71,if(W71<>"",$A$1,"")) | X71: =if(U71,if(V71<>"",if(V71>U71,V71-U71,""),$A$1-U71),"") -> 1388.3117 | AB71: 3 | AC71: 5 | AD71: 10 | AE71: 4 | AH71: =IF(P71="","",P71+AB71+AC71+AD71+AE71+AF71) -> 44767.632 | AI71: =if(AH71,_xlfn.workday.intl(int(AH71),0,"1000000",Holidays!A:A)+18/24,"") -> 44767.75 | AJ71: =if(AJ71,AJ71,if(AK71<>"",$A$1,"")) | AL71: =if(AI71,if(AJ71<>"",if(AJ71>AI71,AJ71-AI71,""),$A$1-AI71),"") -> 1366.2339 | AN71: =if(AJ71,if(and(hour(AJ71+AN$5)>11,(hour(AJ71+AN$5)<20)),AJ71+AN$5,_xlfn.workday.intl(int(AJ71),1,"1000000",Holidays!A:A)+hour(AJ71+AN$5-$B$1)/24+minute(AJ71)/1440),"") | AO71: =if(AO71,AO71,if(AP71<>"",$A$1,"")) | AQ71: =if(AN71,if(AO71<>"",if(AO71>AN71,AO71-AN71,""),$A$1-AN71),"") | AS71: =if(AJ71,if(and(hour(AJ71+AS$5)>11,(hour(AJ71+AS$5)<20)),AJ71+AS$5,_xlfn.workday.intl(int(AJ71),1,"1000000",Holidays!A:A)+hour(AJ71+AS$5-$B$1)/24+minute(AJ71)/1440),"") | AT71: =if(AT71,AT71,if(AU71<>"",$A$1,"")) | AV71: =if(AS71,if(AT71<>"",if(AT71>AS71,AT71-AS71,""),$A$1-AS71),"") | AX71: shop
A72: 44744.651 | G72: =if(A72,_xlfn.workday.intl(int(A72),1,"1000000",Holidays!A:A)+17/24,"") -> 44745.708 | H72: =if(H72,H72,if(I72<>"",$A$1,"")) -> 44761.514 | I72: done | J72: =if(G72,if(H72<>"",if(H72>G72,H72-G72,""),$A$1-G72),"") -> 15.805556 | K72: =if(G72,_xlfn.workday.intl(int(G72),0,"1000000",Holidays!A:A)+19/24,"") -> 44745.792 | L72: =if(L72,L72,if(M72<>"",$A$1,"")) -> 44773.573 | M72: done | N72: =if(K72,if(L72<>"",if(L72>K72,L72-K72,""),$A$1-K72),"") -> 27.781415 | O72: =if(A72,_xlfn.WORKDAY.INTL(A72,O$5,"1000000",Holidays!A:A)+hour(A72)/24+MINUTE(A72)/1440,"") -> 44745.65 | P72: 44744.776 | Q72: done | R72: =if(O72,if(P72<>"",if(P72>O72,P72-O72,""),$A$1-O72),"") | U72: =if(O72,_xlfn.WORKDAY.INTL(O72,U$5,"1000000",Holidays!A:A)+hour(O72)/24+MINUTE(O72)/1440,"") -> 44747.65 | V72: =if(V72,V72,if(W72<>"",$A$1,"")) | X72: =if(U72,if(V72<>"",if(V72>U72,V72-U72,""),$A$1-U72),"") -> 1386.3339 | AB72: 1 | AH72: =IF(P72="","",P72+AB72+AC72+AD72+AE72+AF72) -> 44745.776 | AI72: =if(AH72,_xlfn.workday.intl(int(AH72),0,"1000000",Holidays!A:A)+18/24,"") -> 44745.75 | AJ72: =if(AJ72,AJ72,if(AK72<>"",$A$1,"")) | AL72: =if(AI72,if(AJ72<>"",if(AJ72>AI72,AJ72-AI72,""),$A$1-AI72),"") -> 1388.2339 | AN72: =if(AJ72,if(and(hour(AJ72+AN$5)>11,(hour(AJ72+AN$5)<20)),AJ72+AN$5,_xlfn.workday.intl(int(AJ72),1,"1000000",Holidays!A:A)+hour(AJ72+AN$5-$B$1)/24+minute(AJ72)/1440),"") | AO72: =if(AO72,AO72,if(AP72<>"",$A$1,"")) | AQ72: =if(AN72,if(AO72<>"",if(AO72>AN72,AO72-AN72,""),$A$1-AN72),"") | AS72: =if(AJ72,if(and(hour(AJ72+AS$5)>11,(hour(AJ72+AS$5)<20)),AJ72+AS$5,_xlfn.workday.intl(int(AJ72),1,"1000000",Holidays!A:A)+hour(AJ72+AS$5-$B$1)/24+minute(AJ72)/1440),"") | AT72: =if(AT72,AT72,if(AU72<>"",$A$1,"")) | AV72: =if(AS72,if(AT72<>"",if(AT72>AS72,AT72-AS72,""),$A$1-AS72),"") | AX72: shop
A73: 44745.766 | G73: =if(A73,_xlfn.workday.intl(int(A73),1,"1000000",Holidays!A:A)+17/24,"") -> 44747.708 | H73: =if(H73,H73,if(I73<>"",$A$1,"")) -> 44777.497 | I73: done | J73: =if(G73,if(H73<>"",if(H73>G73,H73-G73,""),$A$1-G73),"") -> 29.788492 | K73: =if(G73,_xlfn.workday.intl(int(G73),0,"1000000",Holidays!A:A)+19/24,"") -> 44747.792 | L73: =if(L73,L73,if(M73<>"",$A$1,"")) -> 44773.573 | M73: done | N73: =if(K73,if(L73<>"",if(L73>K73,L73-K73,""),$A$1-K73),"") -> 25.781415 | O73: =if(A73,_xlfn.WORKDAY.INTL(A73,O$5,"1000000",Holidays!A:A)+hour(A73)/24+MINUTE(A73)/1440,"") -> 44747.765 | P73: 44747.62 | Q73: done | R73: =if(O73,if(P73<>"",if(P73>O73,P73-O73,""),$A$1-O73),"") | U73: =if(O73,_xlfn.WORKDAY.INTL(O73,U$5,"1000000",Holidays!A:A)+hour(O73)/24+MINUTE(O73)/1440,"") -> 44748.765 | V73: =if(V73,V73,if(W73<>"",$A$1,"")) | X73: =if(U73,if(V73<>"",if(V73>U73,V73-U73,""),$A$1-U73),"") -> 1385.2186 | AH73: =IF(P73="","",P73+AB73+AC73+AD73+AE73+AF73) -> 44747.62 | AI73: =if(AH73,_xlfn.workday.intl(int(AH73),0,"1000000",Holidays!A:A)+18/24,"") -> 44747.75 | AJ73: =if(AJ73,AJ73,if(AK73<>"",$A$1,"")) | AL73: =if(AI73,if(AJ73<>"",if(AJ73>AI73,AJ73-AI73,""),$A$1-AI73),"") -> 1386.2339 | AN73: =if(AJ73,if(and(hour(AJ73+AN$5)>11,(hour(AJ73+AN$5)<20)),AJ73+AN$5,_xlfn.workday.intl(int(AJ73),1,"1000000",Holidays!A:A)+hour(AJ73+AN$5-$B$1)/24+minute(AJ73)/1440),"") | AO73: =if(AO73,AO73,if(AP73<>"",$A$1,"")) | AQ73: =if(AN73,if(AO73<>"",if(AO73>AN73,AO73-AN73,""),$A$1-AN73),"") | AS73: =if(AJ73,if(and(hour(AJ73+AS$5)>11,(hour(AJ73+AS$5)<20)),AJ73+AS$5,_xlfn.workday.intl(int(AJ73),1,"1000000",Holidays!A:A)+hour(AJ73+AS$5-$B$1)/24+minute(AJ73)/1440),"") | AT73: =if(AT73,AT73,if(AU73<>"",$A$1,"")) | AV73: =if(AS73,if(AT73<>"",if(AT73>AS73,AT73-AS73,""),$A$1-AS73),"") | AX73: hold
A74: 44747.525 | G74: =if(A74,_xlfn.workday.intl(int(A74),1,"1000000",Holidays!A:A)+17/24,"") -> 44748.708 | H74: =if(H74,H74,if(I74<>"",$A$1,"")) -> 44761.508 | I74: done | J74: =if(G74,if(H74<>"",if(H74>G74,H74-G74,""),$A$1-G74),"") -> 12.800058 | K74: =if(G74,_xlfn.workday.intl(int(G74),0,"1000000",Holidays!A:A)+19/24,"") -> 44748.792 | L74: =if(L74,L74,if(M74<>"",$A$1,"")) -> 44761.508 | M74: done | N74: =if(K74,if(L74<>"",if(L74>K74,L74-K74,""),$A$1-K74),"") -> 12.716762 | O74: =if(A74,_xlfn.WORKDAY.INTL(A74,O$5,"1000000",Holidays!A:A)+hour(A74)/24+MINUTE(A74)/1440,"") -> 44748.524 | P74: 44750.721 | Q74: done | R74: =if(O74,if(P74<>"",if(P74>O74,P74-O74,""),$A$1-O74),"") -> 2.1963962 | U74: =if(O74,_xlfn.WORKDAY.INTL(O74,U$5,"1000000",Holidays!A:A)+hour(O74)/24+MINUTE(O74)/1440,"") -> 44749.524 | V74: =if(V74,V74,if(W74<>"",$A$1,"")) | X74: =if(U74,if(V74<>"",if(V74>U74,V74-U74,""),$A$1-U74),"") -> 1384.4596 | AH74: =IF(P74="","",P74+AB74+AC74+AD74+AE74+AF74) -> 44750.721 | AI74: =if(AH74,_xlfn.workday.intl(int(AH74),0,"1000000",Holidays!A:A)+18/24,"") -> 44750.75 | AJ74: =if(AJ74,AJ74,if(AK74<>"",$A$1,"")) -> 44757.541 | AK74: done | AL74: =if(AI74,if(AJ74<>"",if(AJ74>AI74,AJ74-AI74,""),$A$1-AI74),"") -> 6.7913564 | AN74: =if(AJ74,if(and(hour(AJ74+AN$5)>11,(hour(AJ74+AN$5)<20)),AJ74+AN$5,_xlfn.workday.intl(int(AJ74),1,"1000000",Holidays!A:A)+hour(AJ74+AN$5-$B$1)/24+minute(AJ74)/1440),"") -> 44758.541 | AO74: =if(AO74,AO74,if(AP74<>"",$A$1,"")) -> 44757.541 | AP74: done | AQ74: =if(AN74,if(AO74<>"",if(AO74>AN74,AO74-AN74,""),$A$1-AN74),"") | AS74: =if(AJ74,if(and(hour(AJ74+AS$5)>11,(hour(AJ74+AS$5)<20)),AJ74+AS$5,_xlfn.workday.intl(int(AJ74),1,"1000000",Holidays!A:A)+hour(AJ74+AS$5-$B$1)/24+minute(AJ74)/1440),"") -> 44759.541 | AT74: =if(AT74,AT74,if(AU74<>"",$A$1,"")) -> 44757.542 | AU74: yes | AV74: =if(AS74,if(AT74<>"",if(AT74>AS74,AT74-AS74,""),$A$1-AS74),"") | AX74: done
A75: 44752.564 | G75: =if(A75,_xlfn.workday.intl(int(A75),1,"1000000",Holidays!A:A)+17/24,"") -> 44754.708 | H75: =if(H75,H75,if(I75<>"",$A$1,"")) | J75: =if(G75,if(H75<>"",if(H75>G75,H75-G75,""),$A$1-G75),"") -> 1379.2756 | K75: =if(G75,_xlfn.workday.intl(int(G75),0,"1000000",Holidays!A:A)+19/24,"") -> 44754.792 | L75: =if(L75,L75,if(M75<>"",$A$1,"")) -> 44772.516 | M75: done | N75: =if(K75,if(L75<>"",if(L75>K75,L75-K75,""),$A$1-K75),"") -> 17.724079 | O75: =if(A75,_xlfn.WORKDAY.INTL(A75,O$5,"1000000",Holidays!A:A)+hour(A75)/24+MINUTE(A75)/1440,"") -> 44754.563 | P75: 44761.512 | Q75: done | R75: =if(O75,if(P75<>"",if(P75>O75,P75-O75,""),$A$1-O75),"") -> 6.9490764 | U75: =if(O75,_xlfn.WORKDAY.INTL(O75,U$5,"1000000",Holidays!A:A)+hour(O75)/24+MINUTE(O75)/1440,"") -> 44755.563 | V75: =if(V75,V75,if(W75<>"",$A$1,"")) | X75: =if(U75,if(V75<>"",if(V75>U75,V75-U75,""),$A$1-U75),"") -> 1378.4207 | AH75: =IF(P75="","",P75+AB75+AC75+AD75+AE75+AF75) -> 44761.512 | AI75: =if(AH75,_xlfn.workday.intl(int(AH75),0,"1000000",Holidays!A:A)+18/24,"") -> 44761.75 | AJ75: =if(AJ75,AJ75,if(AK75<>"",$A$1,"")) | AL75: =if(AI75,if(AJ75<>"",if(AJ75>AI75,AJ75-AI75,""),$A$1-AI75),"") -> 1372.2339 | AN75: =if(AJ75,if(and(hour(AJ75+AN$5)>11,(hour(AJ75+AN$5)<20)),AJ75+AN$5,_xlfn.workday.intl(int(AJ75),1,"1000000",Holidays!A:A)+hour(AJ75+AN$5-$B$1)/24+minute(AJ75)/1440),"") | AO75: =if(AO75,AO75,if(AP75<>"",$A$1,"")) | AQ75: =if(AN75,if(AO75<>"",if(AO75>AN75,AO75-AN75,""),$A$1-AN75),"") | AS75: =if(AJ75,if(and(hour(AJ75+AS$5)>11,(hour(AJ75+AS$5)<20)),AJ75+AS$5,_xlfn.workday.intl(int(AJ75),1,"1000000",Holidays!A:A)+hour(AJ75+AS$5-$B$1)/24+minute(AJ75)/1440),"") | AT75: =if(AT75,AT75,if(AU75<>"",$A$1,"")) | AV75: =if(AS75,if(AT75<>"",if(AT75>AS75,AT75-AS75,""),$A$1-AS75),"") | AX75: hold
A76: 44754.547 | G76: =if(A76,_xlfn.workday.intl(int(A76),1,"1000000",Holidays!A:A)+17/24,"") -> 44755.708 | H76: =if(H76,H76,if(I76<>"",$A$1,"")) | J76: =if(G76,if(H76<>"",if(H76>G76,H76-G76,""),$A$1-G76),"") -> 1378.2756 | K76: =if(G76,_xlfn.workday.intl(int(G76),0,"1000000",Holidays!A:A)+19/24,"") -> 44755.792 | L76: =if(L76,L76,if(M76<>"",$A$1,"")) -> 44772.516 | M76: done | N76: =if(K76,if(L76<>"",if(L76>K76,L76-K76,""),$A$1-K76),"") -> 16.724079 | O76: =if(A76,_xlfn.WORKDAY.INTL(A76,O$5,"1000000",Holidays!A:A)+hour(A76)/24+MINUTE(A76)/1440,"") -> 44755.547 | P76: 44754.578 | Q76: done | R76: =if(O76,if(P76<>"",if(P76>O76,P76-O76,""),$A$1-O76),"") | U76: =if(O76,_xlfn.WORKDAY.INTL(O76,U$5,"1000000",Holidays!A:A)+hour(O76)/24+MINUTE(O76)/1440,"") -> 44756.547 | V76: =if(V76,V76,if(W76<>"",$A$1,"")) | X76: =if(U76,if(V76<>"",if(V76>U76,V76-U76,""),$A$1-U76),"") -> 1377.4367 | AH76: =IF(P76="","",P76+AB76+AC76+AD76+AE76+AF76) -> 44754.578 | AI76: =if(AH76,_xlfn.workday.intl(int(AH76),0,"1000000",Holidays!A:A)+18/24,"") -> 44754.75 | AJ76: =if(AJ76,AJ76,if(AK76<>"",$A$1,"")) | AL76: =if(AI76,if(AJ76<>"",if(AJ76>AI76,AJ76-AI76,""),$A$1-AI76),"") -> 1379.2339 | AN76: =if(AJ76,if(and(hour(AJ76+AN$5)>11,(hour(AJ76+AN$5)<20)),AJ76+AN$5,_xlfn.workday.intl(int(AJ76),1,"1000000",Holidays!A:A)+hour(AJ76+AN$5-$B$1)/24+minute(AJ76)/1440),"") | AO76: =if(AO76,AO76,if(AP76<>"",$A$1,"")) | AQ76: =if(AN76,if(AO76<>"",if(AO76>AN76,AO76-AN76,""),$A$1-AN76),"") | AS76: =if(AJ76,if(and(hour(AJ76+AS$5)>11,(hour(AJ76+AS$5)<20)),AJ76+AS$5,_xlfn.workday.intl(int(AJ76),1,"1000000",Holidays!A:A)+hour(AJ76+AS$5-$B$1)/24+minute(AJ76)/1440),"") | AT76: =if(AT76,AT76,if(AU76<>"",$A$1,"")) | AV76: =if(AS76,if(AT76<>"",if(AT76>AS76,AT76-AS76,""),$A$1-AS76),"") | AX76: hold
A77: 44754.583 | G77: =if(A77,_xlfn.workday.intl(int(A77),1,"1000000",Holidays!A:A)+17/24,"") -> 44755.708 | H77: =if(H77,H77,if(I77<>"",$A$1,"")) | J77: =if(G77,if(H77<>"",if(H77>G77,H77-G77,""),$A$1-G77),"") -> 1378.2756 | K77: =if(G77,_xlfn.workday.intl(int(G77),0,"1000000",Holidays!A:A)+19/24,"") -> 44755.792 | L77: =if(L77,L77,if(M77<>"",$A$1,"")) -> 44772.515 | M77: done | N77: =if(K77,if(L77<>"",if(L77>K77,L77-K77,""),$A$1-K77),"") -> 16.723672 | O77: =if(A77,_xlfn.WORKDAY.INTL(A77,O$5,"1000000",Holidays!A:A)+hour(A77)/24+MINUTE(A77)/1440,"") -> 44755.583 | P77: 44757.541 | Q77: done | R77: =if(O77,if(P77<>"",if(P77>O77,P77-O77,""),$A$1-O77),"") -> 1.9585448 | U77: =if(O77,_xlfn.WORKDAY.INTL(O77,U$5,"1000000",Holidays!A:A)+hour(O77)/24+MINUTE(O77)/1440,"") -> 44756.583 | V77: =if(V77,V77,if(W77<>"",$A$1,"")) | X77: =if(U77,if(V77<>"",if(V77>U77,V77-U77,""),$A$1-U77),"") -> 1377.4013 | AH77: =IF(P77="","",P77+AB77+AC77+AD77+AE77+AF77) -> 44757.541 | AI77: =if(AH77,_xlfn.workday.intl(int(AH77),0,"1000000",Holidays!A:A)+18/24,"") -> 44757.75 | AJ77: =if(AJ77,AJ77,if(AK77<>"",$A$1,"")) | AL77: =if(AI77,if(AJ77<>"",if(AJ77>AI77,AJ77-AI77,""),$A$1-AI77),"") -> 1376.2339 | AN77: =if(AJ77,if(and(hour(AJ77+AN$5)>11,(hour(AJ77+AN$5)<20)),AJ77+AN$5,_xlfn.workday.intl(int(AJ77),1,"1000000",Holidays!A:A)+hour(AJ77+AN$5-$B$1)/24+minute(AJ77)/1440),"") | AO77: =if(AO77,AO77,if(AP77<>"",$A$1,"")) | AQ77: =if(AN77,if(AO77<>"",if(AO77>AN77,AO77-AN77,""),$A$1-AN77),"") | AS77: =if(AJ77,if(and(hour(AJ77+AS$5)>11,(hour(AJ77+AS$5)<20)),AJ77+AS$5,_xlfn.workday.intl(int(AJ77),1,"1000000",Holidays!A:A)+hour(AJ77+AS$5-$B$1)/24+minute(AJ77)/1440),"") | AT77: =if(AT77,AT77,if(AU77<>"",$A$1,"")) | AV77: =if(AS77,if(AT77<>"",if(AT77>AS77,AT77-AS77,""),$A$1-AS77),"") | AX77: hold
A78: 44754.584 | G78: =if(A78,_xlfn.workday.intl(int(A78),1,"1000000",Holidays!A:A)+17/24,"") -> 44755.708 | H78: =if(H78,H78,if(I78<>"",$A$1,"")) -> 44761.508 | I78: done | J78: =if(G78,if(H78<>"",if(H78>G78,H78-G78,""),$A$1-G78),"") -> 5.7993503 | K78: =if(G78,_xlfn.workday.intl(int(G78),0,"1000000",Holidays!A:A)+19/24,"") -> 44755.792 | L78: =if(L78,L78,if(M78<>"",$A$1,"")) -> 44761.508 | M78: done | N78: =if(K78,if(L78<>"",if(L78>K78,L78-K78,""),$A$1-K78),"") -> 5.7160697 | O78: =if(A78,_xlfn.WORKDAY.INTL(A78,O$5,"1000000",Holidays!A:A)+hour(A78)/24+MINUTE(A78)/1440,"") -> 44755.583 | P78: 44757.541 | Q78: done | R78: =if(O78,if(P78<>"",if(P78>O78,P78-O78,""),$A$1-O78),"") -> 1.9576285 | U78: =if(O78,_xlfn.WORKDAY.INTL(O78,U$5,"1000000",Holidays!A:A)+hour(O78)/24+MINUTE(O78)/1440,"") -> 44756.583 | V78: =if(V78,V78,if(W78<>"",$A$1,"")) | X78: =if(U78,if(V78<>"",if(V78>U78,V78-U78,""),$A$1-U78),"") -> 1377.4006 | AH78: =IF(P78="","",P78+AB78+AC78+AD78+AE78+AF78) -> 44757.541 | AI78: =if(AH78,_xlfn.workday.intl(int(AH78),0,"1000000",Holidays!A:A)+18/24,"") -> 44757.75 | AJ78: =if(AJ78,AJ78,if(AK78<>"",$A$1,"")) -> 44761.508 | AK78: done | AL78: =if(AI78,if(AJ78<>"",if(AJ78>AI78,AJ78-AI78,""),$A$1-AI78),"") -> 3.7578274 | AN78: =if(AJ78,if(and(hour(AJ78+AN$5)>11,(hour(AJ78+AN$5)<20)),AJ78+AN$5,_xlfn.workday.intl(int(AJ78),1,"1000000",Holidays!A:A)+hour(AJ78+AN$5-$B$1)/24+minute(AJ78)/1440),"") -> 44762.508 | AO78: =if(AO78,AO78,if(AP78<>"",$A$1,"")) -> 44761.508 | AP78: done | AQ78: =if(AN78,if(AO78<>"",if(AO78>AN78,AO78-AN78,""),$A$1-AN78),"") | AS78: =if(AJ78,if(and(hour(AJ78+AS$5)>11,(hour(AJ78+AS$5)<20)),AJ78+AS$5,_xlfn.workday.intl(int(AJ78),1,"1000000",Holidays!A:A)+hour(AJ78+AS$5-$B$1)/24+minute(AJ78)/1440),"") -> 44763.508 | AT78: =if(AT78,AT78,if(AU78<>"",$A$1,"")) -> 44761.508 | AU78: yes | AV78: =if(AS78,if(AT78<>"",if(AT78>AS78,AT78-AS78,""),$A$1-AS78),"") | AX78: done
A79: 44754.612 | G79: =if(A79,_xlfn.workday.intl(int(A79),1,"1000000",Holidays!A:A)+17/24,"") -> 44755.708 | H79: =if(H79,H79,if(I79<>"",$A$1,"")) | J79: =if(G79,if(H79<>"",if(H79>G79,H79-G79,""),$A$1-G79),"") -> 1378.2756 | K79: =if(G79,_xlfn.workday.intl(int(G79),0,"1000000",Holidays!A:A)+19/24,"") -> 44755.792 | L79: =if(L79,L79,if(M79<>"",$A$1,"")) -> 44772.515 | M79: done | N79: =if(K79,if(L79<>"",if(L79>K79,L79-K79,""),$A$1-K79),"") -> 16.723551 | O79: =if(A79,_xlfn.WORKDAY.INTL(A79,O$5,"1000000",Holidays!A:A)+hour(A79)/24+MINUTE(A79)/1440,"") -> 44755.612 | P79: 44757.54 | Q79: done | R79: =if(O79,if(P79<>"",if(P79>O79,P79-O79,""),$A$1-O79),"") -> 1.9284526 | U79: =if(O79,_xlfn.WORKDAY.INTL(O79,U$5,"1000000",Holidays!A:A)+hour(O79)/24+MINUTE(O79)/1440,"") -> 44756.612 | V79: =if(V79,V79,if(W79<>"",$A$1,"")) | X79: =if(U79,if(V79<>"",if(V79>U79,V79-U79,""),$A$1-U79),"") -> 1377.3721 | AH79: =IF(P79="","",P79+AB79+AC79+AD79+AE79+AF79) -> 44757.54 | AI79: =if(AH79,_xlfn.workday.intl(int(AH79),0,"1000000",Holidays!A:A)+18/24,"") -> 44757.75 | AJ79: =if(AJ79,AJ79,if(AK79<>"",$A$1,"")) | AL79: =if(AI79,if(AJ79<>"",if(AJ79>AI79,AJ79-AI79,""),$A$1-AI79),"") -> 1376.2339 | AN79: =if(AJ79,if(and(hour(AJ79+AN$5)>11,(hour(AJ79+AN$5)<20)),AJ79+AN$5,_xlfn.workday.intl(int(AJ79),1,"1000000",Holidays!A:A)+hour(AJ79+AN$5-$B$1)/24+minute(AJ79)/1440),"") | AO79: =if(AO79,AO79,if(AP79<>"",$A$1,"")) | AQ79: =if(AN79,if(AO79<>"",if(AO79>AN79,AO79-AN79,""),$A$1-AN79),"") | AS79: =if(AJ79,if(and(hour(AJ79+AS$5)>11,(hour(AJ79+AS$5)<20)),AJ79+AS$5,_xlfn.workday.intl(int(AJ79),1,"1000000",Holidays!A:A)+hour(AJ79+AS$5-$B$1)/24+minute(AJ79)/1440),"") | AT79: =if(AT79,AT79,if(AU79<>"",$A$1,"")) | AV79: =if(AS79,if(AT79<>"",if(AT79>AS79,AT79-AS79,""),$A$1-AS79),"") | AX79: No Response
A80: 44755.683 | G80: =if(#REF!,_xlfn.workday.intl(int(#REF!),1,"1000000",Holidays!A:A)+17/24,"") -> #REF! | H80: =if(H80,H80,if(I80<>"",$A$1,"")) -> 44761.507 | I80: done | J80: =if(G80,if(H80<>"",if(H80>G80,H80-G80,""),$A$1-G80),"") -> #REF! | K80: =if(G80,_xlfn.workday.intl(int(G80),0,"1000000",Holidays!A:A)+19/24,"") -> #REF! | L80: =if(L80,L80,if(M80<>"",$A$1,"")) -> 44761.507 | M80: done | N80: =if(K80,if(L80<>"",if(L80>K80,L80-K80,""),$A$1-K80),"") -> #REF! | O80: =if(A80,_xlfn.WORKDAY.INTL(A80,O$5,"1000000",Holidays!A:A)+hour(A80)/24+MINUTE(A80)/1440,"") -> 44756.683 | P80: 44757.541 | Q80: done | R80: =if(O80,if(P80<>"",if(P80>O80,P80-O80,""),$A$1-O80),"") -> 0.85789736 | U80: =if(O80,_xlfn.WORKDAY.INTL(O80,U$5,"1000000",Holidays!A:A)+hour(O80)/24+MINUTE(O80)/1440,"") -> 44757.683 | V80: =if(V80,V80,if(W80<>"",$A$1,"")) | X80: =if(U80,if(V80<>"",if(V80>U80,V80-U80,""),$A$1-U80),"") -> 1376.3013 | AH80: =IF(P80="","",P80+AB80+AC80+AD80+AE80+AF80) -> 44757.541 | AI80: =if(AH80,_xlfn.workday.intl(int(AH80),0,"1000000",Holidays!A:A)+18/24,"") -> 44757.75 | AJ80: =if(AJ80,AJ80,if(AK80<>"",$A$1,"")) -> 44761.507 | AK80: done | AL80: =if(AI80,if(AJ80<>"",if(AJ80>AI80,AJ80-AI80,""),$A$1-AI80),"") -> 3.7569209 | AN80: =if(AJ80,if(and(hour(AJ80+AN$5)>11,(hour(AJ80+AN$5)<20)),AJ80+AN$5,_xlfn.workday.intl(int(AJ80),1,"1000000",Holidays!A:A)+hour(AJ80+AN$5-$B$1)/24+minute(AJ80)/1440),"") -> 44762.507 | AO80: =if(AO80,AO80,if(AP80<>"",$A$1,"")) -> 44761.507 | AP80: done | AQ80: =if(AN80,if(AO80<>"",if(AO80>AN80,AO80-AN80,""),$A$1-AN80),"") | AS80: =if(AJ80,if(and(hour(AJ80+AS$5)>11,(hour(AJ80+AS$5)<20)),AJ80+AS$5,_xlfn.workday.intl(int(AJ80),1,"1000000",Holidays!A:A)+hour(AJ80+AS$5-$B$1)/24+minute(AJ80)/1440),"") -> 44763.507 | AT80: =if(AT80,AT80,if(AU80<>"",$A$1,"")) -> 44761.507 | AU80: yes | AV80: =if(AS80,if(AT80<>"",if(AT80>AS80,AT80-AS80,""),$A$1-AS80),"") | AX80: done
A81: 44757.521 | G81: =if(A80,_xlfn.workday.intl(int(A80),1,"1000000",Holidays!A:A)+17/24,"") -> 44756.708 | H81: =if(H81,H81,if(I81<>"",$A$1,"")) | J81: =if(G81,if(H81<>"",if(H81>G81,H81-G81,""),$A$1-G81),"") -> 1377.2756 | K81: =if(G81,_xlfn.workday.intl(int(G81),0,"1000000",Holidays!A:A)+19/24,"") -> 44756.792 | L81: =if(L81,L81,if(M81<>"",$A$1,"")) -> 44772.515 | M81: done | N81: =if(K81,if(L81<>"",if(L81>K81,L81-K81,""),$A$1-K81),"") -> 15.723401 | O81: =if(A81,_xlfn.WORKDAY.INTL(A81,O$5,"1000000",Holidays!A:A)+hour(A81)/24+MINUTE(A81)/1440,"") -> 44758.521 | P81: 44757.54 | Q81: done | R81: =if(O81,if(P81<>"",if(P81>O81,P81-O81,""),$A$1-O81),"") | U81: =if(O81,_xlfn.WORKDAY.INTL(O81,U$5,"1000000",Holidays!A:A)+hour(O81)/24+MINUTE(O81)/1440,"") -> 44759.521 | V81: =if(V81,V81,if(W81<>"",$A$1,"")) | X81: =if(U81,if(V81<>"",if(V81>U81,V81-U81,""),$A$1-U81),"") -> 1374.4631 | AH81: =IF(P81="","",P81+AB81+AC81+AD81+AE81+AF81) -> 44757.54 | AI81: =if(AH81,_xlfn.workday.intl(int(AH81),0,"1000000",Holidays!A:A)+18/24,"") -> 44757.75 | AJ81: =if(AJ81,AJ81,if(AK81<>"",$A$1,"")) -> 44887.758 | AK81: done | AL81: =if(AI81,if(AJ81<>"",if(AJ81>AI81,AJ81-AI81,""),$A$1-AI81),"") -> 130.00772 | AN81: =if(AJ81,if(and(hour(AJ81+AN$5)>11,(hour(AJ81+AN$5)<20)),AJ81+AN$5,_xlfn.workday.intl(int(AJ81),1,"1000000",Holidays!A:A)+hour(AJ81+AN$5-$B$1)/24+minute(AJ81)/1440),"") -> 44888.758 | AO81: =if(AO81,AO81,if(AP81<>"",$A$1,"")) -> 44887.758 | AP81: done | AQ81: =if(AN81,if(AO81<>"",if(AO81>AN81,AO81-AN81,""),$A$1-AN81),"") | AS81: =if(AJ81,if(and(hour(AJ81+AS$5)>11,(hour(AJ81+AS$5)<20)),AJ81+AS$5,_xlfn.workday.intl(int(AJ81),1,"1000000",Holidays!A:A)+hour(AJ81+AS$5-$B$1)/24+minute(AJ81)/1440),"") -> 44889.758 | AT81: =if(AT81,AT81,if(AU81<>"",$A$1,"")) -> 44887.758 | AU81: yes | AV81: =if(AS81,if(AT81<>"",if(AT81>AS81,AT81-AS81,""),$A$1-AS81),"") | AX81: done
A82: 44758.594 | G82: =if(A82,_xlfn.workday.intl(int(A82),1,"1000000",Holidays!A:A)+17/24,"") -> 44759.708 | H82: =if(H82,H82,if(I82<>"",$A$1,"")) | J82: =if(G82,if(H82<>"",if(H82>G82,H82-G82,""),$A$1-G82),"") -> 1374.2756 | K82: =if(G82,_xlfn.workday.intl(int(G82),0,"1000000",Holidays!A:A)+19/24,"") -> 44759.792 | L82: =if(L82,L82,if(M82<>"",$A$1,"")) -> 44772.515 | M82: done | N82: =if(K82,if(L82<>"",if(L82>K82,L82-K82,""),$A$1-K82),"") -> 12.723083 | O82: =if(A82,_xlfn.WORKDAY.INTL(A82,O$5,"1000000",Holidays!A:A)+hour(A82)/24+MINUTE(A82)/1440,"") -> 44759.593 | P82: 44769.635 | Q82: done | R82: =if(O82,if(P82<>"",if(P82>O82,P82-O82,""),$A$1-O82),"") -> 10.041953 | U82: =if(O82,_xlfn.WORKDAY.INTL(O82,U$5,"1000000",Holidays!A:A)+hour(O82)/24+MINUTE(O82)/1440,"") -> 44761.593 | V82: =if(V82,V82,if(W82<>"",$A$1,"")) | X82: =if(U82,if(V82<>"",if(V82>U82,V82-U82,""),$A$1-U82),"") -> 1372.3909 | AB82: 5 | AC82: 2 | AH82: =IF(P82="","",P82+AB82+AC82+AD82+AE82+AF82) -> 44776.635 | AI82: =if(AH82,_xlfn.workday.intl(int(AH82),0,"1000000",Holidays!A:A)+18/24,"") -> 44776.75 | AJ82: =if(AJ82,AJ82,if(AK82<>"",$A$1,"")) | AL82: =if(AI82,if(AJ82<>"",if(AJ82>AI82,AJ82-AI82,""),$A$1-AI82),"") -> 1357.2339 | AN82: =if(AJ82,if(and(hour(AJ82+AN$5)>11,(hour(AJ82+AN$5)<20)),AJ82+AN$5,_xlfn.workday.intl(int(AJ82),1,"1000000",Holidays!A:A)+hour(AJ82+AN$5-$B$1)/24+minute(AJ82)/1440),"") | AO82: =if(AO82,AO82,if(AP82<>"",$A$1,"")) -> 44777.495 | AP82: done | AQ82: =if(AN82,if(AO82<>"",if(AO82>AN82,AO82-AN82,""),$A$1-AN82),"") | AS82: =if(AJ82,if(and(hour(AJ82+AS$5)>11,(hour(AJ82+AS$5)<20)),AJ82+AS$5,_xlfn.workday.intl(int(AJ82),1,"1000000",Holidays!A:A)+hour(AJ82+AS$5-$B$1)/24+minute(AJ82)/1440),"") | AT82: =if(AT82,AT82,if(AU82<>"",$A$1,"")) | AV82: =if(AS82,if(AT82<>"",if(AT82>AS82,AT82-AS82,""),$A$1-AS82),"") | AX82: shop
A83: 44761.516 | G83: =if(A83,_xlfn.workday.intl(int(A83),1,"1000000",Holidays!A:A)+17/24,"") -> 44762.708 | H83: =if(H83,H83,if(I83<>"",$A$1,"")) -> 44777.495 | I83: done | J83: =if(G83,if(H83<>"",if(H83>G83,H83-G83,""),$A$1-G83),"") -> 14.786265 | K83: =if(G83,_xlfn.workday.intl(int(G83),0,"1000000",Holidays!A:A)+19/24,"") -> 44762.792 | L83: =if(L83,L83,if(M83<>"",$A$1,"")) -> 44773.574 | M83: done | N83: =if(K83,if(L83<>"",if(L83>K83,L83-K83,""),$A$1-K83),"") -> 10.782163 | O83: =if(A83,_xlfn.WORKDAY.INTL(A83,O$5,"1000000",Holidays!A:A)+hour(A83)/24+MINUTE(A83)/1440,"") -> 44762.516 | P83: 44763.475 | Q83: done | R83: =if(O83,if(P83<>"",if(P83>O83,P83-O83,""),$A$1-O83),"") -> 0.95879763 | U83: =if(O83,_xlfn.WORKDAY.INTL(O83,U$5,"1000000",Holidays!A:A)+hour(O83)/24+MINUTE(O83)/1440,"") -> 44763.516 | V83: =if(V83,V83,if(W83<>"",$A$1,"")) | X83: =if(U83,if(V83<>"",if(V83>U83,V83-U83,""),$A$1-U83),"") -> 1370.4679 | AB83: 1 | AH83: =IF(P83="","",P83+AB83+AC83+AD83+AE83+AF83) -> 44764.475 | AI83: =if(AH83,_xlfn.workday.intl(int(AH83),0,"1000000",Holidays!A:A)+18/24,"") -> 44764.75 | AJ83: =if(AJ83,AJ83,if(AK83<>"",$A$1,"")) -> 44778.542 | AK83: done | AL83: =if(AI83,if(AJ83<>"",if(AJ83>AI83,AJ83-AI83,""),$A$1-AI83),"") -> 13.791771 | AN83: =if(AJ83,if(and(hour(AJ83+AN$5)>11,(hour(AJ83+AN$5)<20)),AJ83+AN$5,_xlfn.workday.intl(int(AJ83),1,"1000000",Holidays!A:A)+hour(AJ83+AN$5-$B$1)/24+minute(AJ83)/1440),"") -> 44779.542 | AO83: =if(AO83,AO83,if(AP83<>"",$A$1,"")) -> 44777.495 | AP83: done | AQ83: =if(AN83,if(AO83<>"",if(AO83>AN83,AO83-AN83,""),$A$1-AN83),"") | AS83: =if(AJ83,if(and(hour(AJ83+AS$5)>11,(hour(AJ83+AS$5)<20)),AJ83+AS$5,_xlfn.workday.intl(int(AJ83),1,"1000000",Holidays!A:A)+hour(AJ83+AS$5-$B$1)/24+minute(AJ83)/1440),"") -> 44780.542 | AT83: =if(AT83,AT83,if(AU83<>"",$A$1,"")) -> 44778.542 | AU83: yes | AV83: =if(AS83,if(AT83<>"",if(AT83>AS83,AT83-AS83,""),$A$1-AS83),"") | AX83: done
A84: 44763.506 | G84: =if(A84,_xlfn.workday.intl(int(A84),1,"1000000",Holidays!A:A)+17/24,"") -> 44764.708 | H84: =if(H84,H84,if(I84<>"",$A$1,"")) -> 44764.508 | I84: Done | J84: =if(G84,if(H84<>"",if(H84>G84,H84-G84,""),$A$1-G84),"") | K84: =if(G84,_xlfn.workday.intl(int(G84),0,"1000000",Holidays!A:A)+19/24,"") -> 44764.792 | L84: =if(L84,L84,if(M84<>"",$A$1,"")) -> 44773.574 | M84: done | N84: =if(K84,if(L84<>"",if(L84>K84,L84-K84,""),$A$1-K84),"") -> 8.7825245 | O84: =if(A84,_xlfn.WORKDAY.INTL(A84,O$5,"1000000",Holidays!A:A)+hour(A84)/24+MINUTE(A84)/1440,"") -> 44764.506 | P84: 44764.508 | Q84: Done | R84: =if(O84,if(P84<>"",if(P84>O84,P84-O84,""),$A$1-O84),"") -> 0.0020028588 | U84: =if(O84,_xlfn.WORKDAY.INTL(O84,U$5,"1000000",Holidays!A:A)+hour(O84)/24+MINUTE(O84)/1440,"") -> 44765.506 | V84: =if(V84,V84,if(W84<>"",$A$1,"")) | X84: =if(U84,if(V84<>"",if(V84>U84,V84-U84,""),$A$1-U84),"") -> 1368.4784 | AB84: 1 | AC84: 1 | AH84: =IF(P84="","",P84+AB84+AC84+AD84+AE84+AF84) -> 44766.508 | AI84: =if(AH84,_xlfn.workday.intl(int(AH84),0,"1000000",Holidays!A:A)+18/24,"") -> 44766.75 | AJ84: =if(AJ84,AJ84,if(AK84<>"",$A$1,"")) -> 44766.708 | AK84: done | AL84: =if(AI84,if(AJ84<>"",if(AJ84>AI84,AJ84-AI84,""),$A$1-AI84),"") | AN84: =if(AJ84,if(and(hour(AJ84+AN$5)>11,(hour(AJ84+AN$5)<20)),AJ84+AN$5,_xlfn.workday.intl(int(AJ84),1,"1000000",Holidays!A:A)+hour(AJ84+AN$5-$B$1)/24+minute(AJ84)/1440),"") -> 44767.708 | AO84: =if(AO84,AO84,if(AP84<>"",$A$1,"")) -> 44777.494 | AP84: Done | AQ84: =if(AN84,if(AO84<>"",if(AO84>AN84,AO84-AN84,""),$A$1-AN84),"") -> 9.7855927 | AS84: =if(AJ84,if(and(hour(AJ84+AS$5)>11,(hour(AJ84+AS$5)<20)),AJ84+AS$5,_xlfn.workday.intl(int(AJ84),1,"1000000",Holidays!A:A)+hour(AJ84+AS$5-$B$1)/24+minute(AJ84)/1440),"") -> 44768.708 | AT84: =if(AT84,AT84,if(AU84<>"",$A$1,"")) -> 44887.754 | AU84: yes | AV84: =if(AS84,if(AT84<>"",if(AT84>AS84,AT84-AS84,""),$A$1-AS84),"") -> 119.04571 | AX84: done
A85: 44764.508 | G85: =if(A85,_xlfn.workday.intl(int(A85),1,"1000000",Holidays!A:A)+17/24,"") -> 44765.708 | H85: =if(H85,H85,if(I85<>"",$A$1,"")) -> 44808.595 | I85: Done | J85: =if(G85,if(H85<>"",if(H85>G85,H85-G85,""),$A$1-G85),"") -> 42.886929 | K85: =if(G85,_xlfn.workday.intl(int(G85),0,"1000000",Holidays!A:A)+19/24,"") -> 44765.792 | L85: =if(L85,L85,if(M85<>"",$A$1,"")) -> 44772.514 | M85: done | N85: =if(K85,if(L85<>"",if(L85>K85,L85-K85,""),$A$1-K85),"") -> 6.7225536 | O85: =if(A85,_xlfn.WORKDAY.INTL(A85,O$5,"1000000",Holidays!A:A)+hour(A85)/24+MINUTE(A85)/1440,"") -> 44765.507 | P85: 44766.708 | Q85: Done | R85: =if(O85,if(P85<>"",if(P85>O85,P85-O85,""),$A$1-O85),"") -> 1.2005979 | U85: =if(O85,_xlfn.WORKDAY.INTL(O85,U$5,"1000000",Holidays!A:A)+hour(O85)/24+MINUTE(O85)/1440,"") -> 44766.507 | V85: =if(V85,V85,if(W85<>"",$A$1,"")) | X85: =if(U85,if(V85<>"",if(V85>U85,V85-U85,""),$A$1-U85),"") -> 1367.477 | AB85: 1 | AC85: 5 | AD85: 2 | AE85: 1 | AH85: =IF(P85="","",P85+AB85+AC85+AD85+AE85+AF85) -> 44775.708 | AI85: =if(AH85,_xlfn.workday.intl(int(AH85),0,"1000000",Holidays!A:A)+18/24,"") -> 44775.75 | AJ85: =if(AJ85,AJ85,if(AK85<>"",$A$1,"")) -> 44808.595 | AK85: done | AL85: =if(AI85,if(AJ85<>"",if(AJ85>AI85,AJ85-AI85,""),$A$1-AI85),"") -> 32.845323 | AN85: =if(AJ85,if(and(hour(AJ85+AN$5)>11,(hour(AJ85+AN$5)<20)),AJ85+AN$5,_xlfn.workday.intl(int(AJ85),1,"1000000",Holidays!A:A)+hour(AJ85+AN$5-$B$1)/24+minute(AJ85)/1440),"") -> 44809.595 | AO85: =if(AO85,AO85,if(AP85<>"",$A$1,"")) -> 44766.629 | AP85: Done | AQ85: =if(AN85,if(AO85<>"",if(AO85>AN85,AO85-AN85,""),$A$1-AN85),"") | AS85: =if(AJ85,if(and(hour(AJ85+AS$5)>11,(hour(AJ85+AS$5)<20)),AJ85+AS$5,_xlfn.workday.intl(int(AJ85),1,"1000000",Holidays!A:A)+hour(AJ85+AS$5-$B$1)/24+minute(AJ85)/1440),"") -> 44810.595 | AT85: =if(AT85,AT85,if(AU85<>"",$A$1,"")) -> 44808.595 | AU85: yes | AV85: =if(AS85,if(AT85<>"",if(AT85>AS85,AT85-AS85,""),$A$1-AS85),"") | AX85: done
A86: 44766.629 | G86: =if(A86,_xlfn.workday.intl(int(A86),1,"1000000",Holidays!A:A)+17/24,"") -> 44768.708 | H86: =if(H86,H86,if(I86<>"",$A$1,"")) -> 44773.566 | I86: done | J86: =if(G86,if(H86<>"",if(H86>G86,H86-G86,""),$A$1-G86),"") -> 4.8576069 | K86: =if(G86,_xlfn.workday.intl(int(G86),0,"1000000",Holidays!A:A)+19/24,"") -> 44768.792 | L86: =if(L86,L86,if(M86<>"",$A$1,"")) -> 44773.566 | M86: done | N86: =if(K86,if(L86<>"",if(L86>K86,L86-K86,""),$A$1-K86),"") -> 4.7742736 | O86: =if(A86,_xlfn.WORKDAY.INTL(A86,O$5,"1000000",Holidays!A:A)+hour(A86)/24+MINUTE(A86)/1440,"") -> 44768.628 | P86: 44773.566 | Q86: done | R86: =if(O86,if(P86<>"",if(P86>O86,P86-O86,""),$A$1-O86),"") -> 4.9378318 | U86: =if(O86,_xlfn.WORKDAY.INTL(O86,U$5,"1000000",Holidays!A:A)+hour(O86)/24+MINUTE(O86)/1440,"") -> 44769.628 | V86: =if(V86,V86,if(W86<>"",$A$1,"")) | X86: =if(U86,if(V86<>"",if(V86>U86,V86-U86,""),$A$1-U86),"") -> 1364.3554 | AH86: =IF(P86="","",P86+AB86+AC86+AD86+AE86+AF86) -> 44773.566 | AI86: =if(AH86,_xlfn.workday.intl(int(AH86),0,"1000000",Holidays!A:A)+18/24,"") -> 44773.75 | AJ86: =if(AJ86,AJ86,if(AK86<>"",$A$1,"")) | AL86: =if(AI86,if(AJ86<>"",if(AJ86>AI86,AJ86-AI86,""),$A$1-AI86),"") -> 1360.2339 | AN86: =if(AJ86,if(and(hour(AJ86+AN$5)>11,(hour(AJ86+AN$5)<20)),AJ86+AN$5,_xlfn.workday.intl(int(AJ86),1,"1000000",Holidays!A:A)+hour(AJ86+AN$5-$B$1)/24+minute(AJ86)/1440),"") | AO86: =if(AO86,AO86,if(AP86<>"",$A$1,"")) | AQ86: =if(AN86,if(AO86<>"",if(AO86>AN86,AO86-AN86,""),$A$1-AN86),"") | AS86: =if(AJ86,if(and(hour(AJ86+AS$5)>11,(hour(AJ86+AS$5)<20)),AJ86+AS$5,_xlfn.workday.intl(int(AJ86),1,"1000000",Holidays!A:A)+hour(AJ86+AS$5-$B$1)/24+minute(AJ86)/1440),"") | AT86: =if(AT86,AT86,if(AU86<>"",$A$1,"")) -> 44842.66 | AU86: yes | AV86: =if(AS86,if(AT86<>"",if(AT86>AS86,AT86-AS86,""),$A$1-AS86),"") | AX86: hold
A87: 44768.49 | G87: =if(A87,_xlfn.workday.intl(int(A87),1,"1000000",Holidays!A:A)+17/24,"") -> 44769.708 | H87: =if(H87,H87,if(I87<>"",$A$1,"")) -> 44773.568 | I87: done | J87: =if(G87,if(H87<>"",if(H87>G87,H87-G87,""),$A$1-G87),"") -> 3.8594265 | K87: =if(G87,_xlfn.workday.intl(int(G87),0,"1000000",Holidays!A:A)+19/24,"") -> 44769.792 | L87: =if(L87,L87,if(M87<>"",$A$1,"")) -> 44772.514 | M87: done | N87: =if(K87,if(L87<>"",if(L87>K87,L87-K87,""),$A$1-K87),"") -> 2.7221557 | O87: =if(A87,_xlfn.WORKDAY.INTL(A87,O$5,"1000000",Holidays!A:A)+hour(A87)/24+MINUTE(A87)/1440,"") -> 44769.49 | P87: 44770.5 | Q87: done | R87: =if(O87,if(P87<>"",if(P87>O87,P87-O87,""),$A$1-O87),"") -> 1.0104949 | U87: =if(O87,_xlfn.WORKDAY.INTL(O87,U$5,"1000000",Holidays!A:A)+hour(O87)/24+MINUTE(O87)/1440,"") -> 44770.49 | V87: =if(V87,V87,if(W87<>"",$A$1,"")) | X87: =if(U87,if(V87<>"",if(V87>U87,V87-U87,""),$A$1-U87),"") -> 1363.4943 | AB87: 1 | AC87: 4 | AD87: 3 | AH87: =IF(P87="","",P87+AB87+AC87+AD87+AE87+AF87) -> 44778.5 | AI87: =if(AH87,_xlfn.workday.intl(int(AH87),0,"1000000",Holidays!A:A)+18/24,"") -> 44778.75 | AJ87: =if(AJ87,AJ87,if(AK87<>"",$A$1,"")) -> 44773.567 | AK87: done | AL87: =if(AI87,if(AJ87<>"",if(AJ87>AI87,AJ87-AI87,""),$A$1-AI87),"") | AN87: =if(AJ87,if(and(hour(AJ87+AN$5)>11,(hour(AJ87+AN$5)<20)),AJ87+AN$5,_xlfn.workday.intl(int(AJ87),1,"1000000",Holidays!A:A)+hour(AJ87+AN$5-$B$1)/24+minute(AJ87)/1440),"") -> 44774.567 | AO87: =if(AO87,AO87,if(AP87<>"",$A$1,"")) -> 44777.493 | AP87: done | AQ87: =if(AN87,if(AO87<>"",if(AO87>AN87,AO87-AN87,""),$A$1-AN87),"") -> 2.9258237 | AS87: =if(AJ87,if(and(hour(AJ87+AS$5)>11,(hour(AJ87+AS$5)<20)),AJ87+AS$5,_xlfn.workday.intl(int(AJ87),1,"1000000",Holidays!A:A)+hour(AJ87+AS$5-$B$1)/24+minute(AJ87)/1440),"") -> 44775.567 | AT87: =if(AT87,AT87,if(AU87<>"",$A$1,"")) -> 44799.779 | AU87: yes | AV87: =if(AS87,if(AT87<>"",if(AT87>AS87,AT87-AS87,""),$A$1-AS87),"") -> 24.211259 | AX87: done
A88: 44768.491 | G88: =if(A88,_xlfn.workday.intl(int(A88),1,"1000000",Holidays!A:A)+17/24,"") -> 44769.708 | H88: =if(H88,H88,if(I88<>"",$A$1,"")) | J88: =if(G88,if(H88<>"",if(H88>G88,H88-G88,""),$A$1-G88),"") -> 1364.2756 | K88: =if(G88,_xlfn.workday.intl(int(G88),0,"1000000",Holidays!A:A)+19/24,"") -> 44769.792 | L88: =if(L88,L88,if(M88<>"",$A$1,"")) -> 44773.574 | M88: done | N88: =if(K88,if(L88<>"",if(L88>K88,L88-K88,""),$A$1-K88),"") -> 3.7825245 | O88: =if(A88,_xlfn.WORKDAY.INTL(A88,O$5,"1000000",Holidays!A:A)+hour(A88)/24+MINUTE(A88)/1440,"") -> 44769.491 | R88: =if(O88,if(P88<>"",if(P88>O88,P88-O88,""),$A$1-O88),"") -> 1364.4929 | U88: =if(O88,_xlfn.WORKDAY.INTL(O88,U$5,"1000000",Holidays!A:A)+hour(O88)/24+MINUTE(O88)/1440,"") -> 44770.491 | V88: =if(V88,V88,if(W88<>"",$A$1,"")) | X88: =if(U88,if(V88<>"",if(V88>U88,V88-U88,""),$A$1-U88),"") -> 1363.4929 | AH88: =IF(P88="","",P88+AB88+AC88+AD88+AE88+AF88) | AI88: =if(AH88,_xlfn.workday.intl(int(AH88),0,"1000000",Holidays!A:A)+18/24,"") | AJ88: =if(AJ88,AJ88,if(AK88<>"",$A$1,"")) | AL88: =if(AI88,if(AJ88<>"",if(AJ88>AI88,AJ88-AI88,""),$A$1-AI88),"") | AN88: =if(AJ88,if(and(hour(AJ88+AN$5)>11,(hour(AJ88+AN$5)<20)),AJ88+AN$5,_xlfn.workday.intl(int(AJ88),1,"1000000",Holidays!A:A)+hour(AJ88+AN$5-$B$1)/24+minute(AJ88)/1440),"") | AO88: =if(AO88,AO88,if(AP88<>"",$A$1,"")) | AQ88: =if(AN88,if(AO88<>"",if(AO88>AN88,AO88-AN88,""),$A$1-AN88),"") | AS88: =if(AJ88,if(and(hour(AJ88+AS$5)>11,(hour(AJ88+AS$5)<20)),AJ88+AS$5,_xlfn.workday.intl(int(AJ88),1,"1000000",Holidays!A:A)+hour(AJ88+AS$5-$B$1)/24+minute(AJ88)/1440),"") | AT88: =if(AT88,AT88,if(AU88<>"",$A$1,"")) | AV88: =if(AS88,if(AT88<>"",if(AT88>AS88,AT88-AS88,""),$A$1-AS88),"") | AX88: hold
A89: 44769.722 | G89: =if(A89,_xlfn.workday.intl(int(A89),1,"1000000",Holidays!A:A)+17/24,"") -> 44770.708 | H89: =if(H89,H89,if(I89<>"",$A$1,"")) -> 44773.564 | I89: done | J89: =if(G89,if(H89<>"",if(H89>G89,H89-G89,""),$A$1-G89),"") -> 2.8555811 | K89: =if(G89,_xlfn.workday.intl(int(G89),0,"1000000",Holidays!A:A)+19/24,"") -> 44770.792 | L89: =if(L89,L89,if(M89<>"",$A$1,"")) -> 44773.564 | M89: done | N89: =if(K89,if(L89<>"",if(L89>K89,L89-K89,""),$A$1-K89),"") -> 2.7726114 | O89: =if(A89,_xlfn.WORKDAY.INTL(A89,O$5,"1000000",Holidays!A:A)+hour(A89)/24+MINUTE(A89)/1440,"") -> 44770.722 | P89: 44777.569 | Q89: done | R89: =if(O89,if(P89<>"",if(P89>O89,P89-O89,""),$A$1-O89),"") -> 6.8478316 | U89: =if(O89,_xlfn.WORKDAY.INTL(O89,U$5,"1000000",Holidays!A:A)+hour(O89)/24+MINUTE(O89)/1440,"") -> 44771.722 | V89: =if(V89,V89,if(W89<>"",$A$1,"")) | X89: =if(U89,if(V89<>"",if(V89>U89,V89-U89,""),$A$1-U89),"") -> 1362.2624 | AB89: 1 | AH89: =IF(P89="","",P89+AB89+AC89+AD89+AE89+AF89) -> 44778.569 | AI89: =if(AH89,_xlfn.workday.intl(int(AH89),0,"1000000",Holidays!A:A)+18/24,"") -> 44778.75 | AJ89: =if(AJ89,AJ89,if(AK89<>"",$A$1,"")) | AL89: =if(AI89,if(AJ89<>"",if(AJ89>AI89,AJ89-AI89,""),$A$1-AI89),"") -> 1355.2339 | AN89: =if(AJ89,if(and(hour(AJ89+AN$5)>11,(hour(AJ89+AN$5)<20)),AJ89+AN$5,_xlfn.workday.intl(int(AJ89),1,"1000000",Holidays!A:A)+hour(AJ89+AN$5-$B$1)/24+minute(AJ89)/1440),"") | AO89: =if(AO89,AO89,if(AP89<>"",$A$1,"")) | AQ89: =if(AN89,if(AO89<>"",if(AO89>AN89,AO89-AN89,""),$A$1-AN89),"") | AS89: =if(AJ89,if(and(hour(AJ89+AS$5)>11,(hour(AJ89+AS$5)<20)),AJ89+AS$5,_xlfn.workday.intl(int(AJ89),1,"1000000",Holidays!A:A)+hour(AJ89+AS$5-$B$1)/24+minute(AJ89)/1440),"") | AT89: =if(AT89,AT89,if(AU89<>"",$A$1,"")) | AV89: =if(AS89,if(AT89<>"",if(AT89>AS89,AT89-AS89,""),$A$1-AS89),"") | AX89: confirm karenge kunal ji
A90: 44770.698 | G90: =if(A90,_xlfn.workday.intl(int(A90),1,"1000000",Holidays!A:A)+17/24,"") -> 44771.708 | H90: =if(H90,H90,if(I90<>"",$A$1,"")) -> 44773.564 | I90: done | J90: =if(G90,if(H90<>"",if(H90>G90,H90-G90,""),$A$1-G90),"") -> 1.8555811 | K90: =if(G90,_xlfn.workday.intl(int(G90),0,"1000000",Holidays!A:A)+19/24,"") -> 44771.792 | L90: =if(L90,L90,if(M90<>"",$A$1,"")) -> 44772.514 | M90: done | N90: =if(K90,if(L90<>"",if(L90>K90,L90-K90,""),$A$1-K90),"") -> 0.72282623 | O90: =if(A90,_xlfn.WORKDAY.INTL(A90,O$5,"1000000",Holidays!A:A)+hour(A90)/24+MINUTE(A90)/1440,"") -> 44771.698 | P90: 44772.514 | Q90: done | R90: =if(O90,if(P90<>"",if(P90>O90,P90-O90,""),$A$1-O90),"") -> 0.8164334 | U90: =if(O90,_xlfn.WORKDAY.INTL(O90,U$5,"1000000",Holidays!A:A)+hour(O90)/24+MINUTE(O90)/1440,"") -> 44772.698 | V90: =if(V90,V90,if(W90<>"",$A$1,"")) | X90: =if(U90,if(V90<>"",if(V90>U90,V90-U90,""),$A$1-U90),"") -> 1361.286 | AB90: 1 | AC90: 5 | AH90: =IF(P90="","",P90+AB90+AC90+AD90+AE90+AF90) -> 44778.514 | AI90: =if(AH90,_xlfn.workday.intl(int(AH90),0,"1000000",Holidays!A:A)+18/24,"") -> 44778.75 | AJ90: =if(AJ90,AJ90,if(AK90<>"",$A$1,"")) -> 44777.492 | AK90: done | AL90: =if(AI90,if(AJ90<>"",if(AJ90>AI90,AJ90-AI90,""),$A$1-AI90),"") | AO90: =if(AO90,AO90,if(AP90<>"",$A$1,"")) -> 44773.564 | AP90: done | AQ90: =if(AN90,if(AO90<>"",if(AO90>AN90,AO90-AN90,""),$A$1-AN90),"") | AS90: =if(AJ90,if(and(hour(AJ90+AS$5)>11,(hour(AJ90+AS$5)<20)),AJ90+AS$5,_xlfn.workday.intl(int(AJ90),1,"1000000",Holidays!A:A)+hour(AJ90+AS$5-$B$1)/24+minute(AJ90)/1440),"") -> 44778.492 | AT90: =if(AT90,AT90,if(AU90<>"",$A$1,"")) | AV90: =if(AS90,if(AT90<>"",if(AT90>AS90,AT90-AS90,""),$A$1-AS90),"") -> 1355.4922 | AX90: no response
A91: 44776.699 | G91: =if(A91,_xlfn.workday.intl(int(A91),1,"1000000",Holidays!A:A)+17/24,"") -> 44777.708 | H91: =if(H91,H91,if(I91<>"",$A$1,"")) | J91: =if(G91,if(H91<>"",if(H91>G91,H91-G91,""),$A$1-G91),"") -> 1356.2756 | K91: =if(G91,_xlfn.workday.intl(int(G91),0,"1000000",Holidays!A:A)+19/24,"") -> 44777.792 | L91: =if(L91,L91,if(M91<>"",$A$1,"")) -> 44777.483 | M91: done | N91: =if(K91,if(L91<>"",if(L91>K91,L91-K91,""),$A$1-K91),"") | O91: =if(A91,_xlfn.WORKDAY.INTL(A91,O$5,"1000000",Holidays!A:A)+hour(A91)/24+MINUTE(A91)/1440,"") -> 44777.699 | P91: 44776.748 | Q91: done | R91: =if(O91,if(P91<>"",if(P91>O91,P91-O91,""),$A$1-O91),"") | U91: =if(O91,_xlfn.WORKDAY.INTL(O91,U$5,"1000000",Holidays!A:A)+hour(O91)/24+MINUTE(O91)/1440,"") -> 44778.699 | V91: =if(V91,V91,if(W91<>"",$A$1,"")) | X91: =if(U91,if(V91<>"",if(V91>U91,V91-U91,""),$A$1-U91),"") -> 1355.2846 | AB91: 1 | AH91: =IF(P91="","",P91+AB91+AC91+AD91+AE91+AF91) -> 44777.748 | AI91: =if(AH91,_xlfn.workday.intl(int(AH91),0,"1000000",Holidays!A:A)+18/24,"") -> 44777.75 | AJ91: =if(AJ91,AJ91,if(AK91<>"",$A$1,"")) | AL91: =if(AI91,if(AJ91<>"",if(AJ91>AI91,AJ91-AI91,""),$A$1-AI91),"") -> 1356.2339 | AN91: =if(AJ91,if(and(hour(AJ91+AN$5)>11,(hour(AJ91+AN$5)<20)),AJ91+AN$5,_xlfn.workday.intl(int(AJ91),1,"1000000",Holidays!A:A)+hour(AJ91+AN$5-$B$1)/24+minute(AJ91)/1440),"") | AO91: =if(AO91,AO91,if(AP91<>"",$A$1,"")) | AQ91: =if(AN91,if(AO91<>"",if(AO91>AN91,AO91-AN91,""),$A$1-AN91),"") | AS91: =if(AJ91,if(and(hour(AJ91+AS$5)>11,(hour(AJ91+AS$5)<20)),AJ91+AS$5,_xlfn.workday.intl(int(AJ91),1,"1000000",Holidays!A:A)+hour(AJ91+AS$5-$B$1)/24+minute(AJ91)/1440),"") | AT91: =if(AT91,AT91,if(AU91<>"",$A$1,"")) | AX91: Navaratri
A92: 44776.703 | G92: =if(A92,_xlfn.workday.intl(int(A92),1,"1000000",Holidays!A:A)+17/24,"") -> 44777.708 | H92: =if(H92,H92,if(I92<>"",$A$1,"")) -> 44824.672 | I92: done | J92: =if(G92,if(H92<>"",if(H92>G92,H92-G92,""),$A$1-G92),"") -> 46.963325 | K92: =if(G92,_xlfn.workday.intl(int(G92),0,"1000000",Holidays!A:A)+19/24,"") -> 44777.792 | L92: =if(L92,L92,if(M92<>"",$A$1,"")) -> 44814.511 | M92: done | N92: =if(K92,if(L92<>"",if(L92>K92,L92-K92,""),$A$1-K92),"") -> 36.719532 | O92: =if(A92,_xlfn.WORKDAY.INTL(A92,O$5,"1000000",Holidays!A:A)+hour(A92)/24+MINUTE(A92)/1440,"") -> 44777.703 | P92: 44814.511 | Q92: done | R92: =if(O92,if(P92<>"",if(P92>O92,P92-O92,""),$A$1-O92),"") -> 36.808447 | U92: =if(O92,_xlfn.WORKDAY.INTL(O92,U$5,"1000000",Holidays!A:A)+hour(O92)/24+MINUTE(O92)/1440,"") -> 44778.703 | V92: =if(V92,V92,if(W92<>"",$A$1,"")) | X92: =if(U92,if(V92<>"",if(V92>U92,V92-U92,""),$A$1-U92),"") -> 1355.2811 | AB92: 1 | AH92: =IF(P92="","",P92+AB92+AC92+AD92+AE92+AF92) -> 44815.511 | AI92: =if(AH92,_xlfn.workday.intl(int(AH92),0,"1000000",Holidays!A:A)+18/24,"") -> 44815.75 | AJ92: =if(AJ92,AJ92,if(AK92<>"",$A$1,"")) -> 44824.672 | AK92: done | AL92: =if(AI92,if(AJ92<>"",if(AJ92>AI92,AJ92-AI92,""),$A$1-AI92),"") -> 8.9216796 | AN92: =if(AJ92,if(and(hour(AJ92+AN$5)>11,(hour(AJ92+AN$5)<20)),AJ92+AN$5,_xlfn.workday.intl(int(AJ92),1,"1000000",Holidays!A:A)+hour(AJ92+AN$5-$B$1)/24+minute(AJ92)/1440),"") -> 44825.672 | AO92: =if(AO92,AO92,if(AP92<>"",$A$1,"")) -> 44824.672 | AP92: done | AQ92: =if(AN92,if(AO92<>"",if(AO92>AN92,AO92-AN92,""),$A$1-AN92),"") | AS92: =if(AJ92,if(and(hour(AJ92+AS$5)>11,(hour(AJ92+AS$5)<20)),AJ92+AS$5,_xlfn.workday.intl(int(AJ92),1,"1000000",Holidays!A:A)+hour(AJ92+AS$5-$B$1)/24+minute(AJ92)/1440),"") -> 44826.672 | AT92: =if(AT92,AT92,if(AU92<>"",$A$1,"")) -> 44824.672 | AU92: yes | AV92: =if(AS92,if(AT92<>"",if(AT92>AS92,AT92-AS92,""),$A$1-AS92),"") | AX92: done
