Workbook

Sheet FR1
A1: Timestamp | B1: Walk In Client Name | C1: Number | D1: No of People | E1: In Time | F1: Which Counter | G1: Attend By | H1: Items Seen | I1: If Not What were they looking for or why didn't they buy | J1: Kitty Explained/Give | K1: Out Time | L1: Gift Given | M1: Google Review Taken | N1: Insta Follow | O1: Communication | P1: Relation | Q1: Kitty Interested | R1: CLIENT TYPE | S1: Sale
A2: 45284.59 | B2: Om parkash | C2: 9811023449 | D2: 1 | E2: 0.097222222 | F2: Gold | G2: Bhumika | H2: Bangles | J2: Not interested | K2: 0.11597222 | L2: Yes | M2: Yes | N2: Not use | O2: CELLS | P2: Sir
A3: 45284.654 | B3: Sudhanshu | C3: 9610072943 | D3: 1 | E3: 0.10069444 | F3: Diamond | G3: Chhaya | H3: Chain with solitaire pendent | K3: 0.14583333 | L3: Yes | M3: Yes | N3: Not usr | O3: WA ONLY | P3: Sir
A4: 45284.655 | B4: Mukul | C4: 7042183683 | D4: 2 | E4: 0.25625 | F4: Gold | G4: Mansa,pooja | H4: Not sale | I4: Customer want gold bar not available this itme | J4: No | K4: 0.27083333 | L4: No | M4: No | N4: No | O4: WA ONLY | P4: Sir
A5: 45284.66 | B5: Benuji | C5: 9810668596 | D5: 1 | E5: 0.51736111 | F5: Diamond | G5: Sanjeev sir,chhaya, pooja | H5: CVD, tops, ring | J5: No | K5: 0.11458333 | L5: Yes | M5: Yes | N5: Not use insta | O5: WA ONLY, OWNER CONTACT ONLY | P5: Sir, Madam
A6: 45284.662 | B6: Shikha | C6: 8178148800 | D6: 3 | E6: 0.0625 | F6: Gold | G6: Reena, mansa | H6: Gold ring | K6: 0.086805556 | L6: Yes | N6: Yes | O6: WA ONLY | P6: Sir, Madam
A7: 45284.798 | B7: Tushar | C7: 9953450909 | D7: 2 | E7: 0.25 | F7: Gold | G7: Chhaya | H7: Gold gents ring | K7: 0.29861111 | L7: Yes | M7: Yes | N7: Yes | O7: WA ONLY, OWNER CONTACT ONLY | P7: Sir, Madam
A8: 45284.819 | B8: Tushar | C8: 9953450909 | D8: 2 | E8: 0.25 | F8: Gold | G8: Chhaya | H8: Gold ring | J8: Yes | K8: 0.3125 | L8: Yes | M8: Yes | N8: Yes | O8: WA ONLY, OWNER CONTACT ONLY | P8: Sir, Madam
A9: 45284.827 | B9: Atoshi | C9: 8700173741 | D9: 1 | E9: 0.25347222 | F9: Gold | G9: Mansa | H9: Gold ring,penden | J9: Yes | K9: 0.33333333 | L9: Yes | M9: Yes | N9: Yes | O9: WA ONLY, OWNER CONTACT ONLY | P9: Madam
A10: 45284.828 | B10: Afsana begam | C10: 9311691012 | D10: 1 | E10: 0.23958333 | F10: Gold | G10: Chhaya | H10: Ringyes | J10: Yes | K10: 0.3125 | L10: Yes | M10: Yes | N10: Not use | O10: WA ONLY | P10: Sir, Madam
A11: 45286.701 | B11: Sunita mehta | C11: 9810222843 | D11: 3 | E11: 0.11111111 | F11: Diamond | G11: Sanjeev sir,seema mam,reema | H11: Rapier Diamond ring | I11: Rapier Diamond ring | K11: 0.16666667 | L11: No | M11: Already done | N11: Already done | O11: WA ONLY | P11: Sir, Madam
A12: 45286.702 | B12: Amit kumar | C12: 9821489150 | D12: 1 | E12: 0.12847222 | F12: Gold | G12: Pooja | H12: Gold chain repair | K12: 0.12986111 | L12: No | O12: WA ONLY | P12: Sir, Madam
A13: 45286.703 | B13: Uttam | C13: 9810007503 | D13: 1 | E13: 0.12986111 | F13: Diamond | G13: Reema | H13: Repaire Diamond ring | K13: 0.13541667 | L13: Yes | M13: Already done | N13: Already done | O13: WA ONLY | P13: Sir
A14: 45286.706 | B14: Kritanjli | C14: 9873041853 | D14: 1 | E14: 0.16875 | F14: Antic | G14: Chhaya | H14: Gems gold ring( pic the order no concern person) | I14: no concern person | J14: no concern person | K14: 0.17708333 | L14: Yes | M14: no concern person | N14: no concern person | O14: WA ONLY | P14: Sir
A15: 45287.719 | B15: Pragya | C15: 9910603300 | D15: 1 | E15: 0.29513889 | F15: Diamond | G15: Reema | H15: Not sale any set because customer wont home and told which set he liked | K15: 0.34375 | L15: Yes | O15: WA ONLY | P15: Madam
A16: 45287.721 | B16: Raj karan | C16: 9560358448 | D16: 2 | E16: 0.19097222 | G16: Gold | H16: Customer wants Pendent but process in order | K16: 0.21875 | L16: Yes | M16: Yes | N16: Not use | O16: WA ONLY | P16: Sir, Madam
A17: 45287.772 | B17: Ravi | C17: 8882584436 | D17: 1 | E17: 0.24652778 | F17: Gold | G17: Mansa | H17: Silver anklet | J17: Not interested | K17: 0.27152778 | L17: No | M17: Already done | N17: Already done | O17: WA ONLY | P17: Sir
A18: 45287.803 | B18: Sumit | C18: 9212327770 | D18: 1 | E18: 0.28472222 | F18: Antic | G18: Chhaya | H18: Customer sel own gold coin 100 gm | K18: 0.29861111 | L18: Yes | O18: WA ONLY | P18: Sir
A19: 45288.67 | B19: Anu | C19: 9212674929 | D19: 1 | E19: 0.084027778 | F19: Gold | G19: Bhumika | H19: 2 pair tops | K19: 0.14583333 | L19: Yes | M19: Yes | N19: Not use | O19: WA ONLY | P19: Sir, Madam
A20: 45288.766 | B20: Veena rawal | C20: 8800939462 | D20: 1 | E20: 0.16944444 | F20: Antic | G20: Chhaya | H20: 100 gm gold bar | K20: 0.21875 | L20: Yes | M20: Yes | N20: Yes | O20: WA ONLY | P20: Madam
A21: 45288.783 | B21: Keshar | C21: 99999728283 | D21: 2 | E21: 0.19166667 | F21: Sntic | G21: Pooja | H21: Gold tops,mang tika | J21: Already done | K21: 0.27361111 | L21: Yes | M21: Yes | N21: Yes | O21: WA ONLY | P21: Sir, Madam
A22: 45288.784 | B22: Shilpi puri | C22: 9958950595 | D22: 2 | E22: 0.21041667 | F22: Diamond | G22: Reema | H22: Silver breslet but not sale because breslet not available in the store | K22: 0.22222222 | L22: No | O22: WA ONLY | P22: Madam
A23: 45288.801 | B23: Sharvan | C23: 7021183656 | D23: 1 | E23: 0.26597222 | F23: Gold | G23: Bhumika,mansa | H23: Gold mangal sutr | K23: 0.30208333 | L23: No | M23: Yes | N23: Yse | O23: WA ONLY | P23: Sir
A24: 45288.802 | B24: Mini | C24: 9818926253 | D24: 1 | E24: 0.19027778 | F24: Gold | G24: Bhumika,mansa | H24: Repairing | K24: 0.27291667 | L24: No | M24: Already done | N24: Already done | O24: WA ONLY | P24: Madam
A25: 45289.733 | B25: Shaista | C25: 8860741616 | D25: 1 | E25: 0.068055556 | F25: Gold | G25: Bhumika | H25: 2 pairs tops CVD | J25: Already done | K25: 0.18819444 | L25: Yes | M25: Already done | N25: Already done | O25: WA ONLY, OWNER CONTACT ONLY | P25: Madam
A26: 45289.738 | B26: Aissato guniea | C26: 622130284 | D26: 1 | E26: 0.083333333 | F26: Gold | G26: Bhumika | I26: To pair of chain selecte and ho to home discuss with family and visit in the store after 2 ya 3 days | J26: Not interested | K26: 0.14583333 | L26: Yes | M26: Feedback giving after Purchasing | N26: Noy use | O26: WA ONLY | P26: Madam
A27: 45289.742 | B27: Naresh | C27: 7011729202 | D27: 1 | E27: 0.15833333 | F27: Antic | G27: Chhaya | I27: Discuss with family and visit the store than purchase | J27: Not interested | K27: 0.20833333 | L27: Yes | M27: Customer give the feedback after purchasing | N27: Not use | O27: WA ONLY | P27: Sir
A28: 45289.749 | B28: Nikita | C28: 8860590814 | D28: 2 | E28: 0.20833333 | F28: Gold | G28: Chhaya mansa | I28: Customer will be discussed & visit store | K28: 0.22222222 | L28: Yes | O28: WA ONLY | P28: Sir, Madam
A29: 45289.751 | B29: Reha jain | C29: 8860590814 | D29: 2 | E29: 0.20833333 | F29: Diamond | G29: Reema | I29: 2 diamond ring order | K29: 0.24444444 | L29: No | M29: Yes | N29: Yes | O29: WA ONLY | P29: Sir, Madam
A30: 45289.789 | B30: Priya | C30: 9650745331 | D30: 3 | E30: 0.25069444 | F30: Diamond | G30: Reema | I30: Visit the store after 2 ya 3 days | J30: Already done | K30: 0.2875 | L30: Yes | M30: Already done | N30: Already done | O30: WA ONLY | P30: Madam
A31: 45290.535 | B31: Nada rku | C31: 8974251308 | D31: 1 | E31: 0.48958333 | F31: Diamond | G31: Reema | H31: Gems stone but | I31: One pendent order diamond and gold mix | J31: Not interested | K31: 0.53125 | L31: Yes | M31: Yes | N31: Yes | O31: WA ONLY | P31: Madam
A32: 45290.68 | B32: Urmil | C32: 9810775750 | D32: 2 | E32: 0.061111111 | F32: Antic | G32: Chhaya | I32: Kundan set remaking | J32: Next kitty batch will be customer start kitty | K32: 0.10416667 | L32: Yes | M32: Already done | N32: Already done | O32: WA ONLY | P32: Madam
A33: 45290.681 | B33: Satish yadav | C33: 92122710187 | D33: 1 | E33: 0.17083333 | F33: Gold | G33: Mansa, bhumika | I33: Tomorrow customer visit store with wife and want gold set | J33: Tomorrow come | K33: 0.17777778 | L33: Yes | M33: Tomorrow come | N33: Tomorrow come | O33: WA ONLY | P33: Sir
A34: 45290.773 | B34: Deepak | C34: 9811172888 | D34: 1 | E34: 0.12638889 | F34: Gold,antic | G34: Bhumika,chhaya pooja,msnsa | I34: Again visit | J34: Again visit | K34: 0.25902778 | L34: Yes | M34: After purchasing | N34: After purchasing | O34: WA ONLY, OWNER CONTACT ONLY | P34: Sir
A35: 45290.774 | B35: Om parkash | C35: 9811023449 | D35: 1 | E35: 0.24513889 | F35: Gold | I35: Balance full fill | J35: Not interested | K35: 0.25694444 | L35: Yes | M35: Already done | N35: Already done | O35: WA ONLY | P35: Sir
A36: 45290.781 | B36: Priyanka | C36: 9818668439 | D36: 2 | E36: 0.24513889 | F36: Antic | G36: Pooja,chhaya,seema mam | I36: Aging visit | K36: 0.27986111 | L36: Yes | M36: Again visit | N36: Not use | O36: WA ONLY, OWNER CONTACT ONLY | P36: Madam
A37: 45290.815 | B37: Atoshi | C37: 8700173741 | D37: 2 | E37: 0.29166667 | F37: Gold | G37: Bhumika,mansa | H37: Silver coin 20 gm | J37: Already done | K37: 0.31944444 | L37: Yes | M37: Already done | N37: Already done | O37: WA ONLY | P37: Madam
A38: 45291.693 | B38: Mini | C38: 9818926153 | D38: 1 | E38: 0.52638889 | F38: Gold | G38: Bhumika | I38: Repair diamond set | J38: Not interested | K38: 0.11111111 | L38: Yes | M38: Already done | N38: Already done | O38: WA ONLY | P38: Madam
A39: 45291.694 | B39: Ritu rathi | C39: 9818802720 | D39: 1 | E39: 0.060416667 | F39: Diamond | G39: Reena | I39: One diamond ring order | J39: Already taken | K39: 0.089583333 | L39: Yes | M39: Already done | N39: Already done | O39: WA ONLY, OWNER CONTACT ONLY | P39: Sir, Madam
A40: 45291.696 | B40: Vinita | C40: 9811488999 | D40: 2 | E40: 0.13611111 | F40: Gold | G40: Bhumika | I40: Polki set order | K40: 0.15902778 | L40: Yes | M40: Already done | N40: Already done | O40: WA ONLY, OWNER CONTACT ONLY | P40: Madam
A41: 45291.775 | B41: Tushar | C41: 9953450909 | D41: 1 | E41: 0.25347222 | F41: Antic | G41: Pooja | I41: Pic the order | J41: Not interested | K41: 0.27430556 | L41: Yes | M41: Already done | N41: Already done | O41: WA ONLY | P41: Sir, Madam
A42: 45293.781 | B42: Nikita goel | C42: 9811795829 | D42: 3 | E42: 0.12638889 | F42: Diamond, gold | G42: Mansa,pooja,reena | H42: Gold tops | I42: Change Diamond bangle and order gold chudi | J42: Not interested | K42: 0.19652778 | L42: Yes | M42: Already done | N42: Already done | O42: WA ONLY | P42: Sir, Madam
A43: 45293.782 | B43: Sandeep | C43: 8860211768 | D43: 1 | E43: 0.17777778 | F43: Antic | G43: Pooja | H43: Silver payal | J43: Visit again sunday | K43: 0.21041667 | L43: Yes | M43: Yes | N43: Yes | O43: WA ONLY | P43: Sir, Madam
A44: 45294.671 | B44: Shallja | C44: 8826313399 | D44: 3 | E44: 0.090277778 | F44: Diamond | G44: Reena | I44: Visit again | J44: Visit again | K44: 0.13541667 | L44: Yes | M44: Yes | N44: Yes | O44: WA ONLY | P44: Madam
A45: 45294.81 | B45: Ranbeer kumar | C45: 9810100011 | D45: 2 | E45: 0.09375 | F45: Gold | G45: Bhumika | I45: Pic the order | J45: Already done | K45: 0.17777778 | L45: Yes | M45: Already done | N45: Already done | O45: WA ONLY | P45: Madam
A46: 45295.674 | B46: Subhash | C46: 8920285128 | D46: 1 | E46: 0.044444444 | F46: Gold | G46: Bhumika | I46: Customer not satisfied with tops design | K46: 0.065972222 | L46: No | M46: No | N46: No | O46: WA ONLY | P46: Sir
A47: 45295.766 | B47: Renu manchanda | C47: 8920731234 | D47: 2 | E47: 0.19791667 | F47: Diamond | G47: Reena | I47: Pic the order | K47: 0.26388889 | L47: Yes | M47: Already done | N47: Already done | O47: WA ONLY | P47: Madam
A48: 45296.775 | B48: Krishna | C48: 7053000572 | D48: 1 | E48: 0.53611111 | F48: Gold | G48: Mansa,bhumika | I48: Customer confirm gold rate | J48: Visit again | K48: 0.047222222 | L48: No | M48: No | N48: No | O48: WA ONLY | P48: Sir
A49: 45296.776 | B49: Zaid | C49: 9582588575 | D49: 2 | E49: 0.15763889 | F49: Antic | G49: Pooja,chhaya | I49: Pic the order gold chain | K49: 0.20069444 | L49: Yes | M49: Yes | N49: Yes | O49: WA ONLY | P49: Madam
A50: 45296.778 | B50: Krishna | C50: 7053000572 | D50: 2 | E50: 0.15902778 | F50: Gold | G50: Mansa,bhumika | H50: 10 gold coins | J50: Not interested | K50: 0.25 | L50: Yes | M50: Yes | N50: Yes | O50: WA ONLY | P50: Sir
A51: 45296.802 | B51: Kamal rajput | C51: 9999882673 | D51: 4 | E51: 0.25 | F51: Diamond | G51: Reena | H51: Gold ginni chain | J51: Not interested | K51: 0.29513889 | L51: Yes | M51: Already done | N51: Already done | O51: WA ONLY | P51: Sir, Madam
A52: 45297.641 | B52: Miqal | C52: 7390880818 | D52: 1 | E52: 0.059722222 | F52: Diamond | G52: Mansa,reena | I52: Confirm diamond charges | J52: Not interested | K52: 0.11111111 | L52: Yes | M52: No | N52: No | O52: WA ONLY | P52: Sir
A53: 45297.642 | B53: Purshotam | C53: 8929184477 | D53: 2 | E53: 0.067361111 | F53: Gold | G53: Bhumika | I53: Customer wants nose pin but not satisfied design | J53: Not interested | K53: 0.072916667 | L53: Yes | M53: After porches | N53: After porches | O53: WA ONLY | P53: Sir, Madam
A54: 45297.644 | B54: Shushil kumar | C54: 9971389387 | D54: 2 | E54: 0.10694444 | F54: Antic | G54: Pooja,chhaya | I54: Customer pic order | J54: Not interested | K54: 0.1125 | L54: Yes | M54: Already done | N54: Already done | O54: CELLS | P54: Sir, Madam
A55: 45297.645 | B55: Jitender | C55: 9213171560 | D55: 3 | E55: 0.11527778 | F55: Antic | G55: Pooja,chhaya,mansa | I55: Customer confirm making charges antic gold Customer visit again | J55: Visit again | K55: 0.13472222 | L55: Yes | M55: After parches | N55: After parches | O55: WA ONLY | P55: Sir
A56: 45297.764 | B56: Ronak parveen | C56: 8587085269 | D56: 2 | E56: 0.18680556 | F56: Antic | G56: Chhaya | I56: Repair | K56: 0.19791667 | L56: Yes | M56: Already done | N56: Already done | O56: CELLS | P56: Sir, Madam
A57: 45297.766 | B57: Dipti | C57: 9818756677 | D57: 3 | E57: 0.18888889 | F57: Antic | G57: Chhaya,mansa,pooja | I57: Customer discuss with family than dissaide | K57: 0.26041667 | L57: Yes | M57: Already done | N57: Already done | O57: WA ONLY | P57: Sir, Madam
A58: 45298.759 | B58: Atoshi | C58: 8700173741 | D58: 3 | E58: 0.073611111 | F58: Diamond gold | G58: Bhumika,reena | H58: Gold ring | K58: 0.13194444 | L58: Yes | M58: Already done | N58: Already done | O58: WA ONLY | P58: Madam
A59: 45298.76 | B59: Ritu Choudhary | C59: 9868120901 | D59: 2 | E59: 0.11180556 | F59: Antic | G59: Pooja,chhaya | H59: Gold chain | J59: Not interested | K59: 0.16666667 | L59: Yes | M59: Already done | N59: Already done | O59: WA ONLY | P59: Sir, Madam
A60: 45298.761 | B60: Abbasudin | D60: 2 | E60: 0.17777778 | F60: Antic | G60: Pooja chhaya | I60: Pic the order | J60: Not interested | K60: 0.25694444 | L60: Yes | M60: Already done | N60: Already done | O60: WA ONLY | P60: Sir
A61: 45298.765 | B61: MD salehin | C61: 9525203641 | D61: 2 | E61: 0.20625 | F61: Diamond | G61: Reena | H61: Gold ring | J61: Not interested | K61: 0.23819444 | L61: Yes | M61: Yes | N61: Yes | O61: WA ONLY | P61: Sir, Madam
A62: 45298.766 | B62: Gorav | C62: 9999507907 | D62: 1 | E62: 0.21180556 | F62: Gold | G62: Pooja | I62: Ring repairing | K62: 0.21666667 | L62: Yes | M62: Visit again | N62: Visit again | O62: WA ONLY | P62: Sir
A63: 45298.774 | B63: Manjeet | C63: 9643705979 | D63: 3 | E63: 0.15833333 | F63: Antic | G63: Pooja,chhaya | I63: Antic set order | K63: 0.26944444 | L63: Yes | M63: Yes | N63: Yes | O63: WA ONLY | P63: Sir, Madam
A64: 45298.803 | B64: Neena | C64: 9312229038 | D64: 2 | E64: 0.16805556 | F64: Diamond | G64: Reena | H64: Gokd pendent | J64: Already done | K64: 0.29791667 | L64: Yes | M64: Already done | N64: Already done | O64: WA ONLY, OWNER CONTACT ONLY | P64: Madam
A65: 45298.822 | B65: Ina | C65: 9886328522 | D65: 3 | E65: 0.26388889 | F65: Gold | G65: Bhumika | H65: Ina | J65: Visit again | K65: 0.32291667 | L65: Yes | M65: Yes | N65: Yes | O65: WA ONLY | P65: Sir, Madam
A66: 45298.825 | B66: Sagar | C66: 9654141505 | D66: 2 | E66: 0.21319444 | F66: Antic | G66: Chhaya | I66: Antic gold set dissed advance payment done | L66: Yes | M66: Yes | N66: Yes | O66: WA ONLY | P66: Sir, Madam
A67: 45300.739 | B67: Ritu rathi | C67: 9818802702 | D67: 2 | E67: 0.51319444 | F67: Antic | G67: Pooja | H67: Gold tops | J67: Done | K67: 0.083333333 | L67: Yes | M67: Already done | N67: Already done | O67: WA ONLY | P67: Madam
A68: 45300.74 | B68: Shivani | C68: 9560341110 | D68: 4 | E68: 0.51319444 | F68: Diamond | G68: Chhaya | I68: Order diamond ring | J68: Kitty done | K68: 0.051388889 | L68: Yes | M68: Already done | N68: Already done | O68: WA ONLY | P68: Madam
A69: 45300.741 | B69: Khushbu vijay | C69: 7021020509 | D69: 2 | E69: 0.068055556 | F69: Gold | G69: Chhaya | I69: Order | K69: 0.10694444 | L69: Yes | M69: Already done | N69: Already done | O69: WA ONLY | P69: Sir, Madam
A70: 45301.759 | B70: Rakesh ravi | C70: 9711428669 | D70: 1 | E70: 0.097222222 | F70: Diamond | G70: Reena | H70: Silver god | J70: Not interested | K70: 0.12847222 | L70: Yes | M70: Yes | N70: Yes | O70: WA ONLY | P70: Sir
A71: 45301.761 | B71: Shiba | C71: 488017818 | D71: 4 | E71: 0.10555556 | F71: Diamond | G71: Kamini | I71: Diamond earing order | K71: 0.15347222 | L71: Yes | M71: Already done | N71: Already done | O71: WA ONLY | P71: Madam
A72: 45301.762 | B72: Manjeet | C72: 9743705979 | D72: 2 | E72: 0.099305556 | F72: Antic | G72: Chhaya | H72: Antic gold set, silver payal | J72: Not interested | K72: 0.19861111 | L72: Yes | M72: Already done | N72: Already done | O72: WA ONLY | P72: Sir, Madam
A73: 45301.763 | B73: Sanchit | C73: 9821136219 | D73: 1 | E73: 0.14513889 | F73: Antic | G73: Pooja | I73: Visit again | J73: Visit again | K73: 0.15069444 | L73: Yes | M73: After purchase | N73: After purchase | O73: WA ONLY | P73: Sir
A74: 45302.775 | B74: Pc sharma | C74: 9810068111 | D74: 2 | E74: 0.045138889 | F74: Diamond | G74: Reena | H74: Chain with diamond pendant | J74: Not interested | K74: 0.086805556 | L74: Yes | M74: No | N74: Not use | O74: WA ONLY | P74: Sir, Madam
A75: 45302.776 | B75: Shiba | C75: 61+488017818 | D75: 1 | E75: 0.11805556 | F75: Diamond | G75: Kamini | I75: Repair | J75: Not interested | K75: 0.13541667 | L75: Yes | M75: Yes | N75: Already done | O75: WA ONLY | P75: Madam
A76: 45302.777 | B76: Sumit | C76: 9899222680 | D76: 2 | E76: 0.18402778 | F76: Diamond | G76: Reena | I76: Repair | K76: 0.20555556 | L76: Yes | M76: Already done | N76: Already done | O76: WA ONLY | P76: Sir, Madam
A77: 45302.807 | B77: Vabhav garg | C77: 0911019947 | D77: 1 | E77: 0.26041667 | F77: Gold | G77: Bhumika | I77: Confirm gold rate | J77: Visit again | K77: 0.29305556 | L77: Yes | M77: Visit again | N77: Visit again | O77: WA ONLY | P77: Sir
A78: 45302.808 | B78: Rajni | C78: 9711216574 | D78: 3 | E78: 0.28819444 | F78: Diamond | G78: Reena,pooja | I78: Visit again | J78: Visit again | K78: 0.29305556 | L78: Yes | M78: After purchase | N78: After purchase | O78: WA ONLY | P78: Madam
A79: 45303.772 | B79: Anita kapoor | C79: 8010046101 | D79: 2 | E79: 0.53958333 | F79: Diamond | G79: Reena | I79: Repair | J79: Done | K79: 0.041666667 | L79: Yes | M79: Already done | N79: Already done | O79: WA ONLY | P79: Sir, Madam
A80: 45304.744 | B80: Seema | C80: 9643705979 | D80: 2 | E80: 0.041666667 | F80: Gold | G80: Bhumika | I80: Payment done | J80: Done | K80: 0.072916667 | L80: Yes | M80: Already done | N80: Already done | O80: WA ONLY | P80: Madam
A81: 45304.747 | B81: Hina | C81: 9780560701 | D81: 3 | E81: 0.073611111 | F81: Gold | G81: Bhumika | I81: Size issue gold bangles | J81: Visit again | K81: 0.10902778 | L81: Yes | M81: Visit again | N81: Visit again | O81: WA ONLY | P81: Sir, Madam
A82: 45304.748 | B82: Poonam | C82: 8700909391 | D82: 2 | E82: 0.14444444 | F82: Diamond | G82: Reena | H82: Gold bali | J82: Not interested | K82: 0.17708333 | L82: Yes | M82: Yes | N82: Yes | O82: WA ONLY | P82: Sir, Madam
A83: 45304.749 | B83: Kavita | C83: 8860036737 | D83: 3 | E83: 0.18333333 | F83: Gold | G83: Bhumika | I83: Gents silver ring | K83: 0.17708333 | L83: Yes | M83: No | N83: No | O83: WA ONLY | P83: Sir, Madam
A84: 45305.752 | B84: Umera | C84: 7385216713 | D84: 2 | E84: 0.060416667 | F84: Gold | G84: Bhumika | I84: Customer not satisfied with nose pin design gold | K84: 0.046527778 | L84: Yes | M84: No | N84: No | O84: WA ONLY | P84: Sir, Madam
A85: 45305.753 | B85: Gagan | C85: 9810337136 | D85: 2 | E85: 0.12916667 | F85: Diamond | G85: Reena | I85: Visit again | J85: Visit again | K85: 0.14861111 | L85: Yes | M85: No | N85: No | O85: WA ONLY | P85: Sir, Madam
A86: 45305.754 | B86: Sanjay | C86: 9899442938 | D86: 2 | E86: 0.125 | F86: Antic | G86: Bhumika | H86: Gold chain | J86: Not interested | K86: 0.14861111 | L86: Yes | M86: Yes | N86: Yes | O86: WA ONLY | P86: Sir, Madam
A87: 45305.755 | B87: Rahul | C87: 981144932 | D87: 1 | E87: 0.21875 | F87: Gold | G87: Bhumika | I87: Visit again Tuesday | J87: Visit again Tuesday | K87: 0.24652778 | L87: Yes | M87: Visit again | N87: Visit again | O87: WA ONLY | P87: Sir
A88: 45305.814 | B88: Rahul | C88: 9811448932 | D88: 1 | E88: 0.21875 | F88: Diamond | G88: Reena | I88: Payment done diamond set ordered | K88: 0.24652778 | L88: Yes | M88: No | N88: No | O88: WA ONLY | P88: Sir, Madam
A89: 45305.815 | B89: Aanad | C89: 9810857727 | D89: 2 | E89: 0.22708333 | F89: Diamond | G89: Reena | I89: Visit again | K89: 0.28402778 | L89: Yes | M89: Already done | N89: Already done | O89: WA ONLY | P89: Sir, Madam
A90: 45307.762 | B90: Hardeep | C90: 9999446004 | D90: 2 | E90: 0.10347222 | F90: Gold | G90: Bhumika | I90: Diamond ring order | K90: 0.17847222 | L90: Yes | M90: Already done | N90: Already done | O90: WA ONLY | P90: Sir, Madam
A91: 45308.755 | B91: Annu | C91: 9319319976 | D91: 1 | E91: 0.063888889 | F91: Diamond | G91: Reena | I91: Visit again | J91: Visit again | K91: 0.091666667 | L91: Yes | M91: Visit again | N91: Visit again | O91: WA ONLY | P91: Madam
A92: 45308.778 | B92: Neven cutuc | C92: +38592246190 | D92: 1 | E92: 0.15138889 | F92: Diamond | G92: Reena | I92: Visit again | J92: Visit Alain | K92: 0.17847222 | L92: Yes | M92: Visit again | N92: Visit again | O92: WA ONLY | P92: Sir
A93: 45308.779 | B93: Sanchit | C93: 9821136219 | D93: 2 | E93: 0.19097222 | F93: Antic | G93: Pooja,chhaya | J93: Visit again | K93: 0.22430556 | L93: Yes | M93: Visit again | N93: Visit again | O93: WA ONLY | P93: Sir
A94: 45308.805 | B94: Renu manchanda | C94: 9820731234 | D94: 3 | E94: 0.25555556 | F94: Antic | G94: Chhaya | I94: Pic the order | K94: 0.30416667 | L94: Yes | M94: Already done | N94: Already done | O94: WA ONLY | P94: Madam
A95: 45309.784 | B95: Sunal | C95: 9971989789 | D95: 3 | E95: 0.11805556 | F95: Diamond | G95: Reena | I95: Visit again | J95: Visit again | K95: 0.12083333 | L95: Yes | M95: After purchase | N95: After purchase | O95: WA ONLY | P95: Sir, Madam
A96: 45309.786 | B96: Neven | C96: +385922462190 | D96: 1 | E96: 0.14791667 | F96: Diamond | G96: Reena | I96: Visit again | J96: Visit again | K96: 0.15277778 | L96: Yes | M96: After purchase | N96: After purchase | O96: WA ONLY | P96: Sir
A97: 45310.786 | B97: Meetu | C97: 9560915533 | D97: 2 | E97: 0.15833333 | F97: Diamond | G97: Reena | I97: Pic the diamond set | K97: 0.22430556 | L97: Yes | N97: already done | O97: WA ONLY | P97: Sir, Madam
A98: 45310.805 | B98: Sabera | C98: 52531720 | D98: 2 | E98: 0.15833333 | F98: Gold | G98: Chhaya | H98: Gold bangles,gold chain | J98: Not interested because it's forner | K98: 0.3125 | L98: Yes | M98: No | N98: No | O98: WA ONLY | P98: Madam
A99: 45311.766 | B99: Deepshi | C99: 8218058775 | D99: 2 | E99: 0.15555556 | F99: Gold | G99: Pooja | H99: Silver payal,bichhue. | J99: Not interested | K99: 0.23263889 | L99: Yes | M99: Yes | N99: Yes | O99: WA ONLY | P99: Sir, Madam
A100: 45311.767 | B100: Urmil | C100: 9810775750 | D100: 1 | E100: 0.15277778 | F100: Antic | G100: Chhaya | I100: Order | K100: 0.18958333 | L100: Yes | M100: Already done | N100: Already done | O100: WA ONLY | P100: Madam
...

Sheet old sheet data
A1: Timestamp | B1: Name | C1: Mobile | D1: Address | E1: Locality | F1: Your Birthday | G1: Your Anniversary | H1: Mail Id | I1: Reference Of | J1: Person Name
A2: 45205.477 | B2: saurav | C2: 9811464488 | D2: 2229, Sunsea, Hardhyan Singh Road, Karol Bagh | E2: Option 1
A3: 45212.663 | B3: Khushi | C3: 8506019383 | D3: Mzinejdhedbhxkk | E3: East | J3: Khushi
A4: 45213.541 | B4: Shah alam ji | C4: 9667903553 | D4: F-610A Sha complexes near bank of baroda | E4: North | F4: 19367 | J4: Chhaya
A5: 45214.583 | B5: Dr Shaista Khan | C5: 8860741616 | D5: T44/1, kalu sarai, hauz khas, new delhi 110016 | E5: South | F5: 45015 | G5: 45214 | H5: Shaistakhan343@yahoo.in | J5: Khushi
A6: 45214.585 | B6: Rita chaudhary | C6: 9868120901 | D6: G 41 spaze privy sector72gurgaon | E6: Gurgaon | F6: 45035 | H6: ritachaudhry19@gmail.com | J6: Khushi
A7: 45214.588 | B7: Rajbala | C7: 9582262162 | D7: 162, munirka, new delhi 110016 | E7: South | F7: 45292 | I7: Shaista khan | J7: Khushi
A8: 45214.588 | B8: Krishna rathi | C8: 9818294768 | D8: Munirka 222 | E8: South | I8: Shaista khan | J8: Khushi
A9: 45214.589 | B9: Rama gupta | C9: 7678373300 | D9: Sunder vihar | J9: Khushi
A10: 45214.589 | B10: Shilpa gupta | C10: 8447442044 | D10: Rohini east | E10: East | F10: 26261 | G10: 33711 | J10: Lipi
A11: 45214.594 | B11: Niharika | C11: 9419877098 | D11: Jammu | E11: Outstation | G11: 43498 | I11: Seema ma'am | J11: Harsha
A12: 45214.595 | B12: Chetan patel | C12: 7383344655 | D12: Delhi | E12: South | I12: Seema ma'am | J12: Harsha
A13: 45214.602 | B13: Surendra gupta | C13: 9810190708 | D13: C 181 vivek vihar delhi 110095 | E13: East | F13: 45050 | H13: gupta2019surendra@gmail.com | I13: Sanjeev garg | J13: Khushi
A14: 45214.609 | B14: Richa chaudhry | C14: 9810483570 | D14: G-1, 42 spaze privi sector-72 gurgao | E14: Gurgaon | J14: Khushi
A15: 45214.617 | B15: Arvind kumar gupta | C15: 9810403852 | D15: B-245 ramprastha colony gaziabad | E15: Outstation | J15: Khushi
A16: 45214.638 | B16: Sandhya gupta | C16: 8800699054 | D16: C-181 vivek vihar | J16: Khushi
A17: 45214.667 | B17: Rashi jain | C17: 8510007279 | D17: New delhi | J17: Khushi
A18: 45214.679 | B18: Nimishagupta | C18: 9811088872 | D18: G320 preet vihar | E18: East | F18: 45145 | G18: 45061 | I18: Sanjeev garg | J18: priya
A19: 45214.69 | B19: Sudesh jain | C19: 9811263840 | D19: A-114, upperground floor, saraswati vihar, delhi 110034 | E19: North | F19: 45203 | J19: Khushi
A20: 45214.691 | B20: bhavana vadudeva | C20: 9810042634 | D20: 7c pocket 12 vaishali apartments kalkaji extdion new delhi19 | E20: East | F20: 45020 | G20: 45215 | I20: saurav garg | J20: Priya pc
A21: 45214.712 | B21: Soniya gupta | C21: 9599223396 | D21: D for Delhi 133 sorajval bihar | E21: East | F21: 45209 | J21: Priya pc
A22: 45214.72 | B22: prial | C22: 9910925269 | D22: 149 sector 14 faridabad | E22: East | I22: upasna bhandari | J22: priya
A23: 45214.724 | B23: Yatin jain | C23: 9811233455 | D23: BA-36 west shalimar bagh new delhi-88 | E23: North | F23: 33114 | G23: 43936 | H23: Yatin@jaincogroup.com | I23: Tuti garg | J23: Khushi
A24: 45214.725 | B24: Ritu jain | C24: 9582808468 | D24: 67/3 zamrudpur g. K part 1 | J24: priya pc
A25: 45215.566 | B25: pankaj bansal | C25: 9911014950 | D25: b49 east jyoti nagar | E25: East | I25: sanjeev garg | J25: Priya pc
A26: 45215.57 | B26: Rohini | C26: 9990014950 | D26: Jyoti nagar | J26: priya pc
A27: 45215.572 | B27: Jl ahuja | C27: 9818017921 | D27: L 74 ground floor kirti nagar | J27: priya pc
A28: 45215.573 | B28: Shashi ahuja | C28: 9811108266 | D28: L 74 kirti nagar | H28: Jla80shashi @hotmail.com | I28: Jl ahuja | J28: Khushi
A29: 45215.574 | B29: Kavita kapila | C29: 9015802726 | D29: 57 a ua jawahar nagar 3 rd floor | J29: Khushi
A30: 45215.574 | B30: Khushboo kapila | C30: 9891567166 | D30: Jawahar nagar | I30: Kavita kapila | J30: Khushi
A31: 45215.587 | B31: Aastha | C31: 7011435956 | D31: Dlf moti nagar | J31: Khushi
A32: 45215.61 | B32: Santosh | C32: 9212157824 | D32: 5925/4gali no. 1 devnagar karol bagh | E32: Central | F32: 27139 | J32: Khushi
A33: 45215.611 | B33: Kusum singh | C33: 8368953488 | D33: T 47 ratan nagar karol bagh | J33: priya pc
A34: 45215.611 | B34: Atoshi singh | C34: 8700173441 | D34: Karol bagh | J34: priya pc
A35: 45215.612 | B35: Himanshu | C35: 8368329315 | D35: Dev nagar karolbagh | E35: Central | F35: 45205 | H35: Hc278368@gmailcom | J35: Khushi
A36: 45215.614 | B36: Ritu rathi | C36: 9818802720 | D36: Dlf moti nagar | J36: Khushi
A37: 45215.649 | B37: vanshika | C37: 9069461111 | D37: b 2101 painiyar park secter 61 gudgao | F37: 45219 | J37: Priya pc
A38: 45215.749 | B38: Mukesh mehta | C38: 9312401235 | D38: 2695 mukherjee nagar | J38: Khushi
A39: 45215.75 | B39: Ishaan | C39: 9312401235 | D39: Mukherjee nagar | I39: Mukesh mehta | J39: Khushi
A40: 45215.76 | B40: Mwaka | C40: 9821166531 | D40: J 197 gamma 2 greater noida | H40: Mnynamukonda@gmail.com | J40: Khushi
A41: 45215.767 | B41: Seema mehta | C41: 9810626049 | D41: 7 a!/70 wa channa market karol bagh | J41: Khushi
A42: 45216.593 | B42: Seema chawla | C42: 9818304747 | D42: Sec-44 noida | J42: Khushi
A43: 45216.593 | B43: Jyoti kohli | C43: 9810089431 | D43: Sec -45 noida | J43: Khushi
A44: 45216.594 | B44: Mrs makkar | C44: 9811573620 | D44: Sec-44 noida | J44: Khushi
A45: 45216.641 | B45: Richa | C45: 9899993041 | D45: 51/4 db gupta road karol bagh | H45: Rita. Alagh@yahoo.com | J45: Khushi
A46: 45216.641 | B46: Charu | C46: 9871089414 | D46: 210 1 floor vaishali pitampura | J46: Khushi
A47: 45217.65 | B47: Manish khandelwal | C47: 9891147247 | D47: 59/14 second floor new rohtak cinema | J47: Khushi
A48: 45217.706 | B48: Sabina | C48: 9811157112 | D48: 135 sunder nagar | J48: Khushi
A49: 45217.724 | B49: Bhavna chopra | C49: 9582142278 | D49: B-38, Parijat Apartment, west enclave | E49: North | F49: 45144 | G49: 45031 | H49: Chopra. Bhavna87@gmail.com | I49: Nikhil | J49: Khushi
A50: 45217.743 | B50: Dr. Bharat bhushan chauhan | C50: 9560861515 | D50: 12a/2101 lotud balword noida | J50: Khushi
A51: 45217.758 | B51: Manju rani | C51: 9999245123 | D51: R Block R-78+A Dilshad Garden | E51: East | F51: 23687 | G51: 32842 | J51: priya
A52: 45217.782 | B52: Jai bhagwan goel | C52: 8920332096 | D52: 216 joshi road karol bagh | F52: 44970 | H52: Shagungoel77@gmail.com | J52: Khushi
A53: 45217.793 | B53: Nidima goel | C53: 7982275693 | D53: 216 joshi road karol bagh | F53: 45224 | G53: 45095 | J53: Khushi
A54: 45221.572 | B54: Bhavika | C54: 9711917365 | D54: 3241 school lane paharganj | E54: Central | F54: 35931 | H54: Bhavikagola.110@gmail.com | I54: Seema mam | J54: Khushi
A55: 45221.577 | B55: Manish | C55: 9653177126 | D55: Neb saray near star gym | E55: South | F55: 32182 | H55: Manishchamling.m | J55: Khushi
A56: 45221.612 | B56: Nisha kumari | C56: 8285021778 | D56: C-186 west patel nagar, first floor 110008 | E56: West | F56: 35295 | I56: Mannnisha08@gmail.com | J56: Khushi
A57: 45221.753 | B57: Priyanka bhatia | C57: 9871231215 | D57: Villⁿ9⁹, tower 21, lA Tropicana, khyber Pass, civil ljnes Delhi- 110054 | E57: North | F57: 26829 | I57: Mrs Seema Garg. Mr Sanjeev Garg | J57: Khushi
A58: 45221.802 | B58: Dr Sadia lahid | C58: 9911338801 | D58: Shaheen bagh okla | E58: South | F58: 32438 | H58: Khaliddcu@g mail .com | I58: Mr Sanjeev ji | J58: Khushi
A59: 45221.827 | B59: Ratna Gupta | C59: 9899726672 | D59: B-1, 801, Ambience lagoon, DlF phase-3, Gurgoan, Haryana, 112002 | E59: Gurgaon | F59: 27194 | H59: Vimmi g 74 @g mail .com | J59: Khushi
A60: 45223.52 | B60: Anamta Rehman | C60: 9999999999 | D60: Leela hotel | H60: AnamtaRehman@1cloud.com | J60: Khushi
A61: 45223.538 | B61: Varun verma | C61: 9711538399 | D61: 1037, 40 foota road , Jain nagar near car pointt | E61: Central | F61: 33865 | H61: awesomevarun99@ gmail.com | I61: Arushi | J61: Khushi
A62: 45223.554 | B62: Pratham Arora | C62: 9810752706 | D62: 273, G.J. - second, Delhi-110009 | E62: Central | F62: 36498 | H62: a pratham | I62: Sonam Arora | J62: Khushi
A63: 45223.648 | B63: Pummy Arora | C63: 9873044658 | D63: 14A/12, WEA, Pusa road , Karol Bagh New Delhi - 110005 | E63: West | F63: 60853 | I63: Known since years | J63: Khushi
A64: 45223.657 | B64: Navya Sharma | C64: 9818881865 | D64: 289/10, Joshi Road, Karol Bagh, New Delhi-110005 | E64: West | F64: 40389 | I64: Sanjeev sir | J64: Khushi
A65: 45223.673 | B65: Dr Shaista Khan | C65: 8860741616 | D65: T-44/1, Kalu Sarai , Hauz Khas NewDelhi- 110016 | E65: South | H65: Shaista Khan343@Yahoo.in | J65: priya pc
A66: 45223.691 | B66: Rashi Sikka | C66: 9810813833 | D66: B-5/11 Safdarjung Enclave | E66: South | F66: 63190 | H66: Sikkarashi@yahoo.co.i n | I66: Mr Sanjeev | J66: priya pc
A67: 45224.536 | B67: Dr Bharat bhusan chauhan | C67: 9560861515 | D67: 12A/2101 lotus Bailward Noida | E67: Noida | H67: drbharat bhusan11@g mail .com | J67: Khushi
A68: 45224.591 | B68: Rita Chaudhary | C68: 9868120901 | D68: G- 142, Spaze Privy, Sonna road, sector-72, Gurugram-122101 | E68: Gurgaon | J68: Khushi
A69: 45224.602 | B69: Jai Bhagwan Goel | C69: 8920332096 | D69: 216 Joshi road , Karol Bagh | H69: Shagun goel 77@g mail.com | J69: Khushi
A70: 45224.609 | B70: Mamta Varma | C70: 8080774351 | D70: Plot no 58, Mahadev nagar | E70: Central | F70: 30357 | H70: Mamta unique101@ gmail.com | I70: Poonam | J70: Khushi
A71: 45224.718 | B71: Biakchhan Thuami | C71: 8974243952 | D71: H no NC- IV/4/2. New Capital Complex Aizawl-796001
A72: 45224.747 | B72: Raman Sharma | C72: 9971149898 | D72: 149, sector-14, Faridabad Haryana | E72: South | J72: Khushi
A73: 45224.76 | B73: Nisha kumari | C73: 8285021778 | D73: C-186 , west Patel nagar, first floor- 110008 | E73: West | F73: 40408 | H73: Mannisha08@gmail.com | J73: Khushi
A74: 45224.787 | B74: Pooja gupta | C74: 9810795881 | D74: A-306, Sector 31, noida-31 | E74: Noida | F74: 29774 | H74: Gupta.pooja 44@ gmail.com | J74: Khushi
A75: 45224.804 | B75: Anu | C75: 9212674929 | D75: ED/88 | E75: West | F75: 40281 | I75: Friend | J75: Khushi
A76: 45225.7 | B76: BIAKCHHAN. THUAMI | C76: 8974243952 | D76: H.no NC - I V/4/ 2. New capital complex Aizawl- 796001, Mizoram | E76: Outstation | J76: Khushi
A77: 45225.706 | B77: POOJA | C77: 8527612512 | D77: 25/9, Ground floor, East Patel Nagar | E77: East | F77: 29597 | G77: 37942 | J77: Khushi
A78: 45225.718 | B78: Pappu kumar | C78: 9953473951 | D78: Thancy nagar Anand Parvat Gali no- 9 | E78: West | J78: Khushi
A79: 45225.74 | B79: Atushi Singh | C79: 8700173741 | D79: T-47, Plotno 19, Ratan Nagar, New Rohtak Road , Karol Bagh | E79: West | J79: Khushi
A80: 45225.753 | B80: Dr Arshad | C80: 9871537826 | D80: B 161/204, Gautam Nagar, New Delhi-110049 | E80: South | J80: Khushi
A81: 45225.764 | B81: Ayushi Agarwal | C81: 9990998601 | D81: 76, Sangam apartments, Paschim vihar, Delhi- 110087 | E81: East | F81: 35317 | I81: Walking | J81: Khushi
A82: 45225.775 | B82: Neetu Arora | C82: 8130027978 | D82: 319, Dr Mukherjee Nagar, Delhi-110009 | E82: North | F82: 28634 | G82: 37017 | I82: Self | J82: Khushi
A83: 45225.784 | B83: Noor Bhatia | C83: 8800337448 | D83: Rajouri Garden | E83: West | F83: 34356 | J83: Khushi
A84: 45225.795 | B84: Mehar Chopra | C84: 9582142278 | D84: A-36. Brij vihar appartment Pitampura. Delhi-11003410034100 | E84: East | F84: 44883 | G84: 41713 | J84: Khushi
A85: 45225.8 | B85: POOJA GUPTA | C85: 9810795881 | D85: A-306, sector 31 noida-201301 | E85: Noida | F85: 29774 | G85: 38313 | H85: gupta.pooja44@gmail.com | J85: Khushi
A86: 45226.638 | B86: Preeti Kothari | C86: 9999251803 | D86: G-27, sector 27, Noida | E86: Noida | H86: preetikothari1510@gmail.com | J86: Khushi
A87: 45226.794 | B87: Bharti Chaudhary | C87: 9015429927 | D87: H no - 186, Gali no- 9, Block-B, Bhajanpura⁹ | E87: East | J87: Khushi
A88: 45226.817 | B88: Pratham Arora | C88: 9810752706 | D88: H no 273, G.J- I I, Delhi-110009 | E88: East | F88: 36498 | I88: Suman Arora | J88: Khushi
A89: 45227.648 | B89: Gurinder singh | C89: 9810100011 | D89: AC 9. Ganga Ram vatika, near Tilak Nagar, New Delhi 110018 | E89: West | G89: 31754 | H89: gilardmanw@yahoo.co.in | I89: Mom Ranbir kaur | J89: Khushi
A90: 45227.659 | B90: Neha Bansal | C90: 9054700000 | D90: H no 13, sector 22-A, mandi gobindgarh | E90: Outstation | F90: 30552 | G90: 39781 | J90: Khushi
A91: 45228.539 | B91: Bharti Khanna | C91: 9873833656 | D91: They are known person | J91: Khushi
A92: 45230.463 | B92: Nisha | C92: 9899264838 | D92: E- 65, Moti Bagh-1, New Delhi-110021 | E92: West | H92: Sati_nisha@yahoo.com | J92: Khushi
A93: 45230.473 | B93: Vijay kumar Bharat | C93: 9717636281 | D93: 216/D 6BN/RPSFP Dayabashi, Delhi -110035 | E93: Central | F93: 26769 | H93: Vijaykumar15041973@gmail.com | J93: Khushi
A94: 45231.495 | B94: Amit aggarwal | C94: 9971315613 | D94: 1304 Pragti Towers , 26 Rajendra Place New Delhi | E94: Central | F94: 29668 | G94: 39478 | H94: Amit Aggarwal21@gmail.com | J94: Khushi
A95: 45231.69 | B95: Rajkumar | C95: 8447416899 | D95: 109/4, Railway colony, Thomson Road, New Delhi-110002 | E95: Central | F95: 34500 | I95: Sir | J95: Khushi
A96: 45231.709 | B96: Shailender kumar shrivastav | C96: 9599868554 | D96: House no-80c, vikas nagar, Uttam nagar | E96: West | F96: 45087 | H96: Loveaajkal9599@gmail.com | I96: Walking | J96: Khushi
A97: 45231.712 | B97: Akram | C97: 9267917945 | D97: Old mustafabad, gali no 1, near Dilshad Mashid | E97: East | F97: 33109 | J97: Khushi
A98: 45231.718 | B98: FARUK | C98: 8130953608 | D98: Bangladesh | E98: Outstation | G98: 30352
A99: 45231.811 | B99: Naveen | C99: 9899142150 | D99: B-1/1C, Ashok vihar,Phase-3 | E99: North | J99: Khushi
A100: 45231.813 | B100: Anita Mehra | C100: 9899152387 | D100: I- block, Shakur Pur. DELHI | E100: East | F100: 23524 | J100: Khushi
...

Sheet Data Paste
A1: Timestamp | B1: Walk In Client Name | C1: Number | D1: No of People | E1: In Time | F1: Which Counter | G1: Attend By | H1: Items Seen | I1: If Not What were they looking for or why didn't they buy | J1: Kitty Explained/Give | K1: Out Time | L1: Gift Given | M1: Google Review Taken | N1: Insta Follow | O1: Communication | P1: Relation | Q1: Kitty Interested | R1: CLIENT TYPE | S1: Sale
A2: 45736.784 | B2: Atoshi | C2: 8700173741 | D2: 1 | E2: 0.25347222 | F2: Gold | G2: Deepali | H2: Gold ring,penden | J2: Yes | K2: 0.33333333 | L2: Yes | M2: Yes | N2: Yes | O2: WA ONLY, OWNER CONTACT ONLY | P2: Madam
A3: 45736.787 | B3: Afsana begam | C3: 9311691012 | D3: 1 | E3: 0.23958333 | F3: Gold | G3: Deepali | H3: Ringyes | J3: Yes | K3: 0.3125 | L3: Yes | M3: Yes | N3: Not use | O3: WA ONLY | P3: Sir, Madam
A4: 45736.788 | B4: Amit kumar | C4: 9821489150 | D4: 1 | E4: 0.12847222 | F4: Gold | G4: Deepali | H4: Gold chain repair | K4: 0.12986111 | L4: No | O4: WA ONLY | P4: Sir, Madam
A5: 45736.789 | B5: Uttam | C5: 9810007503 | D5: 1 | E5: 0.12986111 | F5: Diamond | G5: Deepali | H5: Repaire Diamond ring | K5: 0.13541667 | L5: Yes | M5: Already done | N5: Already done | O5: WA ONLY | P5: Sir
A6: 45736.79 | B6: Kritanjli | C6: 9873041853 | D6: 1 | E6: 0.16875 | F6: Antic | G6: Deepali | H6: Gems gold ring( pic the order no concern person) | I6: no concern person | J6: no concern person | K6: 0.17708333 | L6: Yes | M6: no concern person | N6: no concern person | O6: WA ONLY | P6: Sir
A7: 45736.791 | B7: Pragya | C7: 9910603300 | D7: 1 | E7: 0.29513889 | F7: Diamond | G7: Deepali | H7: Not sale any set because customer wont home and told which set he liked | K7: 0.34375 | L7: Yes | O7: WA ONLY | P7: Madam
A8: 45736.797 | B8: Raj karan | C8: 9560358448 | D8: 2 | E8: 0.19097222 | G8: Deepali | H8: Customer wants Pendent but process in order | K8: 0.21875 | L8: Yes | M8: Yes | N8: Not use | O8: WA ONLY | P8: Sir, Madam
A9: 45736.813 | B9: Ravi | C9: 8882584436 | D9: 1 | E9: 0.24652778 | F9: Gold | G9: Deepali | H9: Silver anklet | J9: Not interested | K9: 0.27152778 | L9: No | M9: Already done | N9: Already done | O9: WA ONLY | P9: Sir
A10: 45736.814 | B10: Sumit | C10: 9212327770 | D10: 1 | E10: 0.28472222 | F10: Antic | G10: Deepali | H10: Customer sel own gold coin 100 gm | K10: 0.29861111 | L10: Yes | O10: WA ONLY | P10: Sir
A11: 45736.815 | B11: Anu | C11: 9212674929 | D11: 1 | E11: 0.084027778 | F11: Gold | G11: Deepali | H11: 2 pair tops | K11: 0.14583333 | L11: Yes | M11: Yes | N11: Not use | O11: WA ONLY | P11: Sir, Madam
A12: 45736.815 | B12: Keshar | C12: 99999728283 | D12: 2 | E12: 0.19166667 | F12: Sntic | G12: Deepali | H12: Gold tops,mang tika | J12: Already done | K12: 0.27361111 | L12: Yes | M12: Yes | N12: Yes | O12: WA ONLY | P12: Sir, Madam
A13: 45734.75 | B13: Om parkash | C13: 9811023449 | D13: 1 | E13: 0.097222222 | F13: Gold | G13: Deepali | H13: Bangles | J13: Not interested | K13: 0.11597222 | L13: Yes | M13: Yes | N13: Not use | O13: CELLS | P13: Sir
A14: 45734.767 | B14: Sudhanshu | C14: 9610072943 | D14: 1 | E14: 0.10069444 | F14: Diamond | G14: Deepali | H14: Chain with solitaire pendent | K14: 0.14583333 | L14: Yes | M14: Yes | N14: Not usr | O14: WA ONLY | P14: Sir
A15: 45734.771 | B15: Mukul | C15: 7042183683 | D15: 2 | E15: 0.25625 | F15: Gold | G15: Deepali | H15: Not sale | I15: Customer want gold bar not available this itme | J15: No | K15: 0.27083333 | L15: No | M15: No | N15: No | O15: WA ONLY | P15: Sir
A16: 45734.774 | B16: Benuji | C16: 9810668596 | D16: 1 | E16: 0.51736111 | F16: Diamond | G16: Deepali | H16: CVD, tops, ring | J16: No | K16: 0.11458333 | L16: Yes | M16: Yes | N16: Not use insta | O16: WA ONLY, OWNER CONTACT ONLY | P16: Sir, Madam
A17: 45734.778 | B17: Shikha | C17: 8178148800 | D17: 3 | E17: 0.0625 | F17: Gold | G17: Deepali | H17: Gold ring | K17: 0.086805556 | L17: Yes | N17: Yes | O17: WA ONLY | P17: Sir, Madam
A18: 45734.781 | B18: Tushar | C18: 9953450909 | D18: 2 | E18: 0.25 | F18: Gold | G18: Sapna | H18: Gold gents ring | K18: 0.29861111 | L18: Yes | M18: Yes | N18: Yes | O18: WA ONLY, OWNER CONTACT ONLY | P18: Sir, Madam
A19: 45737.641 | B19: Parmod | C19: 9891143023 | D19: 2 | E19: 0.10416667 | F19: Diamond | G19: Preeti | I19: Discuss with family | J19: Discuss with family | K19: 0.13888889 | L19: Yes | M19: No after purchase | N19: No after purchase | O19: WA ONLY | P19: Sir, Madam
A20: 45737.645 | B20: Alifiya | C20: 7838408250 | D20: 6 | E20: 0.31111111 | F20: gold | G20: Sapna | I20: Customer not satisfied gold ring design | J20: Not interested | K20: 0.31736111 | L20: Yes | M20: No after purchase | N20: No after purchase | O20: WA ONLY | P20: Sir, Madam
A21: 45737.647 | B21: Ankush sharma | C21: 9817922929 | D21: 1 | E21: 0.082638889 | F21: Diamond | G21: Preeti | I21: Confirm diamond rate with kerot | J21: Not interested | K21: 0.084722222 | L21: Yes | M21: No | N21: No | O21: WA ONLY | P21: Sir
A22: 45737.647 | B22: Anita | C22: 8010046101 | D22: 2 | E22: 0.11666667 | F22: Antic | G22: Suman | I22: Done the payment | J22: Not interested | K22: 0.13541667 | L22: Yes | M22: Already done | N22: Already done | O22: WA ONLY | P22: Sir, Madam
A23: 45737.647 | B23: Rajeev gera | C23: 9990145453 | D23: 1 | E23: 0.12222222 | F23: Gold | G23: Sapna | H23: Antic gold set | J23: Not interested | K23: 0.20972222 | L23: Yes | M23: Already done | N23: Already done | O23: WA ONLY, OWNER CONTACT ONLY | P23: Sir, Madam
A24: 45737.649 | B24: Saloni | C24: 8287645704 | D24: 1 | E24: 0.14027778 | F24: Diamond | G24: Preeti | I24: Visit again with family | J24: Visit again with family | K24: 0.16319444 | L24: Yes | M24: After purchase | N24: After purchase | O24: WA ONLY | P24: Madam
A25: 45737.651 | B25: Monika | C25: 7300620421 | D25: 1 | E25: 0.05 | F25: Antic | G25: Suman | I25: Visit again | J25: Not interested | K25: 0.0625 | L25: Yes | M25: Already done | N25: Already done | O25: WA ONLY | P25: Madam
A26: 45737.652 | B26: Atoshi | C26: 8700173741 | D26: 1 | E26: 0.17986111 | F26: Antic | G26: Suman | I26: Payment done and oder | J26: Not interested | K26: 0.20694444 | L26: Yes | M26: Already done | N26: Already done | O26: WA ONLY | P26: Madam
A27: 45737.652 | B27: Naidu | C27: 9717611464 | D27: 2 | E27: 0.25 | F27: Antic | G27: Deepali | H27: Gold kids earing | J27: Not interested | K27: 0.30416667 | L27: Yes | M27: Yes | N27: Yes | O27: WA ONLY | P27: Sir, Madam
A28: 45737.653 | B28: Priyal | C28: 9910925269 | D28: 1 | E28: 0.29166667 | F28: Diamond | G28: Preeti | H28: Two breslet diamond | J28: Not interested | K28: 0.36319444 | L28: Yes | M28: Already done | N28: Already done | O28: WA ONLY | P28: Sir, Madam
A29: 45737.653 | B29: Dr. Mehta | C29: 9310857548 | D29: 1 | E29: 0.52708333 | F29: Diamond | G29: Preeti | I29: 2 diamond set approval | J29: Not interested | M29: Already done | N29: Already done | O29: WA ONLY | P29: Sir
A30: 45737.658 | B30: Shivani manchanda | C30: 9560341110 | D30: 1 | E30: 0.049305556 | F30: Antic | G30: Suman | I30: Pic the order | K30: 0.075 | L30: Yes | M30: Already done | N30: Already done | O30: WA ONLY | P30: Madam
A31: 45737.658 | B31: Bharti | C31: 9873833656 | D31: 1 | E31: 0.0625 | F31: Gold | G31: Sapna | H31: Gaems stone | J31: Not interested | K31: 0.071527778 | L31: Yes | M31: Already done | N31: Already done | O31: WA ONLY | P31: Madam
A32: 45737.658 | B32: P.d sharma | C32: 9971097482 | D32: 1 | E32: 0.092361111 | F32: Gold | G32: Sapna | I32: Customer not satisfied gold Bali making charges | J32: Not interested | K32: 0.095833333 | L32: Yes | M32: No | N32: No | O32: WA ONLY | P32: Sir, Madam
A33: 45737.66 | B33: Tahir | C33: 6205203880 | D33: 1 | E33: 0.092361111 | F33: Gold | G33: Sapna | H33: Gold chain | J33: Not interested | K33: 0.16805556 | L33: Yes | M33: Yes | N33: Yes | O33: WA ONLY | P33: Sir, Madam
A34: 45737.66 | B34: R.k tiwari | C34: 9555152166 | D34: 1 | E34: 0.14375 | F34: Gold | G34: Sapna | I34: Customer not satisfied with hold jhumki design | J34: Not interested | K34: 0.15972222 | L34: Yes | M34: No | N34: No | O34: WA ONLY | P34: Sir, Madam
A35: 45738.575 | B35: Gurman Singh | C35: 9899226225 | D35: 1 | E35: 0.10277778 | F35: Diamond | G35: Preeti | H35: Diamond pendent set | J35: Not interested | K35: 0.16041667 | L35: Yes | M35: Already done | N35: Already done | O35: WA ONLY | P35: Sir
A36: 45738.578 | B36: Mehek dhawan | C36: 9999678088 | D36: 2 | E36: 0.22916667 | F36: Antic | G36: Suman | I36: Customer discuss with family and visit again | J36: Not interested | K36: 0.26458333 | L36: Yes | M36: No | N36: No | O36: WA ONLY | P36: Sir, Madam
A37: 45738.611 | B37: Anil Choudhary | C37: 9811456708 | D37: 1 | E37: 0.29305556 | F37: Gold | G37: Sapna | I37: Visit again | J37: Visit again | K37: 0.29791667 | L37: Yes | M37: No | N37: No | O37: WA ONLY | P37: Sir, Madam
A38: 45738.615 | B38: Gurmeet | C38: 9971052404 | D38: 1 | E38: 0.14236111 | F38: Gold,diamond | G38: Sapna | H38: Silver ganesh and Laxmi murti | J38: Not interested | K38: 0.19097222 | L38: Yes | M38: Yes | N38: Not use | O38: WA ONLY | P38: Sir, Madam
A39: 45738.618 | B39: Shushil kumar | C39: 9971389387 | D39: 1 | E39: 0.17708333 | F39: Antic | G39: Suman | I39: Advance payment done | J39: Not interested | K39: 0.23333333 | L39: Yes | M39: Already done | N39: Already done | O39: WA ONLY | P39: Sir, Madam
A40: 45738.618 | B40: Shushil kumar | C40: 9971389387 | D40: 1 | E40: 0.17708333 | F40: Antic | G40: Suman | I40: Advance payment done | J40: Not interested | K40: 0.23333333 | L40: Yes | M40: Already done | N40: Already done | O40: WA ONLY | P40: Sir, Madam
A41: 45738.619 | B41: Atoshi | C41: 8700173741 | D41: 1 | E41: 0.25555556 | F41: Antic | G41: Suman | I41: Pic the order | J41: Not interested | K41: 0.25902778 | L41: Yes | M41: Already done | N41: Already done | O41: WA ONLY | P41: Sir, Madam
A42: 45738.62 | B42: Meeru | C42: 9871024292 | D42: 1 | E42: 0.18055556 | F42: Diamond, antic | G42: Sapna | H42: Antic pendent set | J42: Not interested | K42: 0.28680556 | L42: Yes | M42: Already done | N42: Already done | O42: WA ONLY | P42: Sir, Madam
A43: 45738.62 | B43: Dinesh | C43: 9873273593 | D43: 1 | E43: 0.25972222 | F43: Antic | G43: Suman | I43: Customer not satisfied with antic set price | J43: Not interested | K43: 0.29652778 | L43: No | M43: No | N43: No | O43: WA ONLY | P43: Sir, Madam
A44: 45738.699 | B44: Zeeshan | C44: 9310379264 | D44: 1 | E44: 0.28194444 | F44: Antic | G44: Suman | I44: Customer visit again | J44: Visit again | K44: 0.31875 | L44: Yes | M44: No | N44: No | O44: WA ONLY | P44: Sir, Madam
A45: 45738.7 | B45: Neha | C45: 7217786373 | D45: 2 | E45: 0.090277778 | F45: Gold | G45: Sapna | I45: Customer discuss with family and visit again | J45: No | K45: 0.1125 | L45: Yes | M45: No | N45: No | O45: WA ONLY | P45: Sir, Madam
A46: 45738.701 | B46: Neha | C46: 9910773855 | D46: 2 | E46: 0.095138889 | F46: Diamond | G46: Preeti | I46: Visit again | J46: No | K46: 0.095138889 | L46: Yes | M46: No | N46: No | O46: WA ONLY | P46: Sir, Madam
A47: 45738.702 | B47: Zeba | C47: 9369837260 | D47: 1 | E47: 0.10694444 | F47: Antic | G47: Suman | H47: Gold chain | J47: Not interested | K47: 0.13680556 | L47: Yes | M47: Yes | N47: No | O47: WA ONLY | P47: Sir, Madam
A48: 45738.703 | B48: Indu | C48: 9818110346 | D48: 1 | E48: 0.17777778 | F48: Diamond | G48: Preeti | H48: Stone | J48: Not interested | K48: 0.23958333 | L48: Yes | M48: Already done | N48: Already done | O48: WA ONLY | P48: Madam
A49: 45738.704 | B49: Ritu | C49: 9818802720 | D49: 1 | E49: 0.21458333 | F49: Diamond | G49: Deepali | I49: Pic the order | J49: Already done | K49: 0.29166667 | L49: Yes | M49: Already done | N49: Already done | O49: WA ONLY | P49: Sir, Madam
A50: 45738.704 | B50: Saurabh | C50: 9811755998 | D50: 5 | E50: 0.2375 | F50: Antic | G50: Deepali | H50: One diamond ring | J50: Not interested | K50: 0.30486111 | L50: Yes | M50: Already done | N50: Already done | O50: WA ONLY | P50: Sir, Madam
A51: 45738.706 | B51: Neha | C51: 9892203082 | D51: 6 | E51: 0.30694444 | F51: Gold | G51: Sapna | I51: Customer again visit | J51: Customer again visit | K51: 0.31527778 | L51: Yes | M51: No | N51: No | O51: WA ONLY | P51: Sir, Madam
A52: 45738.697 | B52: Priyal khatri | D52: 1 | E52: 0.08125 | F52: Antic | G52: Suman | I52: Pic the order and payment done | J52: Not interested | K52: 0.084027778 | L52: Yes | M52: Already done | N52: Already done | O52: WA ONLY | P52: Sir
A53: 45738.781 | B53: Sunny | C53: 9910278945 | D53: 1 | E53: 0.090277778 | F53: Gold | G53: Sapna | I53: Customer want labron diamond ring and visit again discuss with family | J53: Visit again | K53: 0.10416667 | L53: No | M53: No | N53: No | O53: WA ONLY | P53: Sir
A54: 45742.636 | B54: Sahil | C54: 8094884343 | D54: 1 | E54: 0.069444444 | F54: Diamond | G54: Preeti | I54: Visit again | J54: Visit again | K54: 0.075 | L54: Yes | M54: Already done | N54: Already done | O54: WA ONLY | P54: Sir
A55: 45742.638 | B55: Zeba | C55: 9369837260 | D55: 1 | E55: 0.25763889 | F55: Antic | G55: suman | H55: Gold earrings | J55: Not interested | K55: 0.28541667 | L55: Yes | M55: Already done | N55: Already done | O55: WA ONLY | P55: Sir, Madam
A56: 45742.638 | B56: Jagreet | C56: 9958166341 | D56: 1 | E56: 0.15694444 | F56: Antic | G56: suman | I56: Visit again with family | J56: Visit again | K56: 0.17986111 | L56: Yes | M56: No | N56: No | O56: WA ONLY | P56: Sir, Madam
A57: 45742.642 | B57: Nikita goyal | C57: 9811795829 | D57: Q | E57: 0.19444444 | F57: Diamond | G57: Deepali | I57: Pic the order | J57: Not interested | K57: 0.20694444 | L57: Yes | M57: Already done | N57: Already done | O57: WA ONLY | P57: Madam
A58: 45742.643 | B58: Atoshi | C58: 8700173741 | D58: 1 | E58: 0.049305556 | F58: Antic | G58: suman | I58: Pic the order | J58: Not interested | K58: 0.077777778 | L58: Yes | M58: Already done | N58: Already done | O58: WA ONLY | P58: Sir, Madam
A59: 45742.645 | B59: Meetu goyal | C59: 9560915533 | D59: Pic the order | E59: 0.072916667 | F59: Diamond | G59: Deepali | I59: Pic the order | K59: 0.19791667 | L59: Yes | M59: Already done | N59: Already done | O59: WA ONLY | P59: Madam
A60: 45742.646 | B60: Sudhanshu | C60: 9818311188 | D60: 1 | E60: 0.073611111 | F60: Antic | G60: suman | H60: Antic gold set | J60: Not interested | K60: 0.10416667 | L60: Yes | M60: No | N60: No | O60: WA ONLY | P60: Sir
A61: 45742.649 | B61: Nidhi | C61: 9810947581 | D61: 3 | E61: 0.13472222 | F61: Diamond | G61: Deepali | I61: Customer visit again | J61: Customer visit agsi | K61: 0.14444444 | L61: Yes | M61: No | N61: No | O61: WA ONLY | P61: Sir, Madam
A62: 45742.65 | B62: Manish | C62: 8130437059 | D62: 1 | E62: 0.125 | F62: Gold | G62: Sapna | I62: Adjust gold ring size | J62: Not interested | K62: 0.13541667 | L62: Yes | M62: No | N62: No | O62: WA ONLY | P62: Sir, Madam
A63: 45742.652 | B63: Gurendar | C63: 8587888357 | D63: 1 | E63: 0.23611111 | F63: Antic | G63: Deepali | I63: Customer visit again | J63: Customer visit again | K63: 0.26875 | L63: Yes | M63: No | N63: No | O63: WA ONLY | P63: Sir, Madam
A64: 45742.652 | B64: Laxshata | C64: 7827182727 | D64: 1 | E64: 0.52083333 | F64: Antic | G64: suman | H64: Gold ring,chain,earing,nose pin. | J64: Not interested | K64: 0.13958333 | L64: Yes | M64: Yes | N64: Yes | O64: WA ONLY | P64: Sir, Madam
A65: 45742.666 | B65: Shishir | C65: 9868723560 | D65: 1 | E65: 0.19652778 | F65: Gold | G65: Sapna | I65: Customer wants 3 gm gold ring but not satisfied with design | J65: No | K65: 0.20833333 | L65: No | M65: No | N65: No | O65: WA ONLY | P65: Sir
A66: 45742.667 | B66: Shagufta | C66: 7827399396 | D66: 3 | E66: 0.26666667 | F66: Gold | G66: Sapna | I66: Exchange gold | J66: No | K66: 0.27638889 | L66: Yes | M66: No | N66: No | O66: WA ONLY | P66: Sir, Madam
A67: 45746.665 | B67: Deepak | C67: 9899615881 | D67: 1 | E67: 0.52083333 | F67: Antic | G67: Deepali | H67: Pendent set,gold boli | J67: No | K67: 0.17222222 | L67: Yes | M67: Yes | N67: Yes | O67: WA ONLY | P67: Sir, Madam
A68: 45746.667 | B68: Umesh | C68: 9311580781 | D68: 1 | E68: 0.044444444 | F68: Gold | G68: Sapna | H68: Gold ring | J68: No | K68: 0.0625 | L68: Yes | M68: Yes | N68: No | O68: WA ONLY | P68: Sir
A69: 45746.668 | B69: Rahul malik | C69: 9818766685 | D69: 1 | E69: 0.083333333 | F69: Antic | G69: suman | I69: Pic the order | J69: No | K69: 0.10416667 | L69: Yes | M69: Already done | N69: Already done | O69: WA ONLY | P69: Sir, Madam
A70: 3/30/0205 16:06:00 | B70: Charu | C70: 9871089414 | D70: 1 | E70: 0.16666667 | F70: Antic c | G70: suman | I70: Pic the order | K70: 0.20833333 | L70: Yes | M70: Already done | N70: Already done | O70: WA ONLY | P70: Madam
A71: 45746.672 | B71: Sarita dilavri | C71: 6138828800 | D71: 3 | E71: 0.52083333 | F71: Diamond | G71: Deepali | H71: Diamond jewellery | J71: No | K71: 0.1875 | L71: Yes | M71: Already done | N71: Already done | O71: WA ONLY | P71: Sir, Madam
A72: 45746.674 | B72: Gulnaaz | C72: 9711686788 | D72: 2 | E72: 0.28611111 | F72: Gold | G72: Sapna | I72: Customer visit again | J72: No | K72: 0.29652778 | L72: No | M72: No | N72: No | O72: WA ONLY | P72: Sir, Madam
A73: 45746.674 | B73: Ajeet singh | C73: 9958481195 | D73: 1 | E73: 0.29027778 | F73: Antic | G73: suman | H73: Diamond ring | J73: No | K73: 0.32083333 | L73: Yes | M73: Yes | N73: Yes | O73: WA ONLY | P73: Sir, Madam
A74: 45746.676 | B74: Usha gupta | C74: 9650557706 | D74: 1 | E74: 0.063194444 | F74: Antic | G74: Deepali | I74: Customer visit again | J74: No | K74: 0.081944444 | L74: Yes | M74: No | N74: No | O74: WA ONLY | P74: Madam
A75: 45746.676 | B75: Nitin | D75: 1 | E75: 0.11458333 | F75: Antic | G75: suman | I75: Customer visit again | J75: No | K75: 0.13333333 | L75: Yes | M75: Already done | N75: Already done | O75: WA ONLY | P75: Sir
A76: 45746.677 | B76: Atoshi | C76: 8700173741 | D76: 1 | E76: 0.16666667 | F76: Gold | G76: Deepali | I76: Talk to sir | J76: Already done | K76: 0.18680556 | L76: Yes | M76: Already done | N76: Already done | O76: WA ONLY | P76: Madam
A77: 45746.678 | B77: Ritu | C77: 9625148818 | D77: 1 | E77: 0.16666667 | F77: Antic | G77: suman | H77: Bracelet | J77: No | K77: 0.19791667 | L77: Yes | M77: Already done | N77: Already done | O77: WA ONLY | P77: Didi
A78: 45746.688 | B78: Ajeet singh | C78: 9958481195 | D78: 1 | E78: 0.20833333 | F78: Antic | G78: suman | I78: Pic the order | J78: No | K78: 0.22569444 | L78: Yes | M78: Already done | N78: Already done | O78: WA ONLY | P78: Sir, Madam
A79: 45750.777 | B79: Bharti | C79: 9873833656 | D79: 1 | E79: 0.17708333 | F79: Gold | G79: Sapna | J79: Kitty concern | K79: 0.19097222 | L79: Yes | M79: Already done | N79: Already done | O79: WA ONLY | P79: Madam
A80: 45750.778 | B80: Sonam | C80: 9654311323 | D80: 3 | E80: 0.27430556 | F80: Diamond | G80: Deepali | H80: Diamond breslet | J80: No | K80: 0.32777778 | L80: Yes | M80: Yes | N80: Yes | O80: WA ONLY | P80: Sir, Madam
A81: 45750.778 | B81: Shabir | C81: 9419015579 | D81: 1 | E81: 0.25 | F81: Gold | G81: Sapna | I81: Customer not satisfied with gold ring design | J81: No | K81: 0.25972222 | L81: Yes | M81: No | N81: No | O81: WA ONLY | P81: Sir
A82: 45750.779 | B82: Pooja | C82: 9641078740 | D82: 1 | E82: 0.26805556 | F82: Antic | G82: suman | I82: Customer visit again | J82: No | K82: 0.27361111 | L82: Yes | M82: No | N82: No | O82: WA ONLY | P82: Sir, Madam
A83: 45750.779 | B83: Aditi | C83: 8448763272 | D83: 3 | E83: 0.52083333 | F83: Antic | G83: suman | I83: Customer discuss with family and visit again | J83: No | K83: 0.13194444 | L83: Yes | M83: No | N83: No | O83: CELLS | P83: Sir, Madam
A84: 45750.785 | B84: Saiyam | C84: 801080601 | D84: 1 | E84: 0.52847222 | F84: Diamond | G84: Deepali | H84: Diamond breslet | J84: No | K84: 0.079861111 | L84: Yes | M84: Already done | N84: Already done | O84: WA ONLY | P84: Sir, Madam
A85: 45750.786 | B85: Vishal | C85: 9873652585 | D85: 1 | E85: 0.055555556 | F85: Gold | G85: Sapna | I85: Visit again | J85: No | K85: 0.059027778 | L85: Yes | M85: No | N85: No | O85: WA ONLY | P85: Sir
A86: 45751.62 | B86: Chhotu gupta | C86: 9534107191 | D86: 1 | E86: 0.16875 | F86: Gold | G86: Sapna | H86: Diamond nose pin | J86: No | K86: 0.19097222 | L86: Yes | M86: Yes | N86: Not use | O86: WA ONLY | P86: Sir
A87: 45347.711 | B87: Gaurav | C87: 7906897981 | D87: 1 | E87: 0.125 | F87: Antic | G87: suman | H87: Antic gold set order | J87: No | K87: 0.19583333 | L87: Yes | M87: Yes | N87: Yes | O87: WA ONLY | P87: Sir, Madam
A88: 45751.622 | B88: Preeti | C88: 9818057450 | D88: 1 | E88: 0.047916667 | F88: Gold | G88: Deepali | I88: Customer not satisfied with design | J88: No | K88: 0.053472222 | L88: Yes | M88: No | N88: No | O88: WA ONLY | P88: Madam
A89: 45751.622 | B89: Vandita | C89: 7838194917 | D89: 1 | E89: 0.070138889 | F89: Diamond | G89: Deepali | I89: Customer visit again | J89: No | K89: 0.094444444 | L89: Yes | M89: No | N89: No | O89: WA ONLY | P89: Madam
A90: 45751.622 | B90: Kamla devi | C90: 8800315834 | D90: 1 | E90: 0.076388889 | F90: Antic | G90: suman | I90: Customer buy mnpc coin not satisfied with design | J90: No | K90: 0.0875 | L90: Yes | M90: No | N90: No | O90: WA ONLY | P90: Madam
A91: 45751.623 | B91: Nansi | C91: 9625811996 | D91: 1 | E91: 0.12430556 | F91: Gold | G91: Sapna | I91: Customer visit msrch | J91: No | K91: 0.13402778 | L91: Yes | M91: No | N91: No | O91: WA ONLY | P91: Madam
A92: 45751.625 | B92: Manoj | C92: 9212157824 | D92: 2 | E92: 0.12847222 | F92: Gold | G92: Sapna | H92: Gold chain order | J92: Yes | K92: 0.19444444 | L92: Yes | M92: Already done | N92: Already done | O92: WA ONLY | P92: Sir, Madam
A93: 45751.692 | B93: Anil kumar | C93: 8923711703 | D93: 2 | E93: 0.11805556 | F93: Diamond | G93: Preeti | I93: Customer discuss with family and visit again | J93: No | K93: 0.13194444 | L93: No | M93: No | N93: No | O93: WA ONLY | P93: Sir
A94: 45751.698 | B94: Sudeep | C94: 9813566322 | D94: 1 | E94: 0.53888889 | F94: Antic | G94: suman | I94: Customer discuss with family and visit again | J94: No | K94: 0.068055556 | L94: Yes | M94: No | N94: No | O94: WA ONLY | P94: Sir
A95: 45751.699 | B95: Rihan ali khan | C95: 9899070017 | D95: 3 | E95: 0.098611111 | F95: Gold | G95: Sapna | H95: Gold pendent, bali | J95: No | K95: 0.15208333 | L95: Yes | M95: Yes | N95: No | O95: WA ONLY | P95: Sir, Madam
A96: 45751.701 | B96: Mansoor | C96: 9810878387 | D96: 1 | E96: 0.22986111 | F96: Gold | G96: Sapna | I96: Customer visit again | J96: No | K96: 0.23263889 | L96: Yes | M96: No | N96: No | O96: WA ONLY | P96: Sir, Madam
A97: 45751.702 | B97: Priyanka mehta | C97: 9711100748 | D97: 2 | E97: 0.625 | F97: Plain Gold | G97: Sapna | H97: Gold mangl sutr | K97: 0.59861111 | L97: Yes | M97: Yes | N97: Yes | O97: WA ONLY, CALL | P97: Madam | Q97: No | R97: OLD
A98: 45751.702 | B98: Deepanshu goyal | C98: 7292019394 | D98: 1 | E98: 0.625 | F98: Plain Gold | G98: Sapna | I98: Pick up Order | K98: 0.62986111 | L98: Yes | M98: Already done | N98: Already done | O98: WA ONLY, CALL | P98: Madam | Q98: No | R98: OLD
A99: 45751.703 | B99: Jai kishan | C99: 9971162532 | D99: 2 | E99: 0.64722222 | F99: Plain Gold | G99: Sapna | H99: 2 ring gents, oder nose pic cvd | K99: 0.71319444 | L99: Yes | M99: Yes | N99: Yes | O99: WA ONLY, CALL | P99: Sir | Q99: No | R99: OLD
A100: 45751.703 | B100: Yogesh goyal | C100: 9371162532 | D100: 1 | E100: 0.64861111 | F100: Antique Gold | G100: suman | H100: Silver coin,gold chain | K100: 0.76041667 | L100: Yes | M100: Yes | N100: No | O100: WA ONLY, CALL | P100: Sir | Q100: No | R100: NEW WALK IN
...

Sheet Sales yes
A1: How many Days | B1: Message
A2: 0 | B2: Name ji, Wholeheartdly thank you for your trust and making a purchase today with us. We welcome you to Sun Sea Family, Your Wedding Jewellery Specialist. | C2: Thank You
A3: 8 | B3: This offer is between you and me | C3: Overview of Services - Highlight custom designs, repairs, and other services.
A4: 15 | C4: Feedback Request - Encourage feedback on their shopping experience.
A5: 22 | C5: Offer Announcement - Share a special offer for WhatsApp subscribers.
A6: 29 | C6: Loyalty Program Introduction - Invite clients to join your loyalty program.
A7: 36 | C7: Jewelry Care Tips - Educate clients on maintaining their jewelry.
A8: 43 | C8: Monthly Gold Rate Update - Keep clients informed about the market.
A9: 50 | C9: Styling Tips - Share advice on styling jewelry for different occasions.
A10: 57 | C10: Share a positive customer testimonial to build trust and credibility.
A11: 64 | C11: Highlight new arrivals or trending collections.
A12: 71 | C12: Introduce the Kitty Scheme - Encourage clients to enroll.
A13: 78 | C13: Special Promotion - Announce an exclusive discount or event for members.
A14: 85 | C14: Poll or Question - Engage clients with interactive content.
A15: 92 | C15: Behind-the-Scenes Look - Give insight into the jewelry-making process.
... A17: 106 | C17: Final Message - Recap of engagement, invite feedback, and encourage future store visits.
C18: Monthly Gold Rate Updates: First Monday of each month.
C19: Quarterly Newsletter: Include updates, offers, testimonials, and invitations to store events.

Sheet Sales no
A1: How many Days | B1: Message

Sheet Print
A1: S No | B1: {='FR1'!A1:P1} -> Timestamp | C1: Walk In Client Name | D1: Number | E1: No of People | F1: In Time | G1: Which Counter | H1: Attend By | I1: Items Seen | J1: If Not What were they looking for or why didn't they buy | K1: Kitty Explained/Give | L1: Out Time | M1: Gift Given | N1: Google Review Taken | O1: Insta Follow | P1: Communication | Q1: Relation | R1: Kitty Interested | S1: Client type | T1: Client type
A14: {=if(B14:B1013<>"",ROW(B14:B1013)-1,"")}

Sheet Sheet3

Sheet OUTPUT
A1: {=UNIQUE('FR1'!C:C)} -> Number | B1: FREQUENCY | C1: NAME | D1: TIME | E1: SALE STATUS
A2: 9811023449 | B2: =COUNTIF('FR1'!C:C, A2) -> 2 | C2: {=INDEX('FR1'!B:B, MATCH(A2, 'FR1'!C:C, 0))} -> Om parkash | D2: {=INDEX('FR1'!A:A, MATCH(A2, 'FR1'!C:C, 0))} -> 45284.59 | E2: {=IF(ISBLANK(INDEX('FR1'!H:H, MATCH(A2, 'FR1'!C:C, 0))), "LEAD OPEN", INDEX('FR1'!H:H, MATCH(A2, 'FR1'!C:C, 0)))} -> Bangles | F2: =IF(ISBLANK(INDEX(FR1!F2:R1000, MATCH(A2, FR1!C:C, 0), 1)), "No additional data", INDEX(FR1!F2:R1000, MATCH(A2, FR1!C:C, 0), 1)) // Adjust the range to cover your data -> #ERROR!
A3: 9610072943 | B3: =COUNTIF('FR1'!C:C, A3) -> 1 | C3: {=INDEX('FR1'!B:B, MATCH(A3, 'FR1'!C:C, 0))} -> Sudhanshu | D3: {=INDEX('FR1'!A:A, MATCH(A3, 'FR1'!C:C, 0))} -> 45284.654 | E3: {=IF(ISBLANK(INDEX('FR1'!H:H, MATCH(A3, 'FR1'!C:C, 0))), "LEAD OPEN", INDEX('FR1'!H:H, MATCH(A3, 'FR1'!C:C, 0)))} -> Chain with solitaire pendent
A4: 7042183683 | B4: =COUNTIF('FR1'!C:C, A4) -> 1 | C4: {=INDEX('FR1'!B:B, MATCH(A4, 'FR1'!C:C, 0))} -> Mukul | D4: {=INDEX('FR1'!A:A, MATCH(A4, 'FR1'!C:C, 0))} -> 45284.655 | E4: {=IF(ISBLANK(INDEX('FR1'!H:H, MATCH(A4, 'FR1'!C:C, 0))), "LEAD OPEN", INDEX('FR1'!H:H, MATCH(A4, 'FR1'!C:C, 0)))} -> Not sale
A5: 9810668596 | B5: =COUNTIF('FR1'!C:C, A5) -> 1 | C5: {=INDEX('FR1'!B:B, MATCH(A5, 'FR1'!C:C, 0))} -> Benuji | D5: {=INDEX('FR1'!A:A, MATCH(A5, 'FR1'!C:C, 0))} -> 45284.66 | E5: {=IF(ISBLANK(INDEX('FR1'!H:H, MATCH(A5, 'FR1'!C:C, 0))), "LEAD OPEN", INDEX('FR1'!H:H, MATCH(A5, 'FR1'!C:C, 0)))} -> CVD, tops, ring
A6: 8178148800 | B6: =COUNTIF('FR1'!C:C, A6) -> 3 | C6: {=INDEX('FR1'!B:B, MATCH(A6, 'FR1'!C:C, 0))} -> Shikha | D6: {=INDEX('FR1'!A:A, MATCH(A6, 'FR1'!C:C, 0))} -> 45284.662 | E6: {=IF(ISBLANK(INDEX('FR1'!H:H, MATCH(A6, 'FR1'!C:C, 0))), "LEAD OPEN", INDEX('FR1'!H:H, MATCH(A6, 'FR1'!C:C, 0)))} -> Gold ring
A7: 9953450909 | B7: =COUNTIF('FR1'!C:C, A7) -> 3 | C7: {=INDEX('FR1'!B:B, MATCH(A7, 'FR1'!C:C, 0))} -> Tushar | D7: {=INDEX('FR1'!A:A, MATCH(A7, 'FR1'!C:C, 0))} -> 45284.798 | E7: {=IF(ISBLANK(INDEX('FR1'!H:H, MATCH(A7, 'FR1'!C:C, 0))), "LEAD OPEN", INDEX('FR1'!H:H, MATCH(A7, 'FR1'!C:C, 0)))} -> Gold gents ring
A8: 8700173741 | B8: =COUNTIF('FR1'!C:C, A8) -> 11 | C8: {=INDEX('FR1'!B:B, MATCH(A8, 'FR1'!C:C, 0))} -> Atoshi | D8: {=INDEX('FR1'!A:A, MATCH(A8, 'FR1'!C:C, 0))} -> 45284.827 | E8: {=IF(ISBLANK(INDEX('FR1'!H:H, MATCH(A8, 'FR1'!C:C, 0))), "LEAD OPEN", INDEX('FR1'!H:H, MATCH(A8, 'FR1'!C:C, 0)))} -> Gold ring,penden
A9: 9311691012 | B9: =COUNTIF('FR1'!C:C, A9) -> 4 | C9: {=INDEX('FR1'!B:B, MATCH(A9, 'FR1'!C:C, 0))} -> Afsana begam | D9: {=INDEX('FR1'!A:A, MATCH(A9, 'FR1'!C:C, 0))} -> 45284.828 | E9: {=IF(ISBLANK(INDEX('FR1'!H:H, MATCH(A9, 'FR1'!C:C, 0))), "LEAD OPEN", INDEX('FR1'!H:H, MATCH(A9, 'FR1'!C:C, 0)))} -> Ringyes
A10: 9810222843 | B10: =COUNTIF('FR1'!C:C, A10) -> 1 | C10: {=INDEX('FR1'!B:B, MATCH(A10, 'FR1'!C:C, 0))} -> Sunita mehta | D10: {=INDEX('FR1'!A:A, MATCH(A10, 'FR1'!C:C, 0))} -> 45286.701 | E10: {=IF(ISBLANK(INDEX('FR1'!H:H, MATCH(A10, 'FR1'!C:C, 0))), "LEAD OPEN", INDEX('FR1'!H:H, MATCH(A10, 'FR1'!C:C, 0)))} -> Rapier Diamond ring
A11: 9821489150 | B11: =COUNTIF('FR1'!C:C, A11) -> 1 | C11: {=INDEX('FR1'!B:B, MATCH(A11, 'FR1'!C:C, 0))} -> Amit kumar | D11: {=INDEX('FR1'!A:A, MATCH(A11, 'FR1'!C:C, 0))} -> 45286.702 | E11: {=IF(ISBLANK(INDEX('FR1'!H:H, MATCH(A11, 'FR1'!C:C, 0))), "LEAD OPEN", INDEX('FR1'!H:H, MATCH(A11, 'FR1'!C:C, 0)))} -> Gold chain repair
A12: 9810007503 | B12: =COUNTIF('FR1'!C:C, A12) -> 2 | C12: {=INDEX('FR1'!B:B, MATCH(A12, 'FR1'!C:C, 0))} -> Uttam | D12: {=INDEX('FR1'!A:A, MATCH(A12, 'FR1'!C:C, 0))} -> 45286.703 | E12: {=IF(ISBLANK(INDEX('FR1'!H:H, MATCH(A12, 'FR1'!C:C, 0))), "LEAD OPEN", INDEX('FR1'!H:H, MATCH(A12, 'FR1'!C:C, 0)))} -> Repaire Diamond ring
A13: 9873041853 | B13: =COUNTIF('FR1'!C:C, A13) -> 5 | C13: {=INDEX('FR1'!B:B, MATCH(A13, 'FR1'!C:C, 0))} -> Kritanjli | D13: {=INDEX('FR1'!A:A, MATCH(A13, 'FR1'!C:C, 0))} -> 45286.706 | E13: {=IF(ISBLANK(INDEX('FR1'!H:H, MATCH(A13, 'FR1'!C:C, 0))), "LEAD OPEN", INDEX('FR1'!H:H, MATCH(A13, 'FR1'!C:C, 0)))} -> Gems gold ring( pic the order no concern person)
A14: 9910603300 | B14: =COUNTIF('FR1'!C:C, A14) -> 1 | C14: {=INDEX('FR1'!B:B, MATCH(A14, 'FR1'!C:C, 0))} -> Pragya | D14: {=INDEX('FR1'!A:A, MATCH(A14, 'FR1'!C:C, 0))} -> 45287.719 | E14: {=IF(ISBLANK(INDEX('FR1'!H:H, MATCH(A14, 'FR1'!C:C, 0))), "LEAD OPEN", INDEX('FR1'!H:H, MATCH(A14, 'FR1'!C:C, 0)))} -> Not sale any set because customer wont home and told which set he liked
... A52: 9868120901 | B52: =COUNTIF('FR1'!C:C, A52) -> 1 | C52: {=INDEX('FR1'!B:B, MATCH(A52, 'FR1'!C:C, 0))} -> Ritu Choudhary | D52: {=INDEX('FR1'!A:A, MATCH(A52, 'FR1'!C:C, 0))} -> 45298.76 | E52: {=IF(ISBLANK(INDEX('FR1'!H:H, MATCH(A52, 'FR1'!C:C, 0))), "LEAD OPEN", INDEX('FR1'!H:H, MATCH(A52, 'FR1'!C:C, 0)))} -> Gold chain
B53: =COUNTIF('FR1'!C:C, A53) -> 0 | C53: {=INDEX('FR1'!B:B, MATCH(A53, 'FR1'!C:C, 0))} -> #N/A | D53: {=INDEX('FR1'!A:A, MATCH(A53, 'FR1'!C:C, 0))} -> #N/A | E53: {=IF(ISBLANK(INDEX('FR1'!H:H, MATCH(A53, 'FR1'!C:C, 0))), "LEAD OPEN", INDEX('FR1'!H:H, MATCH(A53, 'FR1'!C:C, 0)))} -> #N/A
A54: 9525203641 | B54: =COUNTIF('FR1'!C:C, A54) -> 1 | C54: {=INDEX('FR1'!B:B, MATCH(A54, 'FR1'!C:C, 0))} -> MD salehin | D54: {=INDEX('FR1'!A:A, MATCH(A54, 'FR1'!C:C, 0))} -> 45298.765 | E54: {=IF(ISBLANK(INDEX('FR1'!H:H, MATCH(A54, 'FR1'!C:C, 0))), "LEAD OPEN", INDEX('FR1'!H:H, MATCH(A54, 'FR1'!C:C, 0)))} -> Gold ring
A55: 9999507907 | B55: =COUNTIF('FR1'!C:C, A55) -> 1 | C55: {=INDEX('FR1'!B:B, MATCH(A55, 'FR1'!C:C, 0))} -> Gorav | D55: {=INDEX('FR1'!A:A, MATCH(A55, 'FR1'!C:C, 0))} -> 45298.766 | E55: {=IF(ISBLANK(INDEX('FR1'!H:H, MATCH(A55, 'FR1'!C:C, 0))), "LEAD OPEN", INDEX('FR1'!H:H, MATCH(A55, 'FR1'!C:C, 0)))} -> LEAD OPEN
A56: 9643705979 | B56: =COUNTIF('FR1'!C:C, A56) -> 3 | C56: {=INDEX('FR1'!B:B, MATCH(A56, 'FR1'!C:C, 0))} -> Manjeet | D56: {=INDEX('FR1'!A:A, MATCH(A56, 'FR1'!C:C, 0))} -> 45298.774 | E56: {=IF(ISBLANK(INDEX('FR1'!H:H, MATCH(A56, 'FR1'!C:C, 0))), "LEAD OPEN", INDEX('FR1'!H:H, MATCH(A56, 'FR1'!C:C, 0)))} -> LEAD OPEN
A57: 9312229038 | B57: =COUNTIF('FR1'!C:C, A57) -> 1 | C57: {=INDEX('FR1'!B:B, MATCH(A57, 'FR1'!C:C, 0))} -> Neena | D57: {=INDEX('FR1'!A:A, MATCH(A57, 'FR1'!C:C, 0))} -> 45298.803 | E57: {=IF(ISBLANK(INDEX('FR1'!H:H, MATCH(A57, 'FR1'!C:C, 0))), "LEAD OPEN", INDEX('FR1'!H:H, MATCH(A57, 'FR1'!C:C, 0)))} -> Gokd pendent
A58: 9886328522 | B58: =COUNTIF('FR1'!C:C, A58) -> 1 | C58: {=INDEX('FR1'!B:B, MATCH(A58, 'FR1'!C:C, 0))} -> Ina | D58: {=INDEX('FR1'!A:A, MATCH(A58, 'FR1'!C:C, 0))} -> 45298.822 | E58: {=IF(ISBLANK(INDEX('FR1'!H:H, MATCH(A58, 'FR1'!C:C, 0))), "LEAD OPEN", INDEX('FR1'!H:H, MATCH(A58, 'FR1'!C:C, 0)))} -> Ina
A59: 9654141505 | B59: =COUNTIF('FR1'!C:C, A59) -> 4 | C59: {=INDEX('FR1'!B:B, MATCH(A59, 'FR1'!C:C, 0))} -> Sagar | D59: {=INDEX('FR1'!A:A, MATCH(A59, 'FR1'!C:C, 0))} -> 45298.825 | E59: {=IF(ISBLANK(INDEX('FR1'!H:H, MATCH(A59, 'FR1'!C:C, 0))), "LEAD OPEN", INDEX('FR1'!H:H, MATCH(A59, 'FR1'!C:C, 0)))} -> LEAD OPEN
A60: 9818802702 | B60: =COUNTIF('FR1'!C:C, A60) -> 1 | C60: {=INDEX('FR1'!B:B, MATCH(A60, 'FR1'!C:C, 0))} -> Ritu rathi | D60: {=INDEX('FR1'!A:A, MATCH(A60, 'FR1'!C:C, 0))} -> 45300.739 | E60: {=IF(ISBLANK(INDEX('FR1'!H:H, MATCH(A60, 'FR1'!C:C, 0))), "LEAD OPEN", INDEX('FR1'!H:H, MATCH(A60, 'FR1'!C:C, 0)))} -> Gold tops
A61: 9560341110 | B61: =COUNTIF('FR1'!C:C, A61) -> 2 | C61: {=INDEX('FR1'!B:B, MATCH(A61, 'FR1'!C:C, 0))} -> Shivani | D61: {=INDEX('FR1'!A:A, MATCH(A61, 'FR1'!C:C, 0))} -> 45300.74 | E61: {=IF(ISBLANK(INDEX('FR1'!H:H, MATCH(A61, 'FR1'!C:C, 0))), "LEAD OPEN", INDEX('FR1'!H:H, MATCH(A61, 'FR1'!C:C, 0)))} -> LEAD OPEN
A62: 7021020509 | B62: =COUNTIF('FR1'!C:C, A62) -> 1 | C62: {=INDEX('FR1'!B:B, MATCH(A62, 'FR1'!C:C, 0))} -> Khushbu vijay | D62: {=INDEX('FR1'!A:A, MATCH(A62, 'FR1'!C:C, 0))} -> 45300.741 | E62: {=IF(ISBLANK(INDEX('FR1'!H:H, MATCH(A62, 'FR1'!C:C, 0))), "LEAD OPEN", INDEX('FR1'!H:H, MATCH(A62, 'FR1'!C:C, 0)))} -> LEAD OPEN
A63: 9711428669 | B63: =COUNTIF('FR1'!C:C, A63) -> 1 | C63: {=INDEX('FR1'!B:B, MATCH(A63, 'FR1'!C:C, 0))} -> Rakesh ravi | D63: {=INDEX('FR1'!A:A, MATCH(A63, 'FR1'!C:C, 0))} -> 45301.759 | E63: {=IF(ISBLANK(INDEX('FR1'!H:H, MATCH(A63, 'FR1'!C:C, 0))), "LEAD OPEN", INDEX('FR1'!H:H, MATCH(A63, 'FR1'!C:C, 0)))} -> Silver god
A64: 488017818 | B64: =COUNTIF('FR1'!C:C, A64) -> 1 | C64: {=INDEX('FR1'!B:B, MATCH(A64, 'FR1'!C:C, 0))} -> Shiba | D64: {=INDEX('FR1'!A:A, MATCH(A64, 'FR1'!C:C, 0))} -> 45301.761 | E64: {=IF(ISBLANK(INDEX('FR1'!H:H, MATCH(A64, 'FR1'!C:C, 0))), "LEAD OPEN", INDEX('FR1'!H:H, MATCH(A64, 'FR1'!C:C, 0)))} -> LEAD OPEN
A65: 9743705979 | B65: =COUNTIF('FR1'!C:C, A65) -> 1 | C65: {=INDEX('FR1'!B:B, MATCH(A65, 'FR1'!C:C, 0))} -> Manjeet | D65: {=INDEX('FR1'!A:A, MATCH(A65, 'FR1'!C:C, 0))} -> 45301.762 | E65: {=IF(ISBLANK(INDEX('FR1'!H:H, MATCH(A65, 'FR1'!C:C, 0))), "LEAD OPEN", INDEX('FR1'!H:H, MATCH(A65, 'FR1'!C:C, 0)))} -> Antic gold set, silver payal
... A67: 9810068111 | B67: =COUNTIF('FR1'!C:C, A67) -> 1 | C67: {=INDEX('FR1'!B:B, MATCH(A67, 'FR1'!C:C, 0))} -> Pc sharma | D67: {=INDEX('FR1'!A:A, MATCH(A67, 'FR1'!C:C, 0))} -> 45302.775 | E67: {=IF(ISBLANK(INDEX('FR1'!H:H, MATCH(A67, 'FR1'!C:C, 0))), "LEAD OPEN", INDEX('FR1'!H:H, MATCH(A67, 'FR1'!C:C, 0)))} -> Chain with diamond pendant
A68: 61+488017818 | B68: =COUNTIF('FR1'!C:C, A68) -> 1 | C68: {=INDEX('FR1'!B:B, MATCH(A68, 'FR1'!C:C, 0))} -> Shiba | D68: {=INDEX('FR1'!A:A, MATCH(A68, 'FR1'!C:C, 0))} -> 45302.776 | E68: {=IF(ISBLANK(INDEX('FR1'!H:H, MATCH(A68, 'FR1'!C:C, 0))), "LEAD OPEN", INDEX('FR1'!H:H, MATCH(A68, 'FR1'!C:C, 0)))} -> LEAD OPEN
A69: 9899222680 | B69: =COUNTIF('FR1'!C:C, A69) -> 1 | C69: {=INDEX('FR1'!B:B, MATCH(A69, 'FR1'!C:C, 0))} -> Sumit | D69: {=INDEX('FR1'!A:A, MATCH(A69, 'FR1'!C:C, 0))} -> 45302.777 | E69: {=IF(ISBLANK(INDEX('FR1'!H:H, MATCH(A69, 'FR1'!C:C, 0))), "LEAD OPEN", INDEX('FR1'!H:H, MATCH(A69, 'FR1'!C:C, 0)))} -> LEAD OPEN
A70: 0911019947 | B70: =COUNTIF('FR1'!C:C, A70) -> 1 | C70: {=INDEX('FR1'!B:B, MATCH(A70, 'FR1'!C:C, 0))} -> Vabhav garg | D70: {=INDEX('FR1'!A:A, MATCH(A70, 'FR1'!C:C, 0))} -> 45302.807 | E70: {=IF(ISBLANK(INDEX('FR1'!H:H, MATCH(A70, 'FR1'!C:C, 0))), "LEAD OPEN", INDEX('FR1'!H:H, MATCH(A70, 'FR1'!C:C, 0)))} -> LEAD OPEN
A71: 9711216574 | B71: =COUNTIF('FR1'!C:C, A71) -> 1 | C71: {=INDEX('FR1'!B:B, MATCH(A71, 'FR1'!C:C, 0))} -> Rajni | D71: {=INDEX('FR1'!A:A, MATCH(A71, 'FR1'!C:C, 0))} -> 45302.808 | E71: {=IF(ISBLANK(INDEX('FR1'!H:H, MATCH(A71, 'FR1'!C:C, 0))), "LEAD OPEN", INDEX('FR1'!H:H, MATCH(A71, 'FR1'!C:C, 0)))} -> LEAD OPEN
A72: 8010046101 | B72: =COUNTIF('FR1'!C:C, A72) -> 3 | C72: {=INDEX('FR1'!B:B, MATCH(A72, 'FR1'!C:C, 0))} -> Anita kapoor | D72: {=INDEX('FR1'!A:A, MATCH(A72, 'FR1'!C:C, 0))} -> 45303.772 | E72: {=IF(ISBLANK(INDEX('FR1'!H:H, MATCH(A72, 'FR1'!C:C, 0))), "LEAD OPEN", INDEX('FR1'!H:H, MATCH(A72, 'FR1'!C:C, 0)))} -> LEAD OPEN
A73: 9780560701 | B73: =COUNTIF('FR1'!C:C, A73) -> 1 | C73: {=INDEX('FR1'!B:B, MATCH(A73, 'FR1'!C:C, 0))} -> Hina | D73: {=INDEX('FR1'!A:A, MATCH(A73, 'FR1'!C:C, 0))} -> 45304.747 | E73: {=IF(ISBLANK(INDEX('FR1'!H:H, MATCH(A73, 'FR1'!C:C, 0))), "LEAD OPEN", INDEX('FR1'!H:H, MATCH(A73, 'FR1'!C:C, 0)))} -> LEAD OPEN
A74: 8700909391 | B74: =COUNTIF('FR1'!C:C, A74) -> 1 | C74: {=INDEX('FR1'!B:B, MATCH(A74, 'FR1'!C:C, 0))} -> Poonam | D74: {=INDEX('FR1'!A:A, MATCH(A74, 'FR1'!C:C, 0))} -> 45304.748 | E74: {=IF(ISBLANK(INDEX('FR1'!H:H, MATCH(A74, 'FR1'!C:C, 0))), "LEAD OPEN", INDEX('FR1'!H:H, MATCH(A74, 'FR1'!C:C, 0)))} -> Gold bali
A75: 8860036737 | B75: =COUNTIF('FR1'!C:C, A75) -> 1 | C75: {=INDEX('FR1'!B:B, MATCH(A75, 'FR1'!C:C, 0))} -> Kavita | D75: {=INDEX('FR1'!A:A, MATCH(A75, 'FR1'!C:C, 0))} -> 45304.749 | E75: {=IF(ISBLANK(INDEX('FR1'!H:H, MATCH(A75, 'FR1'!C:C, 0))), "LEAD OPEN", INDEX('FR1'!H:H, MATCH(A75, 'FR1'!C:C, 0)))} -> LEAD OPEN
A76: 7385216713 | B76: =COUNTIF('FR1'!C:C, A76) -> 1 | C76: {=INDEX('FR1'!B:B, MATCH(A76, 'FR1'!C:C, 0))} -> Umera | D76: {=INDEX('FR1'!A:A, MATCH(A76, 'FR1'!C:C, 0))} -> 45305.752 | E76: {=IF(ISBLANK(INDEX('FR1'!H:H, MATCH(A76, 'FR1'!C:C, 0))), "LEAD OPEN", INDEX('FR1'!H:H, MATCH(A76, 'FR1'!C:C, 0)))} -> LEAD OPEN
A77: 9810337136 | B77: =COUNTIF('FR1'!C:C, A77) -> 1 | C77: {=INDEX('FR1'!B:B, MATCH(A77, 'FR1'!C:C, 0))} -> Gagan | D77: {=INDEX('FR1'!A:A, MATCH(A77, 'FR1'!C:C, 0))} -> 45305.753 | E77: {=IF(ISBLANK(INDEX('FR1'!H:H, MATCH(A77, 'FR1'!C:C, 0))), "LEAD OPEN", INDEX('FR1'!H:H, MATCH(A77, 'FR1'!C:C, 0)))} -> LEAD OPEN
A78: 9899442938 | B78: =COUNTIF('FR1'!C:C, A78) -> 1 | C78: {=INDEX('FR1'!B:B, MATCH(A78, 'FR1'!C:C, 0))} -> Sanjay | D78: {=INDEX('FR1'!A:A, MATCH(A78, 'FR1'!C:C, 0))} -> 45305.754 | E78: {=IF(ISBLANK(INDEX('FR1'!H:H, MATCH(A78, 'FR1'!C:C, 0))), "LEAD OPEN", INDEX('FR1'!H:H, MATCH(A78, 'FR1'!C:C, 0)))} -> Gold chain
A79: 981144932 | B79: =COUNTIF('FR1'!C:C, A79) -> 1 | C79: {=INDEX('FR1'!B:B, MATCH(A79, 'FR1'!C:C, 0))} -> Rahul | D79: {=INDEX('FR1'!A:A, MATCH(A79, 'FR1'!C:C, 0))} -> 45305.755 | E79: {=IF(ISBLANK(INDEX('FR1'!H:H, MATCH(A79, 'FR1'!C:C, 0))), "LEAD OPEN", INDEX('FR1'!H:H, MATCH(A79, 'FR1'!C:C, 0)))} -> LEAD OPEN
A80: 9811448932 | B80: =COUNTIF('FR1'!C:C, A80) -> 1 | C80: {=INDEX('FR1'!B:B, MATCH(A80, 'FR1'!C:C, 0))} -> Rahul | D80: {=INDEX('FR1'!A:A, MATCH(A80, 'FR1'!C:C, 0))} -> 45305.814 | E80: {=IF(ISBLANK(INDEX('FR1'!H:H, MATCH(A80, 'FR1'!C:C, 0))), "LEAD OPEN", INDEX('FR1'!H:H, MATCH(A80, 'FR1'!C:C, 0)))} -> LEAD OPEN
A81: 9810857727 | B81: =COUNTIF('FR1'!C:C, A81) -> 2 | C81: {=INDEX('FR1'!B:B, MATCH(A81, 'FR1'!C:C, 0))} -> Aanad | D81: {=INDEX('FR1'!A:A, MATCH(A81, 'FR1'!C:C, 0))} -> 45305.815 | E81: {=IF(ISBLANK(INDEX('FR1'!H:H, MATCH(A81, 'FR1'!C:C, 0))), "LEAD OPEN", INDEX('FR1'!H:H, MATCH(A81, 'FR1'!C:C, 0)))} -> LEAD OPEN
A82: 9999446004 | B82: =COUNTIF('FR1'!C:C, A82) -> 1 | C82: {=INDEX('FR1'!B:B, MATCH(A82, 'FR1'!C:C, 0))} -> Hardeep | D82: {=INDEX('FR1'!A:A, MATCH(A82, 'FR1'!C:C, 0))} -> 45307.762 | E82: {=IF(ISBLANK(INDEX('FR1'!H:H, MATCH(A82, 'FR1'!C:C, 0))), "LEAD OPEN", INDEX('FR1'!H:H, MATCH(A82, 'FR1'!C:C, 0)))} -> LEAD OPEN
A83: 9319319976 | B83: =COUNTIF('FR1'!C:C, A83) -> 1 | C83: {=INDEX('FR1'!B:B, MATCH(A83, 'FR1'!C:C, 0))} -> Annu | D83: {=INDEX('FR1'!A:A, MATCH(A83, 'FR1'!C:C, 0))} -> 45308.755 | E83: {=IF(ISBLANK(INDEX('FR1'!H:H, MATCH(A83, 'FR1'!C:C, 0))), "LEAD OPEN", INDEX('FR1'!H:H, MATCH(A83, 'FR1'!C:C, 0)))} -> LEAD OPEN
A84: +38592246190 | B84: =COUNTIF('FR1'!C:C, A84) -> 1 | C84: {=INDEX('FR1'!B:B, MATCH(A84, 'FR1'!C:C, 0))} -> Neven cutuc | D84: {=INDEX('FR1'!A:A, MATCH(A84, 'FR1'!C:C, 0))} -> 45308.778 | E84: {=IF(ISBLANK(INDEX('FR1'!H:H, MATCH(A84, 'FR1'!C:C, 0))), "LEAD OPEN", INDEX('FR1'!H:H, MATCH(A84, 'FR1'!C:C, 0)))} -> LEAD OPEN
A85: 9820731234 | B85: =COUNTIF('FR1'!C:C, A85) -> 1 | C85: {=INDEX('FR1'!B:B, MATCH(A85, 'FR1'!C:C, 0))} -> Renu manchanda | D85: {=INDEX('FR1'!A:A, MATCH(A85, 'FR1'!C:C, 0))} -> 45308.805 | E85: {=IF(ISBLANK(INDEX('FR1'!H:H, MATCH(A85, 'FR1'!C:C, 0))), "LEAD OPEN", INDEX('FR1'!H:H, MATCH(A85, 'FR1'!C:C, 0)))} -> LEAD OPEN
A86: 9971989789 | B86: =COUNTIF('FR1'!C:C, A86) -> 1 | C86: {=INDEX('FR1'!B:B, MATCH(A86, 'FR1'!C:C, 0))} -> Sunal | D86: {=INDEX('FR1'!A:A, MATCH(A86, 'FR1'!C:C, 0))} -> 45309.784 | E86: {=IF(ISBLANK(INDEX('FR1'!H:H, MATCH(A86, 'FR1'!C:C, 0))), "LEAD OPEN", INDEX('FR1'!H:H, MATCH(A86, 'FR1'!C:C, 0)))} -> LEAD OPEN
A87: +385922462190 | B87: =COUNTIF('FR1'!C:C, A87) -> 1 | C87: {=INDEX('FR1'!B:B, MATCH(A87, 'FR1'!C:C, 0))} -> Neven | D87: {=INDEX('FR1'!A:A, MATCH(A87, 'FR1'!C:C, 0))} -> 45309.786 | E87: {=IF(ISBLANK(INDEX('FR1'!H:H, MATCH(A87, 'FR1'!C:C, 0))), "LEAD OPEN", INDEX('FR1'!H:H, MATCH(A87, 'FR1'!C:C, 0)))} -> LEAD OPEN
A88: 9560915533 | B88: =COUNTIF('FR1'!C:C, A88) -> 3 | C88: {=INDEX('FR1'!B:B, MATCH(A88, 'FR1'!C:C, 0))} -> Meetu | D88: {=INDEX('FR1'!A:A, MATCH(A88, 'FR1'!C:C, 0))} -> 45310.786 | E88: {=IF(ISBLANK(INDEX('FR1'!H:H, MATCH(A88, 'FR1'!C:C, 0))), "LEAD OPEN", INDEX('FR1'!H:H, MATCH(A88, 'FR1'!C:C, 0)))} -> LEAD OPEN
A89: 52531720 | B89: =COUNTIF('FR1'!C:C, A89) -> 1 | C89: {=INDEX('FR1'!B:B, MATCH(A89, 'FR1'!C:C, 0))} -> Sabera | D89: {=INDEX('FR1'!A:A, MATCH(A89, 'FR1'!C:C, 0))} -> 45310.805 | E89: {=IF(ISBLANK(INDEX('FR1'!H:H, MATCH(A89, 'FR1'!C:C, 0))), "LEAD OPEN", INDEX('FR1'!H:H, MATCH(A89, 'FR1'!C:C, 0)))} -> Gold bangles,gold chain
A90: 8218058775 | B90: =COUNTIF('FR1'!C:C, A90) -> 1 | C90: {=INDEX('FR1'!B:B, MATCH(A90, 'FR1'!C:C, 0))} -> Deepshi | D90: {=INDEX('FR1'!A:A, MATCH(A90, 'FR1'!C:C, 0))} -> 45311.766 | E90: {=IF(ISBLANK(INDEX('FR1'!H:H, MATCH(A90, 'FR1'!C:C, 0))), "LEAD OPEN", INDEX('FR1'!H:H, MATCH(A90, 'FR1'!C:C, 0)))} -> Silver payal,bichhue.
A91: 9891143023 | B91: =COUNTIF('FR1'!C:C, A91) -> 1 | C91: {=INDEX('FR1'!B:B, MATCH(A91, 'FR1'!C:C, 0))} -> Parmod | D91: {=INDEX('FR1'!A:A, MATCH(A91, 'FR1'!C:C, 0))} -> 45312.793 | E91: {=IF(ISBLANK(INDEX('FR1'!H:H, MATCH(A91, 'FR1'!C:C, 0))), "LEAD OPEN", INDEX('FR1'!H:H, MATCH(A91, 'FR1'!C:C, 0)))} -> LEAD OPEN
A92: 8375933947 | B92: =COUNTIF('FR1'!C:C, A92) -> 4 | C92: {=INDEX('FR1'!B:B, MATCH(A92, 'FR1'!C:C, 0))} -> Pargati | D92: {=INDEX('FR1'!A:A, MATCH(A92, 'FR1'!C:C, 0))} -> 45312.794 | E92: {=IF(ISBLANK(INDEX('FR1'!H:H, MATCH(A92, 'FR1'!C:C, 0))), "LEAD OPEN", INDEX('FR1'!H:H, MATCH(A92, 'FR1'!C:C, 0)))} -> LEAD OPEN
A93: 7838408250 | B93: =COUNTIF('FR1'!C:C, A93) -> 1 | C93: {=INDEX('FR1'!B:B, MATCH(A93, 'FR1'!C:C, 0))} -> Alifiya | D93: {=INDEX('FR1'!A:A, MATCH(A93, 'FR1'!C:C, 0))} -> 45312.817 | E93: {=IF(ISBLANK(INDEX('FR1'!H:H, MATCH(A93, 'FR1'!C:C, 0))), "LEAD OPEN", INDEX('FR1'!H:H, MATCH(A93, 'FR1'!C:C, 0)))} -> LEAD OPEN
A94: 9817922929 | B94: =COUNTIF('FR1'!C:C, A94) -> 1 | C94: {=INDEX('FR1'!B:B, MATCH(A94, 'FR1'!C:C, 0))} -> Ankush sharma | D94: {=INDEX('FR1'!A:A, MATCH(A94, 'FR1'!C:C, 0))} -> 45314.748 | E94: {=IF(ISBLANK(INDEX('FR1'!H:H, MATCH(A94, 'FR1'!C:C, 0))), "LEAD OPEN", INDEX('FR1'!H:H, MATCH(A94, 'FR1'!C:C, 0)))} -> LEAD OPEN
A95: 9990145453 | B95: =COUNTIF('FR1'!C:C, A95) -> 2 | C95: {=INDEX('FR1'!B:B, MATCH(A95, 'FR1'!C:C, 0))} -> Rajeev gera | D95: {=INDEX('FR1'!A:A, MATCH(A95, 'FR1'!C:C, 0))} -> 45314.75 | E95: {=IF(ISBLANK(INDEX('FR1'!H:H, MATCH(A95, 'FR1'!C:C, 0))), "LEAD OPEN", INDEX('FR1'!H:H, MATCH(A95, 'FR1'!C:C, 0)))} -> Antic gold set
A96: 8287645704 | B96: =COUNTIF('FR1'!C:C, A96) -> 1 | C96: {=INDEX('FR1'!B:B, MATCH(A96, 'FR1'!C:C, 0))} -> Saloni | D96: {=INDEX('FR1'!A:A, MATCH(A96, 'FR1'!C:C, 0))} -> 45314.755 | E96: {=IF(ISBLANK(INDEX('FR1'!H:H, MATCH(A96, 'FR1'!C:C, 0))), "LEAD OPEN", INDEX('FR1'!H:H, MATCH(A96, 'FR1'!C:C, 0)))} -> LEAD OPEN
A97: +23052526697 | B97: =COUNTIF('FR1'!C:C, A97) -> 2 | C97: {=INDEX('FR1'!B:B, MATCH(A97, 'FR1'!C:C, 0))} -> Anjli | D97: {=INDEX('FR1'!A:A, MATCH(A97, 'FR1'!C:C, 0))} -> 45314.758 | E97: {=IF(ISBLANK(INDEX('FR1'!H:H, MATCH(A97, 'FR1'!C:C, 0))), "LEAD OPEN", INDEX('FR1'!H:H, MATCH(A97, 'FR1'!C:C, 0)))} -> LEAD OPEN
A98: 7300620421 | B98: =COUNTIF('FR1'!C:C, A98) -> 2 | C98: {=INDEX('FR1'!B:B, MATCH(A98, 'FR1'!C:C, 0))} -> Monika | D98: {=INDEX('FR1'!A:A, MATCH(A98, 'FR1'!C:C, 0))} -> 45319.721 | E98: {=IF(ISBLANK(INDEX('FR1'!H:H, MATCH(A98, 'FR1'!C:C, 0))), "LEAD OPEN", INDEX('FR1'!H:H, MATCH(A98, 'FR1'!C:C, 0)))} -> LEAD OPEN
A99: 9717611464 | B99: =COUNTIF('FR1'!C:C, A99) -> 1 | C99: {=INDEX('FR1'!B:B, MATCH(A99, 'FR1'!C:C, 0))} -> Naidu | D99: {=INDEX('FR1'!A:A, MATCH(A99, 'FR1'!C:C, 0))} -> 45319.723 | E99: {=IF(ISBLANK(INDEX('FR1'!H:H, MATCH(A99, 'FR1'!C:C, 0))), "LEAD OPEN", INDEX('FR1'!H:H, MATCH(A99, 'FR1'!C:C, 0)))} -> Gold kids earing
A100: 9910925269 | B100: =COUNTIF('FR1'!C:C, A100) -> 2 | C100: {=INDEX('FR1'!B:B, MATCH(A100, 'FR1'!C:C, 0))} -> Priyal | D100: {=INDEX('FR1'!A:A, MATCH(A100, 'FR1'!C:C, 0))} -> 45319.724 | E100: {=IF(ISBLANK(INDEX('FR1'!H:H, MATCH(A100, 'FR1'!C:C, 0))), "LEAD OPEN", INDEX('FR1'!H:H, MATCH(A100, 'FR1'!C:C, 0)))} -> Two breslet diamond
A101: 9310857548 | B101: =COUNTIF('FR1'!C:C, A101) -> 1 | C101: {=INDEX('FR1'!B:B, MATCH(A101, 'FR1'!C:C, 0))} -> Dr. Mehta | D101: {=INDEX('FR1'!A:A, MATCH(A101, 'FR1'!C:C, 0))} -> 45319.725 | E101: {=IF(ISBLANK(INDEX('FR1'!H:H, MATCH(A101, 'FR1'!C:C, 0))), "LEAD OPEN", INDEX('FR1'!H:H, MATCH(A101, 'FR1'!C:C, 0)))} -> LEAD OPEN
A102: 9873833656 | B102: =COUNTIF('FR1'!C:C, A102) -> 4 | C102: {=INDEX('FR1'!B:B, MATCH(A102, 'FR1'!C:C, 0))} -> Bharti | D102: {=INDEX('FR1'!A:A, MATCH(A102, 'FR1'!C:C, 0))} -> 45319.728 | E102: {=IF(ISBLANK(INDEX('FR1'!H:H, MATCH(A102, 'FR1'!C:C, 0))), "LEAD OPEN", INDEX('FR1'!H:H, MATCH(A102, 'FR1'!C:C, 0)))} -> Gaems stone
A103: 9971097482 | B103: =COUNTIF('FR1'!C:C, A103) -> 1 | C103: {=INDEX('FR1'!B:B, MATCH(A103, 'FR1'!C:C, 0))} -> P.d sharma | D103: {=INDEX('FR1'!A:A, MATCH(A103, 'FR1'!C:C, 0))} -> 45319.73 | E103: {=IF(ISBLANK(INDEX('FR1'!H:H, MATCH(A103, 'FR1'!C:C, 0))), "LEAD OPEN", INDEX('FR1'!H:H, MATCH(A103, 'FR1'!C:C, 0)))} -> LEAD OPEN
A104: 6205203880 | B104: =COUNTIF('FR1'!C:C, A104) -> 1 | C104: {=INDEX('FR1'!B:B, MATCH(A104, 'FR1'!C:C, 0))} -> Tahir | D104: {=INDEX('FR1'!A:A, MATCH(A104, 'FR1'!C:C, 0))} -> 45319.731 | E104: {=IF(ISBLANK(INDEX('FR1'!H:H, MATCH(A104, 'FR1'!C:C, 0))), "LEAD OPEN", INDEX('FR1'!H:H, MATCH(A104, 'FR1'!C:C, 0)))} -> Gold chain
A105: 9555152166 | B105: =COUNTIF('FR1'!C:C, A105) -> 2 | C105: {=INDEX('FR1'!B:B, MATCH(A105, 'FR1'!C:C, 0))} -> R.k tiwari | D105: {=INDEX('FR1'!A:A, MATCH(A105, 'FR1'!C:C, 0))} -> 45319.732 | E105: {=IF(ISBLANK(INDEX('FR1'!H:H, MATCH(A105, 'FR1'!C:C, 0))), "LEAD OPEN", INDEX('FR1'!H:H, MATCH(A105, 'FR1'!C:C, 0)))} -> LEAD OPEN
A106: 9899226225 | B106: =COUNTIF('FR1'!C:C, A106) -> 7 | C106: {=INDEX('FR1'!B:B, MATCH(A106, 'FR1'!C:C, 0))} -> Gurman Singh | D106: {=INDEX('FR1'!A:A, MATCH(A106, 'FR1'!C:C, 0))} -> 45319.733 | E106: {=IF(ISBLANK(INDEX('FR1'!H:H, MATCH(A106, 'FR1'!C:C, 0))), "LEAD OPEN", INDEX('FR1'!H:H, MATCH(A106, 'FR1'!C:C, 0)))} -> Diamond pendent set
A107: 9999678088 | B107: =COUNTIF('FR1'!C:C, A107) -> 1 | C107: {=INDEX('FR1'!B:B, MATCH(A107, 'FR1'!C:C, 0))} -> Mehek dhawan | D107: {=INDEX('FR1'!A:A, MATCH(A107, 'FR1'!C:C, 0))} -> 45319.766 | E107: {=IF(ISBLANK(INDEX('FR1'!H:H, MATCH(A107, 'FR1'!C:C, 0))), "LEAD OPEN", INDEX('FR1'!H:H, MATCH(A107, 'FR1'!C:C, 0)))} -> LEAD OPEN
A108: 9811456708 | B108: =COUNTIF('FR1'!C:C, A108) -> 1 | C108: {=INDEX('FR1'!B:B, MATCH(A108, 'FR1'!C:C, 0))} -> Anil Choudhary | D108: {=INDEX('FR1'!A:A, MATCH(A108, 'FR1'!C:C, 0))} -> 45319.799 | E108: {=IF(ISBLANK(INDEX('FR1'!H:H, MATCH(A108, 'FR1'!C:C, 0))), "LEAD OPEN", INDEX('FR1'!H:H, MATCH(A108, 'FR1'!C:C, 0)))} -> LEAD OPEN
A109: 9971052404 | B109: =COUNTIF('FR1'!C:C, A109) -> 1 | C109: {=INDEX('FR1'!B:B, MATCH(A109, 'FR1'!C:C, 0))} -> Gurmeet | D109: {=INDEX('FR1'!A:A, MATCH(A109, 'FR1'!C:C, 0))} -> 45322.728 | E109: {=IF(ISBLANK(INDEX('FR1'!H:H, MATCH(A109, 'FR1'!C:C, 0))), "LEAD OPEN", INDEX('FR1'!H:H, MATCH(A109, 'FR1'!C:C, 0)))} -> Silver ganesh and Laxmi murti
... A174: 9910138678 | B174: =COUNTIF('FR1'!C:C, A174) -> 2 | C174: {=INDEX('FR1'!B:B, MATCH(A174, 'FR1'!C:C, 0))} -> Sanjay | D174: {=INDEX('FR1'!A:A, MATCH(A174, 'FR1'!C:C, 0))} -> 45359.778 | E174: {=IF(ISBLANK(INDEX('FR1'!H:H, MATCH(A174, 'FR1'!C:C, 0))), "LEAD OPEN", INDEX('FR1'!H:H, MATCH(A174, 'FR1'!C:C, 0)))} -> Gents gold eing
A175: +33751058354 | B175: =COUNTIF('FR1'!C:C, A175) -> 1 | C175: {=INDEX('FR1'!B:B, MATCH(A175, 'FR1'!C:C, 0))} -> Hasan | D175: {=INDEX('FR1'!A:A, MATCH(A175, 'FR1'!C:C, 0))} -> 45359.78 | E175: {=IF(ISBLANK(INDEX('FR1'!H:H, MATCH(A175, 'FR1'!C:C, 0))), "LEAD OPEN", INDEX('FR1'!H:H, MATCH(A175, 'FR1'!C:C, 0)))} -> 2 gold ring, gold tops
A176: 9958029273 | B176: =COUNTIF('FR1'!C:C, A176) -> 2 | C176: {=INDEX('FR1'!B:B, MATCH(A176, 'FR1'!C:C, 0))} -> Sakshi | D176: {=INDEX('FR1'!A:A, MATCH(A176, 'FR1'!C:C, 0))} -> 45359.791 | E176: {=IF(ISBLANK(INDEX('FR1'!H:H, MATCH(A176, 'FR1'!C:C, 0))), "LEAD OPEN", INDEX('FR1'!H:H, MATCH(A176, 'FR1'!C:C, 0)))} -> LEAD OPEN
A177: 9717383278 | B177: =COUNTIF('FR1'!C:C, A177) -> 1 | C177: {=INDEX('FR1'!B:B, MATCH(A177, 'FR1'!C:C, 0))} -> Mehak | D177: {=INDEX('FR1'!A:A, MATCH(A177, 'FR1'!C:C, 0))} -> 45359.792 | E177: {=IF(ISBLANK(INDEX('FR1'!H:H, MATCH(A177, 'FR1'!C:C, 0))), "LEAD OPEN", INDEX('FR1'!H:H, MATCH(A177, 'FR1'!C:C, 0)))} -> One diamond set
A178: 9891184192 | B178: =COUNTIF('FR1'!C:C, A178) -> 2 | C178: {=INDEX('FR1'!B:B, MATCH(A178, 'FR1'!C:C, 0))} -> Javed aslam ansari | D178: {=INDEX('FR1'!A:A, MATCH(A178, 'FR1'!C:C, 0))} -> 45359.798 | E178: {=IF(ISBLANK(INDEX('FR1'!H:H, MATCH(A178, 'FR1'!C:C, 0))), "LEAD OPEN", INDEX('FR1'!H:H, MATCH(A178, 'FR1'!C:C, 0)))} -> Gold tops
A179: 9131934410 | B179: =COUNTIF('FR1'!C:C, A179) -> 1 | C179: {=INDEX('FR1'!B:B, MATCH(A179, 'FR1'!C:C, 0))} -> Vivek | D179: {=INDEX('FR1'!A:A, MATCH(A179, 'FR1'!C:C, 0))} -> 45360.748 | E179: {=IF(ISBLANK(INDEX('FR1'!H:H, MATCH(A179, 'FR1'!C:C, 0))), "LEAD OPEN", INDEX('FR1'!H:H, MATCH(A179, 'FR1'!C:C, 0)))} -> Ledis gold ring
A180: 8375030384 | B180: =COUNTIF('FR1'!C:C, A180) -> 1 | C180: {=INDEX('FR1'!B:B, MATCH(A180, 'FR1'!C:C, 0))} -> Raj | D180: {=INDEX('FR1'!A:A, MATCH(A180, 'FR1'!C:C, 0))} -> 45360.749 | E180: {=IF(ISBLANK(INDEX('FR1'!H:H, MATCH(A180, 'FR1'!C:C, 0))), "LEAD OPEN", INDEX('FR1'!H:H, MATCH(A180, 'FR1'!C:C, 0)))} -> LEAD OPEN
A181: 9958509653 | B181: =COUNTIF('FR1'!C:C, A181) -> 1 | C181: {=INDEX('FR1'!B:B, MATCH(A181, 'FR1'!C:C, 0))} -> Sameer | D181: {=INDEX('FR1'!A:A, MATCH(A181, 'FR1'!C:C, 0))} -> 45360.762 | E181: {=IF(ISBLANK(INDEX('FR1'!H:H, MATCH(A181, 'FR1'!C:C, 0))), "LEAD OPEN", INDEX('FR1'!H:H, MATCH(A181, 'FR1'!C:C, 0)))} -> LEAD OPEN
A182: 9999978172 | B182: =COUNTIF('FR1'!C:C, A182) -> 1 | C182: {=INDEX('FR1'!B:B, MATCH(A182, 'FR1'!C:C, 0))} -> Manoj gupta | D182: {=INDEX('FR1'!A:A, MATCH(A182, 'FR1'!C:C, 0))} -> 45360.775 | E182: {=IF(ISBLANK(INDEX('FR1'!H:H, MATCH(A182, 'FR1'!C:C, 0))), "LEAD OPEN", INDEX('FR1'!H:H, MATCH(A182, 'FR1'!C:C, 0)))} -> LEAD OPEN
A183: 9873787782 | B183: =COUNTIF('FR1'!C:C, A183) -> 1 | C183: {=INDEX('FR1'!B:B, MATCH(A183, 'FR1'!C:C, 0))} -> Ankari | D183: {=INDEX('FR1'!A:A, MATCH(A183, 'FR1'!C:C, 0))} -> 45361.761 | E183: {=IF(ISBLANK(INDEX('FR1'!H:H, MATCH(A183, 'FR1'!C:C, 0))), "LEAD OPEN", INDEX('FR1'!H:H, MATCH(A183, 'FR1'!C:C, 0)))} -> LEAD OPEN
A184: 9810766703 | B184: =COUNTIF('FR1'!C:C, A184) -> 1 | C184: {=INDEX('FR1'!B:B, MATCH(A184, 'FR1'!C:C, 0))} -> Subhan | D184: {=INDEX('FR1'!A:A, MATCH(A184, 'FR1'!C:C, 0))} -> 45361.773 | E184: {=IF(ISBLANK(INDEX('FR1'!H:H, MATCH(A184, 'FR1'!C:C, 0))), "LEAD OPEN", INDEX('FR1'!H:H, MATCH(A184, 'FR1'!C:C, 0)))} -> Turkish set
A185: 9650785711 | B185: =COUNTIF('FR1'!C:C, A185) -> 1 | C185: {=INDEX('FR1'!B:B, MATCH(A185, 'FR1'!C:C, 0))} -> Bhawna | D185: {=INDEX('FR1'!A:A, MATCH(A185, 'FR1'!C:C, 0))} -> 45361.775 | E185: {=IF(ISBLANK(INDEX('FR1'!H:H, MATCH(A185, 'FR1'!C:C, 0))), "LEAD OPEN", INDEX('FR1'!H:H, MATCH(A185, 'FR1'!C:C, 0)))} -> Mix matel ring
A186: 8825179746 | B186: =COUNTIF('FR1'!C:C, A186) -> 1 | C186: {=INDEX('FR1'!B:B, MATCH(A186, 'FR1'!C:C, 0))} -> Nisha kumari | D186: {=INDEX('FR1'!A:A, MATCH(A186, 'FR1'!C:C, 0))} -> 45361.777 | E186: {=IF(ISBLANK(INDEX('FR1'!H:H, MATCH(A186, 'FR1'!C:C, 0))), "LEAD OPEN", INDEX('FR1'!H:H, MATCH(A186, 'FR1'!C:C, 0)))} -> LEAD OPEN
A187: 9268948231 | B187: =COUNTIF('FR1'!C:C, A187) -> 1 | C187: {=INDEX('FR1'!B:B, MATCH(A187, 'FR1'!C:C, 0))} -> Md.wasim | D187: {=INDEX('FR1'!A:A, MATCH(A187, 'FR1'!C:C, 0))} -> 45361.779 | E187: {=IF(ISBLANK(INDEX('FR1'!H:H, MATCH(A187, 'FR1'!C:C, 0))), "LEAD OPEN", INDEX('FR1'!H:H, MATCH(A187, 'FR1'!C:C, 0)))} -> LEAD OPEN
... A201: 9711009801 | B201: =COUNTIF('FR1'!C:C, A201) -> 1 | C201: {=INDEX('FR1'!B:B, MATCH(A201, 'FR1'!C:C, 0))} -> Sapna | D201: {=INDEX('FR1'!A:A, MATCH(A201, 'FR1'!C:C, 0))} -> 45366.758 | E201: {=IF(ISBLANK(INDEX('FR1'!H:H, MATCH(A201, 'FR1'!C:C, 0))), "LEAD OPEN", INDEX('FR1'!H:H, MATCH(A201, 'FR1'!C:C, 0)))} -> LEAD OPEN
A202: 9868442620 | B202: =COUNTIF('FR1'!C:C, A202) -> 1 | E202: {=IF(ISBLANK(INDEX('FR1'!H:H, MATCH(A202, 'FR1'!C:C, 0))), "LEAD OPEN", INDEX('FR1'!H:H, MATCH(A202, 'FR1'!C:C, 0)))} -> Mangal sutr
A203: 991711476067 | B203: =COUNTIF('FR1'!C:C, A203) -> 1 | E203: {=IF(ISBLANK(INDEX('FR1'!H:H, MATCH(A203, 'FR1'!C:C, 0))), "LEAD OPEN", INDEX('FR1'!H:H, MATCH(A203, 'FR1'!C:C, 0)))} -> Diamond manglsutr
A204: 91711476067 | B204: =COUNTIF('FR1'!C:C, A204) -> 1 | E204: {=IF(ISBLANK(INDEX('FR1'!H:H, MATCH(A204, 'FR1'!C:C, 0))), "LEAD OPEN", INDEX('FR1'!H:H, MATCH(A204, 'FR1'!C:C, 0)))} -> Gold band
A205: 9812319370 | B205: =COUNTIF('FR1'!C:C, A205) -> 1 | E205: {=IF(ISBLANK(INDEX('FR1'!H:H, MATCH(A205, 'FR1'!C:C, 0))), "LEAD OPEN", INDEX('FR1'!H:H, MATCH(A205, 'FR1'!C:C, 0)))} -> Diamond rig,bangles
A206: 7906897961 | B206: =COUNTIF('FR1'!C:C, A206) -> 1 | E206: {=IF(ISBLANK(INDEX('FR1'!H:H, MATCH(A206, 'FR1'!C:C, 0))), "LEAD OPEN", INDEX('FR1'!H:H, MATCH(A206, 'FR1'!C:C, 0)))} -> LEAD OPEN
A207: 9560757721 | B207: =COUNTIF('FR1'!C:C, A207) -> 1 | E207: {=IF(ISBLANK(INDEX('FR1'!H:H, MATCH(A207, 'FR1'!C:C, 0))), "LEAD OPEN", INDEX('FR1'!H:H, MATCH(A207, 'FR1'!C:C, 0)))} -> LEAD OPEN
A208: 9811791798 | B208: =COUNTIF('FR1'!C:C, A208) -> 1 | E208: {=IF(ISBLANK(INDEX('FR1'!H:H, MATCH(A208, 'FR1'!C:C, 0))), "LEAD OPEN", INDEX('FR1'!H:H, MATCH(A208, 'FR1'!C:C, 0)))} -> Gold chand suraj
A209: 7409100000 | B209: =COUNTIF('FR1'!C:C, A209) -> 1 | E209: {=IF(ISBLANK(INDEX('FR1'!H:H, MATCH(A209, 'FR1'!C:C, 0))), "LEAD OPEN", INDEX('FR1'!H:H, MATCH(A209, 'FR1'!C:C, 0)))} -> LEAD OPEN
A210: 992640208 | B210: =COUNTIF('FR1'!C:C, A210) -> 1 | E210: {=IF(ISBLANK(INDEX('FR1'!H:H, MATCH(A210, 'FR1'!C:C, 0))), "LEAD OPEN", INDEX('FR1'!H:H, MATCH(A210, 'FR1'!C:C, 0)))} -> Gold tops,silver bands
A211: 9818024252 | B211: =COUNTIF('FR1'!C:C, A211) -> 1 | E211: {=IF(ISBLANK(INDEX('FR1'!H:H, MATCH(A211, 'FR1'!C:C, 0))), "LEAD OPEN", INDEX('FR1'!H:H, MATCH(A211, 'FR1'!C:C, 0)))} -> Antic set 1
A212: 8447575487 | B212: =COUNTIF('FR1'!C:C, A212) -> 1 | E212: {=IF(ISBLANK(INDEX('FR1'!H:H, MATCH(A212, 'FR1'!C:C, 0))), "LEAD OPEN", INDEX('FR1'!H:H, MATCH(A212, 'FR1'!C:C, 0)))} -> LEAD OPEN
A213: 7838100747 | B213: =COUNTIF('FR1'!C:C, A213) -> 1 | E213: {=IF(ISBLANK(INDEX('FR1'!H:H, MATCH(A213, 'FR1'!C:C, 0))), "LEAD OPEN", INDEX('FR1'!H:H, MATCH(A213, 'FR1'!C:C, 0)))} -> Gold msg chain
... A241: 7417700981 | B241: =COUNTIF('FR1'!C:C, A241) -> 3 | E241: {=IF(ISBLANK(INDEX('FR1'!H:H, MATCH(A241, 'FR1'!C:C, 0))), "LEAD OPEN", INDEX('FR1'!H:H, MATCH(A241, 'FR1'!C:C, 0)))} -> 1 set,ring
A242: 982124854 | B242: =COUNTIF('FR1'!C:C, A242) -> 1
...
